Workbook

Sheet Start Here
A1: Pet Sitting & Dog Walking Business Manager
A2: Clients · Jobs · Quotes · Invoices · Expenses · Profit dashboard — Google Sheets & Excel
B4: HOW TO USE
B5: 1. Settings | C5: Enter your business name, hourly labor cost, tax set-aside %, mileage rate and your service prices.
B6: 2. Clients | C6: Add each client once: name, contact, service, how often you visit them, and their price. Next due date and overdue flags fill in automatically.
B7: 3. Jobs | C7: Log every visit. Pick the client from the dropdown — price fills in from their record (type in 'Price override' to change it for one job). Mark Paid = Yes when paid.
B8: 4. Expenses | C8: Log supplies, gas, equipment, insurance, ads. Categories come from Settings.
B9: 5. Quote Calculator | C9: Price a new client in seconds from number of pets, medications / special care, travel distance, add-ons and frequency. Shows estimated hours and your profit.
B10: 6. Invoice | C10: Type a Job ID (e.g. J-0001). The invoice fills in. Print or File > Download as PDF.
B11: 7. Dashboard | C11: Pick a year. See revenue, costs, profit, unpaid balance and tax set-aside by month.
B13: COLOR KEY
B14: Yellow cell, blue text | C14: Type here — your inputs
B15: White cell, black text | C15: Calculated automatically — don't type over these
B17: GOOGLE SHEETS
C18: Upload this file to Google Drive, open it, then File > Save as Google Sheets. Everything works in both Excel and Google Sheets.
C19: The example rows (marked EXAMPLE) show the format — delete them when you start. After that, clear a job row instead of deleting it, so Job IDs and invoice numbers stay the same.

Sheet Dashboard
A1: Dashboard
A2: Pick a year. Everything below updates from Jobs and Expenses.
A4: Year | B4: 2026
B5: Revenue | D5: Profit | F5: Unpaid | H5: Tax set-aside
B6: =SUM(B9:B20) -> 99 | D6: =SUM(F9:F20) -> 1.1 | F6: =SUMIFS(Jobs!$J$5:$J$1004,Jobs!$K$5:$K$1004,"No") -> 36 | H6: =MAX(0,B23)*Settings!$B$9 -> 0.275
A8: Month | B8: Revenue | C8: Job costs | D8: Expenses | E8: Jobs | F8: Profit | G8: Margin | H8: Unpaid
A9: =TEXT(DATE($B$4,1,1),"mmm yyyy") -> Jan 2026 | B9: =SUMIFS(Jobs!$J$5:$J$1004,Jobs!$B$5:$B$1004,">="&DATE($B$4,1,1),Jobs!$B$5:$B$1004,"<="&EOMONTH(DATE($B$4,1,1),0)) -> 0 | C9: =SUMIFS(Jobs!$M$5:$M$1004,Jobs!$B$5:$B$1004,">="&DATE($B$4,1,1),Jobs!$B$5:$B$1004,"<="&EOMONTH(DATE($B$4,1,1),0))+SUMIFS(Jobs!$O$5:$O$1004,Jobs!$B$5:$B$1004,">="&DATE($B$4,1,1),Jobs!$B$5:$B$1004,"<="&EOMONTH(DATE($B$4,1,1),0))+SUMIFS(Jobs!$P$5:$P$1004,Jobs!$B$5:$B$1004,">="&DATE($B$4,1,1),Jobs!$B$5:$B$1004,"<="&EOMONTH(DATE($B$4,1,1),0)) -> 0 | D9: =SUMIFS(Expenses!$E$5:$E$1004,Expenses!$A$5:$A$1004,">="&DATE($B$4,1,1),Expenses!$A$5:$A$1004,"<="&EOMONTH(DATE($B$4,1,1),0)) -> 0 | E9: =COUNTIFS(Jobs!$B$5:$B$1004,">="&DATE($B$4,1,1),Jobs!$B$5:$B$1004,"<="&EOMONTH(DATE($B$4,1,1),0)) -> 0 | F9: =B9-C9-D9 -> 0 | G9: =IF(B9=0,0,F9/B9) -> 0 | H9: =SUMIFS(Jobs!$J$5:$J$1004,Jobs!$B$5:$B$1004,">="&DATE($B$4,1,1),Jobs!$B$5:$B$1004,"<="&EOMONTH(DATE($B$4,1,1),0),Jobs!$K$5:$K$1004,"No") -> 0
A10: =TEXT(DATE($B$4,2,1),"mmm yyyy") -> Feb 2026 | B10: =SUMIFS(Jobs!$J$5:$J$1004,Jobs!$B$5:$B$1004,">="&DATE($B$4,2,1),Jobs!$B$5:$B$1004,"<="&EOMONTH(DATE($B$4,2,1),0)) -> 0 | C10: =SUMIFS(Jobs!$M$5:$M$1004,Jobs!$B$5:$B$1004,">="&DATE($B$4,2,1),Jobs!$B$5:$B$1004,"<="&EOMONTH(DATE($B$4,2,1),0))+SUMIFS(Jobs!$O$5:$O$1004,Jobs!$B$5:$B$1004,">="&DATE($B$4,2,1),Jobs!$B$5:$B$1004,"<="&EOMONTH(DATE($B$4,2,1),0))+SUMIFS(Jobs!$P$5:$P$1004,Jobs!$B$5:$B$1004,">="&DATE($B$4,2,1),Jobs!$B$5:$B$1004,"<="&EOMONTH(DATE($B$4,2,1),0)) -> 0 | D10: =SUMIFS(Expenses!$E$5:$E$1004,Expenses!$A$5:$A$1004,">="&DATE($B$4,2,1),Expenses!$A$5:$A$1004,"<="&EOMONTH(DATE($B$4,2,1),0)) -> 0 | E10: =COUNTIFS(Jobs!$B$5:$B$1004,">="&DATE($B$4,2,1),Jobs!$B$5:$B$1004,"<="&EOMONTH(DATE($B$4,2,1),0)) -> 0 | F10: =B10-C10-D10 -> 0 | G10: =IF(B10=0,0,F10/B10) -> 0 | H10: =SUMIFS(Jobs!$J$5:$J$1004,Jobs!$B$5:$B$1004,">="&DATE($B$4,2,1),Jobs!$B$5:$B$1004,"<="&EOMONTH(DATE($B$4,2,1),0),Jobs!$K$5:$K$1004,"No") -> 0
A11: =TEXT(DATE($B$4,3,1),"mmm yyyy") -> Mar 2026 | B11: =SUMIFS(Jobs!$J$5:$J$1004,Jobs!$B$5:$B$1004,">="&DATE($B$4,3,1),Jobs!$B$5:$B$1004,"<="&EOMONTH(DATE($B$4,3,1),0)) -> 0 | C11: =SUMIFS(Jobs!$M$5:$M$1004,Jobs!$B$5:$B$1004,">="&DATE($B$4,3,1),Jobs!$B$5:$B$1004,"<="&EOMONTH(DATE($B$4,3,1),0))+SUMIFS(Jobs!$O$5:$O$1004,Jobs!$B$5:$B$1004,">="&DATE($B$4,3,1),Jobs!$B$5:$B$1004,"<="&EOMONTH(DATE($B$4,3,1),0))+SUMIFS(Jobs!$P$5:$P$1004,Jobs!$B$5:$B$1004,">="&DATE($B$4,3,1),Jobs!$B$5:$B$1004,"<="&EOMONTH(DATE($B$4,3,1),0)) -> 0 | D11: =SUMIFS(Expenses!$E$5:$E$1004,Expenses!$A$5:$A$1004,">="&DATE($B$4,3,1),Expenses!$A$5:$A$1004,"<="&EOMONTH(DATE($B$4,3,1),0)) -> 0 | E11: =COUNTIFS(Jobs!$B$5:$B$1004,">="&DATE($B$4,3,1),Jobs!$B$5:$B$1004,"<="&EOMONTH(DATE($B$4,3,1),0)) -> 0 | F11: =B11-C11-D11 -> 0 | G11: =IF(B11=0,0,F11/B11) -> 0 | H11: =SUMIFS(Jobs!$J$5:$J$1004,Jobs!$B$5:$B$1004,">="&DATE($B$4,3,1),Jobs!$B$5:$B$1004,"<="&EOMONTH(DATE($B$4,3,1),0),Jobs!$K$5:$K$1004,"No") -> 0
A12: =TEXT(DATE($B$4,4,1),"mmm yyyy") -> Apr 2026 | B12: =SUMIFS(Jobs!$J$5:$J$1004,Jobs!$B$5:$B$1004,">="&DATE($B$4,4,1),Jobs!$B$5:$B$1004,"<="&EOMONTH(DATE($B$4,4,1),0)) -> 0 | C12: =SUMIFS(Jobs!$M$5:$M$1004,Jobs!$B$5:$B$1004,">="&DATE($B$4,4,1),Jobs!$B$5:$B$1004,"<="&EOMONTH(DATE($B$4,4,1),0))+SUMIFS(Jobs!$O$5:$O$1004,Jobs!$B$5:$B$1004,">="&DATE($B$4,4,1),Jobs!$B$5:$B$1004,"<="&EOMONTH(DATE($B$4,4,1),0))+SUMIFS(Jobs!$P$5:$P$1004,Jobs!$B$5:$B$1004,">="&DATE($B$4,4,1),Jobs!$B$5:$B$1004,"<="&EOMONTH(DATE($B$4,4,1),0)) -> 0 | D12: =SUMIFS(Expenses!$E$5:$E$1004,Expenses!$A$5:$A$1004,">="&DATE($B$4,4,1),Expenses!$A$5:$A$1004,"<="&EOMONTH(DATE($B$4,4,1),0)) -> 0 | E12: =COUNTIFS(Jobs!$B$5:$B$1004,">="&DATE($B$4,4,1),Jobs!$B$5:$B$1004,"<="&EOMONTH(DATE($B$4,4,1),0)) -> 0 | F12: =B12-C12-D12 -> 0 | G12: =IF(B12=0,0,F12/B12) -> 0 | H12: =SUMIFS(Jobs!$J$5:$J$1004,Jobs!$B$5:$B$1004,">="&DATE($B$4,4,1),Jobs!$B$5:$B$1004,"<="&EOMONTH(DATE($B$4,4,1),0),Jobs!$K$5:$K$1004,"No") -> 0
A13: =TEXT(DATE($B$4,5,1),"mmm yyyy") -> May 2026 | B13: =SUMIFS(Jobs!$J$5:$J$1004,Jobs!$B$5:$B$1004,">="&DATE($B$4,5,1),Jobs!$B$5:$B$1004,"<="&EOMONTH(DATE($B$4,5,1),0)) -> 0 | C13: =SUMIFS(Jobs!$M$5:$M$1004,Jobs!$B$5:$B$1004,">="&DATE($B$4,5,1),Jobs!$B$5:$B$1004,"<="&EOMONTH(DATE($B$4,5,1),0))+SUMIFS(Jobs!$O$5:$O$1004,Jobs!$B$5:$B$1004,">="&DATE($B$4,5,1),Jobs!$B$5:$B$1004,"<="&EOMONTH(DATE($B$4,5,1),0))+SUMIFS(Jobs!$P$5:$P$1004,Jobs!$B$5:$B$1004,">="&DATE($B$4,5,1),Jobs!$B$5:$B$1004,"<="&EOMONTH(DATE($B$4,5,1),0)) -> 0 | D13: =SUMIFS(Expenses!$E$5:$E$1004,Expenses!$A$5:$A$1004,">="&DATE($B$4,5,1),Expenses!$A$5:$A$1004,"<="&EOMONTH(DATE($B$4,5,1),0)) -> 0 | E13: =COUNTIFS(Jobs!$B$5:$B$1004,">="&DATE($B$4,5,1),Jobs!$B$5:$B$1004,"<="&EOMONTH(DATE($B$4,5,1),0)) -> 0 | F13: =B13-C13-D13 -> 0 | G13: =IF(B13=0,0,F13/B13) -> 0 | H13: =SUMIFS(Jobs!$J$5:$J$1004,Jobs!$B$5:$B$1004,">="&DATE($B$4,5,1),Jobs!$B$5:$B$1004,"<="&EOMONTH(DATE($B$4,5,1),0),Jobs!$K$5:$K$1004,"No") -> 0
A14: =TEXT(DATE($B$4,6,1),"mmm yyyy") -> Jun 2026 | B14: =SUMIFS(Jobs!$J$5:$J$1004,Jobs!$B$5:$B$1004,">="&DATE($B$4,6,1),Jobs!$B$5:$B$1004,"<="&EOMONTH(DATE($B$4,6,1),0)) -> 0 | C14: =SUMIFS(Jobs!$M$5:$M$1004,Jobs!$B$5:$B$1004,">="&DATE($B$4,6,1),Jobs!$B$5:$B$1004,"<="&EOMONTH(DATE($B$4,6,1),0))+SUMIFS(Jobs!$O$5:$O$1004,Jobs!$B$5:$B$1004,">="&DATE($B$4,6,1),Jobs!$B$5:$B$1004,"<="&EOMONTH(DATE($B$4,6,1),0))+SUMIFS(Jobs!$P$5:$P$1004,Jobs!$B$5:$B$1004,">="&DATE($B$4,6,1),Jobs!$B$5:$B$1004,"<="&EOMONTH(DATE($B$4,6,1),0)) -> 0 | D14: =SUMIFS(Expenses!$E$5:$E$1004,Expenses!$A$5:$A$1004,">="&DATE($B$4,6,1),Expenses!$A$5:$A$1004,"<="&EOMONTH(DATE($B$4,6,1),0)) -> 0 | E14: =COUNTIFS(Jobs!$B$5:$B$1004,">="&DATE($B$4,6,1),Jobs!$B$5:$B$1004,"<="&EOMONTH(DATE($B$4,6,1),0)) -> 0 | F14: =B14-C14-D14 -> 0 | G14: =IF(B14=0,0,F14/B14) -> 0 | H14: =SUMIFS(Jobs!$J$5:$J$1004,Jobs!$B$5:$B$1004,">="&DATE($B$4,6,1),Jobs!$B$5:$B$1004,"<="&EOMONTH(DATE($B$4,6,1),0),Jobs!$K$5:$K$1004,"No") -> 0
A15: =TEXT(DATE($B$4,7,1),"mmm yyyy") -> Jul 2026 | B15: =SUMIFS(Jobs!$J$5:$J$1004,Jobs!$B$5:$B$1004,">="&DATE($B$4,7,1),Jobs!$B$5:$B$1004,"<="&EOMONTH(DATE($B$4,7,1),0)) -> 0 | C15: =SUMIFS(Jobs!$M$5:$M$1004,Jobs!$B$5:$B$1004,">="&DATE($B$4,7,1),Jobs!$B$5:$B$1004,"<="&EOMONTH(DATE($B$4,7,1),0))+SUMIFS(Jobs!$O$5:$O$1004,Jobs!$B$5:$B$1004,">="&DATE($B$4,7,1),Jobs!$B$5:$B$1004,"<="&EOMONTH(DATE($B$4,7,1),0))+SUMIFS(Jobs!$P$5:$P$1004,Jobs!$B$5:$B$1004,">="&DATE($B$4,7,1),Jobs!$B$5:$B$1004,"<="&EOMONTH(DATE($B$4,7,1),0)) -> 0 | D15: =SUMIFS(Expenses!$E$5:$E$1004,Expenses!$A$5:$A$1004,">="&DATE($B$4,7,1),Expenses!$A$5:$A$1004,"<="&EOMONTH(DATE($B$4,7,1),0)) -> 0 | E15: =COUNTIFS(Jobs!$B$5:$B$1004,">="&DATE($B$4,7,1),Jobs!$B$5:$B$1004,"<="&EOMONTH(DATE($B$4,7,1),0)) -> 0 | F15: =B15-C15-D15 -> 0 | G15: =IF(B15=0,0,F15/B15) -> 0 | H15: =SUMIFS(Jobs!$J$5:$J$1004,Jobs!$B$5:$B$1004,">="&DATE($B$4,7,1),Jobs!$B$5:$B$1004,"<="&EOMONTH(DATE($B$4,7,1),0),Jobs!$K$5:$K$1004,"No") -> 0
A16: =TEXT(DATE($B$4,8,1),"mmm yyyy") -> Aug 2026 | B16: =SUMIFS(Jobs!$J$5:$J$1004,Jobs!$B$5:$B$1004,">="&DATE($B$4,8,1),Jobs!$B$5:$B$1004,"<="&EOMONTH(DATE($B$4,8,1),0)) -> 0 | C16: =SUMIFS(Jobs!$M$5:$M$1004,Jobs!$B$5:$B$1004,">="&DATE($B$4,8,1),Jobs!$B$5:$B$1004,"<="&EOMONTH(DATE($B$4,8,1),0))+SUMIFS(Jobs!$O$5:$O$1004,Jobs!$B$5:$B$1004,">="&DATE($B$4,8,1),Jobs!$B$5:$B$1004,"<="&EOMONTH(DATE($B$4,8,1),0))+SUMIFS(Jobs!$P$5:$P$1004,Jobs!$B$5:$B$1004,">="&DATE($B$4,8,1),Jobs!$B$5:$B$1004,"<="&EOMONTH(DATE($B$4,8,1),0)) -> 0 | D16: =SUMIFS(Expenses!$E$5:$E$1004,Expenses!$A$5:$A$1004,">="&DATE($B$4,8,1),Expenses!$A$5:$A$1004,"<="&EOMONTH(DATE($B$4,8,1),0)) -> 0 | E16: =COUNTIFS(Jobs!$B$5:$B$1004,">="&DATE($B$4,8,1),Jobs!$B$5:$B$1004,"<="&EOMONTH(DATE($B$4,8,1),0)) -> 0 | F16: =B16-C16-D16 -> 0 | G16: =IF(B16=0,0,F16/B16) -> 0 | H16: =SUMIFS(Jobs!$J$5:$J$1004,Jobs!$B$5:$B$1004,">="&DATE($B$4,8,1),Jobs!$B$5:$B$1004,"<="&EOMONTH(DATE($B$4,8,1),0),Jobs!$K$5:$K$1004,"No") -> 0
A17: =TEXT(DATE($B$4,9,1),"mmm yyyy") -> Sep 2026 | B17: =SUMIFS(Jobs!$J$5:$J$1004,Jobs!$B$5:$B$1004,">="&DATE($B$4,9,1),Jobs!$B$5:$B$1004,"<="&EOMONTH(DATE($B$4,9,1),0)) -> 28 | C17: =SUMIFS(Jobs!$M$5:$M$1004,Jobs!$B$5:$B$1004,">="&DATE($B$4,9,1),Jobs!$B$5:$B$1004,"<="&EOMONTH(DATE($B$4,9,1),0))+SUMIFS(Jobs!$O$5:$O$1004,Jobs!$B$5:$B$1004,">="&DATE($B$4,9,1),Jobs!$B$5:$B$1004,"<="&EOMONTH(DATE($B$4,9,1),0))+SUMIFS(Jobs!$P$5:$P$1004,Jobs!$B$5:$B$1004,">="&DATE($B$4,9,1),Jobs!$B$5:$B$1004,"<="&EOMONTH(DATE($B$4,9,1),0)) -> 13.2 | D17: =SUMIFS(Expenses!$E$5:$E$1004,Expenses!$A$5:$A$1004,">="&DATE($B$4,9,1),Expenses!$A$5:$A$1004,"<="&EOMONTH(DATE($B$4,9,1),0)) -> 0 | E17: =COUNTIFS(Jobs!$B$5:$B$1004,">="&DATE($B$4,9,1),Jobs!$B$5:$B$1004,"<="&EOMONTH(DATE($B$4,9,1),0)) -> 1 | F17: =B17-C17-D17 -> 14.8 | G17: =IF(B17=0,0,F17/B17) -> 0.52857143 | H17: =SUMIFS(Jobs!$J$5:$J$1004,Jobs!$B$5:$B$1004,">="&DATE($B$4,9,1),Jobs!$B$5:$B$1004,"<="&EOMONTH(DATE($B$4,9,1),0),Jobs!$K$5:$K$1004,"No") -> 0
A18: =TEXT(DATE($B$4,10,1),"mmm yyyy") -> Oct 2026 | B18: =SUMIFS(Jobs!$J$5:$J$1004,Jobs!$B$5:$B$1004,">="&DATE($B$4,10,1),Jobs!$B$5:$B$1004,"<="&EOMONTH(DATE($B$4,10,1),0)) -> 71 | C18: =SUMIFS(Jobs!$M$5:$M$1004,Jobs!$B$5:$B$1004,">="&DATE($B$4,10,1),Jobs!$B$5:$B$1004,"<="&EOMONTH(DATE($B$4,10,1),0))+SUMIFS(Jobs!$O$5:$O$1004,Jobs!$B$5:$B$1004,">="&DATE($B$4,10,1),Jobs!$B$5:$B$1004,"<="&EOMONTH(DATE($B$4,10,1),0))+SUMIFS(Jobs!$P$5:$P$1004,Jobs!$B$5:$B$1004,">="&DATE($B$4,10,1),Jobs!$B$5:$B$1004,"<="&EOMONTH(DATE($B$4,10,1),0)) -> 26.5 | D18: =SUMIFS(Expenses!$E$5:$E$1004,Expenses!$A$5:$A$1004,">="&DATE($B$4,10,1),Expenses!$A$5:$A$1004,"<="&EOMONTH(DATE($B$4,10,1),0)) -> 58.2 | E18: =COUNTIFS(Jobs!$B$5:$B$1004,">="&DATE($B$4,10,1),Jobs!$B$5:$B$1004,"<="&EOMONTH(DATE($B$4,10,1),0)) -> 2 | F18: =B18-C18-D18 -> -13.7 | G18: =IF(B18=0,0,F18/B18) -> -0.19295775 | H18: =SUMIFS(Jobs!$J$5:$J$1004,Jobs!$B$5:$B$1004,">="&DATE($B$4,10,1),Jobs!$B$5:$B$1004,"<="&EOMONTH(DATE($B$4,10,1),0),Jobs!$K$5:$K$1004,"No") -> 36
A19: =TEXT(DATE($B$4,11,1),"mmm yyyy") -> Nov 2026 | B19: =SUMIFS(Jobs!$J$5:$J$1004,Jobs!$B$5:$B$1004,">="&DATE($B$4,11,1),Jobs!$B$5:$B$1004,"<="&EOMONTH(DATE($B$4,11,1),0)) -> 0 | C19: =SUMIFS(Jobs!$M$5:$M$1004,Jobs!$B$5:$B$1004,">="&DATE($B$4,11,1),Jobs!$B$5:$B$1004,"<="&EOMONTH(DATE($B$4,11,1),0))+SUMIFS(Jobs!$O$5:$O$1004,Jobs!$B$5:$B$1004,">="&DATE($B$4,11,1),Jobs!$B$5:$B$1004,"<="&EOMONTH(DATE($B$4,11,1),0))+SUMIFS(Jobs!$P$5:$P$1004,Jobs!$B$5:$B$1004,">="&DATE($B$4,11,1),Jobs!$B$5:$B$1004,"<="&EOMONTH(DATE($B$4,11,1),0)) -> 0 | D19: =SUMIFS(Expenses!$E$5:$E$1004,Expenses!$A$5:$A$1004,">="&DATE($B$4,11,1),Expenses!$A$5:$A$1004,"<="&EOMONTH(DATE($B$4,11,1),0)) -> 0 | E19: =COUNTIFS(Jobs!$B$5:$B$1004,">="&DATE($B$4,11,1),Jobs!$B$5:$B$1004,"<="&EOMONTH(DATE($B$4,11,1),0)) -> 0 | F19: =B19-C19-D19 -> 0 | G19: =IF(B19=0,0,F19/B19) -> 0 | H19: =SUMIFS(Jobs!$J$5:$J$1004,Jobs!$B$5:$B$1004,">="&DATE($B$4,11,1),Jobs!$B$5:$B$1004,"<="&EOMONTH(DATE($B$4,11,1),0),Jobs!$K$5:$K$1004,"No") -> 0
A20: =TEXT(DATE($B$4,12,1),"mmm yyyy") -> Dec 2026 | B20: =SUMIFS(Jobs!$J$5:$J$1004,Jobs!$B$5:$B$1004,">="&DATE($B$4,12,1),Jobs!$B$5:$B$1004,"<="&EOMONTH(DATE($B$4,12,1),0)) -> 0 | C20: =SUMIFS(Jobs!$M$5:$M$1004,Jobs!$B$5:$B$1004,">="&DATE($B$4,12,1),Jobs!$B$5:$B$1004,"<="&EOMONTH(DATE($B$4,12,1),0))+SUMIFS(Jobs!$O$5:$O$1004,Jobs!$B$5:$B$1004,">="&DATE($B$4,12,1),Jobs!$B$5:$B$1004,"<="&EOMONTH(DATE($B$4,12,1),0))+SUMIFS(Jobs!$P$5:$P$1004,Jobs!$B$5:$B$1004,">="&DATE($B$4,12,1),Jobs!$B$5:$B$1004,"<="&EOMONTH(DATE($B$4,12,1),0)) -> 0 | D20: =SUMIFS(Expenses!$E$5:$E$1004,Expenses!$A$5:$A$1004,">="&DATE($B$4,12,1),Expenses!$A$5:$A$1004,"<="&EOMONTH(DATE($B$4,12,1),0)) -> 0 | E20: =COUNTIFS(Jobs!$B$5:$B$1004,">="&DATE($B$4,12,1),Jobs!$B$5:$B$1004,"<="&EOMONTH(DATE($B$4,12,1),0)) -> 0 | F20: =B20-C20-D20 -> 0 | G20: =IF(B20=0,0,F20/B20) -> 0 | H20: =SUMIFS(Jobs!$J$5:$J$1004,Jobs!$B$5:$B$1004,">="&DATE($B$4,12,1),Jobs!$B$5:$B$1004,"<="&EOMONTH(DATE($B$4,12,1),0),Jobs!$K$5:$K$1004,"No") -> 0
A21: Total | B21: =SUM(B9:B20) -> 99 | C21: =SUM(C9:C20) -> 39.7 | D21: =SUM(D9:D20) -> 58.2 | E21: =SUM(E9:E20) -> 3 | F21: =SUM(F9:F20) -> 1.1 | G21: =IF(B21=0,0,F21/B21) -> 0.011111111 | H21: =SUM(H9:H20) -> 36
A23: Profit for tax estimate | B23: =F21 -> 1.1
A24: Note: Tax set-aside is a planning estimate, not tax advice.

Sheet Clients
A1: Clients
A2: One row per client. Next due date and status update automatically from the Jobs log.
A4: Client name | B4: Phone | C4: Email | D4: Address | E4: Service | F4: Frequency | G4: Price per visit | H4: Start date | I4: Pets, vet & access notes | J4: Visits | K4: Lifetime revenue | L4: Last visit | M4: Next due | N4: Status
A5: EXAMPLE – Johnson Family | B5: (555) 201-3344 | C5: jj@example.com | D5: 12 Oak St | E5: Dog Walk (30 min) | F5: Weekly | G5: 25 | H5: 46254 | I5: Max (lab) & Bella; lockbox 4412; vet Dr. Lee 555-0190 | J5: =IF($A5="","",COUNTIFS(Jobs!$C$5:$C$1004,$A5)) -> 1 | K5: =IF($A5="","",SUMIFS(Jobs!$J$5:$J$1004,Jobs!$C$5:$C$1004,$A5)) -> 35 | L5: =IF(OR($A5="",J5=0),"",_xlfn.MAXIFS(Jobs!$B$5:$B$1004,Jobs!$C$5:$C$1004,$A5)) -> 46296 | M5: =IF(OR($A5="",L5=""),"",IFERROR(IF(INDEX(Settings!$E$33:$E$37,MATCH(F5,Settings!$D$33:$D$37,0))="","",L5+INDEX(Settings!$E$33:$E$37,MATCH(F5,Settings!$D$33:$D$37,0))),"")) -> 46303 | N5: =IF($A5="","",IF(M5="",IF(J5=0,"New","—"),IF(M5<TODAY(),"Overdue",IF(M5-TODAY()<=3,"Due soon","Scheduled")))) -> Overdue
A6: EXAMPLE – Patel Family | B6: (555) 870-1100 | C6: patel@example.com | D6: 400 Main St | E6: Drop-in Visit (30 min) | F6: Every 2 weeks | G6: 28 | H6: 46249 | I6: 2 cats, insulin 8am; key under mat | J6: =IF($A6="","",COUNTIFS(Jobs!$C$5:$C$1004,$A6)) -> 2 | K6: =IF($A6="","",SUMIFS(Jobs!$J$5:$J$1004,Jobs!$C$5:$C$1004,$A6)) -> 64 | L6: =IF(OR($A6="",J6=0),"",_xlfn.MAXIFS(Jobs!$B$5:$B$1004,Jobs!$C$5:$C$1004,$A6)) -> 46308 | M6: =IF(OR($A6="",L6=""),"",IFERROR(IF(INDEX(Settings!$E$33:$E$37,MATCH(F6,Settings!$D$33:$D$37,0))="","",L6+INDEX(Settings!$E$33:$E$37,MATCH(F6,Settings!$D$33:$D$37,0))),"")) -> 46322 | N6: =IF($A6="","",IF(M6="",IF(J6=0,"New","—"),IF(M6<TODAY(),"Overdue",IF(M6-TODAY()<=3,"Due soon","Scheduled")))) -> Scheduled
J7: =IF($A7="","",COUNTIFS(Jobs!$C$5:$C$1004,$A7)) | K7: =IF($A7="","",SUMIFS(Jobs!$J$5:$J$1004,Jobs!$C$5:$C$1004,$A7)) | L7: =IF(OR($A7="",J7=0),"",_xlfn.MAXIFS(Jobs!$B$5:$B$1004,Jobs!$C$5:$C$1004,$A7)) | M7: =IF(OR($A7="",L7=""),"",IFERROR(IF(INDEX(Settings!$E$33:$E$37,MATCH(F7,Settings!$D$33:$D$37,0))="","",L7+INDEX(Settings!$E$33:$E$37,MATCH(F7,Settings!$D$33:$D$37,0))),"")) | N7: =IF($A7="","",IF(M7="",IF(J7=0,"New","—"),IF(M7<TODAY(),"Overdue",IF(M7-TODAY()<=3,"Due soon","Scheduled"))))
J8: =IF($A8="","",COUNTIFS(Jobs!$C$5:$C$1004,$A8)) | K8: =IF($A8="","",SUMIFS(Jobs!$J$5:$J$1004,Jobs!$C$5:$C$1004,$A8)) | L8: =IF(OR($A8="",J8=0),"",_xlfn.MAXIFS(Jobs!$B$5:$B$1004,Jobs!$C$5:$C$1004,$A8)) | M8: =IF(OR($A8="",L8=""),"",IFERROR(IF(INDEX(Settings!$E$33:$E$37,MATCH(F8,Settings!$D$33:$D$37,0))="","",L8+INDEX(Settings!$E$33:$E$37,MATCH(F8,Settings!$D$33:$D$37,0))),"")) | N8: =IF($A8="","",IF(M8="",IF(J8=0,"New","—"),IF(M8<TODAY(),"Overdue",IF(M8-TODAY()<=3,"Due soon","Scheduled"))))
J9: =IF($A9="","",COUNTIFS(Jobs!$C$5:$C$1004,$A9)) | K9: =IF($A9="","",SUMIFS(Jobs!$J$5:$J$1004,Jobs!$C$5:$C$1004,$A9)) | L9: =IF(OR($A9="",J9=0),"",_xlfn.MAXIFS(Jobs!$B$5:$B$1004,Jobs!$C$5:$C$1004,$A9)) | M9: =IF(OR($A9="",L9=""),"",IFERROR(IF(INDEX(Settings!$E$33:$E$37,MATCH(F9,Settings!$D$33:$D$37,0))="","",L9+INDEX(Settings!$E$33:$E$37,MATCH(F9,Settings!$D$33:$D$37,0))),"")) | N9: =IF($A9="","",IF(M9="",IF(J9=0,"New","—"),IF(M9<TODAY(),"Overdue",IF(M9-TODAY()<=3,"Due soon","Scheduled"))))
J10: =IF($A10="","",COUNTIFS(Jobs!$C$5:$C$1004,$A10)) | K10: =IF($A10="","",SUMIFS(Jobs!$J$5:$J$1004,Jobs!$C$5:$C$1004,$A10)) | L10: =IF(OR($A10="",J10=0),"",_xlfn.MAXIFS(Jobs!$B$5:$B$1004,Jobs!$C$5:$C$1004,$A10)) | M10: =IF(OR($A10="",L10=""),"",IFERROR(IF(INDEX(Settings!$E$33:$E$37,MATCH(F10,Settings!$D$33:$D$37,0))="","",L10+INDEX(Settings!$E$33:$E$37,MATCH(F10,Settings!$D$33:$D$37,0))),"")) | N10: =IF($A10="","",IF(M10="",IF(J10=0,"New","—"),IF(M10<TODAY(),"Overdue",IF(M10-TODAY()<=3,"Due soon","Scheduled"))))
J11: =IF($A11="","",COUNTIFS(Jobs!$C$5:$C$1004,$A11)) | K11: =IF($A11="","",SUMIFS(Jobs!$J$5:$J$1004,Jobs!$C$5:$C$1004,$A11)) | L11: =IF(OR($A11="",J11=0),"",_xlfn.MAXIFS(Jobs!$B$5:$B$1004,Jobs!$C$5:$C$1004,$A11)) | M11: =IF(OR($A11="",L11=""),"",IFERROR(IF(INDEX(Settings!$E$33:$E$37,MATCH(F11,Settings!$D$33:$D$37,0))="","",L11+INDEX(Settings!$E$33:$E$37,MATCH(F11,Settings!$D$33:$D$37,0))),"")) | N11: =IF($A11="","",IF(M11="",IF(J11=0,"New","—"),IF(M11<TODAY(),"Overdue",IF(M11-TODAY()<=3,"Due soon","Scheduled"))))
J12: =IF($A12="","",COUNTIFS(Jobs!$C$5:$C$1004,$A12)) | K12: =IF($A12="","",SUMIFS(Jobs!$J$5:$J$1004,Jobs!$C$5:$C$1004,$A12)) | L12: =IF(OR($A12="",J12=0),"",_xlfn.MAXIFS(Jobs!$B$5:$B$1004,Jobs!$C$5:$C$1004,$A12)) | M12: =IF(OR($A12="",L12=""),"",IFERROR(IF(INDEX(Settings!$E$33:$E$37,MATCH(F12,Settings!$D$33:$D$37,0))="","",L12+INDEX(Settings!$E$33:$E$37,MATCH(F12,Settings!$D$33:$D$37,0))),"")) | N12: =IF($A12="","",IF(M12="",IF(J12=0,"New","—"),IF(M12<TODAY(),"Overdue",IF(M12-TODAY()<=3,"Due soon","Scheduled"))))
J13: =IF($A13="","",COUNTIFS(Jobs!$C$5:$C$1004,$A13)) | K13: =IF($A13="","",SUMIFS(Jobs!$J$5:$J$1004,Jobs!$C$5:$C$1004,$A13)) | L13: =IF(OR($A13="",J13=0),"",_xlfn.MAXIFS(Jobs!$B$5:$B$1004,Jobs!$C$5:$C$1004,$A13)) | M13: =IF(OR($A13="",L13=""),"",IFERROR(IF(INDEX(Settings!$E$33:$E$37,MATCH(F13,Settings!$D$33:$D$37,0))="","",L13+INDEX(Settings!$E$33:$E$37,MATCH(F13,Settings!$D$33:$D$37,0))),"")) | N13: =IF($A13="","",IF(M13="",IF(J13=0,"New","—"),IF(M13<TODAY(),"Overdue",IF(M13-TODAY()<=3,"Due soon","Scheduled"))))
J14: =IF($A14="","",COUNTIFS(Jobs!$C$5:$C$1004,$A14)) | K14: =IF($A14="","",SUMIFS(Jobs!$J$5:$J$1004,Jobs!$C$5:$C$1004,$A14)) | L14: =IF(OR($A14="",J14=0),"",_xlfn.MAXIFS(Jobs!$B$5:$B$1004,Jobs!$C$5:$C$1004,$A14)) | M14: =IF(OR($A14="",L14=""),"",IFERROR(IF(INDEX(Settings!$E$33:$E$37,MATCH(F14,Settings!$D$33:$D$37,0))="","",L14+INDEX(Settings!$E$33:$E$37,MATCH(F14,Settings!$D$33:$D$37,0))),"")) | N14: =IF($A14="","",IF(M14="",IF(J14=0,"New","—"),IF(M14<TODAY(),"Overdue",IF(M14-TODAY()<=3,"Due soon","Scheduled"))))
J15: =IF($A15="","",COUNTIFS(Jobs!$C$5:$C$1004,$A15)) | K15: =IF($A15="","",SUMIFS(Jobs!$J$5:$J$1004,Jobs!$C$5:$C$1004,$A15)) | L15: =IF(OR($A15="",J15=0),"",_xlfn.MAXIFS(Jobs!$B$5:$B$1004,Jobs!$C$5:$C$1004,$A15)) | M15: =IF(OR($A15="",L15=""),"",IFERROR(IF(INDEX(Settings!$E$33:$E$37,MATCH(F15,Settings!$D$33:$D$37,0))="","",L15+INDEX(Settings!$E$33:$E$37,MATCH(F15,Settings!$D$33:$D$37,0))),"")) | N15: =IF($A15="","",IF(M15="",IF(J15=0,"New","—"),IF(M15<TODAY(),"Overdue",IF(M15-TODAY()<=3,"Due soon","Scheduled"))))
J16: =IF($A16="","",COUNTIFS(Jobs!$C$5:$C$1004,$A16)) | K16: =IF($A16="","",SUMIFS(Jobs!$J$5:$J$1004,Jobs!$C$5:$C$1004,$A16)) | L16: =IF(OR($A16="",J16=0),"",_xlfn.MAXIFS(Jobs!$B$5:$B$1004,Jobs!$C$5:$C$1004,$A16)) | M16: =IF(OR($A16="",L16=""),"",IFERROR(IF(INDEX(Settings!$E$33:$E$37,MATCH(F16,Settings!$D$33:$D$37,0))="","",L16+INDEX(Settings!$E$33:$E$37,MATCH(F16,Settings!$D$33:$D$37,0))),"")) | N16: =IF($A16="","",IF(M16="",IF(J16=0,"New","—"),IF(M16<TODAY(),"Overdue",IF(M16-TODAY()<=3,"Due soon","Scheduled"))))
J17: =IF($A17="","",COUNTIFS(Jobs!$C$5:$C$1004,$A17)) | K17: =IF($A17="","",SUMIFS(Jobs!$J$5:$J$1004,Jobs!$C$5:$C$1004,$A17)) | L17: =IF(OR($A17="",J17=0),"",_xlfn.MAXIFS(Jobs!$B$5:$B$1004,Jobs!$C$5:$C$1004,$A17)) | M17: =IF(OR($A17="",L17=""),"",IFERROR(IF(INDEX(Settings!$E$33:$E$37,MATCH(F17,Settings!$D$33:$D$37,0))="","",L17+INDEX(Settings!$E$33:$E$37,MATCH(F17,Settings!$D$33:$D$37,0))),"")) | N17: =IF($A17="","",IF(M17="",IF(J17=0,"New","—"),IF(M17<TODAY(),"Overdue",IF(M17-TODAY()<=3,"Due soon","Scheduled"))))
J18: =IF($A18="","",COUNTIFS(Jobs!$C$5:$C$1004,$A18)) | K18: =IF($A18="","",SUMIFS(Jobs!$J$5:$J$1004,Jobs!$C$5:$C$1004,$A18)) | L18: =IF(OR($A18="",J18=0),"",_xlfn.MAXIFS(Jobs!$B$5:$B$1004,Jobs!$C$5:$C$1004,$A18)) | M18: =IF(OR($A18="",L18=""),"",IFERROR(IF(INDEX(Settings!$E$33:$E$37,MATCH(F18,Settings!$D$33:$D$37,0))="","",L18+INDEX(Settings!$E$33:$E$37,MATCH(F18,Settings!$D$33:$D$37,0))),"")) | N18: =IF($A18="","",IF(M18="",IF(J18=0,"New","—"),IF(M18<TODAY(),"Overdue",IF(M18-TODAY()<=3,"Due soon","Scheduled"))))
... J304: =IF($A304="","",COUNTIFS(Jobs!$C$5:$C$1004,$A304)) | K304: =IF($A304="","",SUMIFS(Jobs!$J$5:$J$1004,Jobs!$C$5:$C$1004,$A304)) | L304: =IF(OR($A304="",J304=0),"",_xlfn.MAXIFS(Jobs!$B$5:$B$1004,Jobs!$C$5:$C$1004,$A304)) | M304: =IF(OR($A304="",L304=""),"",IFERROR(IF(INDEX(Settings!$E$33:$E$37,MATCH(F304,Settings!$D$33:$D$37,0))="","",L304+INDEX(Settings!$E$33:$E$37,MATCH(F304,Settings!$D$33:$D$37,0))),"")) | N304: =IF($A304="","",IF(M304="",IF(J304=0,"New","—"),IF(M304<TODAY(),"Overdue",IF(M304-TODAY()<=3,"Due soon","Scheduled"))))

Sheet Jobs
A1: Jobs
A2: Log every visit. Price fills in from the client; type a Price override to change one job.
A4: Job ID | B4: Date | C4: Client | D4: Service | E4: Hours | F4: Sitter | G4: Price override | H4: Price | I4: Add-on charges | J4: Total charged | K4: Paid? | L4: Payment method | M4: Supplies cost | N4: Miles | O4: Labor cost | P4: Mileage cost | Q4: Profit | R4: Notes
A5: =IF(B5="","","J-"&TEXT(ROW()-4,"0000")) -> J-0001 | B5: 46296 | C5: EXAMPLE – Johnson Family | E5: 0.5 | F5: Me | H5: =IF(C5="","",IF(G5<>"",G5,IFERROR(INDEX(Clients!$G$5:$G$304,MATCH(C5,Clients!$A$5:$A$304,0)),0))) -> 25 | I5: 10 | J5: =IF(C5="","",H5+N(I5)) -> 35 | K5: Yes | L5: Zelle | M5: 1.5 | N5: 4 | O5: =IF(C5="","",N(E5)*Settings!$B$8) -> 9 | P5: =IF(C5="","",N(N5)*Settings!$B$10) -> 2.8 | Q5: =IF(C5="","",J5-N(M5)-O5-P5) -> 21.7
A6: =IF(B6="","","J-"&TEXT(ROW()-4,"0000")) -> J-0002 | B6: 46294 | C6: EXAMPLE – Patel Family | E6: 0.5 | F6: Sitter 2 | H6: =IF(C6="","",IF(G6<>"",G6,IFERROR(INDEX(Clients!$G$5:$G$304,MATCH(C6,Clients!$A$5:$A$304,0)),0))) -> 28 | I6: 0 | J6: =IF(C6="","",H6+N(I6)) -> 28 | K6: Yes | L6: Card | M6: 0 | N6: 6 | O6: =IF(C6="","",N(E6)*Settings!$B$8) -> 9 | P6: =IF(C6="","",N(N6)*Settings!$B$10) -> 4.2 | Q6: =IF(C6="","",J6-N(M6)-O6-P6) -> 14.8
A7: =IF(B7="","","J-"&TEXT(ROW()-4,"0000")) -> J-0003 | B7: 46308 | C7: EXAMPLE – Patel Family | E7: 0.5 | F7: Sitter 2 | H7: =IF(C7="","",IF(G7<>"",G7,IFERROR(INDEX(Clients!$G$5:$G$304,MATCH(C7,Clients!$A$5:$A$304,0)),0))) -> 28 | I7: 8 | J7: =IF(C7="","",H7+N(I7)) -> 36 | K7: No | M7: 0 | N7: 6 | O7: =IF(C7="","",N(E7)*Settings!$B$8) -> 9 | P7: =IF(C7="","",N(N7)*Settings!$B$10) -> 4.2 | Q7: =IF(C7="","",J7-N(M7)-O7-P7) -> 22.8
A8: =IF(B8="","","J-"&TEXT(ROW()-4,"0000")) | H8: =IF(C8="","",IF(G8<>"",G8,IFERROR(INDEX(Clients!$G$5:$G$304,MATCH(C8,Clients!$A$5:$A$304,0)),0))) | J8: =IF(C8="","",H8+N(I8)) | O8: =IF(C8="","",N(E8)*Settings!$B$8) | P8: =IF(C8="","",N(N8)*Settings!$B$10) | Q8: =IF(C8="","",J8-N(M8)-O8-P8)
A9: =IF(B9="","","J-"&TEXT(ROW()-4,"0000")) | H9: =IF(C9="","",IF(G9<>"",G9,IFERROR(INDEX(Clients!$G$5:$G$304,MATCH(C9,Clients!$A$5:$A$304,0)),0))) | J9: =IF(C9="","",H9+N(I9)) | O9: =IF(C9="","",N(E9)*Settings!$B$8) | P9: =IF(C9="","",N(N9)*Settings!$B$10) | Q9: =IF(C9="","",J9-N(M9)-O9-P9)
A10: =IF(B10="","","J-"&TEXT(ROW()-4,"0000")) | H10: =IF(C10="","",IF(G10<>"",G10,IFERROR(INDEX(Clients!$G$5:$G$304,MATCH(C10,Clients!$A$5:$A$304,0)),0))) | J10: =IF(C10="","",H10+N(I10)) | O10: =IF(C10="","",N(E10)*Settings!$B$8) | P10: =IF(C10="","",N(N10)*Settings!$B$10) | Q10: =IF(C10="","",J10-N(M10)-O10-P10)
A11: =IF(B11="","","J-"&TEXT(ROW()-4,"0000")) | H11: =IF(C11="","",IF(G11<>"",G11,IFERROR(INDEX(Clients!$G$5:$G$304,MATCH(C11,Clients!$A$5:$A$304,0)),0))) | J11: =IF(C11="","",H11+N(I11)) | O11: =IF(C11="","",N(E11)*Settings!$B$8) | P11: =IF(C11="","",N(N11)*Settings!$B$10) | Q11: =IF(C11="","",J11-N(M11)-O11-P11)
A12: =IF(B12="","","J-"&TEXT(ROW()-4,"0000")) | H12: =IF(C12="","",IF(G12<>"",G12,IFERROR(INDEX(Clients!$G$5:$G$304,MATCH(C12,Clients!$A$5:$A$304,0)),0))) | J12: =IF(C12="","",H12+N(I12)) | O12: =IF(C12="","",N(E12)*Settings!$B$8) | P12: =IF(C12="","",N(N12)*Settings!$B$10) | Q12: =IF(C12="","",J12-N(M12)-O12-P12)
A13: =IF(B13="","","J-"&TEXT(ROW()-4,"0000")) | H13: =IF(C13="","",IF(G13<>"",G13,IFERROR(INDEX(Clients!$G$5:$G$304,MATCH(C13,Clients!$A$5:$A$304,0)),0))) | J13: =IF(C13="","",H13+N(I13)) | O13: =IF(C13="","",N(E13)*Settings!$B$8) | P13: =IF(C13="","",N(N13)*Settings!$B$10) | Q13: =IF(C13="","",J13-N(M13)-O13-P13)
A14: =IF(B14="","","J-"&TEXT(ROW()-4,"0000")) | H14: =IF(C14="","",IF(G14<>"",G14,IFERROR(INDEX(Clients!$G$5:$G$304,MATCH(C14,Clients!$A$5:$A$304,0)),0))) | J14: =IF(C14="","",H14+N(I14)) | O14: =IF(C14="","",N(E14)*Settings!$B$8) | P14: =IF(C14="","",N(N14)*Settings!$B$10) | Q14: =IF(C14="","",J14-N(M14)-O14-P14)
A15: =IF(B15="","","J-"&TEXT(ROW()-4,"0000")) | H15: =IF(C15="","",IF(G15<>"",G15,IFERROR(INDEX(Clients!$G$5:$G$304,MATCH(C15,Clients!$A$5:$A$304,0)),0))) | J15: =IF(C15="","",H15+N(I15)) | O15: =IF(C15="","",N(E15)*Settings!$B$8) | P15: =IF(C15="","",N(N15)*Settings!$B$10) | Q15: =IF(C15="","",J15-N(M15)-O15-P15)
A16: =IF(B16="","","J-"&TEXT(ROW()-4,"0000")) | H16: =IF(C16="","",IF(G16<>"",G16,IFERROR(INDEX(Clients!$G$5:$G$304,MATCH(C16,Clients!$A$5:$A$304,0)),0))) | J16: =IF(C16="","",H16+N(I16)) | O16: =IF(C16="","",N(E16)*Settings!$B$8) | P16: =IF(C16="","",N(N16)*Settings!$B$10) | Q16: =IF(C16="","",J16-N(M16)-O16-P16)
A17: =IF(B17="","","J-"&TEXT(ROW()-4,"0000")) | H17: =IF(C17="","",IF(G17<>"",G17,IFERROR(INDEX(Clients!$G$5:$G$304,MATCH(C17,Clients!$A$5:$A$304,0)),0))) | J17: =IF(C17="","",H17+N(I17)) | O17: =IF(C17="","",N(E17)*Settings!$B$8) | P17: =IF(C17="","",N(N17)*Settings!$B$10) | Q17: =IF(C17="","",J17-N(M17)-O17-P17)
A18: =IF(B18="","","J-"&TEXT(ROW()-4,"0000")) | H18: =IF(C18="","",IF(G18<>"",G18,IFERROR(INDEX(Clients!$G$5:$G$304,MATCH(C18,Clients!$A$5:$A$304,0)),0))) | J18: =IF(C18="","",H18+N(I18)) | O18: =IF(C18="","",N(E18)*Settings!$B$8) | P18: =IF(C18="","",N(N18)*Settings!$B$10) | Q18: =IF(C18="","",J18-N(M18)-O18-P18)
A19: =IF(B19="","","J-"&TEXT(ROW()-4,"0000")) | H19: =IF(C19="","",IF(G19<>"",G19,IFERROR(INDEX(Clients!$G$5:$G$304,MATCH(C19,Clients!$A$5:$A$304,0)),0))) | J19: =IF(C19="","",H19+N(I19)) | O19: =IF(C19="","",N(E19)*Settings!$B$8) | P19: =IF(C19="","",N(N19)*Settings!$B$10) | Q19: =IF(C19="","",J19-N(M19)-O19-P19)
... A1004: =IF(B1004="","","J-"&TEXT(ROW()-4,"0000")) | H1004: =IF(C1004="","",IF(G1004<>"",G1004,IFERROR(INDEX(Clients!$G$5:$G$304,MATCH(C1004,Clients!$A$5:$A$304,0)),0))) | J1004: =IF(C1004="","",H1004+N(I1004)) | O1004: =IF(C1004="","",N(E1004)*Settings!$B$8) | P1004: =IF(C1004="","",N(N1004)*Settings!$B$10) | Q1004: =IF(C1004="","",J1004-N(M1004)-O1004-P1004)

Sheet Expenses
A1: Expenses
A2: Every business cost that isn't already on a job (supplies on a job go in the Jobs tab).
A4: Date | B4: Category | C4: Vendor | D4: Description | E4: Amount | F4: Paid with | G4: Receipt saved?
A5: 46298 | B5: Treats & pet supplies | C5: Pet supply store | D5: EXAMPLE – Poop bags, treats, towels | E5: 34.2 | F5: Card | G5: Yes
A6: 46300 | B6: Insurance & bonding | C6: Pet Sitters Associates | D6: EXAMPLE – Monthly pet sitter liability policy | E6: 24 | F6: Card | G6: Yes

Sheet Quote Calculator
A1: Quote Calculator
A2: Price a new client in under a minute. Change the yellow cells.
D3: Add-ons (Yes/No)
A4: Service | B4: Dog Walk (30 min) | D4: =IF(Settings!D24="","",Settings!D24) -> Holiday / short-notice fee | E4: No
A5: Travel miles (one way) | B5: 8 | D5: =IF(Settings!D25="","",Settings!D25) -> Extra 15 minutes | E5: Yes
A6: Number of pets | B6: 2 | D6: =IF(Settings!D26="","",Settings!D26) -> Litter box / cage clean | E6: No
A7: Medications / special-care tasks | B7: 1 | D7: =IF(Settings!D27="","",Settings!D27) -> Plants, mail & trash | E7: No
A8: Frequency | B8: Weekly | D8: =IF(Settings!D28="","",Settings!D28) -> Bath & brush | E8: No
D9: =IF(Settings!D29="","",Settings!D29) -> Training reinforcement | E9: No
A11: RESULT
A12: Base price | B12: =IFERROR(INDEX(Settings!$E$5:$E$12,MATCH(B4,Settings!$D$5:$D$12,0)),0) -> 25
A13: Extra pet adjustment | B13: =MAX(0,B6-1)*Settings!$E$15 -> 8
A14: Medication / special care | B14: =MAX(0,B7)*Settings!$E$16 -> 5
A15: Travel adjustment | B15: =MAX(0,ROUNDUP((B5-5)/5,0))*Settings!$E$17 -> 3
A16: Add-ons | B16: =SUMIFS(Settings!$E$24:$E$29,Settings!$D$24:$D$29,"<>",E4:E9,"Yes") -> 10
A17: Subtotal | B17: =SUM(B12:B16) -> 51
A18: Frequency discount | B18: =-B17*IFERROR(INDEX(Settings!$F$33:$F$37,MATCH(B8,Settings!$D$33:$D$37,0)),0) -> -2.55
A19: QUOTE PRICE | B19: =ROUND(B17+B18,0) -> 48
A21: Estimated hours | B21: =IFERROR(INDEX(Settings!$F$5:$F$12,MATCH(B4,Settings!$D$5:$D$12,0)),0)+MAX(0,B6-1)*Settings!$E$18+MAX(0,B7)*Settings!$E$19+MAX(0,ROUNDUP((B5-5)/5,0))*Settings!$E$20+SUMIFS(Settings!$F$24:$F$29,Settings!$D$24:$D$29,"<>",E4:E9,"Yes") -> 1.1
A22: Labor cost | B22: =B21*Settings!$B$8 -> 19.8
A23: Profit before supplies & travel | B23: =B19-B22 -> 28.2
A24: Effective rate per hour | B24: =IF(B21=0,0,B19/B21) -> 43.636364
A26: Quote factors and add-on prices are set in Settings. The defaults are examples — set your own rates.

Sheet Invoice
A1: Invoice | D1: INVOICE
A2: Type a Job ID in the yellow cell. Print or download as PDF.
A4: Job ID → | B4: J-0003
A6: =Settings!B4 -> Happy Tails Pet Care | D6: Invoice # | E6: =IF(A12="","","INV-"&MID(B4,3,10)) -> INV-0003
A7: =Settings!B5 -> Your Name | D7: Service date | E7: =IFERROR(INDEX(Jobs!$B$5:$B$1004,MATCH($B$4,Jobs!$A$5:$A$1004,0)),"") -> 46308
A8: =Settings!B6 -> (555) 555-0123 | D8: Due date | E8: =IF(E7="","",E7+Settings!$B$11) -> 46322
A9: =Settings!B7 -> hello@example.com | D9: Status | E9: =IF(A12="","",IF(IFERROR(INDEX(Jobs!$K$5:$K$1004,MATCH($B$4,Jobs!$A$5:$A$1004,0)),"")="Yes","PAID","DUE")) -> DUE
A11: BILL TO
A12: =IFERROR(INDEX(Jobs!$C$5:$C$1004,MATCH($B$4,Jobs!$A$5:$A$1004,0))&"","") -> EXAMPLE – Patel Family
A13: =IFERROR(INDEX(Clients!$D$5:$D$304,MATCH(A12,Clients!$A$5:$A$304,0))&"","") -> 400 Main St
A14: =IFERROR(INDEX(Clients!$C$5:$C$304,MATCH(A12,Clients!$A$5:$A$304,0))&"","") -> patel@example.com
A16: Description | E16: Amount
A17: =IF(A12="","",IF(IFERROR(INDEX(Jobs!$D$5:$D$1004,MATCH($B$4,Jobs!$A$5:$A$1004,0)),"")<>"",IFERROR(INDEX(Jobs!$D$5:$D$1004,MATCH($B$4,Jobs!$A$5:$A$1004,0)),""),IFERROR(IF(INDEX(Clients!$E$5:$E$304,MATCH(A12,Clients!$A$5:$A$304,0))&""="",NA(),INDEX(Clients!$E$5:$E$304,MATCH(A12,Clients!$A$5:$A$304,0))&""),"Pet care service"))) -> Drop-in Visit (30 min) | E17: =IFERROR(INDEX(Jobs!$H$5:$H$1004,MATCH($B$4,Jobs!$A$5:$A$1004,0)),"") -> 28
A18: Add-on services | E18: =IFERROR(INDEX(Jobs!$I$5:$I$1004,MATCH($B$4,Jobs!$A$5:$A$1004,0)),"") -> 8
D20: TOTAL | E20: =IF(A12="","",N(E17)+N(E18)) -> 36
A23: Thank you for your business!
A24: ="Payment due within "&Settings!$B$11&" days." -> Payment due within 14 days.

Sheet Settings
A1: Settings
A2: Your business details and defaults. Every yellow cell is editable.
D3: SERVICES | H3: EXPENSE CATEGORIES
A4: Business name | B4: Happy Tails Pet Care | D4: Service | E4: Base price | F4: Est. hours | H4: Treats & pet supplies
A5: Owner / contact | B5: Your Name | D5: Dog Walk (30 min) | E5: 25 | F5: 0.5 | H5: Fuel
A6: Phone | B6: (555) 555-0123 | D6: Dog Walk (60 min) | E6: 40 | F6: 1 | H6: Leashes & gear
A7: Email | B7: hello@example.com | D7: Drop-in Visit (30 min) | E7: 28 | F7: 0.5 | H7: Insurance & bonding
A8: Hourly labor cost (what you pay per sitter-hour) | B8: 18 | D8: Overnight Stay | E8: 90 | F8: 4 | H8: Background check
A9: Tax set-aside % of profit | B9: 0.25 | D9: Puppy Visit | E9: 30 | F9: 0.5 | H9: Advertising
A10: Mileage rate per mile | B10: 0.7 | D10: Pet Taxi | E10: 35 | F10: 0.75 | H10: Vehicle
A11: Invoice due in (days) | B11: 14 | H11: Booking app fees
H12: Subcontractors
H13: Other
D14: QUOTE FACTORS
D15: Per extra pet (over 1) | E15: 8
D16: Per medication / special-care task | E16: 5
D17: Per 5 miles of travel over 5 | E17: 3 | H17: PAYMENT METHODS
D18: Extra hours per extra pet | E18: 0.1 | H18: Cash
D19: Extra hours per medication / task | E19: 0.1 | H19: Card
D20: Extra hours per 5 miles over 5 | E20: 0.15 | H20: Check
H21: Zelle
D22: ADD-ONS | H22: Venmo
D23: Add-on | E23: Price | F23: Hours | H23: Bank transfer
D24: Holiday / short-notice fee | E24: 15 | F24: 0
D25: Extra 15 minutes | E25: 10 | F25: 0.25
D26: Litter box / cage clean | E26: 8 | F26: 0.15
D27: Plants, mail & trash | E27: 5 | F27: 0.1 | H27: SITTERS / STAFF
D28: Bath & brush | E28: 30 | F28: 0.75 | H28: Me
D29: Training reinforcement | E29: 12 | F29: 0.25 | H29: Sitter 2
D31: FREQUENCY
D32: Frequency | E32: Days between | F32: Discount
D33: Daily | E33: 1 | F33: 0.1
D34: Weekly | E34: 7 | F34: 0.05
D35: Every 2 weeks | E35: 14 | F35: 0
D36: Monthly | E36: 30 | F36: 0
D37: One-time | F37: 0
