Workbook

Sheet Start Here
A1: Airbnb Host Business Manager
A2: Bookings · Turnovers · Occupancy & ADR · Expenses · Supplies · Profit dashboard: Google Sheets & Excel
B4: HOW TO USE
B5: 1. Settings | C5: Your business name, tax set-aside %, length-of-stay discounts, booking channels with their fee %, expense categories and cleaner names.
B6: 2. Properties | C6: One row per listing: nightly and weekend rate, cleaning fee, what you pay your cleaner, guests included and the extra-guest fee. Each row shows whether it's occupied today and the next check-in.
B7: 3. Bookings | C7: Log every reservation: property, guest, channel, check-in and check-out. Nights, rent (weekday/weekend aware), cleaning fee, platform fee, payout and your net fill in. Type the real payout from your platform in 'Actual payout' to use it instead of the estimate. Double bookings are flagged.
B8: 4. Turnovers | C8: Your cleaning schedule: every upcoming check-out, the next check-in at that property, the gap, and same-day turnover alerts. Assign the cleaner and tick Done in Bookings.
B9: 5. Expenses | C9: Mortgage or rent, utilities, repairs, supplies, software, insurance. Pick the property, or leave it blank for costs shared across all properties.
B10: 6. Supplies | C10: Par levels for toilet paper, coffee, soap and linens. Items at or below the reorder level turn red with the order quantity and cost.
B11: 7. Pricing Calculator | C11: Price any stay before you accept it (rent, fees, platform cut, cleaning cost and net per night), and find the nightly rate you need to break even.
B12: 8. Dashboard & Monthly Summary | C12: Pick a year. See payout, profit, occupancy, ADR and RevPAR per property and by month. Monthly Summary drills into one property.
B14: COLOR KEY
B15: Yellow cell, blue text | C15: Type here: your inputs
B16: White cell, black text | C16: Calculated automatically. Don't type over these.
B18: KEY TERMS
B19: Occupancy | C19: Booked nights ÷ nights available.
B20: ADR | C20: Average daily rate: rent ÷ booked nights (cleaning and other fees not included).
B21: RevPAR | C21: Rent ÷ nights available. Combines price and occupancy in one number.
B22: Payout | C22: What the platform pays you after its host fee (or the actual payout you type in).
B23: Split months | C23: A stay that crosses into a new month is split by nights, so each month gets its fair share.
B25: GOOGLE SHEETS
C26: Upload this file to Google Drive, open it, then File > Save as Google Sheets. Everything works in both Excel and Google Sheets.
C27: The example rows (marked EXAMPLE) show the format. Delete them when you start. After that, clear a booking row instead of deleting it, so Booking IDs stay the same.
C28: Default fees and rates are examples. Check your own platform fees. Expense categories are an organizing aid, not tax advice. Not affiliated with or endorsed by Airbnb, Inc. or Vrbo.

Sheet Dashboard
A1: Dashboard
A2: Pick a year. Everything updates from Properties, Bookings and Expenses.
A4: Year | B4: 2026 | D4: All properties
A6: Payout | C6: Profit | E6: Occupancy | F6: ADR (avg nightly rate) | H6: Unpaid direct bookings | I6: Tax set-aside
A7: =F22 -> 1241.6 | C7: =I22 -> 949.43 | E7: =C22 -> 0.01369863 | F7: =D22 -> 201 | H7: =SUMIFS(Bookings!$Q$5:$Q$1004,Bookings!$U$5:$U$1004,"No",Bookings!$AA$5:$AA$1004,1) -> 582 | I7: =MAX(0,I22)*Settings!$B$8 -> 237.3575
A9: Month | B9: Nights booked | C9: Occupancy | D9: ADR | E9: RevPAR | F9: Payout | G9: Cleaning costs | H9: Expenses | I9: Profit | K9: Nights available | L9: Rent
A10: =TEXT(DATE($B$4,1,1),"mmm yyyy") -> Jan 2026 | B10: =SUMPRODUCT(Bookings!$AA$5:$AA$1004*(($D$4="All properties")+(Bookings!$D$5:$D$1004=$D$4)>0)*(((((Bookings!$C$5:$C$1004+DATE($B$4,2,1)-ABS(Bookings!$C$5:$C$1004-DATE($B$4,2,1)))/2)-((Bookings!$B$5:$B$1004+DATE($B$4,1,1)+ABS(Bookings!$B$5:$B$1004-DATE($B$4,1,1)))/2))+ABS(((Bookings!$C$5:$C$1004+DATE($B$4,2,1)-ABS(Bookings!$C$5:$C$1004-DATE($B$4,2,1)))/2)-((Bookings!$B$5:$B$1004+DATE($B$4,1,1)+ABS(Bookings!$B$5:$B$1004-DATE($B$4,1,1)))/2)))/2)) -> 0 | C10: =IF(K10=0,0,B10/K10) -> 0 | D10: =IF(B10=0,0,L10/B10) -> 0 | E10: =IF(K10=0,0,L10/K10) -> 0 | F10: =SUMPRODUCT(Bookings!$AA$5:$AA$1004*(($D$4="All properties")+(Bookings!$D$5:$D$1004=$D$4)>0)*(((((Bookings!$C$5:$C$1004+DATE($B$4,2,1)-ABS(Bookings!$C$5:$C$1004-DATE($B$4,2,1)))/2)-((Bookings!$B$5:$B$1004+DATE($B$4,1,1)+ABS(Bookings!$B$5:$B$1004-DATE($B$4,1,1)))/2))+ABS(((Bookings!$C$5:$C$1004+DATE($B$4,2,1)-ABS(Bookings!$C$5:$C$1004-DATE($B$4,2,1)))/2)-((Bookings!$B$5:$B$1004+DATE($B$4,1,1)+ABS(Bookings!$B$5:$B$1004-DATE($B$4,1,1)))/2)))/2)*Bookings!$AC$5:$AC$1004) -> 0 | G10: =SUMPRODUCT(Bookings!$AA$5:$AA$1004*(($D$4="All properties")+(Bookings!$D$5:$D$1004=$D$4)>0)*(((((Bookings!$C$5:$C$1004+DATE($B$4,2,1)-ABS(Bookings!$C$5:$C$1004-DATE($B$4,2,1)))/2)-((Bookings!$B$5:$B$1004+DATE($B$4,1,1)+ABS(Bookings!$B$5:$B$1004-DATE($B$4,1,1)))/2))+ABS(((Bookings!$C$5:$C$1004+DATE($B$4,2,1)-ABS(Bookings!$C$5:$C$1004-DATE($B$4,2,1)))/2)-((Bookings!$B$5:$B$1004+DATE($B$4,1,1)+ABS(Bookings!$B$5:$B$1004-DATE($B$4,1,1)))/2)))/2)*Bookings!$AD$5:$AD$1004) -> 0 | H10: =IF($D$4="All properties",SUMIFS(Expenses!$F$5:$F$1004,Expenses!$A$5:$A$1004,">="&DATE($B$4,1,1),Expenses!$A$5:$A$1004,"<"&DATE($B$4,2,1)),SUMIFS(Expenses!$F$5:$F$1004,Expenses!$A$5:$A$1004,">="&DATE($B$4,1,1),Expenses!$A$5:$A$1004,"<"&DATE($B$4,2,1),Expenses!$B$5:$B$1004,$D$4)) -> 0 | I10: =F10-G10-H10 -> 0 | K10: =SUMPRODUCT((Properties!$A$5:$A$24<>"")*(($D$4="All properties")+(Properties!$A$5:$A$24=$D$4)>0)*(((DATE($B$4,2,1)-((Properties!$K$5:$K$24+DATE($B$4,1,1)+ABS(Properties!$K$5:$K$24-DATE($B$4,1,1)))/2))+ABS(DATE($B$4,2,1)-((Properties!$K$5:$K$24+DATE($B$4,1,1)+ABS(Properties!$K$5:$K$24-DATE($B$4,1,1)))/2)))/2)) -> 31 | L10: =SUMPRODUCT(Bookings!$AA$5:$AA$1004*(($D$4="All properties")+(Bookings!$D$5:$D$1004=$D$4)>0)*(((((Bookings!$C$5:$C$1004+DATE($B$4,2,1)-ABS(Bookings!$C$5:$C$1004-DATE($B$4,2,1)))/2)-((Bookings!$B$5:$B$1004+DATE($B$4,1,1)+ABS(Bookings!$B$5:$B$1004-DATE($B$4,1,1)))/2))+ABS(((Bookings!$C$5:$C$1004+DATE($B$4,2,1)-ABS(Bookings!$C$5:$C$1004-DATE($B$4,2,1)))/2)-((Bookings!$B$5:$B$1004+DATE($B$4,1,1)+ABS(Bookings!$B$5:$B$1004-DATE($B$4,1,1)))/2)))/2)*Bookings!$AB$5:$AB$1004) -> 0
A11: =TEXT(DATE($B$4,2,1),"mmm yyyy") -> Feb 2026 | B11: =SUMPRODUCT(Bookings!$AA$5:$AA$1004*(($D$4="All properties")+(Bookings!$D$5:$D$1004=$D$4)>0)*(((((Bookings!$C$5:$C$1004+DATE($B$4,3,1)-ABS(Bookings!$C$5:$C$1004-DATE($B$4,3,1)))/2)-((Bookings!$B$5:$B$1004+DATE($B$4,2,1)+ABS(Bookings!$B$5:$B$1004-DATE($B$4,2,1)))/2))+ABS(((Bookings!$C$5:$C$1004+DATE($B$4,3,1)-ABS(Bookings!$C$5:$C$1004-DATE($B$4,3,1)))/2)-((Bookings!$B$5:$B$1004+DATE($B$4,2,1)+ABS(Bookings!$B$5:$B$1004-DATE($B$4,2,1)))/2)))/2)) -> 0 | C11: =IF(K11=0,0,B11/K11) -> 0 | D11: =IF(B11=0,0,L11/B11) -> 0 | E11: =IF(K11=0,0,L11/K11) -> 0 | F11: =SUMPRODUCT(Bookings!$AA$5:$AA$1004*(($D$4="All properties")+(Bookings!$D$5:$D$1004=$D$4)>0)*(((((Bookings!$C$5:$C$1004+DATE($B$4,3,1)-ABS(Bookings!$C$5:$C$1004-DATE($B$4,3,1)))/2)-((Bookings!$B$5:$B$1004+DATE($B$4,2,1)+ABS(Bookings!$B$5:$B$1004-DATE($B$4,2,1)))/2))+ABS(((Bookings!$C$5:$C$1004+DATE($B$4,3,1)-ABS(Bookings!$C$5:$C$1004-DATE($B$4,3,1)))/2)-((Bookings!$B$5:$B$1004+DATE($B$4,2,1)+ABS(Bookings!$B$5:$B$1004-DATE($B$4,2,1)))/2)))/2)*Bookings!$AC$5:$AC$1004) -> 0 | G11: =SUMPRODUCT(Bookings!$AA$5:$AA$1004*(($D$4="All properties")+(Bookings!$D$5:$D$1004=$D$4)>0)*(((((Bookings!$C$5:$C$1004+DATE($B$4,3,1)-ABS(Bookings!$C$5:$C$1004-DATE($B$4,3,1)))/2)-((Bookings!$B$5:$B$1004+DATE($B$4,2,1)+ABS(Bookings!$B$5:$B$1004-DATE($B$4,2,1)))/2))+ABS(((Bookings!$C$5:$C$1004+DATE($B$4,3,1)-ABS(Bookings!$C$5:$C$1004-DATE($B$4,3,1)))/2)-((Bookings!$B$5:$B$1004+DATE($B$4,2,1)+ABS(Bookings!$B$5:$B$1004-DATE($B$4,2,1)))/2)))/2)*Bookings!$AD$5:$AD$1004) -> 0 | H11: =IF($D$4="All properties",SUMIFS(Expenses!$F$5:$F$1004,Expenses!$A$5:$A$1004,">="&DATE($B$4,2,1),Expenses!$A$5:$A$1004,"<"&DATE($B$4,3,1)),SUMIFS(Expenses!$F$5:$F$1004,Expenses!$A$5:$A$1004,">="&DATE($B$4,2,1),Expenses!$A$5:$A$1004,"<"&DATE($B$4,3,1),Expenses!$B$5:$B$1004,$D$4)) -> 0 | I11: =F11-G11-H11 -> 0 | K11: =SUMPRODUCT((Properties!$A$5:$A$24<>"")*(($D$4="All properties")+(Properties!$A$5:$A$24=$D$4)>0)*(((DATE($B$4,3,1)-((Properties!$K$5:$K$24+DATE($B$4,2,1)+ABS(Properties!$K$5:$K$24-DATE($B$4,2,1)))/2))+ABS(DATE($B$4,3,1)-((Properties!$K$5:$K$24+DATE($B$4,2,1)+ABS(Properties!$K$5:$K$24-DATE($B$4,2,1)))/2)))/2)) -> 28 | L11: =SUMPRODUCT(Bookings!$AA$5:$AA$1004*(($D$4="All properties")+(Bookings!$D$5:$D$1004=$D$4)>0)*(((((Bookings!$C$5:$C$1004+DATE($B$4,3,1)-ABS(Bookings!$C$5:$C$1004-DATE($B$4,3,1)))/2)-((Bookings!$B$5:$B$1004+DATE($B$4,2,1)+ABS(Bookings!$B$5:$B$1004-DATE($B$4,2,1)))/2))+ABS(((Bookings!$C$5:$C$1004+DATE($B$4,3,1)-ABS(Bookings!$C$5:$C$1004-DATE($B$4,3,1)))/2)-((Bookings!$B$5:$B$1004+DATE($B$4,2,1)+ABS(Bookings!$B$5:$B$1004-DATE($B$4,2,1)))/2)))/2)*Bookings!$AB$5:$AB$1004) -> 0
A12: =TEXT(DATE($B$4,3,1),"mmm yyyy") -> Mar 2026 | B12: =SUMPRODUCT(Bookings!$AA$5:$AA$1004*(($D$4="All properties")+(Bookings!$D$5:$D$1004=$D$4)>0)*(((((Bookings!$C$5:$C$1004+DATE($B$4,4,1)-ABS(Bookings!$C$5:$C$1004-DATE($B$4,4,1)))/2)-((Bookings!$B$5:$B$1004+DATE($B$4,3,1)+ABS(Bookings!$B$5:$B$1004-DATE($B$4,3,1)))/2))+ABS(((Bookings!$C$5:$C$1004+DATE($B$4,4,1)-ABS(Bookings!$C$5:$C$1004-DATE($B$4,4,1)))/2)-((Bookings!$B$5:$B$1004+DATE($B$4,3,1)+ABS(Bookings!$B$5:$B$1004-DATE($B$4,3,1)))/2)))/2)) -> 0 | C12: =IF(K12=0,0,B12/K12) -> 0 | D12: =IF(B12=0,0,L12/B12) -> 0 | E12: =IF(K12=0,0,L12/K12) -> 0 | F12: =SUMPRODUCT(Bookings!$AA$5:$AA$1004*(($D$4="All properties")+(Bookings!$D$5:$D$1004=$D$4)>0)*(((((Bookings!$C$5:$C$1004+DATE($B$4,4,1)-ABS(Bookings!$C$5:$C$1004-DATE($B$4,4,1)))/2)-((Bookings!$B$5:$B$1004+DATE($B$4,3,1)+ABS(Bookings!$B$5:$B$1004-DATE($B$4,3,1)))/2))+ABS(((Bookings!$C$5:$C$1004+DATE($B$4,4,1)-ABS(Bookings!$C$5:$C$1004-DATE($B$4,4,1)))/2)-((Bookings!$B$5:$B$1004+DATE($B$4,3,1)+ABS(Bookings!$B$5:$B$1004-DATE($B$4,3,1)))/2)))/2)*Bookings!$AC$5:$AC$1004) -> 0 | G12: =SUMPRODUCT(Bookings!$AA$5:$AA$1004*(($D$4="All properties")+(Bookings!$D$5:$D$1004=$D$4)>0)*(((((Bookings!$C$5:$C$1004+DATE($B$4,4,1)-ABS(Bookings!$C$5:$C$1004-DATE($B$4,4,1)))/2)-((Bookings!$B$5:$B$1004+DATE($B$4,3,1)+ABS(Bookings!$B$5:$B$1004-DATE($B$4,3,1)))/2))+ABS(((Bookings!$C$5:$C$1004+DATE($B$4,4,1)-ABS(Bookings!$C$5:$C$1004-DATE($B$4,4,1)))/2)-((Bookings!$B$5:$B$1004+DATE($B$4,3,1)+ABS(Bookings!$B$5:$B$1004-DATE($B$4,3,1)))/2)))/2)*Bookings!$AD$5:$AD$1004) -> 0 | H12: =IF($D$4="All properties",SUMIFS(Expenses!$F$5:$F$1004,Expenses!$A$5:$A$1004,">="&DATE($B$4,3,1),Expenses!$A$5:$A$1004,"<"&DATE($B$4,4,1)),SUMIFS(Expenses!$F$5:$F$1004,Expenses!$A$5:$A$1004,">="&DATE($B$4,3,1),Expenses!$A$5:$A$1004,"<"&DATE($B$4,4,1),Expenses!$B$5:$B$1004,$D$4)) -> 0 | I12: =F12-G12-H12 -> 0 | K12: =SUMPRODUCT((Properties!$A$5:$A$24<>"")*(($D$4="All properties")+(Properties!$A$5:$A$24=$D$4)>0)*(((DATE($B$4,4,1)-((Properties!$K$5:$K$24+DATE($B$4,3,1)+ABS(Properties!$K$5:$K$24-DATE($B$4,3,1)))/2))+ABS(DATE($B$4,4,1)-((Properties!$K$5:$K$24+DATE($B$4,3,1)+ABS(Properties!$K$5:$K$24-DATE($B$4,3,1)))/2)))/2)) -> 31 | L12: =SUMPRODUCT(Bookings!$AA$5:$AA$1004*(($D$4="All properties")+(Bookings!$D$5:$D$1004=$D$4)>0)*(((((Bookings!$C$5:$C$1004+DATE($B$4,4,1)-ABS(Bookings!$C$5:$C$1004-DATE($B$4,4,1)))/2)-((Bookings!$B$5:$B$1004+DATE($B$4,3,1)+ABS(Bookings!$B$5:$B$1004-DATE($B$4,3,1)))/2))+ABS(((Bookings!$C$5:$C$1004+DATE($B$4,4,1)-ABS(Bookings!$C$5:$C$1004-DATE($B$4,4,1)))/2)-((Bookings!$B$5:$B$1004+DATE($B$4,3,1)+ABS(Bookings!$B$5:$B$1004-DATE($B$4,3,1)))/2)))/2)*Bookings!$AB$5:$AB$1004) -> 0
A13: =TEXT(DATE($B$4,4,1),"mmm yyyy") -> Apr 2026 | B13: =SUMPRODUCT(Bookings!$AA$5:$AA$1004*(($D$4="All properties")+(Bookings!$D$5:$D$1004=$D$4)>0)*(((((Bookings!$C$5:$C$1004+DATE($B$4,5,1)-ABS(Bookings!$C$5:$C$1004-DATE($B$4,5,1)))/2)-((Bookings!$B$5:$B$1004+DATE($B$4,4,1)+ABS(Bookings!$B$5:$B$1004-DATE($B$4,4,1)))/2))+ABS(((Bookings!$C$5:$C$1004+DATE($B$4,5,1)-ABS(Bookings!$C$5:$C$1004-DATE($B$4,5,1)))/2)-((Bookings!$B$5:$B$1004+DATE($B$4,4,1)+ABS(Bookings!$B$5:$B$1004-DATE($B$4,4,1)))/2)))/2)) -> 0 | C13: =IF(K13=0,0,B13/K13) -> 0 | D13: =IF(B13=0,0,L13/B13) -> 0 | E13: =IF(K13=0,0,L13/K13) -> 0 | F13: =SUMPRODUCT(Bookings!$AA$5:$AA$1004*(($D$4="All properties")+(Bookings!$D$5:$D$1004=$D$4)>0)*(((((Bookings!$C$5:$C$1004+DATE($B$4,5,1)-ABS(Bookings!$C$5:$C$1004-DATE($B$4,5,1)))/2)-((Bookings!$B$5:$B$1004+DATE($B$4,4,1)+ABS(Bookings!$B$5:$B$1004-DATE($B$4,4,1)))/2))+ABS(((Bookings!$C$5:$C$1004+DATE($B$4,5,1)-ABS(Bookings!$C$5:$C$1004-DATE($B$4,5,1)))/2)-((Bookings!$B$5:$B$1004+DATE($B$4,4,1)+ABS(Bookings!$B$5:$B$1004-DATE($B$4,4,1)))/2)))/2)*Bookings!$AC$5:$AC$1004) -> 0 | G13: =SUMPRODUCT(Bookings!$AA$5:$AA$1004*(($D$4="All properties")+(Bookings!$D$5:$D$1004=$D$4)>0)*(((((Bookings!$C$5:$C$1004+DATE($B$4,5,1)-ABS(Bookings!$C$5:$C$1004-DATE($B$4,5,1)))/2)-((Bookings!$B$5:$B$1004+DATE($B$4,4,1)+ABS(Bookings!$B$5:$B$1004-DATE($B$4,4,1)))/2))+ABS(((Bookings!$C$5:$C$1004+DATE($B$4,5,1)-ABS(Bookings!$C$5:$C$1004-DATE($B$4,5,1)))/2)-((Bookings!$B$5:$B$1004+DATE($B$4,4,1)+ABS(Bookings!$B$5:$B$1004-DATE($B$4,4,1)))/2)))/2)*Bookings!$AD$5:$AD$1004) -> 0 | H13: =IF($D$4="All properties",SUMIFS(Expenses!$F$5:$F$1004,Expenses!$A$5:$A$1004,">="&DATE($B$4,4,1),Expenses!$A$5:$A$1004,"<"&DATE($B$4,5,1)),SUMIFS(Expenses!$F$5:$F$1004,Expenses!$A$5:$A$1004,">="&DATE($B$4,4,1),Expenses!$A$5:$A$1004,"<"&DATE($B$4,5,1),Expenses!$B$5:$B$1004,$D$4)) -> 0 | I13: =F13-G13-H13 -> 0 | K13: =SUMPRODUCT((Properties!$A$5:$A$24<>"")*(($D$4="All properties")+(Properties!$A$5:$A$24=$D$4)>0)*(((DATE($B$4,5,1)-((Properties!$K$5:$K$24+DATE($B$4,4,1)+ABS(Properties!$K$5:$K$24-DATE($B$4,4,1)))/2))+ABS(DATE($B$4,5,1)-((Properties!$K$5:$K$24+DATE($B$4,4,1)+ABS(Properties!$K$5:$K$24-DATE($B$4,4,1)))/2)))/2)) -> 30 | L13: =SUMPRODUCT(Bookings!$AA$5:$AA$1004*(($D$4="All properties")+(Bookings!$D$5:$D$1004=$D$4)>0)*(((((Bookings!$C$5:$C$1004+DATE($B$4,5,1)-ABS(Bookings!$C$5:$C$1004-DATE($B$4,5,1)))/2)-((Bookings!$B$5:$B$1004+DATE($B$4,4,1)+ABS(Bookings!$B$5:$B$1004-DATE($B$4,4,1)))/2))+ABS(((Bookings!$C$5:$C$1004+DATE($B$4,5,1)-ABS(Bookings!$C$5:$C$1004-DATE($B$4,5,1)))/2)-((Bookings!$B$5:$B$1004+DATE($B$4,4,1)+ABS(Bookings!$B$5:$B$1004-DATE($B$4,4,1)))/2)))/2)*Bookings!$AB$5:$AB$1004) -> 0
A14: =TEXT(DATE($B$4,5,1),"mmm yyyy") -> May 2026 | B14: =SUMPRODUCT(Bookings!$AA$5:$AA$1004*(($D$4="All properties")+(Bookings!$D$5:$D$1004=$D$4)>0)*(((((Bookings!$C$5:$C$1004+DATE($B$4,6,1)-ABS(Bookings!$C$5:$C$1004-DATE($B$4,6,1)))/2)-((Bookings!$B$5:$B$1004+DATE($B$4,5,1)+ABS(Bookings!$B$5:$B$1004-DATE($B$4,5,1)))/2))+ABS(((Bookings!$C$5:$C$1004+DATE($B$4,6,1)-ABS(Bookings!$C$5:$C$1004-DATE($B$4,6,1)))/2)-((Bookings!$B$5:$B$1004+DATE($B$4,5,1)+ABS(Bookings!$B$5:$B$1004-DATE($B$4,5,1)))/2)))/2)) -> 0 | C14: =IF(K14=0,0,B14/K14) -> 0 | D14: =IF(B14=0,0,L14/B14) -> 0 | E14: =IF(K14=0,0,L14/K14) -> 0 | F14: =SUMPRODUCT(Bookings!$AA$5:$AA$1004*(($D$4="All properties")+(Bookings!$D$5:$D$1004=$D$4)>0)*(((((Bookings!$C$5:$C$1004+DATE($B$4,6,1)-ABS(Bookings!$C$5:$C$1004-DATE($B$4,6,1)))/2)-((Bookings!$B$5:$B$1004+DATE($B$4,5,1)+ABS(Bookings!$B$5:$B$1004-DATE($B$4,5,1)))/2))+ABS(((Bookings!$C$5:$C$1004+DATE($B$4,6,1)-ABS(Bookings!$C$5:$C$1004-DATE($B$4,6,1)))/2)-((Bookings!$B$5:$B$1004+DATE($B$4,5,1)+ABS(Bookings!$B$5:$B$1004-DATE($B$4,5,1)))/2)))/2)*Bookings!$AC$5:$AC$1004) -> 0 | G14: =SUMPRODUCT(Bookings!$AA$5:$AA$1004*(($D$4="All properties")+(Bookings!$D$5:$D$1004=$D$4)>0)*(((((Bookings!$C$5:$C$1004+DATE($B$4,6,1)-ABS(Bookings!$C$5:$C$1004-DATE($B$4,6,1)))/2)-((Bookings!$B$5:$B$1004+DATE($B$4,5,1)+ABS(Bookings!$B$5:$B$1004-DATE($B$4,5,1)))/2))+ABS(((Bookings!$C$5:$C$1004+DATE($B$4,6,1)-ABS(Bookings!$C$5:$C$1004-DATE($B$4,6,1)))/2)-((Bookings!$B$5:$B$1004+DATE($B$4,5,1)+ABS(Bookings!$B$5:$B$1004-DATE($B$4,5,1)))/2)))/2)*Bookings!$AD$5:$AD$1004) -> 0 | H14: =IF($D$4="All properties",SUMIFS(Expenses!$F$5:$F$1004,Expenses!$A$5:$A$1004,">="&DATE($B$4,5,1),Expenses!$A$5:$A$1004,"<"&DATE($B$4,6,1)),SUMIFS(Expenses!$F$5:$F$1004,Expenses!$A$5:$A$1004,">="&DATE($B$4,5,1),Expenses!$A$5:$A$1004,"<"&DATE($B$4,6,1),Expenses!$B$5:$B$1004,$D$4)) -> 0 | I14: =F14-G14-H14 -> 0 | K14: =SUMPRODUCT((Properties!$A$5:$A$24<>"")*(($D$4="All properties")+(Properties!$A$5:$A$24=$D$4)>0)*(((DATE($B$4,6,1)-((Properties!$K$5:$K$24+DATE($B$4,5,1)+ABS(Properties!$K$5:$K$24-DATE($B$4,5,1)))/2))+ABS(DATE($B$4,6,1)-((Properties!$K$5:$K$24+DATE($B$4,5,1)+ABS(Properties!$K$5:$K$24-DATE($B$4,5,1)))/2)))/2)) -> 31 | L14: =SUMPRODUCT(Bookings!$AA$5:$AA$1004*(($D$4="All properties")+(Bookings!$D$5:$D$1004=$D$4)>0)*(((((Bookings!$C$5:$C$1004+DATE($B$4,6,1)-ABS(Bookings!$C$5:$C$1004-DATE($B$4,6,1)))/2)-((Bookings!$B$5:$B$1004+DATE($B$4,5,1)+ABS(Bookings!$B$5:$B$1004-DATE($B$4,5,1)))/2))+ABS(((Bookings!$C$5:$C$1004+DATE($B$4,6,1)-ABS(Bookings!$C$5:$C$1004-DATE($B$4,6,1)))/2)-((Bookings!$B$5:$B$1004+DATE($B$4,5,1)+ABS(Bookings!$B$5:$B$1004-DATE($B$4,5,1)))/2)))/2)*Bookings!$AB$5:$AB$1004) -> 0
A15: =TEXT(DATE($B$4,6,1),"mmm yyyy") -> Jun 2026 | B15: =SUMPRODUCT(Bookings!$AA$5:$AA$1004*(($D$4="All properties")+(Bookings!$D$5:$D$1004=$D$4)>0)*(((((Bookings!$C$5:$C$1004+DATE($B$4,7,1)-ABS(Bookings!$C$5:$C$1004-DATE($B$4,7,1)))/2)-((Bookings!$B$5:$B$1004+DATE($B$4,6,1)+ABS(Bookings!$B$5:$B$1004-DATE($B$4,6,1)))/2))+ABS(((Bookings!$C$5:$C$1004+DATE($B$4,7,1)-ABS(Bookings!$C$5:$C$1004-DATE($B$4,7,1)))/2)-((Bookings!$B$5:$B$1004+DATE($B$4,6,1)+ABS(Bookings!$B$5:$B$1004-DATE($B$4,6,1)))/2)))/2)) -> 0 | C15: =IF(K15=0,0,B15/K15) -> 0 | D15: =IF(B15=0,0,L15/B15) -> 0 | E15: =IF(K15=0,0,L15/K15) -> 0 | F15: =SUMPRODUCT(Bookings!$AA$5:$AA$1004*(($D$4="All properties")+(Bookings!$D$5:$D$1004=$D$4)>0)*(((((Bookings!$C$5:$C$1004+DATE($B$4,7,1)-ABS(Bookings!$C$5:$C$1004-DATE($B$4,7,1)))/2)-((Bookings!$B$5:$B$1004+DATE($B$4,6,1)+ABS(Bookings!$B$5:$B$1004-DATE($B$4,6,1)))/2))+ABS(((Bookings!$C$5:$C$1004+DATE($B$4,7,1)-ABS(Bookings!$C$5:$C$1004-DATE($B$4,7,1)))/2)-((Bookings!$B$5:$B$1004+DATE($B$4,6,1)+ABS(Bookings!$B$5:$B$1004-DATE($B$4,6,1)))/2)))/2)*Bookings!$AC$5:$AC$1004) -> 0 | G15: =SUMPRODUCT(Bookings!$AA$5:$AA$1004*(($D$4="All properties")+(Bookings!$D$5:$D$1004=$D$4)>0)*(((((Bookings!$C$5:$C$1004+DATE($B$4,7,1)-ABS(Bookings!$C$5:$C$1004-DATE($B$4,7,1)))/2)-((Bookings!$B$5:$B$1004+DATE($B$4,6,1)+ABS(Bookings!$B$5:$B$1004-DATE($B$4,6,1)))/2))+ABS(((Bookings!$C$5:$C$1004+DATE($B$4,7,1)-ABS(Bookings!$C$5:$C$1004-DATE($B$4,7,1)))/2)-((Bookings!$B$5:$B$1004+DATE($B$4,6,1)+ABS(Bookings!$B$5:$B$1004-DATE($B$4,6,1)))/2)))/2)*Bookings!$AD$5:$AD$1004) -> 0 | H15: =IF($D$4="All properties",SUMIFS(Expenses!$F$5:$F$1004,Expenses!$A$5:$A$1004,">="&DATE($B$4,6,1),Expenses!$A$5:$A$1004,"<"&DATE($B$4,7,1)),SUMIFS(Expenses!$F$5:$F$1004,Expenses!$A$5:$A$1004,">="&DATE($B$4,6,1),Expenses!$A$5:$A$1004,"<"&DATE($B$4,7,1),Expenses!$B$5:$B$1004,$D$4)) -> 0 | I15: =F15-G15-H15 -> 0 | K15: =SUMPRODUCT((Properties!$A$5:$A$24<>"")*(($D$4="All properties")+(Properties!$A$5:$A$24=$D$4)>0)*(((DATE($B$4,7,1)-((Properties!$K$5:$K$24+DATE($B$4,6,1)+ABS(Properties!$K$5:$K$24-DATE($B$4,6,1)))/2))+ABS(DATE($B$4,7,1)-((Properties!$K$5:$K$24+DATE($B$4,6,1)+ABS(Properties!$K$5:$K$24-DATE($B$4,6,1)))/2)))/2)) -> 30 | L15: =SUMPRODUCT(Bookings!$AA$5:$AA$1004*(($D$4="All properties")+(Bookings!$D$5:$D$1004=$D$4)>0)*(((((Bookings!$C$5:$C$1004+DATE($B$4,7,1)-ABS(Bookings!$C$5:$C$1004-DATE($B$4,7,1)))/2)-((Bookings!$B$5:$B$1004+DATE($B$4,6,1)+ABS(Bookings!$B$5:$B$1004-DATE($B$4,6,1)))/2))+ABS(((Bookings!$C$5:$C$1004+DATE($B$4,7,1)-ABS(Bookings!$C$5:$C$1004-DATE($B$4,7,1)))/2)-((Bookings!$B$5:$B$1004+DATE($B$4,6,1)+ABS(Bookings!$B$5:$B$1004-DATE($B$4,6,1)))/2)))/2)*Bookings!$AB$5:$AB$1004) -> 0
A16: =TEXT(DATE($B$4,7,1),"mmm yyyy") -> Jul 2026 | B16: =SUMPRODUCT(Bookings!$AA$5:$AA$1004*(($D$4="All properties")+(Bookings!$D$5:$D$1004=$D$4)>0)*(((((Bookings!$C$5:$C$1004+DATE($B$4,8,1)-ABS(Bookings!$C$5:$C$1004-DATE($B$4,8,1)))/2)-((Bookings!$B$5:$B$1004+DATE($B$4,7,1)+ABS(Bookings!$B$5:$B$1004-DATE($B$4,7,1)))/2))+ABS(((Bookings!$C$5:$C$1004+DATE($B$4,8,1)-ABS(Bookings!$C$5:$C$1004-DATE($B$4,8,1)))/2)-((Bookings!$B$5:$B$1004+DATE($B$4,7,1)+ABS(Bookings!$B$5:$B$1004-DATE($B$4,7,1)))/2)))/2)) -> 0 | C16: =IF(K16=0,0,B16/K16) -> 0 | D16: =IF(B16=0,0,L16/B16) -> 0 | E16: =IF(K16=0,0,L16/K16) -> 0 | F16: =SUMPRODUCT(Bookings!$AA$5:$AA$1004*(($D$4="All properties")+(Bookings!$D$5:$D$1004=$D$4)>0)*(((((Bookings!$C$5:$C$1004+DATE($B$4,8,1)-ABS(Bookings!$C$5:$C$1004-DATE($B$4,8,1)))/2)-((Bookings!$B$5:$B$1004+DATE($B$4,7,1)+ABS(Bookings!$B$5:$B$1004-DATE($B$4,7,1)))/2))+ABS(((Bookings!$C$5:$C$1004+DATE($B$4,8,1)-ABS(Bookings!$C$5:$C$1004-DATE($B$4,8,1)))/2)-((Bookings!$B$5:$B$1004+DATE($B$4,7,1)+ABS(Bookings!$B$5:$B$1004-DATE($B$4,7,1)))/2)))/2)*Bookings!$AC$5:$AC$1004) -> 0 | G16: =SUMPRODUCT(Bookings!$AA$5:$AA$1004*(($D$4="All properties")+(Bookings!$D$5:$D$1004=$D$4)>0)*(((((Bookings!$C$5:$C$1004+DATE($B$4,8,1)-ABS(Bookings!$C$5:$C$1004-DATE($B$4,8,1)))/2)-((Bookings!$B$5:$B$1004+DATE($B$4,7,1)+ABS(Bookings!$B$5:$B$1004-DATE($B$4,7,1)))/2))+ABS(((Bookings!$C$5:$C$1004+DATE($B$4,8,1)-ABS(Bookings!$C$5:$C$1004-DATE($B$4,8,1)))/2)-((Bookings!$B$5:$B$1004+DATE($B$4,7,1)+ABS(Bookings!$B$5:$B$1004-DATE($B$4,7,1)))/2)))/2)*Bookings!$AD$5:$AD$1004) -> 0 | H16: =IF($D$4="All properties",SUMIFS(Expenses!$F$5:$F$1004,Expenses!$A$5:$A$1004,">="&DATE($B$4,7,1),Expenses!$A$5:$A$1004,"<"&DATE($B$4,8,1)),SUMIFS(Expenses!$F$5:$F$1004,Expenses!$A$5:$A$1004,">="&DATE($B$4,7,1),Expenses!$A$5:$A$1004,"<"&DATE($B$4,8,1),Expenses!$B$5:$B$1004,$D$4)) -> 0 | I16: =F16-G16-H16 -> 0 | K16: =SUMPRODUCT((Properties!$A$5:$A$24<>"")*(($D$4="All properties")+(Properties!$A$5:$A$24=$D$4)>0)*(((DATE($B$4,8,1)-((Properties!$K$5:$K$24+DATE($B$4,7,1)+ABS(Properties!$K$5:$K$24-DATE($B$4,7,1)))/2))+ABS(DATE($B$4,8,1)-((Properties!$K$5:$K$24+DATE($B$4,7,1)+ABS(Properties!$K$5:$K$24-DATE($B$4,7,1)))/2)))/2)) -> 31 | L16: =SUMPRODUCT(Bookings!$AA$5:$AA$1004*(($D$4="All properties")+(Bookings!$D$5:$D$1004=$D$4)>0)*(((((Bookings!$C$5:$C$1004+DATE($B$4,8,1)-ABS(Bookings!$C$5:$C$1004-DATE($B$4,8,1)))/2)-((Bookings!$B$5:$B$1004+DATE($B$4,7,1)+ABS(Bookings!$B$5:$B$1004-DATE($B$4,7,1)))/2))+ABS(((Bookings!$C$5:$C$1004+DATE($B$4,8,1)-ABS(Bookings!$C$5:$C$1004-DATE($B$4,8,1)))/2)-((Bookings!$B$5:$B$1004+DATE($B$4,7,1)+ABS(Bookings!$B$5:$B$1004-DATE($B$4,7,1)))/2)))/2)*Bookings!$AB$5:$AB$1004) -> 0
A17: =TEXT(DATE($B$4,8,1),"mmm yyyy") -> Aug 2026 | B17: =SUMPRODUCT(Bookings!$AA$5:$AA$1004*(($D$4="All properties")+(Bookings!$D$5:$D$1004=$D$4)>0)*(((((Bookings!$C$5:$C$1004+DATE($B$4,9,1)-ABS(Bookings!$C$5:$C$1004-DATE($B$4,9,1)))/2)-((Bookings!$B$5:$B$1004+DATE($B$4,8,1)+ABS(Bookings!$B$5:$B$1004-DATE($B$4,8,1)))/2))+ABS(((Bookings!$C$5:$C$1004+DATE($B$4,9,1)-ABS(Bookings!$C$5:$C$1004-DATE($B$4,9,1)))/2)-((Bookings!$B$5:$B$1004+DATE($B$4,8,1)+ABS(Bookings!$B$5:$B$1004-DATE($B$4,8,1)))/2)))/2)) -> 0 | C17: =IF(K17=0,0,B17/K17) -> 0 | D17: =IF(B17=0,0,L17/B17) -> 0 | E17: =IF(K17=0,0,L17/K17) -> 0 | F17: =SUMPRODUCT(Bookings!$AA$5:$AA$1004*(($D$4="All properties")+(Bookings!$D$5:$D$1004=$D$4)>0)*(((((Bookings!$C$5:$C$1004+DATE($B$4,9,1)-ABS(Bookings!$C$5:$C$1004-DATE($B$4,9,1)))/2)-((Bookings!$B$5:$B$1004+DATE($B$4,8,1)+ABS(Bookings!$B$5:$B$1004-DATE($B$4,8,1)))/2))+ABS(((Bookings!$C$5:$C$1004+DATE($B$4,9,1)-ABS(Bookings!$C$5:$C$1004-DATE($B$4,9,1)))/2)-((Bookings!$B$5:$B$1004+DATE($B$4,8,1)+ABS(Bookings!$B$5:$B$1004-DATE($B$4,8,1)))/2)))/2)*Bookings!$AC$5:$AC$1004) -> 0 | G17: =SUMPRODUCT(Bookings!$AA$5:$AA$1004*(($D$4="All properties")+(Bookings!$D$5:$D$1004=$D$4)>0)*(((((Bookings!$C$5:$C$1004+DATE($B$4,9,1)-ABS(Bookings!$C$5:$C$1004-DATE($B$4,9,1)))/2)-((Bookings!$B$5:$B$1004+DATE($B$4,8,1)+ABS(Bookings!$B$5:$B$1004-DATE($B$4,8,1)))/2))+ABS(((Bookings!$C$5:$C$1004+DATE($B$4,9,1)-ABS(Bookings!$C$5:$C$1004-DATE($B$4,9,1)))/2)-((Bookings!$B$5:$B$1004+DATE($B$4,8,1)+ABS(Bookings!$B$5:$B$1004-DATE($B$4,8,1)))/2)))/2)*Bookings!$AD$5:$AD$1004) -> 0 | H17: =IF($D$4="All properties",SUMIFS(Expenses!$F$5:$F$1004,Expenses!$A$5:$A$1004,">="&DATE($B$4,8,1),Expenses!$A$5:$A$1004,"<"&DATE($B$4,9,1)),SUMIFS(Expenses!$F$5:$F$1004,Expenses!$A$5:$A$1004,">="&DATE($B$4,8,1),Expenses!$A$5:$A$1004,"<"&DATE($B$4,9,1),Expenses!$B$5:$B$1004,$D$4)) -> 0 | I17: =F17-G17-H17 -> 0 | K17: =SUMPRODUCT((Properties!$A$5:$A$24<>"")*(($D$4="All properties")+(Properties!$A$5:$A$24=$D$4)>0)*(((DATE($B$4,9,1)-((Properties!$K$5:$K$24+DATE($B$4,8,1)+ABS(Properties!$K$5:$K$24-DATE($B$4,8,1)))/2))+ABS(DATE($B$4,9,1)-((Properties!$K$5:$K$24+DATE($B$4,8,1)+ABS(Properties!$K$5:$K$24-DATE($B$4,8,1)))/2)))/2)) -> 31 | L17: =SUMPRODUCT(Bookings!$AA$5:$AA$1004*(($D$4="All properties")+(Bookings!$D$5:$D$1004=$D$4)>0)*(((((Bookings!$C$5:$C$1004+DATE($B$4,9,1)-ABS(Bookings!$C$5:$C$1004-DATE($B$4,9,1)))/2)-((Bookings!$B$5:$B$1004+DATE($B$4,8,1)+ABS(Bookings!$B$5:$B$1004-DATE($B$4,8,1)))/2))+ABS(((Bookings!$C$5:$C$1004+DATE($B$4,9,1)-ABS(Bookings!$C$5:$C$1004-DATE($B$4,9,1)))/2)-((Bookings!$B$5:$B$1004+DATE($B$4,8,1)+ABS(Bookings!$B$5:$B$1004-DATE($B$4,8,1)))/2)))/2)*Bookings!$AB$5:$AB$1004) -> 0
A18: =TEXT(DATE($B$4,9,1),"mmm yyyy") -> Sep 2026 | B18: =SUMPRODUCT(Bookings!$AA$5:$AA$1004*(($D$4="All properties")+(Bookings!$D$5:$D$1004=$D$4)>0)*(((((Bookings!$C$5:$C$1004+DATE($B$4,10,1)-ABS(Bookings!$C$5:$C$1004-DATE($B$4,10,1)))/2)-((Bookings!$B$5:$B$1004+DATE($B$4,9,1)+ABS(Bookings!$B$5:$B$1004-DATE($B$4,9,1)))/2))+ABS(((Bookings!$C$5:$C$1004+DATE($B$4,10,1)-ABS(Bookings!$C$5:$C$1004-DATE($B$4,10,1)))/2)-((Bookings!$B$5:$B$1004+DATE($B$4,9,1)+ABS(Bookings!$B$5:$B$1004-DATE($B$4,9,1)))/2)))/2)) -> 0 | C18: =IF(K18=0,0,B18/K18) -> 0 | D18: =IF(B18=0,0,L18/B18) -> 0 | E18: =IF(K18=0,0,L18/K18) -> 0 | F18: =SUMPRODUCT(Bookings!$AA$5:$AA$1004*(($D$4="All properties")+(Bookings!$D$5:$D$1004=$D$4)>0)*(((((Bookings!$C$5:$C$1004+DATE($B$4,10,1)-ABS(Bookings!$C$5:$C$1004-DATE($B$4,10,1)))/2)-((Bookings!$B$5:$B$1004+DATE($B$4,9,1)+ABS(Bookings!$B$5:$B$1004-DATE($B$4,9,1)))/2))+ABS(((Bookings!$C$5:$C$1004+DATE($B$4,10,1)-ABS(Bookings!$C$5:$C$1004-DATE($B$4,10,1)))/2)-((Bookings!$B$5:$B$1004+DATE($B$4,9,1)+ABS(Bookings!$B$5:$B$1004-DATE($B$4,9,1)))/2)))/2)*Bookings!$AC$5:$AC$1004) -> 0 | G18: =SUMPRODUCT(Bookings!$AA$5:$AA$1004*(($D$4="All properties")+(Bookings!$D$5:$D$1004=$D$4)>0)*(((((Bookings!$C$5:$C$1004+DATE($B$4,10,1)-ABS(Bookings!$C$5:$C$1004-DATE($B$4,10,1)))/2)-((Bookings!$B$5:$B$1004+DATE($B$4,9,1)+ABS(Bookings!$B$5:$B$1004-DATE($B$4,9,1)))/2))+ABS(((Bookings!$C$5:$C$1004+DATE($B$4,10,1)-ABS(Bookings!$C$5:$C$1004-DATE($B$4,10,1)))/2)-((Bookings!$B$5:$B$1004+DATE($B$4,9,1)+ABS(Bookings!$B$5:$B$1004-DATE($B$4,9,1)))/2)))/2)*Bookings!$AD$5:$AD$1004) -> 0 | H18: =IF($D$4="All properties",SUMIFS(Expenses!$F$5:$F$1004,Expenses!$A$5:$A$1004,">="&DATE($B$4,9,1),Expenses!$A$5:$A$1004,"<"&DATE($B$4,10,1)),SUMIFS(Expenses!$F$5:$F$1004,Expenses!$A$5:$A$1004,">="&DATE($B$4,9,1),Expenses!$A$5:$A$1004,"<"&DATE($B$4,10,1),Expenses!$B$5:$B$1004,$D$4)) -> 0 | I18: =F18-G18-H18 -> 0 | K18: =SUMPRODUCT((Properties!$A$5:$A$24<>"")*(($D$4="All properties")+(Properties!$A$5:$A$24=$D$4)>0)*(((DATE($B$4,10,1)-((Properties!$K$5:$K$24+DATE($B$4,9,1)+ABS(Properties!$K$5:$K$24-DATE($B$4,9,1)))/2))+ABS(DATE($B$4,10,1)-((Properties!$K$5:$K$24+DATE($B$4,9,1)+ABS(Properties!$K$5:$K$24-DATE($B$4,9,1)))/2)))/2)) -> 30 | L18: =SUMPRODUCT(Bookings!$AA$5:$AA$1004*(($D$4="All properties")+(Bookings!$D$5:$D$1004=$D$4)>0)*(((((Bookings!$C$5:$C$1004+DATE($B$4,10,1)-ABS(Bookings!$C$5:$C$1004-DATE($B$4,10,1)))/2)-((Bookings!$B$5:$B$1004+DATE($B$4,9,1)+ABS(Bookings!$B$5:$B$1004-DATE($B$4,9,1)))/2))+ABS(((Bookings!$C$5:$C$1004+DATE($B$4,10,1)-ABS(Bookings!$C$5:$C$1004-DATE($B$4,10,1)))/2)-((Bookings!$B$5:$B$1004+DATE($B$4,9,1)+ABS(Bookings!$B$5:$B$1004-DATE($B$4,9,1)))/2)))/2)*Bookings!$AB$5:$AB$1004) -> 0
A19: =TEXT(DATE($B$4,10,1),"mmm yyyy") -> Oct 2026 | B19: =SUMPRODUCT(Bookings!$AA$5:$AA$1004*(($D$4="All properties")+(Bookings!$D$5:$D$1004=$D$4)>0)*(((((Bookings!$C$5:$C$1004+DATE($B$4,11,1)-ABS(Bookings!$C$5:$C$1004-DATE($B$4,11,1)))/2)-((Bookings!$B$5:$B$1004+DATE($B$4,10,1)+ABS(Bookings!$B$5:$B$1004-DATE($B$4,10,1)))/2))+ABS(((Bookings!$C$5:$C$1004+DATE($B$4,11,1)-ABS(Bookings!$C$5:$C$1004-DATE($B$4,11,1)))/2)-((Bookings!$B$5:$B$1004+DATE($B$4,10,1)+ABS(Bookings!$B$5:$B$1004-DATE($B$4,10,1)))/2)))/2)) -> 5 | C19: =IF(K19=0,0,B19/K19) -> 0.16129032 | D19: =IF(B19=0,0,L19/B19) -> 201 | E19: =IF(K19=0,0,L19/K19) -> 32.419355 | F19: =SUMPRODUCT(Bookings!$AA$5:$AA$1004*(($D$4="All properties")+(Bookings!$D$5:$D$1004=$D$4)>0)*(((((Bookings!$C$5:$C$1004+DATE($B$4,11,1)-ABS(Bookings!$C$5:$C$1004-DATE($B$4,11,1)))/2)-((Bookings!$B$5:$B$1004+DATE($B$4,10,1)+ABS(Bookings!$B$5:$B$1004-DATE($B$4,10,1)))/2))+ABS(((Bookings!$C$5:$C$1004+DATE($B$4,11,1)-ABS(Bookings!$C$5:$C$1004-DATE($B$4,11,1)))/2)-((Bookings!$B$5:$B$1004+DATE($B$4,10,1)+ABS(Bookings!$B$5:$B$1004-DATE($B$4,10,1)))/2)))/2)*Bookings!$AC$5:$AC$1004) -> 1241.6 | G19: =SUMPRODUCT(Bookings!$AA$5:$AA$1004*(($D$4="All properties")+(Bookings!$D$5:$D$1004=$D$4)>0)*(((((Bookings!$C$5:$C$1004+DATE($B$4,11,1)-ABS(Bookings!$C$5:$C$1004-DATE($B$4,11,1)))/2)-((Bookings!$B$5:$B$1004+DATE($B$4,10,1)+ABS(Bookings!$B$5:$B$1004-DATE($B$4,10,1)))/2))+ABS(((Bookings!$C$5:$C$1004+DATE($B$4,11,1)-ABS(Bookings!$C$5:$C$1004-DATE($B$4,11,1)))/2)-((Bookings!$B$5:$B$1004+DATE($B$4,10,1)+ABS(Bookings!$B$5:$B$1004-DATE($B$4,10,1)))/2)))/2)*Bookings!$AD$5:$AD$1004) -> 130 | H19: =IF($D$4="All properties",SUMIFS(Expenses!$F$5:$F$1004,Expenses!$A$5:$A$1004,">="&DATE($B$4,10,1),Expenses!$A$5:$A$1004,"<"&DATE($B$4,11,1)),SUMIFS(Expenses!$F$5:$F$1004,Expenses!$A$5:$A$1004,">="&DATE($B$4,10,1),Expenses!$A$5:$A$1004,"<"&DATE($B$4,11,1),Expenses!$B$5:$B$1004,$D$4)) -> 162.17 | I19: =F19-G19-H19 -> 949.43 | K19: =SUMPRODUCT((Properties!$A$5:$A$24<>"")*(($D$4="All properties")+(Properties!$A$5:$A$24=$D$4)>0)*(((DATE($B$4,11,1)-((Properties!$K$5:$K$24+DATE($B$4,10,1)+ABS(Properties!$K$5:$K$24-DATE($B$4,10,1)))/2))+ABS(DATE($B$4,11,1)-((Properties!$K$5:$K$24+DATE($B$4,10,1)+ABS(Properties!$K$5:$K$24-DATE($B$4,10,1)))/2)))/2)) -> 31 | L19: =SUMPRODUCT(Bookings!$AA$5:$AA$1004*(($D$4="All properties")+(Bookings!$D$5:$D$1004=$D$4)>0)*(((((Bookings!$C$5:$C$1004+DATE($B$4,11,1)-ABS(Bookings!$C$5:$C$1004-DATE($B$4,11,1)))/2)-((Bookings!$B$5:$B$1004+DATE($B$4,10,1)+ABS(Bookings!$B$5:$B$1004-DATE($B$4,10,1)))/2))+ABS(((Bookings!$C$5:$C$1004+DATE($B$4,11,1)-ABS(Bookings!$C$5:$C$1004-DATE($B$4,11,1)))/2)-((Bookings!$B$5:$B$1004+DATE($B$4,10,1)+ABS(Bookings!$B$5:$B$1004-DATE($B$4,10,1)))/2)))/2)*Bookings!$AB$5:$AB$1004) -> 1005
A20: =TEXT(DATE($B$4,11,1),"mmm yyyy") -> Nov 2026 | B20: =SUMPRODUCT(Bookings!$AA$5:$AA$1004*(($D$4="All properties")+(Bookings!$D$5:$D$1004=$D$4)>0)*(((((Bookings!$C$5:$C$1004+DATE($B$4,12,1)-ABS(Bookings!$C$5:$C$1004-DATE($B$4,12,1)))/2)-((Bookings!$B$5:$B$1004+DATE($B$4,11,1)+ABS(Bookings!$B$5:$B$1004-DATE($B$4,11,1)))/2))+ABS(((Bookings!$C$5:$C$1004+DATE($B$4,12,1)-ABS(Bookings!$C$5:$C$1004-DATE($B$4,12,1)))/2)-((Bookings!$B$5:$B$1004+DATE($B$4,11,1)+ABS(Bookings!$B$5:$B$1004-DATE($B$4,11,1)))/2)))/2)) -> 0 | C20: =IF(K20=0,0,B20/K20) -> 0 | D20: =IF(B20=0,0,L20/B20) -> 0 | E20: =IF(K20=0,0,L20/K20) -> 0 | F20: =SUMPRODUCT(Bookings!$AA$5:$AA$1004*(($D$4="All properties")+(Bookings!$D$5:$D$1004=$D$4)>0)*(((((Bookings!$C$5:$C$1004+DATE($B$4,12,1)-ABS(Bookings!$C$5:$C$1004-DATE($B$4,12,1)))/2)-((Bookings!$B$5:$B$1004+DATE($B$4,11,1)+ABS(Bookings!$B$5:$B$1004-DATE($B$4,11,1)))/2))+ABS(((Bookings!$C$5:$C$1004+DATE($B$4,12,1)-ABS(Bookings!$C$5:$C$1004-DATE($B$4,12,1)))/2)-((Bookings!$B$5:$B$1004+DATE($B$4,11,1)+ABS(Bookings!$B$5:$B$1004-DATE($B$4,11,1)))/2)))/2)*Bookings!$AC$5:$AC$1004) -> 0 | G20: =SUMPRODUCT(Bookings!$AA$5:$AA$1004*(($D$4="All properties")+(Bookings!$D$5:$D$1004=$D$4)>0)*(((((Bookings!$C$5:$C$1004+DATE($B$4,12,1)-ABS(Bookings!$C$5:$C$1004-DATE($B$4,12,1)))/2)-((Bookings!$B$5:$B$1004+DATE($B$4,11,1)+ABS(Bookings!$B$5:$B$1004-DATE($B$4,11,1)))/2))+ABS(((Bookings!$C$5:$C$1004+DATE($B$4,12,1)-ABS(Bookings!$C$5:$C$1004-DATE($B$4,12,1)))/2)-((Bookings!$B$5:$B$1004+DATE($B$4,11,1)+ABS(Bookings!$B$5:$B$1004-DATE($B$4,11,1)))/2)))/2)*Bookings!$AD$5:$AD$1004) -> 0 | H20: =IF($D$4="All properties",SUMIFS(Expenses!$F$5:$F$1004,Expenses!$A$5:$A$1004,">="&DATE($B$4,11,1),Expenses!$A$5:$A$1004,"<"&DATE($B$4,12,1)),SUMIFS(Expenses!$F$5:$F$1004,Expenses!$A$5:$A$1004,">="&DATE($B$4,11,1),Expenses!$A$5:$A$1004,"<"&DATE($B$4,12,1),Expenses!$B$5:$B$1004,$D$4)) -> 0 | I20: =F20-G20-H20 -> 0 | K20: =SUMPRODUCT((Properties!$A$5:$A$24<>"")*(($D$4="All properties")+(Properties!$A$5:$A$24=$D$4)>0)*(((DATE($B$4,12,1)-((Properties!$K$5:$K$24+DATE($B$4,11,1)+ABS(Properties!$K$5:$K$24-DATE($B$4,11,1)))/2))+ABS(DATE($B$4,12,1)-((Properties!$K$5:$K$24+DATE($B$4,11,1)+ABS(Properties!$K$5:$K$24-DATE($B$4,11,1)))/2)))/2)) -> 30 | L20: =SUMPRODUCT(Bookings!$AA$5:$AA$1004*(($D$4="All properties")+(Bookings!$D$5:$D$1004=$D$4)>0)*(((((Bookings!$C$5:$C$1004+DATE($B$4,12,1)-ABS(Bookings!$C$5:$C$1004-DATE($B$4,12,1)))/2)-((Bookings!$B$5:$B$1004+DATE($B$4,11,1)+ABS(Bookings!$B$5:$B$1004-DATE($B$4,11,1)))/2))+ABS(((Bookings!$C$5:$C$1004+DATE($B$4,12,1)-ABS(Bookings!$C$5:$C$1004-DATE($B$4,12,1)))/2)-((Bookings!$B$5:$B$1004+DATE($B$4,11,1)+ABS(Bookings!$B$5:$B$1004-DATE($B$4,11,1)))/2)))/2)*Bookings!$AB$5:$AB$1004) -> 0
A21: =TEXT(DATE($B$4,12,1),"mmm yyyy") -> Dec 2026 | B21: =SUMPRODUCT(Bookings!$AA$5:$AA$1004*(($D$4="All properties")+(Bookings!$D$5:$D$1004=$D$4)>0)*(((((Bookings!$C$5:$C$1004+DATE($B$4,13,1)-ABS(Bookings!$C$5:$C$1004-DATE($B$4,13,1)))/2)-((Bookings!$B$5:$B$1004+DATE($B$4,12,1)+ABS(Bookings!$B$5:$B$1004-DATE($B$4,12,1)))/2))+ABS(((Bookings!$C$5:$C$1004+DATE($B$4,13,1)-ABS(Bookings!$C$5:$C$1004-DATE($B$4,13,1)))/2)-((Bookings!$B$5:$B$1004+DATE($B$4,12,1)+ABS(Bookings!$B$5:$B$1004-DATE($B$4,12,1)))/2)))/2)) -> 0 | C21: =IF(K21=0,0,B21/K21) -> 0 | D21: =IF(B21=0,0,L21/B21) -> 0 | E21: =IF(K21=0,0,L21/K21) -> 0 | F21: =SUMPRODUCT(Bookings!$AA$5:$AA$1004*(($D$4="All properties")+(Bookings!$D$5:$D$1004=$D$4)>0)*(((((Bookings!$C$5:$C$1004+DATE($B$4,13,1)-ABS(Bookings!$C$5:$C$1004-DATE($B$4,13,1)))/2)-((Bookings!$B$5:$B$1004+DATE($B$4,12,1)+ABS(Bookings!$B$5:$B$1004-DATE($B$4,12,1)))/2))+ABS(((Bookings!$C$5:$C$1004+DATE($B$4,13,1)-ABS(Bookings!$C$5:$C$1004-DATE($B$4,13,1)))/2)-((Bookings!$B$5:$B$1004+DATE($B$4,12,1)+ABS(Bookings!$B$5:$B$1004-DATE($B$4,12,1)))/2)))/2)*Bookings!$AC$5:$AC$1004) -> 0 | G21: =SUMPRODUCT(Bookings!$AA$5:$AA$1004*(($D$4="All properties")+(Bookings!$D$5:$D$1004=$D$4)>0)*(((((Bookings!$C$5:$C$1004+DATE($B$4,13,1)-ABS(Bookings!$C$5:$C$1004-DATE($B$4,13,1)))/2)-((Bookings!$B$5:$B$1004+DATE($B$4,12,1)+ABS(Bookings!$B$5:$B$1004-DATE($B$4,12,1)))/2))+ABS(((Bookings!$C$5:$C$1004+DATE($B$4,13,1)-ABS(Bookings!$C$5:$C$1004-DATE($B$4,13,1)))/2)-((Bookings!$B$5:$B$1004+DATE($B$4,12,1)+ABS(Bookings!$B$5:$B$1004-DATE($B$4,12,1)))/2)))/2)*Bookings!$AD$5:$AD$1004) -> 0 | H21: =IF($D$4="All properties",SUMIFS(Expenses!$F$5:$F$1004,Expenses!$A$5:$A$1004,">="&DATE($B$4,12,1),Expenses!$A$5:$A$1004,"<"&DATE($B$4,13,1)),SUMIFS(Expenses!$F$5:$F$1004,Expenses!$A$5:$A$1004,">="&DATE($B$4,12,1),Expenses!$A$5:$A$1004,"<"&DATE($B$4,13,1),Expenses!$B$5:$B$1004,$D$4)) -> 0 | I21: =F21-G21-H21 -> 0 | K21: =SUMPRODUCT((Properties!$A$5:$A$24<>"")*(($D$4="All properties")+(Properties!$A$5:$A$24=$D$4)>0)*(((DATE($B$4,13,1)-((Properties!$K$5:$K$24+DATE($B$4,12,1)+ABS(Properties!$K$5:$K$24-DATE($B$4,12,1)))/2))+ABS(DATE($B$4,13,1)-((Properties!$K$5:$K$24+DATE($B$4,12,1)+ABS(Properties!$K$5:$K$24-DATE($B$4,12,1)))/2)))/2)) -> 31 | L21: =SUMPRODUCT(Bookings!$AA$5:$AA$1004*(($D$4="All properties")+(Bookings!$D$5:$D$1004=$D$4)>0)*(((((Bookings!$C$5:$C$1004+DATE($B$4,13,1)-ABS(Bookings!$C$5:$C$1004-DATE($B$4,13,1)))/2)-((Bookings!$B$5:$B$1004+DATE($B$4,12,1)+ABS(Bookings!$B$5:$B$1004-DATE($B$4,12,1)))/2))+ABS(((Bookings!$C$5:$C$1004+DATE($B$4,13,1)-ABS(Bookings!$C$5:$C$1004-DATE($B$4,13,1)))/2)-((Bookings!$B$5:$B$1004+DATE($B$4,12,1)+ABS(Bookings!$B$5:$B$1004-DATE($B$4,12,1)))/2)))/2)*Bookings!$AB$5:$AB$1004) -> 0
A22: Year total | B22: =SUM(B10:B21) -> 5 | C22: =IF(K22=0,0,B22/K22) -> 0.01369863 | D22: =IF(B22=0,0,L22/B22) -> 201 | E22: =IF(K22=0,0,L22/K22) -> 2.7534247 | F22: =SUM(F10:F21) -> 1241.6 | G22: =SUM(G10:G21) -> 130 | H22: =SUM(H10:H21) -> 162.17 | I22: =SUM(I10:I21) -> 949.43 | K22: =SUM(K10:K21) -> 365 | L22: =SUM(L10:L21) -> 1005
A25: BY PROPERTY
A26: Property | B26: Nights booked | C26: Occupancy | D26: ADR | E26: RevPAR | F26: Payout | G26: Cleaning costs | H26: Expenses | I26: Profit
A27: =IF(Properties!A5="","",Properties!A5) -> EXAMPLE – Lakeview Cabin | B27: =IF($A27="","",SUMPRODUCT(Bookings!$AA$5:$AA$1004*(($A27="All properties")+(Bookings!$D$5:$D$1004=$A27)>0)*(((((Bookings!$C$5:$C$1004+DATE($B$4+1,1,1)-ABS(Bookings!$C$5:$C$1004-DATE($B$4+1,1,1)))/2)-((Bookings!$B$5:$B$1004+DATE($B$4,1,1)+ABS(Bookings!$B$5:$B$1004-DATE($B$4,1,1)))/2))+ABS(((Bookings!$C$5:$C$1004+DATE($B$4+1,1,1)-ABS(Bookings!$C$5:$C$1004-DATE($B$4+1,1,1)))/2)-((Bookings!$B$5:$B$1004+DATE($B$4,1,1)+ABS(Bookings!$B$5:$B$1004-DATE($B$4,1,1)))/2)))/2))) -> 5 | C27: =IF($A27="","",IF(K27=0,0,B27/K27)) -> 0.01369863 | D27: =IF($A27="","",IF(B27=0,0,L27/B27)) -> 201 | E27: =IF($A27="","",IF(K27=0,0,L27/K27)) -> 2.7534247 | F27: =IF($A27="","",SUMPRODUCT(Bookings!$AA$5:$AA$1004*(($A27="All properties")+(Bookings!$D$5:$D$1004=$A27)>0)*(((((Bookings!$C$5:$C$1004+DATE($B$4+1,1,1)-ABS(Bookings!$C$5:$C$1004-DATE($B$4+1,1,1)))/2)-((Bookings!$B$5:$B$1004+DATE($B$4,1,1)+ABS(Bookings!$B$5:$B$1004-DATE($B$4,1,1)))/2))+ABS(((Bookings!$C$5:$C$1004+DATE($B$4+1,1,1)-ABS(Bookings!$C$5:$C$1004-DATE($B$4+1,1,1)))/2)-((Bookings!$B$5:$B$1004+DATE($B$4,1,1)+ABS(Bookings!$B$5:$B$1004-DATE($B$4,1,1)))/2)))/2)*Bookings!$AC$5:$AC$1004)) -> 1241.6 | G27: =IF($A27="","",SUMPRODUCT(Bookings!$AA$5:$AA$1004*(($A27="All properties")+(Bookings!$D$5:$D$1004=$A27)>0)*(((((Bookings!$C$5:$C$1004+DATE($B$4+1,1,1)-ABS(Bookings!$C$5:$C$1004-DATE($B$4+1,1,1)))/2)-((Bookings!$B$5:$B$1004+DATE($B$4,1,1)+ABS(Bookings!$B$5:$B$1004-DATE($B$4,1,1)))/2))+ABS(((Bookings!$C$5:$C$1004+DATE($B$4+1,1,1)-ABS(Bookings!$C$5:$C$1004-DATE($B$4+1,1,1)))/2)-((Bookings!$B$5:$B$1004+DATE($B$4,1,1)+ABS(Bookings!$B$5:$B$1004-DATE($B$4,1,1)))/2)))/2)*Bookings!$AD$5:$AD$1004)) -> 130 | H27: =IF($A27="","",SUMIFS(Expenses!$F$5:$F$1004,Expenses!$A$5:$A$1004,">="&DATE($B$4,1,1),Expenses!$A$5:$A$1004,"<"&DATE($B$4+1,1,1),Expenses!$B$5:$B$1004,$A27)) -> 142.18 | I27: =IF($A27="","",F27-G27-H27) -> 969.42 | K27: =IF($A27="","",SUMPRODUCT((Properties!$A$5:$A$24<>"")*(($A27="All properties")+(Properties!$A$5:$A$24=$A27)>0)*(((DATE($B$4+1,1,1)-((Properties!$K$5:$K$24+DATE($B$4,1,1)+ABS(Properties!$K$5:$K$24-DATE($B$4,1,1)))/2))+ABS(DATE($B$4+1,1,1)-((Properties!$K$5:$K$24+DATE($B$4,1,1)+ABS(Properties!$K$5:$K$24-DATE($B$4,1,1)))/2)))/2))) -> 365 | L27: =IF($A27="","",SUMPRODUCT(Bookings!$AA$5:$AA$1004*(($A27="All properties")+(Bookings!$D$5:$D$1004=$A27)>0)*(((((Bookings!$C$5:$C$1004+DATE($B$4+1,1,1)-ABS(Bookings!$C$5:$C$1004-DATE($B$4+1,1,1)))/2)-((Bookings!$B$5:$B$1004+DATE($B$4,1,1)+ABS(Bookings!$B$5:$B$1004-DATE($B$4,1,1)))/2))+ABS(((Bookings!$C$5:$C$1004+DATE($B$4+1,1,1)-ABS(Bookings!$C$5:$C$1004-DATE($B$4+1,1,1)))/2)-((Bookings!$B$5:$B$1004+DATE($B$4,1,1)+ABS(Bookings!$B$5:$B$1004-DATE($B$4,1,1)))/2)))/2)*Bookings!$AB$5:$AB$1004)) -> 1005
A28: =IF(Properties!A6="","",Properties!A6) | B28: =IF($A28="","",SUMPRODUCT(Bookings!$AA$5:$AA$1004*(($A28="All properties")+(Bookings!$D$5:$D$1004=$A28)>0)*(((((Bookings!$C$5:$C$1004+DATE($B$4+1,1,1)-ABS(Bookings!$C$5:$C$1004-DATE($B$4+1,1,1)))/2)-((Bookings!$B$5:$B$1004+DATE($B$4,1,1)+ABS(Bookings!$B$5:$B$1004-DATE($B$4,1,1)))/2))+ABS(((Bookings!$C$5:$C$1004+DATE($B$4+1,1,1)-ABS(Bookings!$C$5:$C$1004-DATE($B$4+1,1,1)))/2)-((Bookings!$B$5:$B$1004+DATE($B$4,1,1)+ABS(Bookings!$B$5:$B$1004-DATE($B$4,1,1)))/2)))/2))) | C28: =IF($A28="","",IF(K28=0,0,B28/K28)) | D28: =IF($A28="","",IF(B28=0,0,L28/B28)) | E28: =IF($A28="","",IF(K28=0,0,L28/K28)) | F28: =IF($A28="","",SUMPRODUCT(Bookings!$AA$5:$AA$1004*(($A28="All properties")+(Bookings!$D$5:$D$1004=$A28)>0)*(((((Bookings!$C$5:$C$1004+DATE($B$4+1,1,1)-ABS(Bookings!$C$5:$C$1004-DATE($B$4+1,1,1)))/2)-((Bookings!$B$5:$B$1004+DATE($B$4,1,1)+ABS(Bookings!$B$5:$B$1004-DATE($B$4,1,1)))/2))+ABS(((Bookings!$C$5:$C$1004+DATE($B$4+1,1,1)-ABS(Bookings!$C$5:$C$1004-DATE($B$4+1,1,1)))/2)-((Bookings!$B$5:$B$1004+DATE($B$4,1,1)+ABS(Bookings!$B$5:$B$1004-DATE($B$4,1,1)))/2)))/2)*Bookings!$AC$5:$AC$1004)) | G28: =IF($A28="","",SUMPRODUCT(Bookings!$AA$5:$AA$1004*(($A28="All properties")+(Bookings!$D$5:$D$1004=$A28)>0)*(((((Bookings!$C$5:$C$1004+DATE($B$4+1,1,1)-ABS(Bookings!$C$5:$C$1004-DATE($B$4+1,1,1)))/2)-((Bookings!$B$5:$B$1004+DATE($B$4,1,1)+ABS(Bookings!$B$5:$B$1004-DATE($B$4,1,1)))/2))+ABS(((Bookings!$C$5:$C$1004+DATE($B$4+1,1,1)-ABS(Bookings!$C$5:$C$1004-DATE($B$4+1,1,1)))/2)-((Bookings!$B$5:$B$1004+DATE($B$4,1,1)+ABS(Bookings!$B$5:$B$1004-DATE($B$4,1,1)))/2)))/2)*Bookings!$AD$5:$AD$1004)) | H28: =IF($A28="","",SUMIFS(Expenses!$F$5:$F$1004,Expenses!$A$5:$A$1004,">="&DATE($B$4,1,1),Expenses!$A$5:$A$1004,"<"&DATE($B$4+1,1,1),Expenses!$B$5:$B$1004,$A28)) | I28: =IF($A28="","",F28-G28-H28) | K28: =IF($A28="","",SUMPRODUCT((Properties!$A$5:$A$24<>"")*(($A28="All properties")+(Properties!$A$5:$A$24=$A28)>0)*(((DATE($B$4+1,1,1)-((Properties!$K$5:$K$24+DATE($B$4,1,1)+ABS(Properties!$K$5:$K$24-DATE($B$4,1,1)))/2))+ABS(DATE($B$4+1,1,1)-((Properties!$K$5:$K$24+DATE($B$4,1,1)+ABS(Properties!$K$5:$K$24-DATE($B$4,1,1)))/2)))/2))) | L28: =IF($A28="","",SUMPRODUCT(Bookings!$AA$5:$AA$1004*(($A28="All properties")+(Bookings!$D$5:$D$1004=$A28)>0)*(((((Bookings!$C$5:$C$1004+DATE($B$4+1,1,1)-ABS(Bookings!$C$5:$C$1004-DATE($B$4+1,1,1)))/2)-((Bookings!$B$5:$B$1004+DATE($B$4,1,1)+ABS(Bookings!$B$5:$B$1004-DATE($B$4,1,1)))/2))+ABS(((Bookings!$C$5:$C$1004+DATE($B$4+1,1,1)-ABS(Bookings!$C$5:$C$1004-DATE($B$4+1,1,1)))/2)-((Bookings!$B$5:$B$1004+DATE($B$4,1,1)+ABS(Bookings!$B$5:$B$1004-DATE($B$4,1,1)))/2)))/2)*Bookings!$AB$5:$AB$1004))
A29: =IF(Properties!A7="","",Properties!A7) | B29: =IF($A29="","",SUMPRODUCT(Bookings!$AA$5:$AA$1004*(($A29="All properties")+(Bookings!$D$5:$D$1004=$A29)>0)*(((((Bookings!$C$5:$C$1004+DATE($B$4+1,1,1)-ABS(Bookings!$C$5:$C$1004-DATE($B$4+1,1,1)))/2)-((Bookings!$B$5:$B$1004+DATE($B$4,1,1)+ABS(Bookings!$B$5:$B$1004-DATE($B$4,1,1)))/2))+ABS(((Bookings!$C$5:$C$1004+DATE($B$4+1,1,1)-ABS(Bookings!$C$5:$C$1004-DATE($B$4+1,1,1)))/2)-((Bookings!$B$5:$B$1004+DATE($B$4,1,1)+ABS(Bookings!$B$5:$B$1004-DATE($B$4,1,1)))/2)))/2))) | C29: =IF($A29="","",IF(K29=0,0,B29/K29)) | D29: =IF($A29="","",IF(B29=0,0,L29/B29)) | E29: =IF($A29="","",IF(K29=0,0,L29/K29)) | F29: =IF($A29="","",SUMPRODUCT(Bookings!$AA$5:$AA$1004*(($A29="All properties")+(Bookings!$D$5:$D$1004=$A29)>0)*(((((Bookings!$C$5:$C$1004+DATE($B$4+1,1,1)-ABS(Bookings!$C$5:$C$1004-DATE($B$4+1,1,1)))/2)-((Bookings!$B$5:$B$1004+DATE($B$4,1,1)+ABS(Bookings!$B$5:$B$1004-DATE($B$4,1,1)))/2))+ABS(((Bookings!$C$5:$C$1004+DATE($B$4+1,1,1)-ABS(Bookings!$C$5:$C$1004-DATE($B$4+1,1,1)))/2)-((Bookings!$B$5:$B$1004+DATE($B$4,1,1)+ABS(Bookings!$B$5:$B$1004-DATE($B$4,1,1)))/2)))/2)*Bookings!$AC$5:$AC$1004)) | G29: =IF($A29="","",SUMPRODUCT(Bookings!$AA$5:$AA$1004*(($A29="All properties")+(Bookings!$D$5:$D$1004=$A29)>0)*(((((Bookings!$C$5:$C$1004+DATE($B$4+1,1,1)-ABS(Bookings!$C$5:$C$1004-DATE($B$4+1,1,1)))/2)-((Bookings!$B$5:$B$1004+DATE($B$4,1,1)+ABS(Bookings!$B$5:$B$1004-DATE($B$4,1,1)))/2))+ABS(((Bookings!$C$5:$C$1004+DATE($B$4+1,1,1)-ABS(Bookings!$C$5:$C$1004-DATE($B$4+1,1,1)))/2)-((Bookings!$B$5:$B$1004+DATE($B$4,1,1)+ABS(Bookings!$B$5:$B$1004-DATE($B$4,1,1)))/2)))/2)*Bookings!$AD$5:$AD$1004)) | H29: =IF($A29="","",SUMIFS(Expenses!$F$5:$F$1004,Expenses!$A$5:$A$1004,">="&DATE($B$4,1,1),Expenses!$A$5:$A$1004,"<"&DATE($B$4+1,1,1),Expenses!$B$5:$B$1004,$A29)) | I29: =IF($A29="","",F29-G29-H29) | K29: =IF($A29="","",SUMPRODUCT((Properties!$A$5:$A$24<>"")*(($A29="All properties")+(Properties!$A$5:$A$24=$A29)>0)*(((DATE($B$4+1,1,1)-((Properties!$K$5:$K$24+DATE($B$4,1,1)+ABS(Properties!$K$5:$K$24-DATE($B$4,1,1)))/2))+ABS(DATE($B$4+1,1,1)-((Properties!$K$5:$K$24+DATE($B$4,1,1)+ABS(Properties!$K$5:$K$24-DATE($B$4,1,1)))/2)))/2))) | L29: =IF($A29="","",SUMPRODUCT(Bookings!$AA$5:$AA$1004*(($A29="All properties")+(Bookings!$D$5:$D$1004=$A29)>0)*(((((Bookings!$C$5:$C$1004+DATE($B$4+1,1,1)-ABS(Bookings!$C$5:$C$1004-DATE($B$4+1,1,1)))/2)-((Bookings!$B$5:$B$1004+DATE($B$4,1,1)+ABS(Bookings!$B$5:$B$1004-DATE($B$4,1,1)))/2))+ABS(((Bookings!$C$5:$C$1004+DATE($B$4+1,1,1)-ABS(Bookings!$C$5:$C$1004-DATE($B$4+1,1,1)))/2)-((Bookings!$B$5:$B$1004+DATE($B$4,1,1)+ABS(Bookings!$B$5:$B$1004-DATE($B$4,1,1)))/2)))/2)*Bookings!$AB$5:$AB$1004))
A30: =IF(Properties!A8="","",Properties!A8) | B30: =IF($A30="","",SUMPRODUCT(Bookings!$AA$5:$AA$1004*(($A30="All properties")+(Bookings!$D$5:$D$1004=$A30)>0)*(((((Bookings!$C$5:$C$1004+DATE($B$4+1,1,1)-ABS(Bookings!$C$5:$C$1004-DATE($B$4+1,1,1)))/2)-((Bookings!$B$5:$B$1004+DATE($B$4,1,1)+ABS(Bookings!$B$5:$B$1004-DATE($B$4,1,1)))/2))+ABS(((Bookings!$C$5:$C$1004+DATE($B$4+1,1,1)-ABS(Bookings!$C$5:$C$1004-DATE($B$4+1,1,1)))/2)-((Bookings!$B$5:$B$1004+DATE($B$4,1,1)+ABS(Bookings!$B$5:$B$1004-DATE($B$4,1,1)))/2)))/2))) | C30: =IF($A30="","",IF(K30=0,0,B30/K30)) | D30: =IF($A30="","",IF(B30=0,0,L30/B30)) | E30: =IF($A30="","",IF(K30=0,0,L30/K30)) | F30: =IF($A30="","",SUMPRODUCT(Bookings!$AA$5:$AA$1004*(($A30="All properties")+(Bookings!$D$5:$D$1004=$A30)>0)*(((((Bookings!$C$5:$C$1004+DATE($B$4+1,1,1)-ABS(Bookings!$C$5:$C$1004-DATE($B$4+1,1,1)))/2)-((Bookings!$B$5:$B$1004+DATE($B$4,1,1)+ABS(Bookings!$B$5:$B$1004-DATE($B$4,1,1)))/2))+ABS(((Bookings!$C$5:$C$1004+DATE($B$4+1,1,1)-ABS(Bookings!$C$5:$C$1004-DATE($B$4+1,1,1)))/2)-((Bookings!$B$5:$B$1004+DATE($B$4,1,1)+ABS(Bookings!$B$5:$B$1004-DATE($B$4,1,1)))/2)))/2)*Bookings!$AC$5:$AC$1004)) | G30: =IF($A30="","",SUMPRODUCT(Bookings!$AA$5:$AA$1004*(($A30="All properties")+(Bookings!$D$5:$D$1004=$A30)>0)*(((((Bookings!$C$5:$C$1004+DATE($B$4+1,1,1)-ABS(Bookings!$C$5:$C$1004-DATE($B$4+1,1,1)))/2)-((Bookings!$B$5:$B$1004+DATE($B$4,1,1)+ABS(Bookings!$B$5:$B$1004-DATE($B$4,1,1)))/2))+ABS(((Bookings!$C$5:$C$1004+DATE($B$4+1,1,1)-ABS(Bookings!$C$5:$C$1004-DATE($B$4+1,1,1)))/2)-((Bookings!$B$5:$B$1004+DATE($B$4,1,1)+ABS(Bookings!$B$5:$B$1004-DATE($B$4,1,1)))/2)))/2)*Bookings!$AD$5:$AD$1004)) | H30: =IF($A30="","",SUMIFS(Expenses!$F$5:$F$1004,Expenses!$A$5:$A$1004,">="&DATE($B$4,1,1),Expenses!$A$5:$A$1004,"<"&DATE($B$4+1,1,1),Expenses!$B$5:$B$1004,$A30)) | I30: =IF($A30="","",F30-G30-H30) | K30: =IF($A30="","",SUMPRODUCT((Properties!$A$5:$A$24<>"")*(($A30="All properties")+(Properties!$A$5:$A$24=$A30)>0)*(((DATE($B$4+1,1,1)-((Properties!$K$5:$K$24+DATE($B$4,1,1)+ABS(Properties!$K$5:$K$24-DATE($B$4,1,1)))/2))+ABS(DATE($B$4+1,1,1)-((Properties!$K$5:$K$24+DATE($B$4,1,1)+ABS(Properties!$K$5:$K$24-DATE($B$4,1,1)))/2)))/2))) | L30: =IF($A30="","",SUMPRODUCT(Bookings!$AA$5:$AA$1004*(($A30="All properties")+(Bookings!$D$5:$D$1004=$A30)>0)*(((((Bookings!$C$5:$C$1004+DATE($B$4+1,1,1)-ABS(Bookings!$C$5:$C$1004-DATE($B$4+1,1,1)))/2)-((Bookings!$B$5:$B$1004+DATE($B$4,1,1)+ABS(Bookings!$B$5:$B$1004-DATE($B$4,1,1)))/2))+ABS(((Bookings!$C$5:$C$1004+DATE($B$4+1,1,1)-ABS(Bookings!$C$5:$C$1004-DATE($B$4+1,1,1)))/2)-((Bookings!$B$5:$B$1004+DATE($B$4,1,1)+ABS(Bookings!$B$5:$B$1004-DATE($B$4,1,1)))/2)))/2)*Bookings!$AB$5:$AB$1004))
A31: =IF(Properties!A9="","",Properties!A9) | B31: =IF($A31="","",SUMPRODUCT(Bookings!$AA$5:$AA$1004*(($A31="All properties")+(Bookings!$D$5:$D$1004=$A31)>0)*(((((Bookings!$C$5:$C$1004+DATE($B$4+1,1,1)-ABS(Bookings!$C$5:$C$1004-DATE($B$4+1,1,1)))/2)-((Bookings!$B$5:$B$1004+DATE($B$4,1,1)+ABS(Bookings!$B$5:$B$1004-DATE($B$4,1,1)))/2))+ABS(((Bookings!$C$5:$C$1004+DATE($B$4+1,1,1)-ABS(Bookings!$C$5:$C$1004-DATE($B$4+1,1,1)))/2)-((Bookings!$B$5:$B$1004+DATE($B$4,1,1)+ABS(Bookings!$B$5:$B$1004-DATE($B$4,1,1)))/2)))/2))) | C31: =IF($A31="","",IF(K31=0,0,B31/K31)) | D31: =IF($A31="","",IF(B31=0,0,L31/B31)) | E31: =IF($A31="","",IF(K31=0,0,L31/K31)) | F31: =IF($A31="","",SUMPRODUCT(Bookings!$AA$5:$AA$1004*(($A31="All properties")+(Bookings!$D$5:$D$1004=$A31)>0)*(((((Bookings!$C$5:$C$1004+DATE($B$4+1,1,1)-ABS(Bookings!$C$5:$C$1004-DATE($B$4+1,1,1)))/2)-((Bookings!$B$5:$B$1004+DATE($B$4,1,1)+ABS(Bookings!$B$5:$B$1004-DATE($B$4,1,1)))/2))+ABS(((Bookings!$C$5:$C$1004+DATE($B$4+1,1,1)-ABS(Bookings!$C$5:$C$1004-DATE($B$4+1,1,1)))/2)-((Bookings!$B$5:$B$1004+DATE($B$4,1,1)+ABS(Bookings!$B$5:$B$1004-DATE($B$4,1,1)))/2)))/2)*Bookings!$AC$5:$AC$1004)) | G31: =IF($A31="","",SUMPRODUCT(Bookings!$AA$5:$AA$1004*(($A31="All properties")+(Bookings!$D$5:$D$1004=$A31)>0)*(((((Bookings!$C$5:$C$1004+DATE($B$4+1,1,1)-ABS(Bookings!$C$5:$C$1004-DATE($B$4+1,1,1)))/2)-((Bookings!$B$5:$B$1004+DATE($B$4,1,1)+ABS(Bookings!$B$5:$B$1004-DATE($B$4,1,1)))/2))+ABS(((Bookings!$C$5:$C$1004+DATE($B$4+1,1,1)-ABS(Bookings!$C$5:$C$1004-DATE($B$4+1,1,1)))/2)-((Bookings!$B$5:$B$1004+DATE($B$4,1,1)+ABS(Bookings!$B$5:$B$1004-DATE($B$4,1,1)))/2)))/2)*Bookings!$AD$5:$AD$1004)) | H31: =IF($A31="","",SUMIFS(Expenses!$F$5:$F$1004,Expenses!$A$5:$A$1004,">="&DATE($B$4,1,1),Expenses!$A$5:$A$1004,"<"&DATE($B$4+1,1,1),Expenses!$B$5:$B$1004,$A31)) | I31: =IF($A31="","",F31-G31-H31) | K31: =IF($A31="","",SUMPRODUCT((Properties!$A$5:$A$24<>"")*(($A31="All properties")+(Properties!$A$5:$A$24=$A31)>0)*(((DATE($B$4+1,1,1)-((Properties!$K$5:$K$24+DATE($B$4,1,1)+ABS(Properties!$K$5:$K$24-DATE($B$4,1,1)))/2))+ABS(DATE($B$4+1,1,1)-((Properties!$K$5:$K$24+DATE($B$4,1,1)+ABS(Properties!$K$5:$K$24-DATE($B$4,1,1)))/2)))/2))) | L31: =IF($A31="","",SUMPRODUCT(Bookings!$AA$5:$AA$1004*(($A31="All properties")+(Bookings!$D$5:$D$1004=$A31)>0)*(((((Bookings!$C$5:$C$1004+DATE($B$4+1,1,1)-ABS(Bookings!$C$5:$C$1004-DATE($B$4+1,1,1)))/2)-((Bookings!$B$5:$B$1004+DATE($B$4,1,1)+ABS(Bookings!$B$5:$B$1004-DATE($B$4,1,1)))/2))+ABS(((Bookings!$C$5:$C$1004+DATE($B$4+1,1,1)-ABS(Bookings!$C$5:$C$1004-DATE($B$4+1,1,1)))/2)-((Bookings!$B$5:$B$1004+DATE($B$4,1,1)+ABS(Bookings!$B$5:$B$1004-DATE($B$4,1,1)))/2)))/2)*Bookings!$AB$5:$AB$1004))
A32: =IF(Properties!A10="","",Properties!A10) | B32: =IF($A32="","",SUMPRODUCT(Bookings!$AA$5:$AA$1004*(($A32="All properties")+(Bookings!$D$5:$D$1004=$A32)>0)*(((((Bookings!$C$5:$C$1004+DATE($B$4+1,1,1)-ABS(Bookings!$C$5:$C$1004-DATE($B$4+1,1,1)))/2)-((Bookings!$B$5:$B$1004+DATE($B$4,1,1)+ABS(Bookings!$B$5:$B$1004-DATE($B$4,1,1)))/2))+ABS(((Bookings!$C$5:$C$1004+DATE($B$4+1,1,1)-ABS(Bookings!$C$5:$C$1004-DATE($B$4+1,1,1)))/2)-((Bookings!$B$5:$B$1004+DATE($B$4,1,1)+ABS(Bookings!$B$5:$B$1004-DATE($B$4,1,1)))/2)))/2))) | C32: =IF($A32="","",IF(K32=0,0,B32/K32)) | D32: =IF($A32="","",IF(B32=0,0,L32/B32)) | E32: =IF($A32="","",IF(K32=0,0,L32/K32)) | F32: =IF($A32="","",SUMPRODUCT(Bookings!$AA$5:$AA$1004*(($A32="All properties")+(Bookings!$D$5:$D$1004=$A32)>0)*(((((Bookings!$C$5:$C$1004+DATE($B$4+1,1,1)-ABS(Bookings!$C$5:$C$1004-DATE($B$4+1,1,1)))/2)-((Bookings!$B$5:$B$1004+DATE($B$4,1,1)+ABS(Bookings!$B$5:$B$1004-DATE($B$4,1,1)))/2))+ABS(((Bookings!$C$5:$C$1004+DATE($B$4+1,1,1)-ABS(Bookings!$C$5:$C$1004-DATE($B$4+1,1,1)))/2)-((Bookings!$B$5:$B$1004+DATE($B$4,1,1)+ABS(Bookings!$B$5:$B$1004-DATE($B$4,1,1)))/2)))/2)*Bookings!$AC$5:$AC$1004)) | G32: =IF($A32="","",SUMPRODUCT(Bookings!$AA$5:$AA$1004*(($A32="All properties")+(Bookings!$D$5:$D$1004=$A32)>0)*(((((Bookings!$C$5:$C$1004+DATE($B$4+1,1,1)-ABS(Bookings!$C$5:$C$1004-DATE($B$4+1,1,1)))/2)-((Bookings!$B$5:$B$1004+DATE($B$4,1,1)+ABS(Bookings!$B$5:$B$1004-DATE($B$4,1,1)))/2))+ABS(((Bookings!$C$5:$C$1004+DATE($B$4+1,1,1)-ABS(Bookings!$C$5:$C$1004-DATE($B$4+1,1,1)))/2)-((Bookings!$B$5:$B$1004+DATE($B$4,1,1)+ABS(Bookings!$B$5:$B$1004-DATE($B$4,1,1)))/2)))/2)*Bookings!$AD$5:$AD$1004)) | H32: =IF($A32="","",SUMIFS(Expenses!$F$5:$F$1004,Expenses!$A$5:$A$1004,">="&DATE($B$4,1,1),Expenses!$A$5:$A$1004,"<"&DATE($B$4+1,1,1),Expenses!$B$5:$B$1004,$A32)) | I32: =IF($A32="","",F32-G32-H32) | K32: =IF($A32="","",SUMPRODUCT((Properties!$A$5:$A$24<>"")*(($A32="All properties")+(Properties!$A$5:$A$24=$A32)>0)*(((DATE($B$4+1,1,1)-((Properties!$K$5:$K$24+DATE($B$4,1,1)+ABS(Properties!$K$5:$K$24-DATE($B$4,1,1)))/2))+ABS(DATE($B$4+1,1,1)-((Properties!$K$5:$K$24+DATE($B$4,1,1)+ABS(Properties!$K$5:$K$24-DATE($B$4,1,1)))/2)))/2))) | L32: =IF($A32="","",SUMPRODUCT(Bookings!$AA$5:$AA$1004*(($A32="All properties")+(Bookings!$D$5:$D$1004=$A32)>0)*(((((Bookings!$C$5:$C$1004+DATE($B$4+1,1,1)-ABS(Bookings!$C$5:$C$1004-DATE($B$4+1,1,1)))/2)-((Bookings!$B$5:$B$1004+DATE($B$4,1,1)+ABS(Bookings!$B$5:$B$1004-DATE($B$4,1,1)))/2))+ABS(((Bookings!$C$5:$C$1004+DATE($B$4+1,1,1)-ABS(Bookings!$C$5:$C$1004-DATE($B$4+1,1,1)))/2)-((Bookings!$B$5:$B$1004+DATE($B$4,1,1)+ABS(Bookings!$B$5:$B$1004-DATE($B$4,1,1)))/2)))/2)*Bookings!$AB$5:$AB$1004))
A33: =IF(Properties!A11="","",Properties!A11) | B33: =IF($A33="","",SUMPRODUCT(Bookings!$AA$5:$AA$1004*(($A33="All properties")+(Bookings!$D$5:$D$1004=$A33)>0)*(((((Bookings!$C$5:$C$1004+DATE($B$4+1,1,1)-ABS(Bookings!$C$5:$C$1004-DATE($B$4+1,1,1)))/2)-((Bookings!$B$5:$B$1004+DATE($B$4,1,1)+ABS(Bookings!$B$5:$B$1004-DATE($B$4,1,1)))/2))+ABS(((Bookings!$C$5:$C$1004+DATE($B$4+1,1,1)-ABS(Bookings!$C$5:$C$1004-DATE($B$4+1,1,1)))/2)-((Bookings!$B$5:$B$1004+DATE($B$4,1,1)+ABS(Bookings!$B$5:$B$1004-DATE($B$4,1,1)))/2)))/2))) | C33: =IF($A33="","",IF(K33=0,0,B33/K33)) | D33: =IF($A33="","",IF(B33=0,0,L33/B33)) | E33: =IF($A33="","",IF(K33=0,0,L33/K33)) | F33: =IF($A33="","",SUMPRODUCT(Bookings!$AA$5:$AA$1004*(($A33="All properties")+(Bookings!$D$5:$D$1004=$A33)>0)*(((((Bookings!$C$5:$C$1004+DATE($B$4+1,1,1)-ABS(Bookings!$C$5:$C$1004-DATE($B$4+1,1,1)))/2)-((Bookings!$B$5:$B$1004+DATE($B$4,1,1)+ABS(Bookings!$B$5:$B$1004-DATE($B$4,1,1)))/2))+ABS(((Bookings!$C$5:$C$1004+DATE($B$4+1,1,1)-ABS(Bookings!$C$5:$C$1004-DATE($B$4+1,1,1)))/2)-((Bookings!$B$5:$B$1004+DATE($B$4,1,1)+ABS(Bookings!$B$5:$B$1004-DATE($B$4,1,1)))/2)))/2)*Bookings!$AC$5:$AC$1004)) | G33: =IF($A33="","",SUMPRODUCT(Bookings!$AA$5:$AA$1004*(($A33="All properties")+(Bookings!$D$5:$D$1004=$A33)>0)*(((((Bookings!$C$5:$C$1004+DATE($B$4+1,1,1)-ABS(Bookings!$C$5:$C$1004-DATE($B$4+1,1,1)))/2)-((Bookings!$B$5:$B$1004+DATE($B$4,1,1)+ABS(Bookings!$B$5:$B$1004-DATE($B$4,1,1)))/2))+ABS(((Bookings!$C$5:$C$1004+DATE($B$4+1,1,1)-ABS(Bookings!$C$5:$C$1004-DATE($B$4+1,1,1)))/2)-((Bookings!$B$5:$B$1004+DATE($B$4,1,1)+ABS(Bookings!$B$5:$B$1004-DATE($B$4,1,1)))/2)))/2)*Bookings!$AD$5:$AD$1004)) | H33: =IF($A33="","",SUMIFS(Expenses!$F$5:$F$1004,Expenses!$A$5:$A$1004,">="&DATE($B$4,1,1),Expenses!$A$5:$A$1004,"<"&DATE($B$4+1,1,1),Expenses!$B$5:$B$1004,$A33)) | I33: =IF($A33="","",F33-G33-H33) | K33: =IF($A33="","",SUMPRODUCT((Properties!$A$5:$A$24<>"")*(($A33="All properties")+(Properties!$A$5:$A$24=$A33)>0)*(((DATE($B$4+1,1,1)-((Properties!$K$5:$K$24+DATE($B$4,1,1)+ABS(Properties!$K$5:$K$24-DATE($B$4,1,1)))/2))+ABS(DATE($B$4+1,1,1)-((Properties!$K$5:$K$24+DATE($B$4,1,1)+ABS(Properties!$K$5:$K$24-DATE($B$4,1,1)))/2)))/2))) | L33: =IF($A33="","",SUMPRODUCT(Bookings!$AA$5:$AA$1004*(($A33="All properties")+(Bookings!$D$5:$D$1004=$A33)>0)*(((((Bookings!$C$5:$C$1004+DATE($B$4+1,1,1)-ABS(Bookings!$C$5:$C$1004-DATE($B$4+1,1,1)))/2)-((Bookings!$B$5:$B$1004+DATE($B$4,1,1)+ABS(Bookings!$B$5:$B$1004-DATE($B$4,1,1)))/2))+ABS(((Bookings!$C$5:$C$1004+DATE($B$4+1,1,1)-ABS(Bookings!$C$5:$C$1004-DATE($B$4+1,1,1)))/2)-((Bookings!$B$5:$B$1004+DATE($B$4,1,1)+ABS(Bookings!$B$5:$B$1004-DATE($B$4,1,1)))/2)))/2)*Bookings!$AB$5:$AB$1004))
A34: =IF(Properties!A12="","",Properties!A12) | B34: =IF($A34="","",SUMPRODUCT(Bookings!$AA$5:$AA$1004*(($A34="All properties")+(Bookings!$D$5:$D$1004=$A34)>0)*(((((Bookings!$C$5:$C$1004+DATE($B$4+1,1,1)-ABS(Bookings!$C$5:$C$1004-DATE($B$4+1,1,1)))/2)-((Bookings!$B$5:$B$1004+DATE($B$4,1,1)+ABS(Bookings!$B$5:$B$1004-DATE($B$4,1,1)))/2))+ABS(((Bookings!$C$5:$C$1004+DATE($B$4+1,1,1)-ABS(Bookings!$C$5:$C$1004-DATE($B$4+1,1,1)))/2)-((Bookings!$B$5:$B$1004+DATE($B$4,1,1)+ABS(Bookings!$B$5:$B$1004-DATE($B$4,1,1)))/2)))/2))) | C34: =IF($A34="","",IF(K34=0,0,B34/K34)) | D34: =IF($A34="","",IF(B34=0,0,L34/B34)) | E34: =IF($A34="","",IF(K34=0,0,L34/K34)) | F34: =IF($A34="","",SUMPRODUCT(Bookings!$AA$5:$AA$1004*(($A34="All properties")+(Bookings!$D$5:$D$1004=$A34)>0)*(((((Bookings!$C$5:$C$1004+DATE($B$4+1,1,1)-ABS(Bookings!$C$5:$C$1004-DATE($B$4+1,1,1)))/2)-((Bookings!$B$5:$B$1004+DATE($B$4,1,1)+ABS(Bookings!$B$5:$B$1004-DATE($B$4,1,1)))/2))+ABS(((Bookings!$C$5:$C$1004+DATE($B$4+1,1,1)-ABS(Bookings!$C$5:$C$1004-DATE($B$4+1,1,1)))/2)-((Bookings!$B$5:$B$1004+DATE($B$4,1,1)+ABS(Bookings!$B$5:$B$1004-DATE($B$4,1,1)))/2)))/2)*Bookings!$AC$5:$AC$1004)) | G34: =IF($A34="","",SUMPRODUCT(Bookings!$AA$5:$AA$1004*(($A34="All properties")+(Bookings!$D$5:$D$1004=$A34)>0)*(((((Bookings!$C$5:$C$1004+DATE($B$4+1,1,1)-ABS(Bookings!$C$5:$C$1004-DATE($B$4+1,1,1)))/2)-((Bookings!$B$5:$B$1004+DATE($B$4,1,1)+ABS(Bookings!$B$5:$B$1004-DATE($B$4,1,1)))/2))+ABS(((Bookings!$C$5:$C$1004+DATE($B$4+1,1,1)-ABS(Bookings!$C$5:$C$1004-DATE($B$4+1,1,1)))/2)-((Bookings!$B$5:$B$1004+DATE($B$4,1,1)+ABS(Bookings!$B$5:$B$1004-DATE($B$4,1,1)))/2)))/2)*Bookings!$AD$5:$AD$1004)) | H34: =IF($A34="","",SUMIFS(Expenses!$F$5:$F$1004,Expenses!$A$5:$A$1004,">="&DATE($B$4,1,1),Expenses!$A$5:$A$1004,"<"&DATE($B$4+1,1,1),Expenses!$B$5:$B$1004,$A34)) | I34: =IF($A34="","",F34-G34-H34) | K34: =IF($A34="","",SUMPRODUCT((Properties!$A$5:$A$24<>"")*(($A34="All properties")+(Properties!$A$5:$A$24=$A34)>0)*(((DATE($B$4+1,1,1)-((Properties!$K$5:$K$24+DATE($B$4,1,1)+ABS(Properties!$K$5:$K$24-DATE($B$4,1,1)))/2))+ABS(DATE($B$4+1,1,1)-((Properties!$K$5:$K$24+DATE($B$4,1,1)+ABS(Properties!$K$5:$K$24-DATE($B$4,1,1)))/2)))/2))) | L34: =IF($A34="","",SUMPRODUCT(Bookings!$AA$5:$AA$1004*(($A34="All properties")+(Bookings!$D$5:$D$1004=$A34)>0)*(((((Bookings!$C$5:$C$1004+DATE($B$4+1,1,1)-ABS(Bookings!$C$5:$C$1004-DATE($B$4+1,1,1)))/2)-((Bookings!$B$5:$B$1004+DATE($B$4,1,1)+ABS(Bookings!$B$5:$B$1004-DATE($B$4,1,1)))/2))+ABS(((Bookings!$C$5:$C$1004+DATE($B$4+1,1,1)-ABS(Bookings!$C$5:$C$1004-DATE($B$4+1,1,1)))/2)-((Bookings!$B$5:$B$1004+DATE($B$4,1,1)+ABS(Bookings!$B$5:$B$1004-DATE($B$4,1,1)))/2)))/2)*Bookings!$AB$5:$AB$1004))
A35: =IF(Properties!A13="","",Properties!A13) | B35: =IF($A35="","",SUMPRODUCT(Bookings!$AA$5:$AA$1004*(($A35="All properties")+(Bookings!$D$5:$D$1004=$A35)>0)*(((((Bookings!$C$5:$C$1004+DATE($B$4+1,1,1)-ABS(Bookings!$C$5:$C$1004-DATE($B$4+1,1,1)))/2)-((Bookings!$B$5:$B$1004+DATE($B$4,1,1)+ABS(Bookings!$B$5:$B$1004-DATE($B$4,1,1)))/2))+ABS(((Bookings!$C$5:$C$1004+DATE($B$4+1,1,1)-ABS(Bookings!$C$5:$C$1004-DATE($B$4+1,1,1)))/2)-((Bookings!$B$5:$B$1004+DATE($B$4,1,1)+ABS(Bookings!$B$5:$B$1004-DATE($B$4,1,1)))/2)))/2))) | C35: =IF($A35="","",IF(K35=0,0,B35/K35)) | D35: =IF($A35="","",IF(B35=0,0,L35/B35)) | E35: =IF($A35="","",IF(K35=0,0,L35/K35)) | F35: =IF($A35="","",SUMPRODUCT(Bookings!$AA$5:$AA$1004*(($A35="All properties")+(Bookings!$D$5:$D$1004=$A35)>0)*(((((Bookings!$C$5:$C$1004+DATE($B$4+1,1,1)-ABS(Bookings!$C$5:$C$1004-DATE($B$4+1,1,1)))/2)-((Bookings!$B$5:$B$1004+DATE($B$4,1,1)+ABS(Bookings!$B$5:$B$1004-DATE($B$4,1,1)))/2))+ABS(((Bookings!$C$5:$C$1004+DATE($B$4+1,1,1)-ABS(Bookings!$C$5:$C$1004-DATE($B$4+1,1,1)))/2)-((Bookings!$B$5:$B$1004+DATE($B$4,1,1)+ABS(Bookings!$B$5:$B$1004-DATE($B$4,1,1)))/2)))/2)*Bookings!$AC$5:$AC$1004)) | G35: =IF($A35="","",SUMPRODUCT(Bookings!$AA$5:$AA$1004*(($A35="All properties")+(Bookings!$D$5:$D$1004=$A35)>0)*(((((Bookings!$C$5:$C$1004+DATE($B$4+1,1,1)-ABS(Bookings!$C$5:$C$1004-DATE($B$4+1,1,1)))/2)-((Bookings!$B$5:$B$1004+DATE($B$4,1,1)+ABS(Bookings!$B$5:$B$1004-DATE($B$4,1,1)))/2))+ABS(((Bookings!$C$5:$C$1004+DATE($B$4+1,1,1)-ABS(Bookings!$C$5:$C$1004-DATE($B$4+1,1,1)))/2)-((Bookings!$B$5:$B$1004+DATE($B$4,1,1)+ABS(Bookings!$B$5:$B$1004-DATE($B$4,1,1)))/2)))/2)*Bookings!$AD$5:$AD$1004)) | H35: =IF($A35="","",SUMIFS(Expenses!$F$5:$F$1004,Expenses!$A$5:$A$1004,">="&DATE($B$4,1,1),Expenses!$A$5:$A$1004,"<"&DATE($B$4+1,1,1),Expenses!$B$5:$B$1004,$A35)) | I35: =IF($A35="","",F35-G35-H35) | K35: =IF($A35="","",SUMPRODUCT((Properties!$A$5:$A$24<>"")*(($A35="All properties")+(Properties!$A$5:$A$24=$A35)>0)*(((DATE($B$4+1,1,1)-((Properties!$K$5:$K$24+DATE($B$4,1,1)+ABS(Properties!$K$5:$K$24-DATE($B$4,1,1)))/2))+ABS(DATE($B$4+1,1,1)-((Properties!$K$5:$K$24+DATE($B$4,1,1)+ABS(Properties!$K$5:$K$24-DATE($B$4,1,1)))/2)))/2))) | L35: =IF($A35="","",SUMPRODUCT(Bookings!$AA$5:$AA$1004*(($A35="All properties")+(Bookings!$D$5:$D$1004=$A35)>0)*(((((Bookings!$C$5:$C$1004+DATE($B$4+1,1,1)-ABS(Bookings!$C$5:$C$1004-DATE($B$4+1,1,1)))/2)-((Bookings!$B$5:$B$1004+DATE($B$4,1,1)+ABS(Bookings!$B$5:$B$1004-DATE($B$4,1,1)))/2))+ABS(((Bookings!$C$5:$C$1004+DATE($B$4+1,1,1)-ABS(Bookings!$C$5:$C$1004-DATE($B$4+1,1,1)))/2)-((Bookings!$B$5:$B$1004+DATE($B$4,1,1)+ABS(Bookings!$B$5:$B$1004-DATE($B$4,1,1)))/2)))/2)*Bookings!$AB$5:$AB$1004))
A36: =IF(Properties!A14="","",Properties!A14) | B36: =IF($A36="","",SUMPRODUCT(Bookings!$AA$5:$AA$1004*(($A36="All properties")+(Bookings!$D$5:$D$1004=$A36)>0)*(((((Bookings!$C$5:$C$1004+DATE($B$4+1,1,1)-ABS(Bookings!$C$5:$C$1004-DATE($B$4+1,1,1)))/2)-((Bookings!$B$5:$B$1004+DATE($B$4,1,1)+ABS(Bookings!$B$5:$B$1004-DATE($B$4,1,1)))/2))+ABS(((Bookings!$C$5:$C$1004+DATE($B$4+1,1,1)-ABS(Bookings!$C$5:$C$1004-DATE($B$4+1,1,1)))/2)-((Bookings!$B$5:$B$1004+DATE($B$4,1,1)+ABS(Bookings!$B$5:$B$1004-DATE($B$4,1,1)))/2)))/2))) | C36: =IF($A36="","",IF(K36=0,0,B36/K36)) | D36: =IF($A36="","",IF(B36=0,0,L36/B36)) | E36: =IF($A36="","",IF(K36=0,0,L36/K36)) | F36: =IF($A36="","",SUMPRODUCT(Bookings!$AA$5:$AA$1004*(($A36="All properties")+(Bookings!$D$5:$D$1004=$A36)>0)*(((((Bookings!$C$5:$C$1004+DATE($B$4+1,1,1)-ABS(Bookings!$C$5:$C$1004-DATE($B$4+1,1,1)))/2)-((Bookings!$B$5:$B$1004+DATE($B$4,1,1)+ABS(Bookings!$B$5:$B$1004-DATE($B$4,1,1)))/2))+ABS(((Bookings!$C$5:$C$1004+DATE($B$4+1,1,1)-ABS(Bookings!$C$5:$C$1004-DATE($B$4+1,1,1)))/2)-((Bookings!$B$5:$B$1004+DATE($B$4,1,1)+ABS(Bookings!$B$5:$B$1004-DATE($B$4,1,1)))/2)))/2)*Bookings!$AC$5:$AC$1004)) | G36: =IF($A36="","",SUMPRODUCT(Bookings!$AA$5:$AA$1004*(($A36="All properties")+(Bookings!$D$5:$D$1004=$A36)>0)*(((((Bookings!$C$5:$C$1004+DATE($B$4+1,1,1)-ABS(Bookings!$C$5:$C$1004-DATE($B$4+1,1,1)))/2)-((Bookings!$B$5:$B$1004+DATE($B$4,1,1)+ABS(Bookings!$B$5:$B$1004-DATE($B$4,1,1)))/2))+ABS(((Bookings!$C$5:$C$1004+DATE($B$4+1,1,1)-ABS(Bookings!$C$5:$C$1004-DATE($B$4+1,1,1)))/2)-((Bookings!$B$5:$B$1004+DATE($B$4,1,1)+ABS(Bookings!$B$5:$B$1004-DATE($B$4,1,1)))/2)))/2)*Bookings!$AD$5:$AD$1004)) | H36: =IF($A36="","",SUMIFS(Expenses!$F$5:$F$1004,Expenses!$A$5:$A$1004,">="&DATE($B$4,1,1),Expenses!$A$5:$A$1004,"<"&DATE($B$4+1,1,1),Expenses!$B$5:$B$1004,$A36)) | I36: =IF($A36="","",F36-G36-H36) | K36: =IF($A36="","",SUMPRODUCT((Properties!$A$5:$A$24<>"")*(($A36="All properties")+(Properties!$A$5:$A$24=$A36)>0)*(((DATE($B$4+1,1,1)-((Properties!$K$5:$K$24+DATE($B$4,1,1)+ABS(Properties!$K$5:$K$24-DATE($B$4,1,1)))/2))+ABS(DATE($B$4+1,1,1)-((Properties!$K$5:$K$24+DATE($B$4,1,1)+ABS(Properties!$K$5:$K$24-DATE($B$4,1,1)))/2)))/2))) | L36: =IF($A36="","",SUMPRODUCT(Bookings!$AA$5:$AA$1004*(($A36="All properties")+(Bookings!$D$5:$D$1004=$A36)>0)*(((((Bookings!$C$5:$C$1004+DATE($B$4+1,1,1)-ABS(Bookings!$C$5:$C$1004-DATE($B$4+1,1,1)))/2)-((Bookings!$B$5:$B$1004+DATE($B$4,1,1)+ABS(Bookings!$B$5:$B$1004-DATE($B$4,1,1)))/2))+ABS(((Bookings!$C$5:$C$1004+DATE($B$4+1,1,1)-ABS(Bookings!$C$5:$C$1004-DATE($B$4+1,1,1)))/2)-((Bookings!$B$5:$B$1004+DATE($B$4,1,1)+ABS(Bookings!$B$5:$B$1004-DATE($B$4,1,1)))/2)))/2)*Bookings!$AB$5:$AB$1004))
A37: =IF(Properties!A15="","",Properties!A15) | B37: =IF($A37="","",SUMPRODUCT(Bookings!$AA$5:$AA$1004*(($A37="All properties")+(Bookings!$D$5:$D$1004=$A37)>0)*(((((Bookings!$C$5:$C$1004+DATE($B$4+1,1,1)-ABS(Bookings!$C$5:$C$1004-DATE($B$4+1,1,1)))/2)-((Bookings!$B$5:$B$1004+DATE($B$4,1,1)+ABS(Bookings!$B$5:$B$1004-DATE($B$4,1,1)))/2))+ABS(((Bookings!$C$5:$C$1004+DATE($B$4+1,1,1)-ABS(Bookings!$C$5:$C$1004-DATE($B$4+1,1,1)))/2)-((Bookings!$B$5:$B$1004+DATE($B$4,1,1)+ABS(Bookings!$B$5:$B$1004-DATE($B$4,1,1)))/2)))/2))) | C37: =IF($A37="","",IF(K37=0,0,B37/K37)) | D37: =IF($A37="","",IF(B37=0,0,L37/B37)) | E37: =IF($A37="","",IF(K37=0,0,L37/K37)) | F37: =IF($A37="","",SUMPRODUCT(Bookings!$AA$5:$AA$1004*(($A37="All properties")+(Bookings!$D$5:$D$1004=$A37)>0)*(((((Bookings!$C$5:$C$1004+DATE($B$4+1,1,1)-ABS(Bookings!$C$5:$C$1004-DATE($B$4+1,1,1)))/2)-((Bookings!$B$5:$B$1004+DATE($B$4,1,1)+ABS(Bookings!$B$5:$B$1004-DATE($B$4,1,1)))/2))+ABS(((Bookings!$C$5:$C$1004+DATE($B$4+1,1,1)-ABS(Bookings!$C$5:$C$1004-DATE($B$4+1,1,1)))/2)-((Bookings!$B$5:$B$1004+DATE($B$4,1,1)+ABS(Bookings!$B$5:$B$1004-DATE($B$4,1,1)))/2)))/2)*Bookings!$AC$5:$AC$1004)) | G37: =IF($A37="","",SUMPRODUCT(Bookings!$AA$5:$AA$1004*(($A37="All properties")+(Bookings!$D$5:$D$1004=$A37)>0)*(((((Bookings!$C$5:$C$1004+DATE($B$4+1,1,1)-ABS(Bookings!$C$5:$C$1004-DATE($B$4+1,1,1)))/2)-((Bookings!$B$5:$B$1004+DATE($B$4,1,1)+ABS(Bookings!$B$5:$B$1004-DATE($B$4,1,1)))/2))+ABS(((Bookings!$C$5:$C$1004+DATE($B$4+1,1,1)-ABS(Bookings!$C$5:$C$1004-DATE($B$4+1,1,1)))/2)-((Bookings!$B$5:$B$1004+DATE($B$4,1,1)+ABS(Bookings!$B$5:$B$1004-DATE($B$4,1,1)))/2)))/2)*Bookings!$AD$5:$AD$1004)) | H37: =IF($A37="","",SUMIFS(Expenses!$F$5:$F$1004,Expenses!$A$5:$A$1004,">="&DATE($B$4,1,1),Expenses!$A$5:$A$1004,"<"&DATE($B$4+1,1,1),Expenses!$B$5:$B$1004,$A37)) | I37: =IF($A37="","",F37-G37-H37) | K37: =IF($A37="","",SUMPRODUCT((Properties!$A$5:$A$24<>"")*(($A37="All properties")+(Properties!$A$5:$A$24=$A37)>0)*(((DATE($B$4+1,1,1)-((Properties!$K$5:$K$24+DATE($B$4,1,1)+ABS(Properties!$K$5:$K$24-DATE($B$4,1,1)))/2))+ABS(DATE($B$4+1,1,1)-((Properties!$K$5:$K$24+DATE($B$4,1,1)+ABS(Properties!$K$5:$K$24-DATE($B$4,1,1)))/2)))/2))) | L37: =IF($A37="","",SUMPRODUCT(Bookings!$AA$5:$AA$1004*(($A37="All properties")+(Bookings!$D$5:$D$1004=$A37)>0)*(((((Bookings!$C$5:$C$1004+DATE($B$4+1,1,1)-ABS(Bookings!$C$5:$C$1004-DATE($B$4+1,1,1)))/2)-((Bookings!$B$5:$B$1004+DATE($B$4,1,1)+ABS(Bookings!$B$5:$B$1004-DATE($B$4,1,1)))/2))+ABS(((Bookings!$C$5:$C$1004+DATE($B$4+1,1,1)-ABS(Bookings!$C$5:$C$1004-DATE($B$4+1,1,1)))/2)-((Bookings!$B$5:$B$1004+DATE($B$4,1,1)+ABS(Bookings!$B$5:$B$1004-DATE($B$4,1,1)))/2)))/2)*Bookings!$AB$5:$AB$1004))
A38: =IF(Properties!A16="","",Properties!A16) | B38: =IF($A38="","",SUMPRODUCT(Bookings!$AA$5:$AA$1004*(($A38="All properties")+(Bookings!$D$5:$D$1004=$A38)>0)*(((((Bookings!$C$5:$C$1004+DATE($B$4+1,1,1)-ABS(Bookings!$C$5:$C$1004-DATE($B$4+1,1,1)))/2)-((Bookings!$B$5:$B$1004+DATE($B$4,1,1)+ABS(Bookings!$B$5:$B$1004-DATE($B$4,1,1)))/2))+ABS(((Bookings!$C$5:$C$1004+DATE($B$4+1,1,1)-ABS(Bookings!$C$5:$C$1004-DATE($B$4+1,1,1)))/2)-((Bookings!$B$5:$B$1004+DATE($B$4,1,1)+ABS(Bookings!$B$5:$B$1004-DATE($B$4,1,1)))/2)))/2))) | C38: =IF($A38="","",IF(K38=0,0,B38/K38)) | D38: =IF($A38="","",IF(B38=0,0,L38/B38)) | E38: =IF($A38="","",IF(K38=0,0,L38/K38)) | F38: =IF($A38="","",SUMPRODUCT(Bookings!$AA$5:$AA$1004*(($A38="All properties")+(Bookings!$D$5:$D$1004=$A38)>0)*(((((Bookings!$C$5:$C$1004+DATE($B$4+1,1,1)-ABS(Bookings!$C$5:$C$1004-DATE($B$4+1,1,1)))/2)-((Bookings!$B$5:$B$1004+DATE($B$4,1,1)+ABS(Bookings!$B$5:$B$1004-DATE($B$4,1,1)))/2))+ABS(((Bookings!$C$5:$C$1004+DATE($B$4+1,1,1)-ABS(Bookings!$C$5:$C$1004-DATE($B$4+1,1,1)))/2)-((Bookings!$B$5:$B$1004+DATE($B$4,1,1)+ABS(Bookings!$B$5:$B$1004-DATE($B$4,1,1)))/2)))/2)*Bookings!$AC$5:$AC$1004)) | G38: =IF($A38="","",SUMPRODUCT(Bookings!$AA$5:$AA$1004*(($A38="All properties")+(Bookings!$D$5:$D$1004=$A38)>0)*(((((Bookings!$C$5:$C$1004+DATE($B$4+1,1,1)-ABS(Bookings!$C$5:$C$1004-DATE($B$4+1,1,1)))/2)-((Bookings!$B$5:$B$1004+DATE($B$4,1,1)+ABS(Bookings!$B$5:$B$1004-DATE($B$4,1,1)))/2))+ABS(((Bookings!$C$5:$C$1004+DATE($B$4+1,1,1)-ABS(Bookings!$C$5:$C$1004-DATE($B$4+1,1,1)))/2)-((Bookings!$B$5:$B$1004+DATE($B$4,1,1)+ABS(Bookings!$B$5:$B$1004-DATE($B$4,1,1)))/2)))/2)*Bookings!$AD$5:$AD$1004)) | H38: =IF($A38="","",SUMIFS(Expenses!$F$5:$F$1004,Expenses!$A$5:$A$1004,">="&DATE($B$4,1,1),Expenses!$A$5:$A$1004,"<"&DATE($B$4+1,1,1),Expenses!$B$5:$B$1004,$A38)) | I38: =IF($A38="","",F38-G38-H38) | K38: =IF($A38="","",SUMPRODUCT((Properties!$A$5:$A$24<>"")*(($A38="All properties")+(Properties!$A$5:$A$24=$A38)>0)*(((DATE($B$4+1,1,1)-((Properties!$K$5:$K$24+DATE($B$4,1,1)+ABS(Properties!$K$5:$K$24-DATE($B$4,1,1)))/2))+ABS(DATE($B$4+1,1,1)-((Properties!$K$5:$K$24+DATE($B$4,1,1)+ABS(Properties!$K$5:$K$24-DATE($B$4,1,1)))/2)))/2))) | L38: =IF($A38="","",SUMPRODUCT(Bookings!$AA$5:$AA$1004*(($A38="All properties")+(Bookings!$D$5:$D$1004=$A38)>0)*(((((Bookings!$C$5:$C$1004+DATE($B$4+1,1,1)-ABS(Bookings!$C$5:$C$1004-DATE($B$4+1,1,1)))/2)-((Bookings!$B$5:$B$1004+DATE($B$4,1,1)+ABS(Bookings!$B$5:$B$1004-DATE($B$4,1,1)))/2))+ABS(((Bookings!$C$5:$C$1004+DATE($B$4+1,1,1)-ABS(Bookings!$C$5:$C$1004-DATE($B$4+1,1,1)))/2)-((Bookings!$B$5:$B$1004+DATE($B$4,1,1)+ABS(Bookings!$B$5:$B$1004-DATE($B$4,1,1)))/2)))/2)*Bookings!$AB$5:$AB$1004))
... A46: =IF(Properties!A24="","",Properties!A24) | B46: =IF($A46="","",SUMPRODUCT(Bookings!$AA$5:$AA$1004*(($A46="All properties")+(Bookings!$D$5:$D$1004=$A46)>0)*(((((Bookings!$C$5:$C$1004+DATE($B$4+1,1,1)-ABS(Bookings!$C$5:$C$1004-DATE($B$4+1,1,1)))/2)-((Bookings!$B$5:$B$1004+DATE($B$4,1,1)+ABS(Bookings!$B$5:$B$1004-DATE($B$4,1,1)))/2))+ABS(((Bookings!$C$5:$C$1004+DATE($B$4+1,1,1)-ABS(Bookings!$C$5:$C$1004-DATE($B$4+1,1,1)))/2)-((Bookings!$B$5:$B$1004+DATE($B$4,1,1)+ABS(Bookings!$B$5:$B$1004-DATE($B$4,1,1)))/2)))/2))) | C46: =IF($A46="","",IF(K46=0,0,B46/K46)) | D46: =IF($A46="","",IF(B46=0,0,L46/B46)) | E46: =IF($A46="","",IF(K46=0,0,L46/K46)) | F46: =IF($A46="","",SUMPRODUCT(Bookings!$AA$5:$AA$1004*(($A46="All properties")+(Bookings!$D$5:$D$1004=$A46)>0)*(((((Bookings!$C$5:$C$1004+DATE($B$4+1,1,1)-ABS(Bookings!$C$5:$C$1004-DATE($B$4+1,1,1)))/2)-((Bookings!$B$5:$B$1004+DATE($B$4,1,1)+ABS(Bookings!$B$5:$B$1004-DATE($B$4,1,1)))/2))+ABS(((Bookings!$C$5:$C$1004+DATE($B$4+1,1,1)-ABS(Bookings!$C$5:$C$1004-DATE($B$4+1,1,1)))/2)-((Bookings!$B$5:$B$1004+DATE($B$4,1,1)+ABS(Bookings!$B$5:$B$1004-DATE($B$4,1,1)))/2)))/2)*Bookings!$AC$5:$AC$1004)) | G46: =IF($A46="","",SUMPRODUCT(Bookings!$AA$5:$AA$1004*(($A46="All properties")+(Bookings!$D$5:$D$1004=$A46)>0)*(((((Bookings!$C$5:$C$1004+DATE($B$4+1,1,1)-ABS(Bookings!$C$5:$C$1004-DATE($B$4+1,1,1)))/2)-((Bookings!$B$5:$B$1004+DATE($B$4,1,1)+ABS(Bookings!$B$5:$B$1004-DATE($B$4,1,1)))/2))+ABS(((Bookings!$C$5:$C$1004+DATE($B$4+1,1,1)-ABS(Bookings!$C$5:$C$1004-DATE($B$4+1,1,1)))/2)-((Bookings!$B$5:$B$1004+DATE($B$4,1,1)+ABS(Bookings!$B$5:$B$1004-DATE($B$4,1,1)))/2)))/2)*Bookings!$AD$5:$AD$1004)) | H46: =IF($A46="","",SUMIFS(Expenses!$F$5:$F$1004,Expenses!$A$5:$A$1004,">="&DATE($B$4,1,1),Expenses!$A$5:$A$1004,"<"&DATE($B$4+1,1,1),Expenses!$B$5:$B$1004,$A46)) | I46: =IF($A46="","",F46-G46-H46) | K46: =IF($A46="","",SUMPRODUCT((Properties!$A$5:$A$24<>"")*(($A46="All properties")+(Properties!$A$5:$A$24=$A46)>0)*(((DATE($B$4+1,1,1)-((Properties!$K$5:$K$24+DATE($B$4,1,1)+ABS(Properties!$K$5:$K$24-DATE($B$4,1,1)))/2))+ABS(DATE($B$4+1,1,1)-((Properties!$K$5:$K$24+DATE($B$4,1,1)+ABS(Properties!$K$5:$K$24-DATE($B$4,1,1)))/2)))/2))) | L46: =IF($A46="","",SUMPRODUCT(Bookings!$AA$5:$AA$1004*(($A46="All properties")+(Bookings!$D$5:$D$1004=$A46)>0)*(((((Bookings!$C$5:$C$1004+DATE($B$4+1,1,1)-ABS(Bookings!$C$5:$C$1004-DATE($B$4+1,1,1)))/2)-((Bookings!$B$5:$B$1004+DATE($B$4,1,1)+ABS(Bookings!$B$5:$B$1004-DATE($B$4,1,1)))/2))+ABS(((Bookings!$C$5:$C$1004+DATE($B$4+1,1,1)-ABS(Bookings!$C$5:$C$1004-DATE($B$4+1,1,1)))/2)-((Bookings!$B$5:$B$1004+DATE($B$4,1,1)+ABS(Bookings!$B$5:$B$1004-DATE($B$4,1,1)))/2)))/2)*Bookings!$AB$5:$AB$1004))
A47: Shared costs (no property) | H47: =H22-SUM(H27:H46) -> 19.99 | I47: =-H47 -> -19.99
A48: Note: Tax set-aside is a planning estimate, not tax advice. Stays that cross months are split by nights.
A49: Year total profit (row 22) = sum of properties minus shared costs.

Sheet Monthly Summary
A1: Monthly Summary
A2: Pick a property (or All properties) and a year.
A4: Property | B4: All properties | F4: Year | G4: =Dashboard!B4 -> 2026
A6: Month | B6: Nights booked | C6: Occupancy | D6: ADR | E6: RevPAR | F6: Payout | G6: Cleaning costs | H6: Expenses | I6: Profit | K6: Nights available | L6: Rent | M6: Stays (by check-in) | N6: Avg stay (nights) | O6: Cleaning fees collected | P6: Platform fees
A7: =TEXT(DATE($G$4,1,1),"mmm yyyy") -> Jan 2026 | B7: =SUMPRODUCT(Bookings!$AA$5:$AA$1004*(($B$4="All properties")+(Bookings!$D$5:$D$1004=$B$4)>0)*(((((Bookings!$C$5:$C$1004+DATE($G$4,2,1)-ABS(Bookings!$C$5:$C$1004-DATE($G$4,2,1)))/2)-((Bookings!$B$5:$B$1004+DATE($G$4,1,1)+ABS(Bookings!$B$5:$B$1004-DATE($G$4,1,1)))/2))+ABS(((Bookings!$C$5:$C$1004+DATE($G$4,2,1)-ABS(Bookings!$C$5:$C$1004-DATE($G$4,2,1)))/2)-((Bookings!$B$5:$B$1004+DATE($G$4,1,1)+ABS(Bookings!$B$5:$B$1004-DATE($G$4,1,1)))/2)))/2)) -> 0 | C7: =IF(K7=0,0,B7/K7) -> 0 | D7: =IF(B7=0,0,L7/B7) -> 0 | E7: =IF(K7=0,0,L7/K7) -> 0 | F7: =SUMPRODUCT(Bookings!$AA$5:$AA$1004*(($B$4="All properties")+(Bookings!$D$5:$D$1004=$B$4)>0)*(((((Bookings!$C$5:$C$1004+DATE($G$4,2,1)-ABS(Bookings!$C$5:$C$1004-DATE($G$4,2,1)))/2)-((Bookings!$B$5:$B$1004+DATE($G$4,1,1)+ABS(Bookings!$B$5:$B$1004-DATE($G$4,1,1)))/2))+ABS(((Bookings!$C$5:$C$1004+DATE($G$4,2,1)-ABS(Bookings!$C$5:$C$1004-DATE($G$4,2,1)))/2)-((Bookings!$B$5:$B$1004+DATE($G$4,1,1)+ABS(Bookings!$B$5:$B$1004-DATE($G$4,1,1)))/2)))/2)*Bookings!$AC$5:$AC$1004) -> 0 | G7: =SUMPRODUCT(Bookings!$AA$5:$AA$1004*(($B$4="All properties")+(Bookings!$D$5:$D$1004=$B$4)>0)*(((((Bookings!$C$5:$C$1004+DATE($G$4,2,1)-ABS(Bookings!$C$5:$C$1004-DATE($G$4,2,1)))/2)-((Bookings!$B$5:$B$1004+DATE($G$4,1,1)+ABS(Bookings!$B$5:$B$1004-DATE($G$4,1,1)))/2))+ABS(((Bookings!$C$5:$C$1004+DATE($G$4,2,1)-ABS(Bookings!$C$5:$C$1004-DATE($G$4,2,1)))/2)-((Bookings!$B$5:$B$1004+DATE($G$4,1,1)+ABS(Bookings!$B$5:$B$1004-DATE($G$4,1,1)))/2)))/2)*Bookings!$AD$5:$AD$1004) -> 0 | H7: =IF($B$4="All properties",SUMIFS(Expenses!$F$5:$F$1004,Expenses!$A$5:$A$1004,">="&DATE($G$4,1,1),Expenses!$A$5:$A$1004,"<"&DATE($G$4,2,1)),SUMIFS(Expenses!$F$5:$F$1004,Expenses!$A$5:$A$1004,">="&DATE($G$4,1,1),Expenses!$A$5:$A$1004,"<"&DATE($G$4,2,1),Expenses!$B$5:$B$1004,$B$4)) -> 0 | I7: =F7-G7-H7 -> 0 | K7: =SUMPRODUCT((Properties!$A$5:$A$24<>"")*(($B$4="All properties")+(Properties!$A$5:$A$24=$B$4)>0)*(((DATE($G$4,2,1)-((Properties!$K$5:$K$24+DATE($G$4,1,1)+ABS(Properties!$K$5:$K$24-DATE($G$4,1,1)))/2))+ABS(DATE($G$4,2,1)-((Properties!$K$5:$K$24+DATE($G$4,1,1)+ABS(Properties!$K$5:$K$24-DATE($G$4,1,1)))/2)))/2)) -> 31 | L7: =SUMPRODUCT(Bookings!$AA$5:$AA$1004*(($B$4="All properties")+(Bookings!$D$5:$D$1004=$B$4)>0)*(((((Bookings!$C$5:$C$1004+DATE($G$4,2,1)-ABS(Bookings!$C$5:$C$1004-DATE($G$4,2,1)))/2)-((Bookings!$B$5:$B$1004+DATE($G$4,1,1)+ABS(Bookings!$B$5:$B$1004-DATE($G$4,1,1)))/2))+ABS(((Bookings!$C$5:$C$1004+DATE($G$4,2,1)-ABS(Bookings!$C$5:$C$1004-DATE($G$4,2,1)))/2)-((Bookings!$B$5:$B$1004+DATE($G$4,1,1)+ABS(Bookings!$B$5:$B$1004-DATE($G$4,1,1)))/2)))/2)*Bookings!$AB$5:$AB$1004) -> 0 | M7: =SUMPRODUCT(Bookings!$AA$5:$AA$1004*(($B$4="All properties")+(Bookings!$D$5:$D$1004=$B$4)>0)*(Bookings!$B$5:$B$1004>=DATE($G$4,1,1))*(Bookings!$B$5:$B$1004<DATE($G$4,2,1))) -> 0 | N7: =IF(M7=0,0,SUMPRODUCT(Bookings!$AA$5:$AA$1004*(($B$4="All properties")+(Bookings!$D$5:$D$1004=$B$4)>0)*(Bookings!$B$5:$B$1004>=DATE($G$4,1,1))*(Bookings!$B$5:$B$1004<DATE($G$4,2,1))*Bookings!$AH$5:$AH$1004)/M7) -> 0 | O7: =SUMPRODUCT(Bookings!$AA$5:$AA$1004*(($B$4="All properties")+(Bookings!$D$5:$D$1004=$B$4)>0)*(((((Bookings!$C$5:$C$1004+DATE($G$4,2,1)-ABS(Bookings!$C$5:$C$1004-DATE($G$4,2,1)))/2)-((Bookings!$B$5:$B$1004+DATE($G$4,1,1)+ABS(Bookings!$B$5:$B$1004-DATE($G$4,1,1)))/2))+ABS(((Bookings!$C$5:$C$1004+DATE($G$4,2,1)-ABS(Bookings!$C$5:$C$1004-DATE($G$4,2,1)))/2)-((Bookings!$B$5:$B$1004+DATE($G$4,1,1)+ABS(Bookings!$B$5:$B$1004-DATE($G$4,1,1)))/2)))/2)*Bookings!$AF$5:$AF$1004) -> 0 | P7: =SUMPRODUCT(Bookings!$AA$5:$AA$1004*(($B$4="All properties")+(Bookings!$D$5:$D$1004=$B$4)>0)*(((((Bookings!$C$5:$C$1004+DATE($G$4,2,1)-ABS(Bookings!$C$5:$C$1004-DATE($G$4,2,1)))/2)-((Bookings!$B$5:$B$1004+DATE($G$4,1,1)+ABS(Bookings!$B$5:$B$1004-DATE($G$4,1,1)))/2))+ABS(((Bookings!$C$5:$C$1004+DATE($G$4,2,1)-ABS(Bookings!$C$5:$C$1004-DATE($G$4,2,1)))/2)-((Bookings!$B$5:$B$1004+DATE($G$4,1,1)+ABS(Bookings!$B$5:$B$1004-DATE($G$4,1,1)))/2)))/2)*Bookings!$AE$5:$AE$1004) -> 0
A8: =TEXT(DATE($G$4,2,1),"mmm yyyy") -> Feb 2026 | B8: =SUMPRODUCT(Bookings!$AA$5:$AA$1004*(($B$4="All properties")+(Bookings!$D$5:$D$1004=$B$4)>0)*(((((Bookings!$C$5:$C$1004+DATE($G$4,3,1)-ABS(Bookings!$C$5:$C$1004-DATE($G$4,3,1)))/2)-((Bookings!$B$5:$B$1004+DATE($G$4,2,1)+ABS(Bookings!$B$5:$B$1004-DATE($G$4,2,1)))/2))+ABS(((Bookings!$C$5:$C$1004+DATE($G$4,3,1)-ABS(Bookings!$C$5:$C$1004-DATE($G$4,3,1)))/2)-((Bookings!$B$5:$B$1004+DATE($G$4,2,1)+ABS(Bookings!$B$5:$B$1004-DATE($G$4,2,1)))/2)))/2)) -> 0 | C8: =IF(K8=0,0,B8/K8) -> 0 | D8: =IF(B8=0,0,L8/B8) -> 0 | E8: =IF(K8=0,0,L8/K8) -> 0 | F8: =SUMPRODUCT(Bookings!$AA$5:$AA$1004*(($B$4="All properties")+(Bookings!$D$5:$D$1004=$B$4)>0)*(((((Bookings!$C$5:$C$1004+DATE($G$4,3,1)-ABS(Bookings!$C$5:$C$1004-DATE($G$4,3,1)))/2)-((Bookings!$B$5:$B$1004+DATE($G$4,2,1)+ABS(Bookings!$B$5:$B$1004-DATE($G$4,2,1)))/2))+ABS(((Bookings!$C$5:$C$1004+DATE($G$4,3,1)-ABS(Bookings!$C$5:$C$1004-DATE($G$4,3,1)))/2)-((Bookings!$B$5:$B$1004+DATE($G$4,2,1)+ABS(Bookings!$B$5:$B$1004-DATE($G$4,2,1)))/2)))/2)*Bookings!$AC$5:$AC$1004) -> 0 | G8: =SUMPRODUCT(Bookings!$AA$5:$AA$1004*(($B$4="All properties")+(Bookings!$D$5:$D$1004=$B$4)>0)*(((((Bookings!$C$5:$C$1004+DATE($G$4,3,1)-ABS(Bookings!$C$5:$C$1004-DATE($G$4,3,1)))/2)-((Bookings!$B$5:$B$1004+DATE($G$4,2,1)+ABS(Bookings!$B$5:$B$1004-DATE($G$4,2,1)))/2))+ABS(((Bookings!$C$5:$C$1004+DATE($G$4,3,1)-ABS(Bookings!$C$5:$C$1004-DATE($G$4,3,1)))/2)-((Bookings!$B$5:$B$1004+DATE($G$4,2,1)+ABS(Bookings!$B$5:$B$1004-DATE($G$4,2,1)))/2)))/2)*Bookings!$AD$5:$AD$1004) -> 0 | H8: =IF($B$4="All properties",SUMIFS(Expenses!$F$5:$F$1004,Expenses!$A$5:$A$1004,">="&DATE($G$4,2,1),Expenses!$A$5:$A$1004,"<"&DATE($G$4,3,1)),SUMIFS(Expenses!$F$5:$F$1004,Expenses!$A$5:$A$1004,">="&DATE($G$4,2,1),Expenses!$A$5:$A$1004,"<"&DATE($G$4,3,1),Expenses!$B$5:$B$1004,$B$4)) -> 0 | I8: =F8-G8-H8 -> 0 | K8: =SUMPRODUCT((Properties!$A$5:$A$24<>"")*(($B$4="All properties")+(Properties!$A$5:$A$24=$B$4)>0)*(((DATE($G$4,3,1)-((Properties!$K$5:$K$24+DATE($G$4,2,1)+ABS(Properties!$K$5:$K$24-DATE($G$4,2,1)))/2))+ABS(DATE($G$4,3,1)-((Properties!$K$5:$K$24+DATE($G$4,2,1)+ABS(Properties!$K$5:$K$24-DATE($G$4,2,1)))/2)))/2)) -> 28 | L8: =SUMPRODUCT(Bookings!$AA$5:$AA$1004*(($B$4="All properties")+(Bookings!$D$5:$D$1004=$B$4)>0)*(((((Bookings!$C$5:$C$1004+DATE($G$4,3,1)-ABS(Bookings!$C$5:$C$1004-DATE($G$4,3,1)))/2)-((Bookings!$B$5:$B$1004+DATE($G$4,2,1)+ABS(Bookings!$B$5:$B$1004-DATE($G$4,2,1)))/2))+ABS(((Bookings!$C$5:$C$1004+DATE($G$4,3,1)-ABS(Bookings!$C$5:$C$1004-DATE($G$4,3,1)))/2)-((Bookings!$B$5:$B$1004+DATE($G$4,2,1)+ABS(Bookings!$B$5:$B$1004-DATE($G$4,2,1)))/2)))/2)*Bookings!$AB$5:$AB$1004) -> 0 | M8: =SUMPRODUCT(Bookings!$AA$5:$AA$1004*(($B$4="All properties")+(Bookings!$D$5:$D$1004=$B$4)>0)*(Bookings!$B$5:$B$1004>=DATE($G$4,2,1))*(Bookings!$B$5:$B$1004<DATE($G$4,3,1))) -> 0 | N8: =IF(M8=0,0,SUMPRODUCT(Bookings!$AA$5:$AA$1004*(($B$4="All properties")+(Bookings!$D$5:$D$1004=$B$4)>0)*(Bookings!$B$5:$B$1004>=DATE($G$4,2,1))*(Bookings!$B$5:$B$1004<DATE($G$4,3,1))*Bookings!$AH$5:$AH$1004)/M8) -> 0 | O8: =SUMPRODUCT(Bookings!$AA$5:$AA$1004*(($B$4="All properties")+(Bookings!$D$5:$D$1004=$B$4)>0)*(((((Bookings!$C$5:$C$1004+DATE($G$4,3,1)-ABS(Bookings!$C$5:$C$1004-DATE($G$4,3,1)))/2)-((Bookings!$B$5:$B$1004+DATE($G$4,2,1)+ABS(Bookings!$B$5:$B$1004-DATE($G$4,2,1)))/2))+ABS(((Bookings!$C$5:$C$1004+DATE($G$4,3,1)-ABS(Bookings!$C$5:$C$1004-DATE($G$4,3,1)))/2)-((Bookings!$B$5:$B$1004+DATE($G$4,2,1)+ABS(Bookings!$B$5:$B$1004-DATE($G$4,2,1)))/2)))/2)*Bookings!$AF$5:$AF$1004) -> 0 | P8: =SUMPRODUCT(Bookings!$AA$5:$AA$1004*(($B$4="All properties")+(Bookings!$D$5:$D$1004=$B$4)>0)*(((((Bookings!$C$5:$C$1004+DATE($G$4,3,1)-ABS(Bookings!$C$5:$C$1004-DATE($G$4,3,1)))/2)-((Bookings!$B$5:$B$1004+DATE($G$4,2,1)+ABS(Bookings!$B$5:$B$1004-DATE($G$4,2,1)))/2))+ABS(((Bookings!$C$5:$C$1004+DATE($G$4,3,1)-ABS(Bookings!$C$5:$C$1004-DATE($G$4,3,1)))/2)-((Bookings!$B$5:$B$1004+DATE($G$4,2,1)+ABS(Bookings!$B$5:$B$1004-DATE($G$4,2,1)))/2)))/2)*Bookings!$AE$5:$AE$1004) -> 0
A9: =TEXT(DATE($G$4,3,1),"mmm yyyy") -> Mar 2026 | B9: =SUMPRODUCT(Bookings!$AA$5:$AA$1004*(($B$4="All properties")+(Bookings!$D$5:$D$1004=$B$4)>0)*(((((Bookings!$C$5:$C$1004+DATE($G$4,4,1)-ABS(Bookings!$C$5:$C$1004-DATE($G$4,4,1)))/2)-((Bookings!$B$5:$B$1004+DATE($G$4,3,1)+ABS(Bookings!$B$5:$B$1004-DATE($G$4,3,1)))/2))+ABS(((Bookings!$C$5:$C$1004+DATE($G$4,4,1)-ABS(Bookings!$C$5:$C$1004-DATE($G$4,4,1)))/2)-((Bookings!$B$5:$B$1004+DATE($G$4,3,1)+ABS(Bookings!$B$5:$B$1004-DATE($G$4,3,1)))/2)))/2)) -> 0 | C9: =IF(K9=0,0,B9/K9) -> 0 | D9: =IF(B9=0,0,L9/B9) -> 0 | E9: =IF(K9=0,0,L9/K9) -> 0 | F9: =SUMPRODUCT(Bookings!$AA$5:$AA$1004*(($B$4="All properties")+(Bookings!$D$5:$D$1004=$B$4)>0)*(((((Bookings!$C$5:$C$1004+DATE($G$4,4,1)-ABS(Bookings!$C$5:$C$1004-DATE($G$4,4,1)))/2)-((Bookings!$B$5:$B$1004+DATE($G$4,3,1)+ABS(Bookings!$B$5:$B$1004-DATE($G$4,3,1)))/2))+ABS(((Bookings!$C$5:$C$1004+DATE($G$4,4,1)-ABS(Bookings!$C$5:$C$1004-DATE($G$4,4,1)))/2)-((Bookings!$B$5:$B$1004+DATE($G$4,3,1)+ABS(Bookings!$B$5:$B$1004-DATE($G$4,3,1)))/2)))/2)*Bookings!$AC$5:$AC$1004) -> 0 | G9: =SUMPRODUCT(Bookings!$AA$5:$AA$1004*(($B$4="All properties")+(Bookings!$D$5:$D$1004=$B$4)>0)*(((((Bookings!$C$5:$C$1004+DATE($G$4,4,1)-ABS(Bookings!$C$5:$C$1004-DATE($G$4,4,1)))/2)-((Bookings!$B$5:$B$1004+DATE($G$4,3,1)+ABS(Bookings!$B$5:$B$1004-DATE($G$4,3,1)))/2))+ABS(((Bookings!$C$5:$C$1004+DATE($G$4,4,1)-ABS(Bookings!$C$5:$C$1004-DATE($G$4,4,1)))/2)-((Bookings!$B$5:$B$1004+DATE($G$4,3,1)+ABS(Bookings!$B$5:$B$1004-DATE($G$4,3,1)))/2)))/2)*Bookings!$AD$5:$AD$1004) -> 0 | H9: =IF($B$4="All properties",SUMIFS(Expenses!$F$5:$F$1004,Expenses!$A$5:$A$1004,">="&DATE($G$4,3,1),Expenses!$A$5:$A$1004,"<"&DATE($G$4,4,1)),SUMIFS(Expenses!$F$5:$F$1004,Expenses!$A$5:$A$1004,">="&DATE($G$4,3,1),Expenses!$A$5:$A$1004,"<"&DATE($G$4,4,1),Expenses!$B$5:$B$1004,$B$4)) -> 0 | I9: =F9-G9-H9 -> 0 | K9: =SUMPRODUCT((Properties!$A$5:$A$24<>"")*(($B$4="All properties")+(Properties!$A$5:$A$24=$B$4)>0)*(((DATE($G$4,4,1)-((Properties!$K$5:$K$24+DATE($G$4,3,1)+ABS(Properties!$K$5:$K$24-DATE($G$4,3,1)))/2))+ABS(DATE($G$4,4,1)-((Properties!$K$5:$K$24+DATE($G$4,3,1)+ABS(Properties!$K$5:$K$24-DATE($G$4,3,1)))/2)))/2)) -> 31 | L9: =SUMPRODUCT(Bookings!$AA$5:$AA$1004*(($B$4="All properties")+(Bookings!$D$5:$D$1004=$B$4)>0)*(((((Bookings!$C$5:$C$1004+DATE($G$4,4,1)-ABS(Bookings!$C$5:$C$1004-DATE($G$4,4,1)))/2)-((Bookings!$B$5:$B$1004+DATE($G$4,3,1)+ABS(Bookings!$B$5:$B$1004-DATE($G$4,3,1)))/2))+ABS(((Bookings!$C$5:$C$1004+DATE($G$4,4,1)-ABS(Bookings!$C$5:$C$1004-DATE($G$4,4,1)))/2)-((Bookings!$B$5:$B$1004+DATE($G$4,3,1)+ABS(Bookings!$B$5:$B$1004-DATE($G$4,3,1)))/2)))/2)*Bookings!$AB$5:$AB$1004) -> 0 | M9: =SUMPRODUCT(Bookings!$AA$5:$AA$1004*(($B$4="All properties")+(Bookings!$D$5:$D$1004=$B$4)>0)*(Bookings!$B$5:$B$1004>=DATE($G$4,3,1))*(Bookings!$B$5:$B$1004<DATE($G$4,4,1))) -> 0 | N9: =IF(M9=0,0,SUMPRODUCT(Bookings!$AA$5:$AA$1004*(($B$4="All properties")+(Bookings!$D$5:$D$1004=$B$4)>0)*(Bookings!$B$5:$B$1004>=DATE($G$4,3,1))*(Bookings!$B$5:$B$1004<DATE($G$4,4,1))*Bookings!$AH$5:$AH$1004)/M9) -> 0 | O9: =SUMPRODUCT(Bookings!$AA$5:$AA$1004*(($B$4="All properties")+(Bookings!$D$5:$D$1004=$B$4)>0)*(((((Bookings!$C$5:$C$1004+DATE($G$4,4,1)-ABS(Bookings!$C$5:$C$1004-DATE($G$4,4,1)))/2)-((Bookings!$B$5:$B$1004+DATE($G$4,3,1)+ABS(Bookings!$B$5:$B$1004-DATE($G$4,3,1)))/2))+ABS(((Bookings!$C$5:$C$1004+DATE($G$4,4,1)-ABS(Bookings!$C$5:$C$1004-DATE($G$4,4,1)))/2)-((Bookings!$B$5:$B$1004+DATE($G$4,3,1)+ABS(Bookings!$B$5:$B$1004-DATE($G$4,3,1)))/2)))/2)*Bookings!$AF$5:$AF$1004) -> 0 | P9: =SUMPRODUCT(Bookings!$AA$5:$AA$1004*(($B$4="All properties")+(Bookings!$D$5:$D$1004=$B$4)>0)*(((((Bookings!$C$5:$C$1004+DATE($G$4,4,1)-ABS(Bookings!$C$5:$C$1004-DATE($G$4,4,1)))/2)-((Bookings!$B$5:$B$1004+DATE($G$4,3,1)+ABS(Bookings!$B$5:$B$1004-DATE($G$4,3,1)))/2))+ABS(((Bookings!$C$5:$C$1004+DATE($G$4,4,1)-ABS(Bookings!$C$5:$C$1004-DATE($G$4,4,1)))/2)-((Bookings!$B$5:$B$1004+DATE($G$4,3,1)+ABS(Bookings!$B$5:$B$1004-DATE($G$4,3,1)))/2)))/2)*Bookings!$AE$5:$AE$1004) -> 0
A10: =TEXT(DATE($G$4,4,1),"mmm yyyy") -> Apr 2026 | B10: =SUMPRODUCT(Bookings!$AA$5:$AA$1004*(($B$4="All properties")+(Bookings!$D$5:$D$1004=$B$4)>0)*(((((Bookings!$C$5:$C$1004+DATE($G$4,5,1)-ABS(Bookings!$C$5:$C$1004-DATE($G$4,5,1)))/2)-((Bookings!$B$5:$B$1004+DATE($G$4,4,1)+ABS(Bookings!$B$5:$B$1004-DATE($G$4,4,1)))/2))+ABS(((Bookings!$C$5:$C$1004+DATE($G$4,5,1)-ABS(Bookings!$C$5:$C$1004-DATE($G$4,5,1)))/2)-((Bookings!$B$5:$B$1004+DATE($G$4,4,1)+ABS(Bookings!$B$5:$B$1004-DATE($G$4,4,1)))/2)))/2)) -> 0 | C10: =IF(K10=0,0,B10/K10) -> 0 | D10: =IF(B10=0,0,L10/B10) -> 0 | E10: =IF(K10=0,0,L10/K10) -> 0 | F10: =SUMPRODUCT(Bookings!$AA$5:$AA$1004*(($B$4="All properties")+(Bookings!$D$5:$D$1004=$B$4)>0)*(((((Bookings!$C$5:$C$1004+DATE($G$4,5,1)-ABS(Bookings!$C$5:$C$1004-DATE($G$4,5,1)))/2)-((Bookings!$B$5:$B$1004+DATE($G$4,4,1)+ABS(Bookings!$B$5:$B$1004-DATE($G$4,4,1)))/2))+ABS(((Bookings!$C$5:$C$1004+DATE($G$4,5,1)-ABS(Bookings!$C$5:$C$1004-DATE($G$4,5,1)))/2)-((Bookings!$B$5:$B$1004+DATE($G$4,4,1)+ABS(Bookings!$B$5:$B$1004-DATE($G$4,4,1)))/2)))/2)*Bookings!$AC$5:$AC$1004) -> 0 | G10: =SUMPRODUCT(Bookings!$AA$5:$AA$1004*(($B$4="All properties")+(Bookings!$D$5:$D$1004=$B$4)>0)*(((((Bookings!$C$5:$C$1004+DATE($G$4,5,1)-ABS(Bookings!$C$5:$C$1004-DATE($G$4,5,1)))/2)-((Bookings!$B$5:$B$1004+DATE($G$4,4,1)+ABS(Bookings!$B$5:$B$1004-DATE($G$4,4,1)))/2))+ABS(((Bookings!$C$5:$C$1004+DATE($G$4,5,1)-ABS(Bookings!$C$5:$C$1004-DATE($G$4,5,1)))/2)-((Bookings!$B$5:$B$1004+DATE($G$4,4,1)+ABS(Bookings!$B$5:$B$1004-DATE($G$4,4,1)))/2)))/2)*Bookings!$AD$5:$AD$1004) -> 0 | H10: =IF($B$4="All properties",SUMIFS(Expenses!$F$5:$F$1004,Expenses!$A$5:$A$1004,">="&DATE($G$4,4,1),Expenses!$A$5:$A$1004,"<"&DATE($G$4,5,1)),SUMIFS(Expenses!$F$5:$F$1004,Expenses!$A$5:$A$1004,">="&DATE($G$4,4,1),Expenses!$A$5:$A$1004,"<"&DATE($G$4,5,1),Expenses!$B$5:$B$1004,$B$4)) -> 0 | I10: =F10-G10-H10 -> 0 | K10: =SUMPRODUCT((Properties!$A$5:$A$24<>"")*(($B$4="All properties")+(Properties!$A$5:$A$24=$B$4)>0)*(((DATE($G$4,5,1)-((Properties!$K$5:$K$24+DATE($G$4,4,1)+ABS(Properties!$K$5:$K$24-DATE($G$4,4,1)))/2))+ABS(DATE($G$4,5,1)-((Properties!$K$5:$K$24+DATE($G$4,4,1)+ABS(Properties!$K$5:$K$24-DATE($G$4,4,1)))/2)))/2)) -> 30 | L10: =SUMPRODUCT(Bookings!$AA$5:$AA$1004*(($B$4="All properties")+(Bookings!$D$5:$D$1004=$B$4)>0)*(((((Bookings!$C$5:$C$1004+DATE($G$4,5,1)-ABS(Bookings!$C$5:$C$1004-DATE($G$4,5,1)))/2)-((Bookings!$B$5:$B$1004+DATE($G$4,4,1)+ABS(Bookings!$B$5:$B$1004-DATE($G$4,4,1)))/2))+ABS(((Bookings!$C$5:$C$1004+DATE($G$4,5,1)-ABS(Bookings!$C$5:$C$1004-DATE($G$4,5,1)))/2)-((Bookings!$B$5:$B$1004+DATE($G$4,4,1)+ABS(Bookings!$B$5:$B$1004-DATE($G$4,4,1)))/2)))/2)*Bookings!$AB$5:$AB$1004) -> 0 | M10: =SUMPRODUCT(Bookings!$AA$5:$AA$1004*(($B$4="All properties")+(Bookings!$D$5:$D$1004=$B$4)>0)*(Bookings!$B$5:$B$1004>=DATE($G$4,4,1))*(Bookings!$B$5:$B$1004<DATE($G$4,5,1))) -> 0 | N10: =IF(M10=0,0,SUMPRODUCT(Bookings!$AA$5:$AA$1004*(($B$4="All properties")+(Bookings!$D$5:$D$1004=$B$4)>0)*(Bookings!$B$5:$B$1004>=DATE($G$4,4,1))*(Bookings!$B$5:$B$1004<DATE($G$4,5,1))*Bookings!$AH$5:$AH$1004)/M10) -> 0 | O10: =SUMPRODUCT(Bookings!$AA$5:$AA$1004*(($B$4="All properties")+(Bookings!$D$5:$D$1004=$B$4)>0)*(((((Bookings!$C$5:$C$1004+DATE($G$4,5,1)-ABS(Bookings!$C$5:$C$1004-DATE($G$4,5,1)))/2)-((Bookings!$B$5:$B$1004+DATE($G$4,4,1)+ABS(Bookings!$B$5:$B$1004-DATE($G$4,4,1)))/2))+ABS(((Bookings!$C$5:$C$1004+DATE($G$4,5,1)-ABS(Bookings!$C$5:$C$1004-DATE($G$4,5,1)))/2)-((Bookings!$B$5:$B$1004+DATE($G$4,4,1)+ABS(Bookings!$B$5:$B$1004-DATE($G$4,4,1)))/2)))/2)*Bookings!$AF$5:$AF$1004) -> 0 | P10: =SUMPRODUCT(Bookings!$AA$5:$AA$1004*(($B$4="All properties")+(Bookings!$D$5:$D$1004=$B$4)>0)*(((((Bookings!$C$5:$C$1004+DATE($G$4,5,1)-ABS(Bookings!$C$5:$C$1004-DATE($G$4,5,1)))/2)-((Bookings!$B$5:$B$1004+DATE($G$4,4,1)+ABS(Bookings!$B$5:$B$1004-DATE($G$4,4,1)))/2))+ABS(((Bookings!$C$5:$C$1004+DATE($G$4,5,1)-ABS(Bookings!$C$5:$C$1004-DATE($G$4,5,1)))/2)-((Bookings!$B$5:$B$1004+DATE($G$4,4,1)+ABS(Bookings!$B$5:$B$1004-DATE($G$4,4,1)))/2)))/2)*Bookings!$AE$5:$AE$1004) -> 0
A11: =TEXT(DATE($G$4,5,1),"mmm yyyy") -> May 2026 | B11: =SUMPRODUCT(Bookings!$AA$5:$AA$1004*(($B$4="All properties")+(Bookings!$D$5:$D$1004=$B$4)>0)*(((((Bookings!$C$5:$C$1004+DATE($G$4,6,1)-ABS(Bookings!$C$5:$C$1004-DATE($G$4,6,1)))/2)-((Bookings!$B$5:$B$1004+DATE($G$4,5,1)+ABS(Bookings!$B$5:$B$1004-DATE($G$4,5,1)))/2))+ABS(((Bookings!$C$5:$C$1004+DATE($G$4,6,1)-ABS(Bookings!$C$5:$C$1004-DATE($G$4,6,1)))/2)-((Bookings!$B$5:$B$1004+DATE($G$4,5,1)+ABS(Bookings!$B$5:$B$1004-DATE($G$4,5,1)))/2)))/2)) -> 0 | C11: =IF(K11=0,0,B11/K11) -> 0 | D11: =IF(B11=0,0,L11/B11) -> 0 | E11: =IF(K11=0,0,L11/K11) -> 0 | F11: =SUMPRODUCT(Bookings!$AA$5:$AA$1004*(($B$4="All properties")+(Bookings!$D$5:$D$1004=$B$4)>0)*(((((Bookings!$C$5:$C$1004+DATE($G$4,6,1)-ABS(Bookings!$C$5:$C$1004-DATE($G$4,6,1)))/2)-((Bookings!$B$5:$B$1004+DATE($G$4,5,1)+ABS(Bookings!$B$5:$B$1004-DATE($G$4,5,1)))/2))+ABS(((Bookings!$C$5:$C$1004+DATE($G$4,6,1)-ABS(Bookings!$C$5:$C$1004-DATE($G$4,6,1)))/2)-((Bookings!$B$5:$B$1004+DATE($G$4,5,1)+ABS(Bookings!$B$5:$B$1004-DATE($G$4,5,1)))/2)))/2)*Bookings!$AC$5:$AC$1004) -> 0 | G11: =SUMPRODUCT(Bookings!$AA$5:$AA$1004*(($B$4="All properties")+(Bookings!$D$5:$D$1004=$B$4)>0)*(((((Bookings!$C$5:$C$1004+DATE($G$4,6,1)-ABS(Bookings!$C$5:$C$1004-DATE($G$4,6,1)))/2)-((Bookings!$B$5:$B$1004+DATE($G$4,5,1)+ABS(Bookings!$B$5:$B$1004-DATE($G$4,5,1)))/2))+ABS(((Bookings!$C$5:$C$1004+DATE($G$4,6,1)-ABS(Bookings!$C$5:$C$1004-DATE($G$4,6,1)))/2)-((Bookings!$B$5:$B$1004+DATE($G$4,5,1)+ABS(Bookings!$B$5:$B$1004-DATE($G$4,5,1)))/2)))/2)*Bookings!$AD$5:$AD$1004) -> 0 | H11: =IF($B$4="All properties",SUMIFS(Expenses!$F$5:$F$1004,Expenses!$A$5:$A$1004,">="&DATE($G$4,5,1),Expenses!$A$5:$A$1004,"<"&DATE($G$4,6,1)),SUMIFS(Expenses!$F$5:$F$1004,Expenses!$A$5:$A$1004,">="&DATE($G$4,5,1),Expenses!$A$5:$A$1004,"<"&DATE($G$4,6,1),Expenses!$B$5:$B$1004,$B$4)) -> 0 | I11: =F11-G11-H11 -> 0 | K11: =SUMPRODUCT((Properties!$A$5:$A$24<>"")*(($B$4="All properties")+(Properties!$A$5:$A$24=$B$4)>0)*(((DATE($G$4,6,1)-((Properties!$K$5:$K$24+DATE($G$4,5,1)+ABS(Properties!$K$5:$K$24-DATE($G$4,5,1)))/2))+ABS(DATE($G$4,6,1)-((Properties!$K$5:$K$24+DATE($G$4,5,1)+ABS(Properties!$K$5:$K$24-DATE($G$4,5,1)))/2)))/2)) -> 31 | L11: =SUMPRODUCT(Bookings!$AA$5:$AA$1004*(($B$4="All properties")+(Bookings!$D$5:$D$1004=$B$4)>0)*(((((Bookings!$C$5:$C$1004+DATE($G$4,6,1)-ABS(Bookings!$C$5:$C$1004-DATE($G$4,6,1)))/2)-((Bookings!$B$5:$B$1004+DATE($G$4,5,1)+ABS(Bookings!$B$5:$B$1004-DATE($G$4,5,1)))/2))+ABS(((Bookings!$C$5:$C$1004+DATE($G$4,6,1)-ABS(Bookings!$C$5:$C$1004-DATE($G$4,6,1)))/2)-((Bookings!$B$5:$B$1004+DATE($G$4,5,1)+ABS(Bookings!$B$5:$B$1004-DATE($G$4,5,1)))/2)))/2)*Bookings!$AB$5:$AB$1004) -> 0 | M11: =SUMPRODUCT(Bookings!$AA$5:$AA$1004*(($B$4="All properties")+(Bookings!$D$5:$D$1004=$B$4)>0)*(Bookings!$B$5:$B$1004>=DATE($G$4,5,1))*(Bookings!$B$5:$B$1004<DATE($G$4,6,1))) -> 0 | N11: =IF(M11=0,0,SUMPRODUCT(Bookings!$AA$5:$AA$1004*(($B$4="All properties")+(Bookings!$D$5:$D$1004=$B$4)>0)*(Bookings!$B$5:$B$1004>=DATE($G$4,5,1))*(Bookings!$B$5:$B$1004<DATE($G$4,6,1))*Bookings!$AH$5:$AH$1004)/M11) -> 0 | O11: =SUMPRODUCT(Bookings!$AA$5:$AA$1004*(($B$4="All properties")+(Bookings!$D$5:$D$1004=$B$4)>0)*(((((Bookings!$C$5:$C$1004+DATE($G$4,6,1)-ABS(Bookings!$C$5:$C$1004-DATE($G$4,6,1)))/2)-((Bookings!$B$5:$B$1004+DATE($G$4,5,1)+ABS(Bookings!$B$5:$B$1004-DATE($G$4,5,1)))/2))+ABS(((Bookings!$C$5:$C$1004+DATE($G$4,6,1)-ABS(Bookings!$C$5:$C$1004-DATE($G$4,6,1)))/2)-((Bookings!$B$5:$B$1004+DATE($G$4,5,1)+ABS(Bookings!$B$5:$B$1004-DATE($G$4,5,1)))/2)))/2)*Bookings!$AF$5:$AF$1004) -> 0 | P11: =SUMPRODUCT(Bookings!$AA$5:$AA$1004*(($B$4="All properties")+(Bookings!$D$5:$D$1004=$B$4)>0)*(((((Bookings!$C$5:$C$1004+DATE($G$4,6,1)-ABS(Bookings!$C$5:$C$1004-DATE($G$4,6,1)))/2)-((Bookings!$B$5:$B$1004+DATE($G$4,5,1)+ABS(Bookings!$B$5:$B$1004-DATE($G$4,5,1)))/2))+ABS(((Bookings!$C$5:$C$1004+DATE($G$4,6,1)-ABS(Bookings!$C$5:$C$1004-DATE($G$4,6,1)))/2)-((Bookings!$B$5:$B$1004+DATE($G$4,5,1)+ABS(Bookings!$B$5:$B$1004-DATE($G$4,5,1)))/2)))/2)*Bookings!$AE$5:$AE$1004) -> 0
A12: =TEXT(DATE($G$4,6,1),"mmm yyyy") -> Jun 2026 | B12: =SUMPRODUCT(Bookings!$AA$5:$AA$1004*(($B$4="All properties")+(Bookings!$D$5:$D$1004=$B$4)>0)*(((((Bookings!$C$5:$C$1004+DATE($G$4,7,1)-ABS(Bookings!$C$5:$C$1004-DATE($G$4,7,1)))/2)-((Bookings!$B$5:$B$1004+DATE($G$4,6,1)+ABS(Bookings!$B$5:$B$1004-DATE($G$4,6,1)))/2))+ABS(((Bookings!$C$5:$C$1004+DATE($G$4,7,1)-ABS(Bookings!$C$5:$C$1004-DATE($G$4,7,1)))/2)-((Bookings!$B$5:$B$1004+DATE($G$4,6,1)+ABS(Bookings!$B$5:$B$1004-DATE($G$4,6,1)))/2)))/2)) -> 0 | C12: =IF(K12=0,0,B12/K12) -> 0 | D12: =IF(B12=0,0,L12/B12) -> 0 | E12: =IF(K12=0,0,L12/K12) -> 0 | F12: =SUMPRODUCT(Bookings!$AA$5:$AA$1004*(($B$4="All properties")+(Bookings!$D$5:$D$1004=$B$4)>0)*(((((Bookings!$C$5:$C$1004+DATE($G$4,7,1)-ABS(Bookings!$C$5:$C$1004-DATE($G$4,7,1)))/2)-((Bookings!$B$5:$B$1004+DATE($G$4,6,1)+ABS(Bookings!$B$5:$B$1004-DATE($G$4,6,1)))/2))+ABS(((Bookings!$C$5:$C$1004+DATE($G$4,7,1)-ABS(Bookings!$C$5:$C$1004-DATE($G$4,7,1)))/2)-((Bookings!$B$5:$B$1004+DATE($G$4,6,1)+ABS(Bookings!$B$5:$B$1004-DATE($G$4,6,1)))/2)))/2)*Bookings!$AC$5:$AC$1004) -> 0 | G12: =SUMPRODUCT(Bookings!$AA$5:$AA$1004*(($B$4="All properties")+(Bookings!$D$5:$D$1004=$B$4)>0)*(((((Bookings!$C$5:$C$1004+DATE($G$4,7,1)-ABS(Bookings!$C$5:$C$1004-DATE($G$4,7,1)))/2)-((Bookings!$B$5:$B$1004+DATE($G$4,6,1)+ABS(Bookings!$B$5:$B$1004-DATE($G$4,6,1)))/2))+ABS(((Bookings!$C$5:$C$1004+DATE($G$4,7,1)-ABS(Bookings!$C$5:$C$1004-DATE($G$4,7,1)))/2)-((Bookings!$B$5:$B$1004+DATE($G$4,6,1)+ABS(Bookings!$B$5:$B$1004-DATE($G$4,6,1)))/2)))/2)*Bookings!$AD$5:$AD$1004) -> 0 | H12: =IF($B$4="All properties",SUMIFS(Expenses!$F$5:$F$1004,Expenses!$A$5:$A$1004,">="&DATE($G$4,6,1),Expenses!$A$5:$A$1004,"<"&DATE($G$4,7,1)),SUMIFS(Expenses!$F$5:$F$1004,Expenses!$A$5:$A$1004,">="&DATE($G$4,6,1),Expenses!$A$5:$A$1004,"<"&DATE($G$4,7,1),Expenses!$B$5:$B$1004,$B$4)) -> 0 | I12: =F12-G12-H12 -> 0 | K12: =SUMPRODUCT((Properties!$A$5:$A$24<>"")*(($B$4="All properties")+(Properties!$A$5:$A$24=$B$4)>0)*(((DATE($G$4,7,1)-((Properties!$K$5:$K$24+DATE($G$4,6,1)+ABS(Properties!$K$5:$K$24-DATE($G$4,6,1)))/2))+ABS(DATE($G$4,7,1)-((Properties!$K$5:$K$24+DATE($G$4,6,1)+ABS(Properties!$K$5:$K$24-DATE($G$4,6,1)))/2)))/2)) -> 30 | L12: =SUMPRODUCT(Bookings!$AA$5:$AA$1004*(($B$4="All properties")+(Bookings!$D$5:$D$1004=$B$4)>0)*(((((Bookings!$C$5:$C$1004+DATE($G$4,7,1)-ABS(Bookings!$C$5:$C$1004-DATE($G$4,7,1)))/2)-((Bookings!$B$5:$B$1004+DATE($G$4,6,1)+ABS(Bookings!$B$5:$B$1004-DATE($G$4,6,1)))/2))+ABS(((Bookings!$C$5:$C$1004+DATE($G$4,7,1)-ABS(Bookings!$C$5:$C$1004-DATE($G$4,7,1)))/2)-((Bookings!$B$5:$B$1004+DATE($G$4,6,1)+ABS(Bookings!$B$5:$B$1004-DATE($G$4,6,1)))/2)))/2)*Bookings!$AB$5:$AB$1004) -> 0 | M12: =SUMPRODUCT(Bookings!$AA$5:$AA$1004*(($B$4="All properties")+(Bookings!$D$5:$D$1004=$B$4)>0)*(Bookings!$B$5:$B$1004>=DATE($G$4,6,1))*(Bookings!$B$5:$B$1004<DATE($G$4,7,1))) -> 0 | N12: =IF(M12=0,0,SUMPRODUCT(Bookings!$AA$5:$AA$1004*(($B$4="All properties")+(Bookings!$D$5:$D$1004=$B$4)>0)*(Bookings!$B$5:$B$1004>=DATE($G$4,6,1))*(Bookings!$B$5:$B$1004<DATE($G$4,7,1))*Bookings!$AH$5:$AH$1004)/M12) -> 0 | O12: =SUMPRODUCT(Bookings!$AA$5:$AA$1004*(($B$4="All properties")+(Bookings!$D$5:$D$1004=$B$4)>0)*(((((Bookings!$C$5:$C$1004+DATE($G$4,7,1)-ABS(Bookings!$C$5:$C$1004-DATE($G$4,7,1)))/2)-((Bookings!$B$5:$B$1004+DATE($G$4,6,1)+ABS(Bookings!$B$5:$B$1004-DATE($G$4,6,1)))/2))+ABS(((Bookings!$C$5:$C$1004+DATE($G$4,7,1)-ABS(Bookings!$C$5:$C$1004-DATE($G$4,7,1)))/2)-((Bookings!$B$5:$B$1004+DATE($G$4,6,1)+ABS(Bookings!$B$5:$B$1004-DATE($G$4,6,1)))/2)))/2)*Bookings!$AF$5:$AF$1004) -> 0 | P12: =SUMPRODUCT(Bookings!$AA$5:$AA$1004*(($B$4="All properties")+(Bookings!$D$5:$D$1004=$B$4)>0)*(((((Bookings!$C$5:$C$1004+DATE($G$4,7,1)-ABS(Bookings!$C$5:$C$1004-DATE($G$4,7,1)))/2)-((Bookings!$B$5:$B$1004+DATE($G$4,6,1)+ABS(Bookings!$B$5:$B$1004-DATE($G$4,6,1)))/2))+ABS(((Bookings!$C$5:$C$1004+DATE($G$4,7,1)-ABS(Bookings!$C$5:$C$1004-DATE($G$4,7,1)))/2)-((Bookings!$B$5:$B$1004+DATE($G$4,6,1)+ABS(Bookings!$B$5:$B$1004-DATE($G$4,6,1)))/2)))/2)*Bookings!$AE$5:$AE$1004) -> 0
A13: =TEXT(DATE($G$4,7,1),"mmm yyyy") -> Jul 2026 | B13: =SUMPRODUCT(Bookings!$AA$5:$AA$1004*(($B$4="All properties")+(Bookings!$D$5:$D$1004=$B$4)>0)*(((((Bookings!$C$5:$C$1004+DATE($G$4,8,1)-ABS(Bookings!$C$5:$C$1004-DATE($G$4,8,1)))/2)-((Bookings!$B$5:$B$1004+DATE($G$4,7,1)+ABS(Bookings!$B$5:$B$1004-DATE($G$4,7,1)))/2))+ABS(((Bookings!$C$5:$C$1004+DATE($G$4,8,1)-ABS(Bookings!$C$5:$C$1004-DATE($G$4,8,1)))/2)-((Bookings!$B$5:$B$1004+DATE($G$4,7,1)+ABS(Bookings!$B$5:$B$1004-DATE($G$4,7,1)))/2)))/2)) -> 0 | C13: =IF(K13=0,0,B13/K13) -> 0 | D13: =IF(B13=0,0,L13/B13) -> 0 | E13: =IF(K13=0,0,L13/K13) -> 0 | F13: =SUMPRODUCT(Bookings!$AA$5:$AA$1004*(($B$4="All properties")+(Bookings!$D$5:$D$1004=$B$4)>0)*(((((Bookings!$C$5:$C$1004+DATE($G$4,8,1)-ABS(Bookings!$C$5:$C$1004-DATE($G$4,8,1)))/2)-((Bookings!$B$5:$B$1004+DATE($G$4,7,1)+ABS(Bookings!$B$5:$B$1004-DATE($G$4,7,1)))/2))+ABS(((Bookings!$C$5:$C$1004+DATE($G$4,8,1)-ABS(Bookings!$C$5:$C$1004-DATE($G$4,8,1)))/2)-((Bookings!$B$5:$B$1004+DATE($G$4,7,1)+ABS(Bookings!$B$5:$B$1004-DATE($G$4,7,1)))/2)))/2)*Bookings!$AC$5:$AC$1004) -> 0 | G13: =SUMPRODUCT(Bookings!$AA$5:$AA$1004*(($B$4="All properties")+(Bookings!$D$5:$D$1004=$B$4)>0)*(((((Bookings!$C$5:$C$1004+DATE($G$4,8,1)-ABS(Bookings!$C$5:$C$1004-DATE($G$4,8,1)))/2)-((Bookings!$B$5:$B$1004+DATE($G$4,7,1)+ABS(Bookings!$B$5:$B$1004-DATE($G$4,7,1)))/2))+ABS(((Bookings!$C$5:$C$1004+DATE($G$4,8,1)-ABS(Bookings!$C$5:$C$1004-DATE($G$4,8,1)))/2)-((Bookings!$B$5:$B$1004+DATE($G$4,7,1)+ABS(Bookings!$B$5:$B$1004-DATE($G$4,7,1)))/2)))/2)*Bookings!$AD$5:$AD$1004) -> 0 | H13: =IF($B$4="All properties",SUMIFS(Expenses!$F$5:$F$1004,Expenses!$A$5:$A$1004,">="&DATE($G$4,7,1),Expenses!$A$5:$A$1004,"<"&DATE($G$4,8,1)),SUMIFS(Expenses!$F$5:$F$1004,Expenses!$A$5:$A$1004,">="&DATE($G$4,7,1),Expenses!$A$5:$A$1004,"<"&DATE($G$4,8,1),Expenses!$B$5:$B$1004,$B$4)) -> 0 | I13: =F13-G13-H13 -> 0 | K13: =SUMPRODUCT((Properties!$A$5:$A$24<>"")*(($B$4="All properties")+(Properties!$A$5:$A$24=$B$4)>0)*(((DATE($G$4,8,1)-((Properties!$K$5:$K$24+DATE($G$4,7,1)+ABS(Properties!$K$5:$K$24-DATE($G$4,7,1)))/2))+ABS(DATE($G$4,8,1)-((Properties!$K$5:$K$24+DATE($G$4,7,1)+ABS(Properties!$K$5:$K$24-DATE($G$4,7,1)))/2)))/2)) -> 31 | L13: =SUMPRODUCT(Bookings!$AA$5:$AA$1004*(($B$4="All properties")+(Bookings!$D$5:$D$1004=$B$4)>0)*(((((Bookings!$C$5:$C$1004+DATE($G$4,8,1)-ABS(Bookings!$C$5:$C$1004-DATE($G$4,8,1)))/2)-((Bookings!$B$5:$B$1004+DATE($G$4,7,1)+ABS(Bookings!$B$5:$B$1004-DATE($G$4,7,1)))/2))+ABS(((Bookings!$C$5:$C$1004+DATE($G$4,8,1)-ABS(Bookings!$C$5:$C$1004-DATE($G$4,8,1)))/2)-((Bookings!$B$5:$B$1004+DATE($G$4,7,1)+ABS(Bookings!$B$5:$B$1004-DATE($G$4,7,1)))/2)))/2)*Bookings!$AB$5:$AB$1004) -> 0 | M13: =SUMPRODUCT(Bookings!$AA$5:$AA$1004*(($B$4="All properties")+(Bookings!$D$5:$D$1004=$B$4)>0)*(Bookings!$B$5:$B$1004>=DATE($G$4,7,1))*(Bookings!$B$5:$B$1004<DATE($G$4,8,1))) -> 0 | N13: =IF(M13=0,0,SUMPRODUCT(Bookings!$AA$5:$AA$1004*(($B$4="All properties")+(Bookings!$D$5:$D$1004=$B$4)>0)*(Bookings!$B$5:$B$1004>=DATE($G$4,7,1))*(Bookings!$B$5:$B$1004<DATE($G$4,8,1))*Bookings!$AH$5:$AH$1004)/M13) -> 0 | O13: =SUMPRODUCT(Bookings!$AA$5:$AA$1004*(($B$4="All properties")+(Bookings!$D$5:$D$1004=$B$4)>0)*(((((Bookings!$C$5:$C$1004+DATE($G$4,8,1)-ABS(Bookings!$C$5:$C$1004-DATE($G$4,8,1)))/2)-((Bookings!$B$5:$B$1004+DATE($G$4,7,1)+ABS(Bookings!$B$5:$B$1004-DATE($G$4,7,1)))/2))+ABS(((Bookings!$C$5:$C$1004+DATE($G$4,8,1)-ABS(Bookings!$C$5:$C$1004-DATE($G$4,8,1)))/2)-((Bookings!$B$5:$B$1004+DATE($G$4,7,1)+ABS(Bookings!$B$5:$B$1004-DATE($G$4,7,1)))/2)))/2)*Bookings!$AF$5:$AF$1004) -> 0 | P13: =SUMPRODUCT(Bookings!$AA$5:$AA$1004*(($B$4="All properties")+(Bookings!$D$5:$D$1004=$B$4)>0)*(((((Bookings!$C$5:$C$1004+DATE($G$4,8,1)-ABS(Bookings!$C$5:$C$1004-DATE($G$4,8,1)))/2)-((Bookings!$B$5:$B$1004+DATE($G$4,7,1)+ABS(Bookings!$B$5:$B$1004-DATE($G$4,7,1)))/2))+ABS(((Bookings!$C$5:$C$1004+DATE($G$4,8,1)-ABS(Bookings!$C$5:$C$1004-DATE($G$4,8,1)))/2)-((Bookings!$B$5:$B$1004+DATE($G$4,7,1)+ABS(Bookings!$B$5:$B$1004-DATE($G$4,7,1)))/2)))/2)*Bookings!$AE$5:$AE$1004) -> 0
A14: =TEXT(DATE($G$4,8,1),"mmm yyyy") -> Aug 2026 | B14: =SUMPRODUCT(Bookings!$AA$5:$AA$1004*(($B$4="All properties")+(Bookings!$D$5:$D$1004=$B$4)>0)*(((((Bookings!$C$5:$C$1004+DATE($G$4,9,1)-ABS(Bookings!$C$5:$C$1004-DATE($G$4,9,1)))/2)-((Bookings!$B$5:$B$1004+DATE($G$4,8,1)+ABS(Bookings!$B$5:$B$1004-DATE($G$4,8,1)))/2))+ABS(((Bookings!$C$5:$C$1004+DATE($G$4,9,1)-ABS(Bookings!$C$5:$C$1004-DATE($G$4,9,1)))/2)-((Bookings!$B$5:$B$1004+DATE($G$4,8,1)+ABS(Bookings!$B$5:$B$1004-DATE($G$4,8,1)))/2)))/2)) -> 0 | C14: =IF(K14=0,0,B14/K14) -> 0 | D14: =IF(B14=0,0,L14/B14) -> 0 | E14: =IF(K14=0,0,L14/K14) -> 0 | F14: =SUMPRODUCT(Bookings!$AA$5:$AA$1004*(($B$4="All properties")+(Bookings!$D$5:$D$1004=$B$4)>0)*(((((Bookings!$C$5:$C$1004+DATE($G$4,9,1)-ABS(Bookings!$C$5:$C$1004-DATE($G$4,9,1)))/2)-((Bookings!$B$5:$B$1004+DATE($G$4,8,1)+ABS(Bookings!$B$5:$B$1004-DATE($G$4,8,1)))/2))+ABS(((Bookings!$C$5:$C$1004+DATE($G$4,9,1)-ABS(Bookings!$C$5:$C$1004-DATE($G$4,9,1)))/2)-((Bookings!$B$5:$B$1004+DATE($G$4,8,1)+ABS(Bookings!$B$5:$B$1004-DATE($G$4,8,1)))/2)))/2)*Bookings!$AC$5:$AC$1004) -> 0 | G14: =SUMPRODUCT(Bookings!$AA$5:$AA$1004*(($B$4="All properties")+(Bookings!$D$5:$D$1004=$B$4)>0)*(((((Bookings!$C$5:$C$1004+DATE($G$4,9,1)-ABS(Bookings!$C$5:$C$1004-DATE($G$4,9,1)))/2)-((Bookings!$B$5:$B$1004+DATE($G$4,8,1)+ABS(Bookings!$B$5:$B$1004-DATE($G$4,8,1)))/2))+ABS(((Bookings!$C$5:$C$1004+DATE($G$4,9,1)-ABS(Bookings!$C$5:$C$1004-DATE($G$4,9,1)))/2)-((Bookings!$B$5:$B$1004+DATE($G$4,8,1)+ABS(Bookings!$B$5:$B$1004-DATE($G$4,8,1)))/2)))/2)*Bookings!$AD$5:$AD$1004) -> 0 | H14: =IF($B$4="All properties",SUMIFS(Expenses!$F$5:$F$1004,Expenses!$A$5:$A$1004,">="&DATE($G$4,8,1),Expenses!$A$5:$A$1004,"<"&DATE($G$4,9,1)),SUMIFS(Expenses!$F$5:$F$1004,Expenses!$A$5:$A$1004,">="&DATE($G$4,8,1),Expenses!$A$5:$A$1004,"<"&DATE($G$4,9,1),Expenses!$B$5:$B$1004,$B$4)) -> 0 | I14: =F14-G14-H14 -> 0 | K14: =SUMPRODUCT((Properties!$A$5:$A$24<>"")*(($B$4="All properties")+(Properties!$A$5:$A$24=$B$4)>0)*(((DATE($G$4,9,1)-((Properties!$K$5:$K$24+DATE($G$4,8,1)+ABS(Properties!$K$5:$K$24-DATE($G$4,8,1)))/2))+ABS(DATE($G$4,9,1)-((Properties!$K$5:$K$24+DATE($G$4,8,1)+ABS(Properties!$K$5:$K$24-DATE($G$4,8,1)))/2)))/2)) -> 31 | L14: =SUMPRODUCT(Bookings!$AA$5:$AA$1004*(($B$4="All properties")+(Bookings!$D$5:$D$1004=$B$4)>0)*(((((Bookings!$C$5:$C$1004+DATE($G$4,9,1)-ABS(Bookings!$C$5:$C$1004-DATE($G$4,9,1)))/2)-((Bookings!$B$5:$B$1004+DATE($G$4,8,1)+ABS(Bookings!$B$5:$B$1004-DATE($G$4,8,1)))/2))+ABS(((Bookings!$C$5:$C$1004+DATE($G$4,9,1)-ABS(Bookings!$C$5:$C$1004-DATE($G$4,9,1)))/2)-((Bookings!$B$5:$B$1004+DATE($G$4,8,1)+ABS(Bookings!$B$5:$B$1004-DATE($G$4,8,1)))/2)))/2)*Bookings!$AB$5:$AB$1004) -> 0 | M14: =SUMPRODUCT(Bookings!$AA$5:$AA$1004*(($B$4="All properties")+(Bookings!$D$5:$D$1004=$B$4)>0)*(Bookings!$B$5:$B$1004>=DATE($G$4,8,1))*(Bookings!$B$5:$B$1004<DATE($G$4,9,1))) -> 0 | N14: =IF(M14=0,0,SUMPRODUCT(Bookings!$AA$5:$AA$1004*(($B$4="All properties")+(Bookings!$D$5:$D$1004=$B$4)>0)*(Bookings!$B$5:$B$1004>=DATE($G$4,8,1))*(Bookings!$B$5:$B$1004<DATE($G$4,9,1))*Bookings!$AH$5:$AH$1004)/M14) -> 0 | O14: =SUMPRODUCT(Bookings!$AA$5:$AA$1004*(($B$4="All properties")+(Bookings!$D$5:$D$1004=$B$4)>0)*(((((Bookings!$C$5:$C$1004+DATE($G$4,9,1)-ABS(Bookings!$C$5:$C$1004-DATE($G$4,9,1)))/2)-((Bookings!$B$5:$B$1004+DATE($G$4,8,1)+ABS(Bookings!$B$5:$B$1004-DATE($G$4,8,1)))/2))+ABS(((Bookings!$C$5:$C$1004+DATE($G$4,9,1)-ABS(Bookings!$C$5:$C$1004-DATE($G$4,9,1)))/2)-((Bookings!$B$5:$B$1004+DATE($G$4,8,1)+ABS(Bookings!$B$5:$B$1004-DATE($G$4,8,1)))/2)))/2)*Bookings!$AF$5:$AF$1004) -> 0 | P14: =SUMPRODUCT(Bookings!$AA$5:$AA$1004*(($B$4="All properties")+(Bookings!$D$5:$D$1004=$B$4)>0)*(((((Bookings!$C$5:$C$1004+DATE($G$4,9,1)-ABS(Bookings!$C$5:$C$1004-DATE($G$4,9,1)))/2)-((Bookings!$B$5:$B$1004+DATE($G$4,8,1)+ABS(Bookings!$B$5:$B$1004-DATE($G$4,8,1)))/2))+ABS(((Bookings!$C$5:$C$1004+DATE($G$4,9,1)-ABS(Bookings!$C$5:$C$1004-DATE($G$4,9,1)))/2)-((Bookings!$B$5:$B$1004+DATE($G$4,8,1)+ABS(Bookings!$B$5:$B$1004-DATE($G$4,8,1)))/2)))/2)*Bookings!$AE$5:$AE$1004) -> 0
A15: =TEXT(DATE($G$4,9,1),"mmm yyyy") -> Sep 2026 | B15: =SUMPRODUCT(Bookings!$AA$5:$AA$1004*(($B$4="All properties")+(Bookings!$D$5:$D$1004=$B$4)>0)*(((((Bookings!$C$5:$C$1004+DATE($G$4,10,1)-ABS(Bookings!$C$5:$C$1004-DATE($G$4,10,1)))/2)-((Bookings!$B$5:$B$1004+DATE($G$4,9,1)+ABS(Bookings!$B$5:$B$1004-DATE($G$4,9,1)))/2))+ABS(((Bookings!$C$5:$C$1004+DATE($G$4,10,1)-ABS(Bookings!$C$5:$C$1004-DATE($G$4,10,1)))/2)-((Bookings!$B$5:$B$1004+DATE($G$4,9,1)+ABS(Bookings!$B$5:$B$1004-DATE($G$4,9,1)))/2)))/2)) -> 0 | C15: =IF(K15=0,0,B15/K15) -> 0 | D15: =IF(B15=0,0,L15/B15) -> 0 | E15: =IF(K15=0,0,L15/K15) -> 0 | F15: =SUMPRODUCT(Bookings!$AA$5:$AA$1004*(($B$4="All properties")+(Bookings!$D$5:$D$1004=$B$4)>0)*(((((Bookings!$C$5:$C$1004+DATE($G$4,10,1)-ABS(Bookings!$C$5:$C$1004-DATE($G$4,10,1)))/2)-((Bookings!$B$5:$B$1004+DATE($G$4,9,1)+ABS(Bookings!$B$5:$B$1004-DATE($G$4,9,1)))/2))+ABS(((Bookings!$C$5:$C$1004+DATE($G$4,10,1)-ABS(Bookings!$C$5:$C$1004-DATE($G$4,10,1)))/2)-((Bookings!$B$5:$B$1004+DATE($G$4,9,1)+ABS(Bookings!$B$5:$B$1004-DATE($G$4,9,1)))/2)))/2)*Bookings!$AC$5:$AC$1004) -> 0 | G15: =SUMPRODUCT(Bookings!$AA$5:$AA$1004*(($B$4="All properties")+(Bookings!$D$5:$D$1004=$B$4)>0)*(((((Bookings!$C$5:$C$1004+DATE($G$4,10,1)-ABS(Bookings!$C$5:$C$1004-DATE($G$4,10,1)))/2)-((Bookings!$B$5:$B$1004+DATE($G$4,9,1)+ABS(Bookings!$B$5:$B$1004-DATE($G$4,9,1)))/2))+ABS(((Bookings!$C$5:$C$1004+DATE($G$4,10,1)-ABS(Bookings!$C$5:$C$1004-DATE($G$4,10,1)))/2)-((Bookings!$B$5:$B$1004+DATE($G$4,9,1)+ABS(Bookings!$B$5:$B$1004-DATE($G$4,9,1)))/2)))/2)*Bookings!$AD$5:$AD$1004) -> 0 | H15: =IF($B$4="All properties",SUMIFS(Expenses!$F$5:$F$1004,Expenses!$A$5:$A$1004,">="&DATE($G$4,9,1),Expenses!$A$5:$A$1004,"<"&DATE($G$4,10,1)),SUMIFS(Expenses!$F$5:$F$1004,Expenses!$A$5:$A$1004,">="&DATE($G$4,9,1),Expenses!$A$5:$A$1004,"<"&DATE($G$4,10,1),Expenses!$B$5:$B$1004,$B$4)) -> 0 | I15: =F15-G15-H15 -> 0 | K15: =SUMPRODUCT((Properties!$A$5:$A$24<>"")*(($B$4="All properties")+(Properties!$A$5:$A$24=$B$4)>0)*(((DATE($G$4,10,1)-((Properties!$K$5:$K$24+DATE($G$4,9,1)+ABS(Properties!$K$5:$K$24-DATE($G$4,9,1)))/2))+ABS(DATE($G$4,10,1)-((Properties!$K$5:$K$24+DATE($G$4,9,1)+ABS(Properties!$K$5:$K$24-DATE($G$4,9,1)))/2)))/2)) -> 30 | L15: =SUMPRODUCT(Bookings!$AA$5:$AA$1004*(($B$4="All properties")+(Bookings!$D$5:$D$1004=$B$4)>0)*(((((Bookings!$C$5:$C$1004+DATE($G$4,10,1)-ABS(Bookings!$C$5:$C$1004-DATE($G$4,10,1)))/2)-((Bookings!$B$5:$B$1004+DATE($G$4,9,1)+ABS(Bookings!$B$5:$B$1004-DATE($G$4,9,1)))/2))+ABS(((Bookings!$C$5:$C$1004+DATE($G$4,10,1)-ABS(Bookings!$C$5:$C$1004-DATE($G$4,10,1)))/2)-((Bookings!$B$5:$B$1004+DATE($G$4,9,1)+ABS(Bookings!$B$5:$B$1004-DATE($G$4,9,1)))/2)))/2)*Bookings!$AB$5:$AB$1004) -> 0 | M15: =SUMPRODUCT(Bookings!$AA$5:$AA$1004*(($B$4="All properties")+(Bookings!$D$5:$D$1004=$B$4)>0)*(Bookings!$B$5:$B$1004>=DATE($G$4,9,1))*(Bookings!$B$5:$B$1004<DATE($G$4,10,1))) -> 0 | N15: =IF(M15=0,0,SUMPRODUCT(Bookings!$AA$5:$AA$1004*(($B$4="All properties")+(Bookings!$D$5:$D$1004=$B$4)>0)*(Bookings!$B$5:$B$1004>=DATE($G$4,9,1))*(Bookings!$B$5:$B$1004<DATE($G$4,10,1))*Bookings!$AH$5:$AH$1004)/M15) -> 0 | O15: =SUMPRODUCT(Bookings!$AA$5:$AA$1004*(($B$4="All properties")+(Bookings!$D$5:$D$1004=$B$4)>0)*(((((Bookings!$C$5:$C$1004+DATE($G$4,10,1)-ABS(Bookings!$C$5:$C$1004-DATE($G$4,10,1)))/2)-((Bookings!$B$5:$B$1004+DATE($G$4,9,1)+ABS(Bookings!$B$5:$B$1004-DATE($G$4,9,1)))/2))+ABS(((Bookings!$C$5:$C$1004+DATE($G$4,10,1)-ABS(Bookings!$C$5:$C$1004-DATE($G$4,10,1)))/2)-((Bookings!$B$5:$B$1004+DATE($G$4,9,1)+ABS(Bookings!$B$5:$B$1004-DATE($G$4,9,1)))/2)))/2)*Bookings!$AF$5:$AF$1004) -> 0 | P15: =SUMPRODUCT(Bookings!$AA$5:$AA$1004*(($B$4="All properties")+(Bookings!$D$5:$D$1004=$B$4)>0)*(((((Bookings!$C$5:$C$1004+DATE($G$4,10,1)-ABS(Bookings!$C$5:$C$1004-DATE($G$4,10,1)))/2)-((Bookings!$B$5:$B$1004+DATE($G$4,9,1)+ABS(Bookings!$B$5:$B$1004-DATE($G$4,9,1)))/2))+ABS(((Bookings!$C$5:$C$1004+DATE($G$4,10,1)-ABS(Bookings!$C$5:$C$1004-DATE($G$4,10,1)))/2)-((Bookings!$B$5:$B$1004+DATE($G$4,9,1)+ABS(Bookings!$B$5:$B$1004-DATE($G$4,9,1)))/2)))/2)*Bookings!$AE$5:$AE$1004) -> 0
A16: =TEXT(DATE($G$4,10,1),"mmm yyyy") -> Oct 2026 | B16: =SUMPRODUCT(Bookings!$AA$5:$AA$1004*(($B$4="All properties")+(Bookings!$D$5:$D$1004=$B$4)>0)*(((((Bookings!$C$5:$C$1004+DATE($G$4,11,1)-ABS(Bookings!$C$5:$C$1004-DATE($G$4,11,1)))/2)-((Bookings!$B$5:$B$1004+DATE($G$4,10,1)+ABS(Bookings!$B$5:$B$1004-DATE($G$4,10,1)))/2))+ABS(((Bookings!$C$5:$C$1004+DATE($G$4,11,1)-ABS(Bookings!$C$5:$C$1004-DATE($G$4,11,1)))/2)-((Bookings!$B$5:$B$1004+DATE($G$4,10,1)+ABS(Bookings!$B$5:$B$1004-DATE($G$4,10,1)))/2)))/2)) -> 5 | C16: =IF(K16=0,0,B16/K16) -> 0.16129032 | D16: =IF(B16=0,0,L16/B16) -> 201 | E16: =IF(K16=0,0,L16/K16) -> 32.419355 | F16: =SUMPRODUCT(Bookings!$AA$5:$AA$1004*(($B$4="All properties")+(Bookings!$D$5:$D$1004=$B$4)>0)*(((((Bookings!$C$5:$C$1004+DATE($G$4,11,1)-ABS(Bookings!$C$5:$C$1004-DATE($G$4,11,1)))/2)-((Bookings!$B$5:$B$1004+DATE($G$4,10,1)+ABS(Bookings!$B$5:$B$1004-DATE($G$4,10,1)))/2))+ABS(((Bookings!$C$5:$C$1004+DATE($G$4,11,1)-ABS(Bookings!$C$5:$C$1004-DATE($G$4,11,1)))/2)-((Bookings!$B$5:$B$1004+DATE($G$4,10,1)+ABS(Bookings!$B$5:$B$1004-DATE($G$4,10,1)))/2)))/2)*Bookings!$AC$5:$AC$1004) -> 1241.6 | G16: =SUMPRODUCT(Bookings!$AA$5:$AA$1004*(($B$4="All properties")+(Bookings!$D$5:$D$1004=$B$4)>0)*(((((Bookings!$C$5:$C$1004+DATE($G$4,11,1)-ABS(Bookings!$C$5:$C$1004-DATE($G$4,11,1)))/2)-((Bookings!$B$5:$B$1004+DATE($G$4,10,1)+ABS(Bookings!$B$5:$B$1004-DATE($G$4,10,1)))/2))+ABS(((Bookings!$C$5:$C$1004+DATE($G$4,11,1)-ABS(Bookings!$C$5:$C$1004-DATE($G$4,11,1)))/2)-((Bookings!$B$5:$B$1004+DATE($G$4,10,1)+ABS(Bookings!$B$5:$B$1004-DATE($G$4,10,1)))/2)))/2)*Bookings!$AD$5:$AD$1004) -> 130 | H16: =IF($B$4="All properties",SUMIFS(Expenses!$F$5:$F$1004,Expenses!$A$5:$A$1004,">="&DATE($G$4,10,1),Expenses!$A$5:$A$1004,"<"&DATE($G$4,11,1)),SUMIFS(Expenses!$F$5:$F$1004,Expenses!$A$5:$A$1004,">="&DATE($G$4,10,1),Expenses!$A$5:$A$1004,"<"&DATE($G$4,11,1),Expenses!$B$5:$B$1004,$B$4)) -> 162.17 | I16: =F16-G16-H16 -> 949.43 | K16: =SUMPRODUCT((Properties!$A$5:$A$24<>"")*(($B$4="All properties")+(Properties!$A$5:$A$24=$B$4)>0)*(((DATE($G$4,11,1)-((Properties!$K$5:$K$24+DATE($G$4,10,1)+ABS(Properties!$K$5:$K$24-DATE($G$4,10,1)))/2))+ABS(DATE($G$4,11,1)-((Properties!$K$5:$K$24+DATE($G$4,10,1)+ABS(Properties!$K$5:$K$24-DATE($G$4,10,1)))/2)))/2)) -> 31 | L16: =SUMPRODUCT(Bookings!$AA$5:$AA$1004*(($B$4="All properties")+(Bookings!$D$5:$D$1004=$B$4)>0)*(((((Bookings!$C$5:$C$1004+DATE($G$4,11,1)-ABS(Bookings!$C$5:$C$1004-DATE($G$4,11,1)))/2)-((Bookings!$B$5:$B$1004+DATE($G$4,10,1)+ABS(Bookings!$B$5:$B$1004-DATE($G$4,10,1)))/2))+ABS(((Bookings!$C$5:$C$1004+DATE($G$4,11,1)-ABS(Bookings!$C$5:$C$1004-DATE($G$4,11,1)))/2)-((Bookings!$B$5:$B$1004+DATE($G$4,10,1)+ABS(Bookings!$B$5:$B$1004-DATE($G$4,10,1)))/2)))/2)*Bookings!$AB$5:$AB$1004) -> 1005 | M16: =SUMPRODUCT(Bookings!$AA$5:$AA$1004*(($B$4="All properties")+(Bookings!$D$5:$D$1004=$B$4)>0)*(Bookings!$B$5:$B$1004>=DATE($G$4,10,1))*(Bookings!$B$5:$B$1004<DATE($G$4,11,1))) -> 2 | N16: =IF(M16=0,0,SUMPRODUCT(Bookings!$AA$5:$AA$1004*(($B$4="All properties")+(Bookings!$D$5:$D$1004=$B$4)>0)*(Bookings!$B$5:$B$1004>=DATE($G$4,10,1))*(Bookings!$B$5:$B$1004<DATE($G$4,11,1))*Bookings!$AH$5:$AH$1004)/M16) -> 2.5 | O16: =SUMPRODUCT(Bookings!$AA$5:$AA$1004*(($B$4="All properties")+(Bookings!$D$5:$D$1004=$B$4)>0)*(((((Bookings!$C$5:$C$1004+DATE($G$4,11,1)-ABS(Bookings!$C$5:$C$1004-DATE($G$4,11,1)))/2)-((Bookings!$B$5:$B$1004+DATE($G$4,10,1)+ABS(Bookings!$B$5:$B$1004-DATE($G$4,10,1)))/2))+ABS(((Bookings!$C$5:$C$1004+DATE($G$4,11,1)-ABS(Bookings!$C$5:$C$1004-DATE($G$4,11,1)))/2)-((Bookings!$B$5:$B$1004+DATE($G$4,10,1)+ABS(Bookings!$B$5:$B$1004-DATE($G$4,10,1)))/2)))/2)*Bookings!$AF$5:$AF$1004) -> 190 | P16: =SUMPRODUCT(Bookings!$AA$5:$AA$1004*(($B$4="All properties")+(Bookings!$D$5:$D$1004=$B$4)>0)*(((((Bookings!$C$5:$C$1004+DATE($G$4,11,1)-ABS(Bookings!$C$5:$C$1004-DATE($G$4,11,1)))/2)-((Bookings!$B$5:$B$1004+DATE($G$4,10,1)+ABS(Bookings!$B$5:$B$1004-DATE($G$4,10,1)))/2))+ABS(((Bookings!$C$5:$C$1004+DATE($G$4,11,1)-ABS(Bookings!$C$5:$C$1004-DATE($G$4,11,1)))/2)-((Bookings!$B$5:$B$1004+DATE($G$4,10,1)+ABS(Bookings!$B$5:$B$1004-DATE($G$4,10,1)))/2)))/2)*Bookings!$AE$5:$AE$1004) -> 38.4
A17: =TEXT(DATE($G$4,11,1),"mmm yyyy") -> Nov 2026 | B17: =SUMPRODUCT(Bookings!$AA$5:$AA$1004*(($B$4="All properties")+(Bookings!$D$5:$D$1004=$B$4)>0)*(((((Bookings!$C$5:$C$1004+DATE($G$4,12,1)-ABS(Bookings!$C$5:$C$1004-DATE($G$4,12,1)))/2)-((Bookings!$B$5:$B$1004+DATE($G$4,11,1)+ABS(Bookings!$B$5:$B$1004-DATE($G$4,11,1)))/2))+ABS(((Bookings!$C$5:$C$1004+DATE($G$4,12,1)-ABS(Bookings!$C$5:$C$1004-DATE($G$4,12,1)))/2)-((Bookings!$B$5:$B$1004+DATE($G$4,11,1)+ABS(Bookings!$B$5:$B$1004-DATE($G$4,11,1)))/2)))/2)) -> 0 | C17: =IF(K17=0,0,B17/K17) -> 0 | D17: =IF(B17=0,0,L17/B17) -> 0 | E17: =IF(K17=0,0,L17/K17) -> 0 | F17: =SUMPRODUCT(Bookings!$AA$5:$AA$1004*(($B$4="All properties")+(Bookings!$D$5:$D$1004=$B$4)>0)*(((((Bookings!$C$5:$C$1004+DATE($G$4,12,1)-ABS(Bookings!$C$5:$C$1004-DATE($G$4,12,1)))/2)-((Bookings!$B$5:$B$1004+DATE($G$4,11,1)+ABS(Bookings!$B$5:$B$1004-DATE($G$4,11,1)))/2))+ABS(((Bookings!$C$5:$C$1004+DATE($G$4,12,1)-ABS(Bookings!$C$5:$C$1004-DATE($G$4,12,1)))/2)-((Bookings!$B$5:$B$1004+DATE($G$4,11,1)+ABS(Bookings!$B$5:$B$1004-DATE($G$4,11,1)))/2)))/2)*Bookings!$AC$5:$AC$1004) -> 0 | G17: =SUMPRODUCT(Bookings!$AA$5:$AA$1004*(($B$4="All properties")+(Bookings!$D$5:$D$1004=$B$4)>0)*(((((Bookings!$C$5:$C$1004+DATE($G$4,12,1)-ABS(Bookings!$C$5:$C$1004-DATE($G$4,12,1)))/2)-((Bookings!$B$5:$B$1004+DATE($G$4,11,1)+ABS(Bookings!$B$5:$B$1004-DATE($G$4,11,1)))/2))+ABS(((Bookings!$C$5:$C$1004+DATE($G$4,12,1)-ABS(Bookings!$C$5:$C$1004-DATE($G$4,12,1)))/2)-((Bookings!$B$5:$B$1004+DATE($G$4,11,1)+ABS(Bookings!$B$5:$B$1004-DATE($G$4,11,1)))/2)))/2)*Bookings!$AD$5:$AD$1004) -> 0 | H17: =IF($B$4="All properties",SUMIFS(Expenses!$F$5:$F$1004,Expenses!$A$5:$A$1004,">="&DATE($G$4,11,1),Expenses!$A$5:$A$1004,"<"&DATE($G$4,12,1)),SUMIFS(Expenses!$F$5:$F$1004,Expenses!$A$5:$A$1004,">="&DATE($G$4,11,1),Expenses!$A$5:$A$1004,"<"&DATE($G$4,12,1),Expenses!$B$5:$B$1004,$B$4)) -> 0 | I17: =F17-G17-H17 -> 0 | K17: =SUMPRODUCT((Properties!$A$5:$A$24<>"")*(($B$4="All properties")+(Properties!$A$5:$A$24=$B$4)>0)*(((DATE($G$4,12,1)-((Properties!$K$5:$K$24+DATE($G$4,11,1)+ABS(Properties!$K$5:$K$24-DATE($G$4,11,1)))/2))+ABS(DATE($G$4,12,1)-((Properties!$K$5:$K$24+DATE($G$4,11,1)+ABS(Properties!$K$5:$K$24-DATE($G$4,11,1)))/2)))/2)) -> 30 | L17: =SUMPRODUCT(Bookings!$AA$5:$AA$1004*(($B$4="All properties")+(Bookings!$D$5:$D$1004=$B$4)>0)*(((((Bookings!$C$5:$C$1004+DATE($G$4,12,1)-ABS(Bookings!$C$5:$C$1004-DATE($G$4,12,1)))/2)-((Bookings!$B$5:$B$1004+DATE($G$4,11,1)+ABS(Bookings!$B$5:$B$1004-DATE($G$4,11,1)))/2))+ABS(((Bookings!$C$5:$C$1004+DATE($G$4,12,1)-ABS(Bookings!$C$5:$C$1004-DATE($G$4,12,1)))/2)-((Bookings!$B$5:$B$1004+DATE($G$4,11,1)+ABS(Bookings!$B$5:$B$1004-DATE($G$4,11,1)))/2)))/2)*Bookings!$AB$5:$AB$1004) -> 0 | M17: =SUMPRODUCT(Bookings!$AA$5:$AA$1004*(($B$4="All properties")+(Bookings!$D$5:$D$1004=$B$4)>0)*(Bookings!$B$5:$B$1004>=DATE($G$4,11,1))*(Bookings!$B$5:$B$1004<DATE($G$4,12,1))) -> 0 | N17: =IF(M17=0,0,SUMPRODUCT(Bookings!$AA$5:$AA$1004*(($B$4="All properties")+(Bookings!$D$5:$D$1004=$B$4)>0)*(Bookings!$B$5:$B$1004>=DATE($G$4,11,1))*(Bookings!$B$5:$B$1004<DATE($G$4,12,1))*Bookings!$AH$5:$AH$1004)/M17) -> 0 | O17: =SUMPRODUCT(Bookings!$AA$5:$AA$1004*(($B$4="All properties")+(Bookings!$D$5:$D$1004=$B$4)>0)*(((((Bookings!$C$5:$C$1004+DATE($G$4,12,1)-ABS(Bookings!$C$5:$C$1004-DATE($G$4,12,1)))/2)-((Bookings!$B$5:$B$1004+DATE($G$4,11,1)+ABS(Bookings!$B$5:$B$1004-DATE($G$4,11,1)))/2))+ABS(((Bookings!$C$5:$C$1004+DATE($G$4,12,1)-ABS(Bookings!$C$5:$C$1004-DATE($G$4,12,1)))/2)-((Bookings!$B$5:$B$1004+DATE($G$4,11,1)+ABS(Bookings!$B$5:$B$1004-DATE($G$4,11,1)))/2)))/2)*Bookings!$AF$5:$AF$1004) -> 0 | P17: =SUMPRODUCT(Bookings!$AA$5:$AA$1004*(($B$4="All properties")+(Bookings!$D$5:$D$1004=$B$4)>0)*(((((Bookings!$C$5:$C$1004+DATE($G$4,12,1)-ABS(Bookings!$C$5:$C$1004-DATE($G$4,12,1)))/2)-((Bookings!$B$5:$B$1004+DATE($G$4,11,1)+ABS(Bookings!$B$5:$B$1004-DATE($G$4,11,1)))/2))+ABS(((Bookings!$C$5:$C$1004+DATE($G$4,12,1)-ABS(Bookings!$C$5:$C$1004-DATE($G$4,12,1)))/2)-((Bookings!$B$5:$B$1004+DATE($G$4,11,1)+ABS(Bookings!$B$5:$B$1004-DATE($G$4,11,1)))/2)))/2)*Bookings!$AE$5:$AE$1004) -> 0
A18: =TEXT(DATE($G$4,12,1),"mmm yyyy") -> Dec 2026 | B18: =SUMPRODUCT(Bookings!$AA$5:$AA$1004*(($B$4="All properties")+(Bookings!$D$5:$D$1004=$B$4)>0)*(((((Bookings!$C$5:$C$1004+DATE($G$4,13,1)-ABS(Bookings!$C$5:$C$1004-DATE($G$4,13,1)))/2)-((Bookings!$B$5:$B$1004+DATE($G$4,12,1)+ABS(Bookings!$B$5:$B$1004-DATE($G$4,12,1)))/2))+ABS(((Bookings!$C$5:$C$1004+DATE($G$4,13,1)-ABS(Bookings!$C$5:$C$1004-DATE($G$4,13,1)))/2)-((Bookings!$B$5:$B$1004+DATE($G$4,12,1)+ABS(Bookings!$B$5:$B$1004-DATE($G$4,12,1)))/2)))/2)) -> 0 | C18: =IF(K18=0,0,B18/K18) -> 0 | D18: =IF(B18=0,0,L18/B18) -> 0 | E18: =IF(K18=0,0,L18/K18) -> 0 | F18: =SUMPRODUCT(Bookings!$AA$5:$AA$1004*(($B$4="All properties")+(Bookings!$D$5:$D$1004=$B$4)>0)*(((((Bookings!$C$5:$C$1004+DATE($G$4,13,1)-ABS(Bookings!$C$5:$C$1004-DATE($G$4,13,1)))/2)-((Bookings!$B$5:$B$1004+DATE($G$4,12,1)+ABS(Bookings!$B$5:$B$1004-DATE($G$4,12,1)))/2))+ABS(((Bookings!$C$5:$C$1004+DATE($G$4,13,1)-ABS(Bookings!$C$5:$C$1004-DATE($G$4,13,1)))/2)-((Bookings!$B$5:$B$1004+DATE($G$4,12,1)+ABS(Bookings!$B$5:$B$1004-DATE($G$4,12,1)))/2)))/2)*Bookings!$AC$5:$AC$1004) -> 0 | G18: =SUMPRODUCT(Bookings!$AA$5:$AA$1004*(($B$4="All properties")+(Bookings!$D$5:$D$1004=$B$4)>0)*(((((Bookings!$C$5:$C$1004+DATE($G$4,13,1)-ABS(Bookings!$C$5:$C$1004-DATE($G$4,13,1)))/2)-((Bookings!$B$5:$B$1004+DATE($G$4,12,1)+ABS(Bookings!$B$5:$B$1004-DATE($G$4,12,1)))/2))+ABS(((Bookings!$C$5:$C$1004+DATE($G$4,13,1)-ABS(Bookings!$C$5:$C$1004-DATE($G$4,13,1)))/2)-((Bookings!$B$5:$B$1004+DATE($G$4,12,1)+ABS(Bookings!$B$5:$B$1004-DATE($G$4,12,1)))/2)))/2)*Bookings!$AD$5:$AD$1004) -> 0 | H18: =IF($B$4="All properties",SUMIFS(Expenses!$F$5:$F$1004,Expenses!$A$5:$A$1004,">="&DATE($G$4,12,1),Expenses!$A$5:$A$1004,"<"&DATE($G$4,13,1)),SUMIFS(Expenses!$F$5:$F$1004,Expenses!$A$5:$A$1004,">="&DATE($G$4,12,1),Expenses!$A$5:$A$1004,"<"&DATE($G$4,13,1),Expenses!$B$5:$B$1004,$B$4)) -> 0 | I18: =F18-G18-H18 -> 0 | K18: =SUMPRODUCT((Properties!$A$5:$A$24<>"")*(($B$4="All properties")+(Properties!$A$5:$A$24=$B$4)>0)*(((DATE($G$4,13,1)-((Properties!$K$5:$K$24+DATE($G$4,12,1)+ABS(Properties!$K$5:$K$24-DATE($G$4,12,1)))/2))+ABS(DATE($G$4,13,1)-((Properties!$K$5:$K$24+DATE($G$4,12,1)+ABS(Properties!$K$5:$K$24-DATE($G$4,12,1)))/2)))/2)) -> 31 | L18: =SUMPRODUCT(Bookings!$AA$5:$AA$1004*(($B$4="All properties")+(Bookings!$D$5:$D$1004=$B$4)>0)*(((((Bookings!$C$5:$C$1004+DATE($G$4,13,1)-ABS(Bookings!$C$5:$C$1004-DATE($G$4,13,1)))/2)-((Bookings!$B$5:$B$1004+DATE($G$4,12,1)+ABS(Bookings!$B$5:$B$1004-DATE($G$4,12,1)))/2))+ABS(((Bookings!$C$5:$C$1004+DATE($G$4,13,1)-ABS(Bookings!$C$5:$C$1004-DATE($G$4,13,1)))/2)-((Bookings!$B$5:$B$1004+DATE($G$4,12,1)+ABS(Bookings!$B$5:$B$1004-DATE($G$4,12,1)))/2)))/2)*Bookings!$AB$5:$AB$1004) -> 0 | M18: =SUMPRODUCT(Bookings!$AA$5:$AA$1004*(($B$4="All properties")+(Bookings!$D$5:$D$1004=$B$4)>0)*(Bookings!$B$5:$B$1004>=DATE($G$4,12,1))*(Bookings!$B$5:$B$1004<DATE($G$4,13,1))) -> 0 | N18: =IF(M18=0,0,SUMPRODUCT(Bookings!$AA$5:$AA$1004*(($B$4="All properties")+(Bookings!$D$5:$D$1004=$B$4)>0)*(Bookings!$B$5:$B$1004>=DATE($G$4,12,1))*(Bookings!$B$5:$B$1004<DATE($G$4,13,1))*Bookings!$AH$5:$AH$1004)/M18) -> 0 | O18: =SUMPRODUCT(Bookings!$AA$5:$AA$1004*(($B$4="All properties")+(Bookings!$D$5:$D$1004=$B$4)>0)*(((((Bookings!$C$5:$C$1004+DATE($G$4,13,1)-ABS(Bookings!$C$5:$C$1004-DATE($G$4,13,1)))/2)-((Bookings!$B$5:$B$1004+DATE($G$4,12,1)+ABS(Bookings!$B$5:$B$1004-DATE($G$4,12,1)))/2))+ABS(((Bookings!$C$5:$C$1004+DATE($G$4,13,1)-ABS(Bookings!$C$5:$C$1004-DATE($G$4,13,1)))/2)-((Bookings!$B$5:$B$1004+DATE($G$4,12,1)+ABS(Bookings!$B$5:$B$1004-DATE($G$4,12,1)))/2)))/2)*Bookings!$AF$5:$AF$1004) -> 0 | P18: =SUMPRODUCT(Bookings!$AA$5:$AA$1004*(($B$4="All properties")+(Bookings!$D$5:$D$1004=$B$4)>0)*(((((Bookings!$C$5:$C$1004+DATE($G$4,13,1)-ABS(Bookings!$C$5:$C$1004-DATE($G$4,13,1)))/2)-((Bookings!$B$5:$B$1004+DATE($G$4,12,1)+ABS(Bookings!$B$5:$B$1004-DATE($G$4,12,1)))/2))+ABS(((Bookings!$C$5:$C$1004+DATE($G$4,13,1)-ABS(Bookings!$C$5:$C$1004-DATE($G$4,13,1)))/2)-((Bookings!$B$5:$B$1004+DATE($G$4,12,1)+ABS(Bookings!$B$5:$B$1004-DATE($G$4,12,1)))/2)))/2)*Bookings!$AE$5:$AE$1004) -> 0
A19: Year total | B19: =SUM(B7:B18) -> 5 | C19: =IF(K19=0,0,B19/K19) -> 0.01369863 | D19: =IF(B19=0,0,L19/B19) -> 201 | E19: =IF(K19=0,0,L19/K19) -> 2.7534247 | F19: =SUM(F7:F18) -> 1241.6 | G19: =SUM(G7:G18) -> 130 | H19: =SUM(H7:H18) -> 162.17 | I19: =SUM(I7:I18) -> 949.43 | K19: =SUM(K7:K18) -> 365 | L19: =SUM(L7:L18) -> 1005 | M19: =SUM(M7:M18) -> 2 | N19: =IF(M19=0,0,SUMPRODUCT(M7:M18,N7:N18)/M19) -> 2.5 | O19: =SUM(O7:O18) -> 190 | P19: =SUM(P7:P18) -> 38.4
A21: Expenses: with one property picked, only that property's expenses count; shared costs appear under All properties. Stays and average stay count by check-in month.

Sheet Properties
A1: Properties
A2: One row per listing. Rates and fees here feed Bookings and the Pricing Calculator.
A4: Property name | B4: Address | C4: Bedrooms | D4: Max guests | E4: Nightly rate (Sun-Thu) | F4: Weekend rate (Fri-Sat) | G4: Cleaning fee (guest pays) | H4: Cleaner pay per turnover | I4: Guests included | J4: Extra guest fee / night | K4: Listed since | L4: Wi-Fi, lockbox, notes | M4: Today | N4: Next check-in | O4: Upcoming stays
A5: EXAMPLE – Lakeview Cabin | B5: 12 Shore Rd | C5: 2 | D5: 6 | E5: 165 | F5: 210 | G5: 95 | H5: 65 | I5: 4 | J5: 15 | K5: 45809 | L5: Lockbox 4471 · Wi-Fi LakeView5G | M5: =IF($A5="","",IF(COUNTIFS(Bookings!$D$5:$D$1004,$A5,Bookings!$B$5:$B$1004,"<="&TODAY(),Bookings!$C$5:$C$1004,">"&TODAY(),Bookings!$AA$5:$AA$1004,1)>0,"Occupied",IF(COUNTIFS(Bookings!$D$5:$D$1004,$A5,Bookings!$C$5:$C$1004,TODAY(),Bookings!$AA$5:$AA$1004,1)>0,"Turnover today","Vacant"))) -> Vacant | N5: =IF($A5="","",IF(_xlfn.MINIFS(Bookings!$B$5:$B$1004,Bookings!$D$5:$D$1004,$A5,Bookings!$B$5:$B$1004,">="&TODAY(),Bookings!$AA$5:$AA$1004,1)=0,"None",_xlfn.MINIFS(Bookings!$B$5:$B$1004,Bookings!$D$5:$D$1004,$A5,Bookings!$B$5:$B$1004,">="&TODAY(),Bookings!$AA$5:$AA$1004,1))) -> None | O5: =IF($A5="","",COUNTIFS(Bookings!$D$5:$D$1004,$A5,Bookings!$B$5:$B$1004,">="&TODAY(),Bookings!$AA$5:$AA$1004,1)) -> 0
M6: =IF($A6="","",IF(COUNTIFS(Bookings!$D$5:$D$1004,$A6,Bookings!$B$5:$B$1004,"<="&TODAY(),Bookings!$C$5:$C$1004,">"&TODAY(),Bookings!$AA$5:$AA$1004,1)>0,"Occupied",IF(COUNTIFS(Bookings!$D$5:$D$1004,$A6,Bookings!$C$5:$C$1004,TODAY(),Bookings!$AA$5:$AA$1004,1)>0,"Turnover today","Vacant"))) | N6: =IF($A6="","",IF(_xlfn.MINIFS(Bookings!$B$5:$B$1004,Bookings!$D$5:$D$1004,$A6,Bookings!$B$5:$B$1004,">="&TODAY(),Bookings!$AA$5:$AA$1004,1)=0,"None",_xlfn.MINIFS(Bookings!$B$5:$B$1004,Bookings!$D$5:$D$1004,$A6,Bookings!$B$5:$B$1004,">="&TODAY(),Bookings!$AA$5:$AA$1004,1))) | O6: =IF($A6="","",COUNTIFS(Bookings!$D$5:$D$1004,$A6,Bookings!$B$5:$B$1004,">="&TODAY(),Bookings!$AA$5:$AA$1004,1))
M7: =IF($A7="","",IF(COUNTIFS(Bookings!$D$5:$D$1004,$A7,Bookings!$B$5:$B$1004,"<="&TODAY(),Bookings!$C$5:$C$1004,">"&TODAY(),Bookings!$AA$5:$AA$1004,1)>0,"Occupied",IF(COUNTIFS(Bookings!$D$5:$D$1004,$A7,Bookings!$C$5:$C$1004,TODAY(),Bookings!$AA$5:$AA$1004,1)>0,"Turnover today","Vacant"))) | N7: =IF($A7="","",IF(_xlfn.MINIFS(Bookings!$B$5:$B$1004,Bookings!$D$5:$D$1004,$A7,Bookings!$B$5:$B$1004,">="&TODAY(),Bookings!$AA$5:$AA$1004,1)=0,"None",_xlfn.MINIFS(Bookings!$B$5:$B$1004,Bookings!$D$5:$D$1004,$A7,Bookings!$B$5:$B$1004,">="&TODAY(),Bookings!$AA$5:$AA$1004,1))) | O7: =IF($A7="","",COUNTIFS(Bookings!$D$5:$D$1004,$A7,Bookings!$B$5:$B$1004,">="&TODAY(),Bookings!$AA$5:$AA$1004,1))
M8: =IF($A8="","",IF(COUNTIFS(Bookings!$D$5:$D$1004,$A8,Bookings!$B$5:$B$1004,"<="&TODAY(),Bookings!$C$5:$C$1004,">"&TODAY(),Bookings!$AA$5:$AA$1004,1)>0,"Occupied",IF(COUNTIFS(Bookings!$D$5:$D$1004,$A8,Bookings!$C$5:$C$1004,TODAY(),Bookings!$AA$5:$AA$1004,1)>0,"Turnover today","Vacant"))) | N8: =IF($A8="","",IF(_xlfn.MINIFS(Bookings!$B$5:$B$1004,Bookings!$D$5:$D$1004,$A8,Bookings!$B$5:$B$1004,">="&TODAY(),Bookings!$AA$5:$AA$1004,1)=0,"None",_xlfn.MINIFS(Bookings!$B$5:$B$1004,Bookings!$D$5:$D$1004,$A8,Bookings!$B$5:$B$1004,">="&TODAY(),Bookings!$AA$5:$AA$1004,1))) | O8: =IF($A8="","",COUNTIFS(Bookings!$D$5:$D$1004,$A8,Bookings!$B$5:$B$1004,">="&TODAY(),Bookings!$AA$5:$AA$1004,1))
M9: =IF($A9="","",IF(COUNTIFS(Bookings!$D$5:$D$1004,$A9,Bookings!$B$5:$B$1004,"<="&TODAY(),Bookings!$C$5:$C$1004,">"&TODAY(),Bookings!$AA$5:$AA$1004,1)>0,"Occupied",IF(COUNTIFS(Bookings!$D$5:$D$1004,$A9,Bookings!$C$5:$C$1004,TODAY(),Bookings!$AA$5:$AA$1004,1)>0,"Turnover today","Vacant"))) | N9: =IF($A9="","",IF(_xlfn.MINIFS(Bookings!$B$5:$B$1004,Bookings!$D$5:$D$1004,$A9,Bookings!$B$5:$B$1004,">="&TODAY(),Bookings!$AA$5:$AA$1004,1)=0,"None",_xlfn.MINIFS(Bookings!$B$5:$B$1004,Bookings!$D$5:$D$1004,$A9,Bookings!$B$5:$B$1004,">="&TODAY(),Bookings!$AA$5:$AA$1004,1))) | O9: =IF($A9="","",COUNTIFS(Bookings!$D$5:$D$1004,$A9,Bookings!$B$5:$B$1004,">="&TODAY(),Bookings!$AA$5:$AA$1004,1))
M10: =IF($A10="","",IF(COUNTIFS(Bookings!$D$5:$D$1004,$A10,Bookings!$B$5:$B$1004,"<="&TODAY(),Bookings!$C$5:$C$1004,">"&TODAY(),Bookings!$AA$5:$AA$1004,1)>0,"Occupied",IF(COUNTIFS(Bookings!$D$5:$D$1004,$A10,Bookings!$C$5:$C$1004,TODAY(),Bookings!$AA$5:$AA$1004,1)>0,"Turnover today","Vacant"))) | N10: =IF($A10="","",IF(_xlfn.MINIFS(Bookings!$B$5:$B$1004,Bookings!$D$5:$D$1004,$A10,Bookings!$B$5:$B$1004,">="&TODAY(),Bookings!$AA$5:$AA$1004,1)=0,"None",_xlfn.MINIFS(Bookings!$B$5:$B$1004,Bookings!$D$5:$D$1004,$A10,Bookings!$B$5:$B$1004,">="&TODAY(),Bookings!$AA$5:$AA$1004,1))) | O10: =IF($A10="","",COUNTIFS(Bookings!$D$5:$D$1004,$A10,Bookings!$B$5:$B$1004,">="&TODAY(),Bookings!$AA$5:$AA$1004,1))
M11: =IF($A11="","",IF(COUNTIFS(Bookings!$D$5:$D$1004,$A11,Bookings!$B$5:$B$1004,"<="&TODAY(),Bookings!$C$5:$C$1004,">"&TODAY(),Bookings!$AA$5:$AA$1004,1)>0,"Occupied",IF(COUNTIFS(Bookings!$D$5:$D$1004,$A11,Bookings!$C$5:$C$1004,TODAY(),Bookings!$AA$5:$AA$1004,1)>0,"Turnover today","Vacant"))) | N11: =IF($A11="","",IF(_xlfn.MINIFS(Bookings!$B$5:$B$1004,Bookings!$D$5:$D$1004,$A11,Bookings!$B$5:$B$1004,">="&TODAY(),Bookings!$AA$5:$AA$1004,1)=0,"None",_xlfn.MINIFS(Bookings!$B$5:$B$1004,Bookings!$D$5:$D$1004,$A11,Bookings!$B$5:$B$1004,">="&TODAY(),Bookings!$AA$5:$AA$1004,1))) | O11: =IF($A11="","",COUNTIFS(Bookings!$D$5:$D$1004,$A11,Bookings!$B$5:$B$1004,">="&TODAY(),Bookings!$AA$5:$AA$1004,1))
M12: =IF($A12="","",IF(COUNTIFS(Bookings!$D$5:$D$1004,$A12,Bookings!$B$5:$B$1004,"<="&TODAY(),Bookings!$C$5:$C$1004,">"&TODAY(),Bookings!$AA$5:$AA$1004,1)>0,"Occupied",IF(COUNTIFS(Bookings!$D$5:$D$1004,$A12,Bookings!$C$5:$C$1004,TODAY(),Bookings!$AA$5:$AA$1004,1)>0,"Turnover today","Vacant"))) | N12: =IF($A12="","",IF(_xlfn.MINIFS(Bookings!$B$5:$B$1004,Bookings!$D$5:$D$1004,$A12,Bookings!$B$5:$B$1004,">="&TODAY(),Bookings!$AA$5:$AA$1004,1)=0,"None",_xlfn.MINIFS(Bookings!$B$5:$B$1004,Bookings!$D$5:$D$1004,$A12,Bookings!$B$5:$B$1004,">="&TODAY(),Bookings!$AA$5:$AA$1004,1))) | O12: =IF($A12="","",COUNTIFS(Bookings!$D$5:$D$1004,$A12,Bookings!$B$5:$B$1004,">="&TODAY(),Bookings!$AA$5:$AA$1004,1))
M13: =IF($A13="","",IF(COUNTIFS(Bookings!$D$5:$D$1004,$A13,Bookings!$B$5:$B$1004,"<="&TODAY(),Bookings!$C$5:$C$1004,">"&TODAY(),Bookings!$AA$5:$AA$1004,1)>0,"Occupied",IF(COUNTIFS(Bookings!$D$5:$D$1004,$A13,Bookings!$C$5:$C$1004,TODAY(),Bookings!$AA$5:$AA$1004,1)>0,"Turnover today","Vacant"))) | N13: =IF($A13="","",IF(_xlfn.MINIFS(Bookings!$B$5:$B$1004,Bookings!$D$5:$D$1004,$A13,Bookings!$B$5:$B$1004,">="&TODAY(),Bookings!$AA$5:$AA$1004,1)=0,"None",_xlfn.MINIFS(Bookings!$B$5:$B$1004,Bookings!$D$5:$D$1004,$A13,Bookings!$B$5:$B$1004,">="&TODAY(),Bookings!$AA$5:$AA$1004,1))) | O13: =IF($A13="","",COUNTIFS(Bookings!$D$5:$D$1004,$A13,Bookings!$B$5:$B$1004,">="&TODAY(),Bookings!$AA$5:$AA$1004,1))
M14: =IF($A14="","",IF(COUNTIFS(Bookings!$D$5:$D$1004,$A14,Bookings!$B$5:$B$1004,"<="&TODAY(),Bookings!$C$5:$C$1004,">"&TODAY(),Bookings!$AA$5:$AA$1004,1)>0,"Occupied",IF(COUNTIFS(Bookings!$D$5:$D$1004,$A14,Bookings!$C$5:$C$1004,TODAY(),Bookings!$AA$5:$AA$1004,1)>0,"Turnover today","Vacant"))) | N14: =IF($A14="","",IF(_xlfn.MINIFS(Bookings!$B$5:$B$1004,Bookings!$D$5:$D$1004,$A14,Bookings!$B$5:$B$1004,">="&TODAY(),Bookings!$AA$5:$AA$1004,1)=0,"None",_xlfn.MINIFS(Bookings!$B$5:$B$1004,Bookings!$D$5:$D$1004,$A14,Bookings!$B$5:$B$1004,">="&TODAY(),Bookings!$AA$5:$AA$1004,1))) | O14: =IF($A14="","",COUNTIFS(Bookings!$D$5:$D$1004,$A14,Bookings!$B$5:$B$1004,">="&TODAY(),Bookings!$AA$5:$AA$1004,1))
M15: =IF($A15="","",IF(COUNTIFS(Bookings!$D$5:$D$1004,$A15,Bookings!$B$5:$B$1004,"<="&TODAY(),Bookings!$C$5:$C$1004,">"&TODAY(),Bookings!$AA$5:$AA$1004,1)>0,"Occupied",IF(COUNTIFS(Bookings!$D$5:$D$1004,$A15,Bookings!$C$5:$C$1004,TODAY(),Bookings!$AA$5:$AA$1004,1)>0,"Turnover today","Vacant"))) | N15: =IF($A15="","",IF(_xlfn.MINIFS(Bookings!$B$5:$B$1004,Bookings!$D$5:$D$1004,$A15,Bookings!$B$5:$B$1004,">="&TODAY(),Bookings!$AA$5:$AA$1004,1)=0,"None",_xlfn.MINIFS(Bookings!$B$5:$B$1004,Bookings!$D$5:$D$1004,$A15,Bookings!$B$5:$B$1004,">="&TODAY(),Bookings!$AA$5:$AA$1004,1))) | O15: =IF($A15="","",COUNTIFS(Bookings!$D$5:$D$1004,$A15,Bookings!$B$5:$B$1004,">="&TODAY(),Bookings!$AA$5:$AA$1004,1))
M16: =IF($A16="","",IF(COUNTIFS(Bookings!$D$5:$D$1004,$A16,Bookings!$B$5:$B$1004,"<="&TODAY(),Bookings!$C$5:$C$1004,">"&TODAY(),Bookings!$AA$5:$AA$1004,1)>0,"Occupied",IF(COUNTIFS(Bookings!$D$5:$D$1004,$A16,Bookings!$C$5:$C$1004,TODAY(),Bookings!$AA$5:$AA$1004,1)>0,"Turnover today","Vacant"))) | N16: =IF($A16="","",IF(_xlfn.MINIFS(Bookings!$B$5:$B$1004,Bookings!$D$5:$D$1004,$A16,Bookings!$B$5:$B$1004,">="&TODAY(),Bookings!$AA$5:$AA$1004,1)=0,"None",_xlfn.MINIFS(Bookings!$B$5:$B$1004,Bookings!$D$5:$D$1004,$A16,Bookings!$B$5:$B$1004,">="&TODAY(),Bookings!$AA$5:$AA$1004,1))) | O16: =IF($A16="","",COUNTIFS(Bookings!$D$5:$D$1004,$A16,Bookings!$B$5:$B$1004,">="&TODAY(),Bookings!$AA$5:$AA$1004,1))
M17: =IF($A17="","",IF(COUNTIFS(Bookings!$D$5:$D$1004,$A17,Bookings!$B$5:$B$1004,"<="&TODAY(),Bookings!$C$5:$C$1004,">"&TODAY(),Bookings!$AA$5:$AA$1004,1)>0,"Occupied",IF(COUNTIFS(Bookings!$D$5:$D$1004,$A17,Bookings!$C$5:$C$1004,TODAY(),Bookings!$AA$5:$AA$1004,1)>0,"Turnover today","Vacant"))) | N17: =IF($A17="","",IF(_xlfn.MINIFS(Bookings!$B$5:$B$1004,Bookings!$D$5:$D$1004,$A17,Bookings!$B$5:$B$1004,">="&TODAY(),Bookings!$AA$5:$AA$1004,1)=0,"None",_xlfn.MINIFS(Bookings!$B$5:$B$1004,Bookings!$D$5:$D$1004,$A17,Bookings!$B$5:$B$1004,">="&TODAY(),Bookings!$AA$5:$AA$1004,1))) | O17: =IF($A17="","",COUNTIFS(Bookings!$D$5:$D$1004,$A17,Bookings!$B$5:$B$1004,">="&TODAY(),Bookings!$AA$5:$AA$1004,1))
... M24: =IF($A24="","",IF(COUNTIFS(Bookings!$D$5:$D$1004,$A24,Bookings!$B$5:$B$1004,"<="&TODAY(),Bookings!$C$5:$C$1004,">"&TODAY(),Bookings!$AA$5:$AA$1004,1)>0,"Occupied",IF(COUNTIFS(Bookings!$D$5:$D$1004,$A24,Bookings!$C$5:$C$1004,TODAY(),Bookings!$AA$5:$AA$1004,1)>0,"Turnover today","Vacant"))) | N24: =IF($A24="","",IF(_xlfn.MINIFS(Bookings!$B$5:$B$1004,Bookings!$D$5:$D$1004,$A24,Bookings!$B$5:$B$1004,">="&TODAY(),Bookings!$AA$5:$AA$1004,1)=0,"None",_xlfn.MINIFS(Bookings!$B$5:$B$1004,Bookings!$D$5:$D$1004,$A24,Bookings!$B$5:$B$1004,">="&TODAY(),Bookings!$AA$5:$AA$1004,1))) | O24: =IF($A24="","",COUNTIFS(Bookings!$D$5:$D$1004,$A24,Bookings!$B$5:$B$1004,">="&TODAY(),Bookings!$AA$5:$AA$1004,1))

Sheet Bookings
A1: Bookings
A2: Log every reservation. Yellow = you type, white = calculated. Type the real payout in 'Actual payout' when you have it.
Z3: Helper columns: used by the dashboard and turnovers. Don't edit.
A4: Booking ID | B4: Check-in | C4: Check-out | D4: Property | E4: Guest name | F4: Channel | G4: Guests | H4: Nights | I4: Nightly rate override | J4: Rent | K4: Cleaning fee | L4: Extra guest fees | M4: Other fees / discounts | N4: Guest total | O4: Platform fee | P4: Actual payout (optional) | Q4: Payout | R4: Cleaning cost | S4: Net after cleaning | T4: Status | U4: Paid? | V4: Cleaner | W4: Clean done? | X4: Notes | Y4: Check | Z4: Turnover key | AA4: Include | AB4: Rent / night | AC4: Payout / night | AD4: Cleaning cost / night | AE4: Platform fee / night | AF4: Cleaning fee / night | AG4: Check-in key | AH4: Nights (helper)
A5: =IF(B5="","","B-"&TEXT(ROW()-4,"0000")) -> B-0001 | B5: 46297 | C5: 46300 | D5: EXAMPLE – Lakeview Cabin | E5: Jordan P. | F5: Airbnb | G5: 4 | H5: =IF(AND(ISNUMBER(B5),ISNUMBER(C5)),MAX(0,C5-B5),"") -> 3 | J5: =IF(OR(D5="",N(H5)=0),"",IFERROR(IF(I5<>"",H5*I5,ROUND(((H5-(INT((WEEKDAY(B5-6)+H5-1)/7)+INT((WEEKDAY(B5-7)+H5-1)/7)))*INDEX(Properties!$E$5:$E$24,MATCH(D5,Properties!$A$5:$A$24,0))+(INT((WEEKDAY(B5-6)+H5-1)/7)+INT((WEEKDAY(B5-7)+H5-1)/7))*INDEX(Properties!$F$5:$F$24,MATCH(D5,Properties!$A$5:$A$24,0)))*(1-IF(H5>=28,Settings!$B$10,IF(H5>=7,Settings!$B$9,0))),2)),0)) -> 585 | K5: =IF(J5="","",IFERROR(N(INDEX(Properties!$G$5:$G$24,MATCH(D5,Properties!$A$5:$A$24,0))),0)) -> 95 | L5: =IF(J5="","",IFERROR(MAX(0,N(G5)-INDEX(Properties!$I$5:$I$24,MATCH(D5,Properties!$A$5:$A$24,0)))*N(INDEX(Properties!$J$5:$J$24,MATCH(D5,Properties!$A$5:$A$24,0)))*H5,0)) -> 0 | N5: =IF(J5="","",J5+K5+L5+N(M5)) -> 680 | O5: =IF(N5="","",IF(P5<>"",N5-P5,ROUND(N5*IFERROR(INDEX(Settings!$E$5:$E$12,MATCH(F5,Settings!$D$5:$D$12,0)),0),2))) -> 20.4 | Q5: =IF(N5="","",IF(P5<>"",P5,N5-O5)) -> 659.6 | R5: =IF(J5="","",IFERROR(N(INDEX(Properties!$H$5:$H$24,MATCH(D5,Properties!$A$5:$A$24,0))),0)) -> 65 | S5: =IF(Q5="","",Q5-R5) -> 594.6 | T5: Booked | U5: Yes | V5: Maria (cleaner) | W5: Yes | Y5: =IF(OR(D5="",B5="",C5=""),"",IF(N(C5)<=N(B5),"Check dates",IF(T5="Cancelled","",IF(COUNTIFS($D$5:$D$1004,D5,$B$5:$B$1004,"<"&C5,$C$5:$C$1004,">"&B5,$T$5:$T$1004,"<>Cancelled")>1,"Double-booked","")))) | Z5: =IF(AND(AA5=1,ISNUMBER(C5)),C5+ROW()/100000,"") -> 46300 | AA5: =IF(AND(D5<>"",ISNUMBER(B5),ISNUMBER(C5),N(H5)>0,T5<>"Cancelled",J5<>""),1,0) -> 1 | AB5: =IF(AA5=1,J5/H5,0) -> 195 | AC5: =IF(AA5=1,Q5/H5,0) -> 219.86667 | AD5: =IF(AA5=1,R5/H5,0) -> 21.666667 | AE5: =IF(AA5=1,O5/H5,0) -> 6.8 | AF5: =IF(AA5=1,K5/H5,0) -> 31.666667 | AG5: =IF(AA5=1,D5&"|"&TEXT(B5,"0"),"") -> EXAMPLE – Lakeview Cabin|46297 | AH5: =IF(AA5=1,H5,0) -> 3
A6: =IF(B6="","","B-"&TEXT(ROW()-4,"0000")) -> B-0002 | B6: 46304 | C6: 46306 | D6: EXAMPLE – Lakeview Cabin | E6: Sam & Lee R. | F6: Direct booking | G6: 6 | H6: =IF(AND(ISNUMBER(B6),ISNUMBER(C6)),MAX(0,C6-B6),"") -> 2 | J6: =IF(OR(D6="",N(H6)=0),"",IFERROR(IF(I6<>"",H6*I6,ROUND(((H6-(INT((WEEKDAY(B6-6)+H6-1)/7)+INT((WEEKDAY(B6-7)+H6-1)/7)))*INDEX(Properties!$E$5:$E$24,MATCH(D6,Properties!$A$5:$A$24,0))+(INT((WEEKDAY(B6-6)+H6-1)/7)+INT((WEEKDAY(B6-7)+H6-1)/7))*INDEX(Properties!$F$5:$F$24,MATCH(D6,Properties!$A$5:$A$24,0)))*(1-IF(H6>=28,Settings!$B$10,IF(H6>=7,Settings!$B$9,0))),2)),0)) -> 420 | K6: =IF(J6="","",IFERROR(N(INDEX(Properties!$G$5:$G$24,MATCH(D6,Properties!$A$5:$A$24,0))),0)) -> 95 | L6: =IF(J6="","",IFERROR(MAX(0,N(G6)-INDEX(Properties!$I$5:$I$24,MATCH(D6,Properties!$A$5:$A$24,0)))*N(INDEX(Properties!$J$5:$J$24,MATCH(D6,Properties!$A$5:$A$24,0)))*H6,0)) -> 60 | M6: 25 | N6: =IF(J6="","",J6+K6+L6+N(M6)) -> 600 | O6: =IF(N6="","",IF(P6<>"",N6-P6,ROUND(N6*IFERROR(INDEX(Settings!$E$5:$E$12,MATCH(F6,Settings!$D$5:$D$12,0)),0),2))) -> 18 | Q6: =IF(N6="","",IF(P6<>"",P6,N6-O6)) -> 582 | R6: =IF(J6="","",IFERROR(N(INDEX(Properties!$H$5:$H$24,MATCH(D6,Properties!$A$5:$A$24,0))),0)) -> 65 | S6: =IF(Q6="","",Q6-R6) -> 517 | T6: Booked | U6: No | V6: Maria (cleaner) | X6: Pet fee $25 | Y6: =IF(OR(D6="",B6="",C6=""),"",IF(N(C6)<=N(B6),"Check dates",IF(T6="Cancelled","",IF(COUNTIFS($D$5:$D$1004,D6,$B$5:$B$1004,"<"&C6,$C$5:$C$1004,">"&B6,$T$5:$T$1004,"<>Cancelled")>1,"Double-booked","")))) | Z6: =IF(AND(AA6=1,ISNUMBER(C6)),C6+ROW()/100000,"") -> 46306 | AA6: =IF(AND(D6<>"",ISNUMBER(B6),ISNUMBER(C6),N(H6)>0,T6<>"Cancelled",J6<>""),1,0) -> 1 | AB6: =IF(AA6=1,J6/H6,0) -> 210 | AC6: =IF(AA6=1,Q6/H6,0) -> 291 | AD6: =IF(AA6=1,R6/H6,0) -> 32.5 | AE6: =IF(AA6=1,O6/H6,0) -> 9 | AF6: =IF(AA6=1,K6/H6,0) -> 47.5 | AG6: =IF(AA6=1,D6&"|"&TEXT(B6,"0"),"") -> EXAMPLE – Lakeview Cabin|46304 | AH6: =IF(AA6=1,H6,0) -> 2
A7: =IF(B7="","","B-"&TEXT(ROW()-4,"0000")) | H7: =IF(AND(ISNUMBER(B7),ISNUMBER(C7)),MAX(0,C7-B7),"") | J7: =IF(OR(D7="",N(H7)=0),"",IFERROR(IF(I7<>"",H7*I7,ROUND(((H7-(INT((WEEKDAY(B7-6)+H7-1)/7)+INT((WEEKDAY(B7-7)+H7-1)/7)))*INDEX(Properties!$E$5:$E$24,MATCH(D7,Properties!$A$5:$A$24,0))+(INT((WEEKDAY(B7-6)+H7-1)/7)+INT((WEEKDAY(B7-7)+H7-1)/7))*INDEX(Properties!$F$5:$F$24,MATCH(D7,Properties!$A$5:$A$24,0)))*(1-IF(H7>=28,Settings!$B$10,IF(H7>=7,Settings!$B$9,0))),2)),0)) | K7: =IF(J7="","",IFERROR(N(INDEX(Properties!$G$5:$G$24,MATCH(D7,Properties!$A$5:$A$24,0))),0)) | L7: =IF(J7="","",IFERROR(MAX(0,N(G7)-INDEX(Properties!$I$5:$I$24,MATCH(D7,Properties!$A$5:$A$24,0)))*N(INDEX(Properties!$J$5:$J$24,MATCH(D7,Properties!$A$5:$A$24,0)))*H7,0)) | N7: =IF(J7="","",J7+K7+L7+N(M7)) | O7: =IF(N7="","",IF(P7<>"",N7-P7,ROUND(N7*IFERROR(INDEX(Settings!$E$5:$E$12,MATCH(F7,Settings!$D$5:$D$12,0)),0),2))) | Q7: =IF(N7="","",IF(P7<>"",P7,N7-O7)) | R7: =IF(J7="","",IFERROR(N(INDEX(Properties!$H$5:$H$24,MATCH(D7,Properties!$A$5:$A$24,0))),0)) | S7: =IF(Q7="","",Q7-R7) | Y7: =IF(OR(D7="",B7="",C7=""),"",IF(N(C7)<=N(B7),"Check dates",IF(T7="Cancelled","",IF(COUNTIFS($D$5:$D$1004,D7,$B$5:$B$1004,"<"&C7,$C$5:$C$1004,">"&B7,$T$5:$T$1004,"<>Cancelled")>1,"Double-booked","")))) | Z7: =IF(AND(AA7=1,ISNUMBER(C7)),C7+ROW()/100000,"") | AA7: =IF(AND(D7<>"",ISNUMBER(B7),ISNUMBER(C7),N(H7)>0,T7<>"Cancelled",J7<>""),1,0) -> 0 | AB7: =IF(AA7=1,J7/H7,0) -> 0 | AC7: =IF(AA7=1,Q7/H7,0) -> 0 | AD7: =IF(AA7=1,R7/H7,0) -> 0 | AE7: =IF(AA7=1,O7/H7,0) -> 0 | AF7: =IF(AA7=1,K7/H7,0) -> 0 | AG7: =IF(AA7=1,D7&"|"&TEXT(B7,"0"),"") | AH7: =IF(AA7=1,H7,0) -> 0
A8: =IF(B8="","","B-"&TEXT(ROW()-4,"0000")) | H8: =IF(AND(ISNUMBER(B8),ISNUMBER(C8)),MAX(0,C8-B8),"") | J8: =IF(OR(D8="",N(H8)=0),"",IFERROR(IF(I8<>"",H8*I8,ROUND(((H8-(INT((WEEKDAY(B8-6)+H8-1)/7)+INT((WEEKDAY(B8-7)+H8-1)/7)))*INDEX(Properties!$E$5:$E$24,MATCH(D8,Properties!$A$5:$A$24,0))+(INT((WEEKDAY(B8-6)+H8-1)/7)+INT((WEEKDAY(B8-7)+H8-1)/7))*INDEX(Properties!$F$5:$F$24,MATCH(D8,Properties!$A$5:$A$24,0)))*(1-IF(H8>=28,Settings!$B$10,IF(H8>=7,Settings!$B$9,0))),2)),0)) | K8: =IF(J8="","",IFERROR(N(INDEX(Properties!$G$5:$G$24,MATCH(D8,Properties!$A$5:$A$24,0))),0)) | L8: =IF(J8="","",IFERROR(MAX(0,N(G8)-INDEX(Properties!$I$5:$I$24,MATCH(D8,Properties!$A$5:$A$24,0)))*N(INDEX(Properties!$J$5:$J$24,MATCH(D8,Properties!$A$5:$A$24,0)))*H8,0)) | N8: =IF(J8="","",J8+K8+L8+N(M8)) | O8: =IF(N8="","",IF(P8<>"",N8-P8,ROUND(N8*IFERROR(INDEX(Settings!$E$5:$E$12,MATCH(F8,Settings!$D$5:$D$12,0)),0),2))) | Q8: =IF(N8="","",IF(P8<>"",P8,N8-O8)) | R8: =IF(J8="","",IFERROR(N(INDEX(Properties!$H$5:$H$24,MATCH(D8,Properties!$A$5:$A$24,0))),0)) | S8: =IF(Q8="","",Q8-R8) | Y8: =IF(OR(D8="",B8="",C8=""),"",IF(N(C8)<=N(B8),"Check dates",IF(T8="Cancelled","",IF(COUNTIFS($D$5:$D$1004,D8,$B$5:$B$1004,"<"&C8,$C$5:$C$1004,">"&B8,$T$5:$T$1004,"<>Cancelled")>1,"Double-booked","")))) | Z8: =IF(AND(AA8=1,ISNUMBER(C8)),C8+ROW()/100000,"") | AA8: =IF(AND(D8<>"",ISNUMBER(B8),ISNUMBER(C8),N(H8)>0,T8<>"Cancelled",J8<>""),1,0) -> 0 | AB8: =IF(AA8=1,J8/H8,0) -> 0 | AC8: =IF(AA8=1,Q8/H8,0) -> 0 | AD8: =IF(AA8=1,R8/H8,0) -> 0 | AE8: =IF(AA8=1,O8/H8,0) -> 0 | AF8: =IF(AA8=1,K8/H8,0) -> 0 | AG8: =IF(AA8=1,D8&"|"&TEXT(B8,"0"),"") | AH8: =IF(AA8=1,H8,0) -> 0
A9: =IF(B9="","","B-"&TEXT(ROW()-4,"0000")) | H9: =IF(AND(ISNUMBER(B9),ISNUMBER(C9)),MAX(0,C9-B9),"") | J9: =IF(OR(D9="",N(H9)=0),"",IFERROR(IF(I9<>"",H9*I9,ROUND(((H9-(INT((WEEKDAY(B9-6)+H9-1)/7)+INT((WEEKDAY(B9-7)+H9-1)/7)))*INDEX(Properties!$E$5:$E$24,MATCH(D9,Properties!$A$5:$A$24,0))+(INT((WEEKDAY(B9-6)+H9-1)/7)+INT((WEEKDAY(B9-7)+H9-1)/7))*INDEX(Properties!$F$5:$F$24,MATCH(D9,Properties!$A$5:$A$24,0)))*(1-IF(H9>=28,Settings!$B$10,IF(H9>=7,Settings!$B$9,0))),2)),0)) | K9: =IF(J9="","",IFERROR(N(INDEX(Properties!$G$5:$G$24,MATCH(D9,Properties!$A$5:$A$24,0))),0)) | L9: =IF(J9="","",IFERROR(MAX(0,N(G9)-INDEX(Properties!$I$5:$I$24,MATCH(D9,Properties!$A$5:$A$24,0)))*N(INDEX(Properties!$J$5:$J$24,MATCH(D9,Properties!$A$5:$A$24,0)))*H9,0)) | N9: =IF(J9="","",J9+K9+L9+N(M9)) | O9: =IF(N9="","",IF(P9<>"",N9-P9,ROUND(N9*IFERROR(INDEX(Settings!$E$5:$E$12,MATCH(F9,Settings!$D$5:$D$12,0)),0),2))) | Q9: =IF(N9="","",IF(P9<>"",P9,N9-O9)) | R9: =IF(J9="","",IFERROR(N(INDEX(Properties!$H$5:$H$24,MATCH(D9,Properties!$A$5:$A$24,0))),0)) | S9: =IF(Q9="","",Q9-R9) | Y9: =IF(OR(D9="",B9="",C9=""),"",IF(N(C9)<=N(B9),"Check dates",IF(T9="Cancelled","",IF(COUNTIFS($D$5:$D$1004,D9,$B$5:$B$1004,"<"&C9,$C$5:$C$1004,">"&B9,$T$5:$T$1004,"<>Cancelled")>1,"Double-booked","")))) | Z9: =IF(AND(AA9=1,ISNUMBER(C9)),C9+ROW()/100000,"") | AA9: =IF(AND(D9<>"",ISNUMBER(B9),ISNUMBER(C9),N(H9)>0,T9<>"Cancelled",J9<>""),1,0) -> 0 | AB9: =IF(AA9=1,J9/H9,0) -> 0 | AC9: =IF(AA9=1,Q9/H9,0) -> 0 | AD9: =IF(AA9=1,R9/H9,0) -> 0 | AE9: =IF(AA9=1,O9/H9,0) -> 0 | AF9: =IF(AA9=1,K9/H9,0) -> 0 | AG9: =IF(AA9=1,D9&"|"&TEXT(B9,"0"),"") | AH9: =IF(AA9=1,H9,0) -> 0
A10: =IF(B10="","","B-"&TEXT(ROW()-4,"0000")) | H10: =IF(AND(ISNUMBER(B10),ISNUMBER(C10)),MAX(0,C10-B10),"") | J10: =IF(OR(D10="",N(H10)=0),"",IFERROR(IF(I10<>"",H10*I10,ROUND(((H10-(INT((WEEKDAY(B10-6)+H10-1)/7)+INT((WEEKDAY(B10-7)+H10-1)/7)))*INDEX(Properties!$E$5:$E$24,MATCH(D10,Properties!$A$5:$A$24,0))+(INT((WEEKDAY(B10-6)+H10-1)/7)+INT((WEEKDAY(B10-7)+H10-1)/7))*INDEX(Properties!$F$5:$F$24,MATCH(D10,Properties!$A$5:$A$24,0)))*(1-IF(H10>=28,Settings!$B$10,IF(H10>=7,Settings!$B$9,0))),2)),0)) | K10: =IF(J10="","",IFERROR(N(INDEX(Properties!$G$5:$G$24,MATCH(D10,Properties!$A$5:$A$24,0))),0)) | L10: =IF(J10="","",IFERROR(MAX(0,N(G10)-INDEX(Properties!$I$5:$I$24,MATCH(D10,Properties!$A$5:$A$24,0)))*N(INDEX(Properties!$J$5:$J$24,MATCH(D10,Properties!$A$5:$A$24,0)))*H10,0)) | N10: =IF(J10="","",J10+K10+L10+N(M10)) | O10: =IF(N10="","",IF(P10<>"",N10-P10,ROUND(N10*IFERROR(INDEX(Settings!$E$5:$E$12,MATCH(F10,Settings!$D$5:$D$12,0)),0),2))) | Q10: =IF(N10="","",IF(P10<>"",P10,N10-O10)) | R10: =IF(J10="","",IFERROR(N(INDEX(Properties!$H$5:$H$24,MATCH(D10,Properties!$A$5:$A$24,0))),0)) | S10: =IF(Q10="","",Q10-R10) | Y10: =IF(OR(D10="",B10="",C10=""),"",IF(N(C10)<=N(B10),"Check dates",IF(T10="Cancelled","",IF(COUNTIFS($D$5:$D$1004,D10,$B$5:$B$1004,"<"&C10,$C$5:$C$1004,">"&B10,$T$5:$T$1004,"<>Cancelled")>1,"Double-booked","")))) | Z10: =IF(AND(AA10=1,ISNUMBER(C10)),C10+ROW()/100000,"") | AA10: =IF(AND(D10<>"",ISNUMBER(B10),ISNUMBER(C10),N(H10)>0,T10<>"Cancelled",J10<>""),1,0) -> 0 | AB10: =IF(AA10=1,J10/H10,0) -> 0 | AC10: =IF(AA10=1,Q10/H10,0) -> 0 | AD10: =IF(AA10=1,R10/H10,0) -> 0 | AE10: =IF(AA10=1,O10/H10,0) -> 0 | AF10: =IF(AA10=1,K10/H10,0) -> 0 | AG10: =IF(AA10=1,D10&"|"&TEXT(B10,"0"),"") | AH10: =IF(AA10=1,H10,0) -> 0
A11: =IF(B11="","","B-"&TEXT(ROW()-4,"0000")) | H11: =IF(AND(ISNUMBER(B11),ISNUMBER(C11)),MAX(0,C11-B11),"") | J11: =IF(OR(D11="",N(H11)=0),"",IFERROR(IF(I11<>"",H11*I11,ROUND(((H11-(INT((WEEKDAY(B11-6)+H11-1)/7)+INT((WEEKDAY(B11-7)+H11-1)/7)))*INDEX(Properties!$E$5:$E$24,MATCH(D11,Properties!$A$5:$A$24,0))+(INT((WEEKDAY(B11-6)+H11-1)/7)+INT((WEEKDAY(B11-7)+H11-1)/7))*INDEX(Properties!$F$5:$F$24,MATCH(D11,Properties!$A$5:$A$24,0)))*(1-IF(H11>=28,Settings!$B$10,IF(H11>=7,Settings!$B$9,0))),2)),0)) | K11: =IF(J11="","",IFERROR(N(INDEX(Properties!$G$5:$G$24,MATCH(D11,Properties!$A$5:$A$24,0))),0)) | L11: =IF(J11="","",IFERROR(MAX(0,N(G11)-INDEX(Properties!$I$5:$I$24,MATCH(D11,Properties!$A$5:$A$24,0)))*N(INDEX(Properties!$J$5:$J$24,MATCH(D11,Properties!$A$5:$A$24,0)))*H11,0)) | N11: =IF(J11="","",J11+K11+L11+N(M11)) | O11: =IF(N11="","",IF(P11<>"",N11-P11,ROUND(N11*IFERROR(INDEX(Settings!$E$5:$E$12,MATCH(F11,Settings!$D$5:$D$12,0)),0),2))) | Q11: =IF(N11="","",IF(P11<>"",P11,N11-O11)) | R11: =IF(J11="","",IFERROR(N(INDEX(Properties!$H$5:$H$24,MATCH(D11,Properties!$A$5:$A$24,0))),0)) | S11: =IF(Q11="","",Q11-R11) | Y11: =IF(OR(D11="",B11="",C11=""),"",IF(N(C11)<=N(B11),"Check dates",IF(T11="Cancelled","",IF(COUNTIFS($D$5:$D$1004,D11,$B$5:$B$1004,"<"&C11,$C$5:$C$1004,">"&B11,$T$5:$T$1004,"<>Cancelled")>1,"Double-booked","")))) | Z11: =IF(AND(AA11=1,ISNUMBER(C11)),C11+ROW()/100000,"") | AA11: =IF(AND(D11<>"",ISNUMBER(B11),ISNUMBER(C11),N(H11)>0,T11<>"Cancelled",J11<>""),1,0) -> 0 | AB11: =IF(AA11=1,J11/H11,0) -> 0 | AC11: =IF(AA11=1,Q11/H11,0) -> 0 | AD11: =IF(AA11=1,R11/H11,0) -> 0 | AE11: =IF(AA11=1,O11/H11,0) -> 0 | AF11: =IF(AA11=1,K11/H11,0) -> 0 | AG11: =IF(AA11=1,D11&"|"&TEXT(B11,"0"),"") | AH11: =IF(AA11=1,H11,0) -> 0
A12: =IF(B12="","","B-"&TEXT(ROW()-4,"0000")) | H12: =IF(AND(ISNUMBER(B12),ISNUMBER(C12)),MAX(0,C12-B12),"") | J12: =IF(OR(D12="",N(H12)=0),"",IFERROR(IF(I12<>"",H12*I12,ROUND(((H12-(INT((WEEKDAY(B12-6)+H12-1)/7)+INT((WEEKDAY(B12-7)+H12-1)/7)))*INDEX(Properties!$E$5:$E$24,MATCH(D12,Properties!$A$5:$A$24,0))+(INT((WEEKDAY(B12-6)+H12-1)/7)+INT((WEEKDAY(B12-7)+H12-1)/7))*INDEX(Properties!$F$5:$F$24,MATCH(D12,Properties!$A$5:$A$24,0)))*(1-IF(H12>=28,Settings!$B$10,IF(H12>=7,Settings!$B$9,0))),2)),0)) | K12: =IF(J12="","",IFERROR(N(INDEX(Properties!$G$5:$G$24,MATCH(D12,Properties!$A$5:$A$24,0))),0)) | L12: =IF(J12="","",IFERROR(MAX(0,N(G12)-INDEX(Properties!$I$5:$I$24,MATCH(D12,Properties!$A$5:$A$24,0)))*N(INDEX(Properties!$J$5:$J$24,MATCH(D12,Properties!$A$5:$A$24,0)))*H12,0)) | N12: =IF(J12="","",J12+K12+L12+N(M12)) | O12: =IF(N12="","",IF(P12<>"",N12-P12,ROUND(N12*IFERROR(INDEX(Settings!$E$5:$E$12,MATCH(F12,Settings!$D$5:$D$12,0)),0),2))) | Q12: =IF(N12="","",IF(P12<>"",P12,N12-O12)) | R12: =IF(J12="","",IFERROR(N(INDEX(Properties!$H$5:$H$24,MATCH(D12,Properties!$A$5:$A$24,0))),0)) | S12: =IF(Q12="","",Q12-R12) | Y12: =IF(OR(D12="",B12="",C12=""),"",IF(N(C12)<=N(B12),"Check dates",IF(T12="Cancelled","",IF(COUNTIFS($D$5:$D$1004,D12,$B$5:$B$1004,"<"&C12,$C$5:$C$1004,">"&B12,$T$5:$T$1004,"<>Cancelled")>1,"Double-booked","")))) | Z12: =IF(AND(AA12=1,ISNUMBER(C12)),C12+ROW()/100000,"") | AA12: =IF(AND(D12<>"",ISNUMBER(B12),ISNUMBER(C12),N(H12)>0,T12<>"Cancelled",J12<>""),1,0) -> 0 | AB12: =IF(AA12=1,J12/H12,0) -> 0 | AC12: =IF(AA12=1,Q12/H12,0) -> 0 | AD12: =IF(AA12=1,R12/H12,0) -> 0 | AE12: =IF(AA12=1,O12/H12,0) -> 0 | AF12: =IF(AA12=1,K12/H12,0) -> 0 | AG12: =IF(AA12=1,D12&"|"&TEXT(B12,"0"),"") | AH12: =IF(AA12=1,H12,0) -> 0
A13: =IF(B13="","","B-"&TEXT(ROW()-4,"0000")) | H13: =IF(AND(ISNUMBER(B13),ISNUMBER(C13)),MAX(0,C13-B13),"") | J13: =IF(OR(D13="",N(H13)=0),"",IFERROR(IF(I13<>"",H13*I13,ROUND(((H13-(INT((WEEKDAY(B13-6)+H13-1)/7)+INT((WEEKDAY(B13-7)+H13-1)/7)))*INDEX(Properties!$E$5:$E$24,MATCH(D13,Properties!$A$5:$A$24,0))+(INT((WEEKDAY(B13-6)+H13-1)/7)+INT((WEEKDAY(B13-7)+H13-1)/7))*INDEX(Properties!$F$5:$F$24,MATCH(D13,Properties!$A$5:$A$24,0)))*(1-IF(H13>=28,Settings!$B$10,IF(H13>=7,Settings!$B$9,0))),2)),0)) | K13: =IF(J13="","",IFERROR(N(INDEX(Properties!$G$5:$G$24,MATCH(D13,Properties!$A$5:$A$24,0))),0)) | L13: =IF(J13="","",IFERROR(MAX(0,N(G13)-INDEX(Properties!$I$5:$I$24,MATCH(D13,Properties!$A$5:$A$24,0)))*N(INDEX(Properties!$J$5:$J$24,MATCH(D13,Properties!$A$5:$A$24,0)))*H13,0)) | N13: =IF(J13="","",J13+K13+L13+N(M13)) | O13: =IF(N13="","",IF(P13<>"",N13-P13,ROUND(N13*IFERROR(INDEX(Settings!$E$5:$E$12,MATCH(F13,Settings!$D$5:$D$12,0)),0),2))) | Q13: =IF(N13="","",IF(P13<>"",P13,N13-O13)) | R13: =IF(J13="","",IFERROR(N(INDEX(Properties!$H$5:$H$24,MATCH(D13,Properties!$A$5:$A$24,0))),0)) | S13: =IF(Q13="","",Q13-R13) | Y13: =IF(OR(D13="",B13="",C13=""),"",IF(N(C13)<=N(B13),"Check dates",IF(T13="Cancelled","",IF(COUNTIFS($D$5:$D$1004,D13,$B$5:$B$1004,"<"&C13,$C$5:$C$1004,">"&B13,$T$5:$T$1004,"<>Cancelled")>1,"Double-booked","")))) | Z13: =IF(AND(AA13=1,ISNUMBER(C13)),C13+ROW()/100000,"") | AA13: =IF(AND(D13<>"",ISNUMBER(B13),ISNUMBER(C13),N(H13)>0,T13<>"Cancelled",J13<>""),1,0) -> 0 | AB13: =IF(AA13=1,J13/H13,0) -> 0 | AC13: =IF(AA13=1,Q13/H13,0) -> 0 | AD13: =IF(AA13=1,R13/H13,0) -> 0 | AE13: =IF(AA13=1,O13/H13,0) -> 0 | AF13: =IF(AA13=1,K13/H13,0) -> 0 | AG13: =IF(AA13=1,D13&"|"&TEXT(B13,"0"),"") | AH13: =IF(AA13=1,H13,0) -> 0
A14: =IF(B14="","","B-"&TEXT(ROW()-4,"0000")) | H14: =IF(AND(ISNUMBER(B14),ISNUMBER(C14)),MAX(0,C14-B14),"") | J14: =IF(OR(D14="",N(H14)=0),"",IFERROR(IF(I14<>"",H14*I14,ROUND(((H14-(INT((WEEKDAY(B14-6)+H14-1)/7)+INT((WEEKDAY(B14-7)+H14-1)/7)))*INDEX(Properties!$E$5:$E$24,MATCH(D14,Properties!$A$5:$A$24,0))+(INT((WEEKDAY(B14-6)+H14-1)/7)+INT((WEEKDAY(B14-7)+H14-1)/7))*INDEX(Properties!$F$5:$F$24,MATCH(D14,Properties!$A$5:$A$24,0)))*(1-IF(H14>=28,Settings!$B$10,IF(H14>=7,Settings!$B$9,0))),2)),0)) | K14: =IF(J14="","",IFERROR(N(INDEX(Properties!$G$5:$G$24,MATCH(D14,Properties!$A$5:$A$24,0))),0)) | L14: =IF(J14="","",IFERROR(MAX(0,N(G14)-INDEX(Properties!$I$5:$I$24,MATCH(D14,Properties!$A$5:$A$24,0)))*N(INDEX(Properties!$J$5:$J$24,MATCH(D14,Properties!$A$5:$A$24,0)))*H14,0)) | N14: =IF(J14="","",J14+K14+L14+N(M14)) | O14: =IF(N14="","",IF(P14<>"",N14-P14,ROUND(N14*IFERROR(INDEX(Settings!$E$5:$E$12,MATCH(F14,Settings!$D$5:$D$12,0)),0),2))) | Q14: =IF(N14="","",IF(P14<>"",P14,N14-O14)) | R14: =IF(J14="","",IFERROR(N(INDEX(Properties!$H$5:$H$24,MATCH(D14,Properties!$A$5:$A$24,0))),0)) | S14: =IF(Q14="","",Q14-R14) | Y14: =IF(OR(D14="",B14="",C14=""),"",IF(N(C14)<=N(B14),"Check dates",IF(T14="Cancelled","",IF(COUNTIFS($D$5:$D$1004,D14,$B$5:$B$1004,"<"&C14,$C$5:$C$1004,">"&B14,$T$5:$T$1004,"<>Cancelled")>1,"Double-booked","")))) | Z14: =IF(AND(AA14=1,ISNUMBER(C14)),C14+ROW()/100000,"") | AA14: =IF(AND(D14<>"",ISNUMBER(B14),ISNUMBER(C14),N(H14)>0,T14<>"Cancelled",J14<>""),1,0) -> 0 | AB14: =IF(AA14=1,J14/H14,0) -> 0 | AC14: =IF(AA14=1,Q14/H14,0) -> 0 | AD14: =IF(AA14=1,R14/H14,0) -> 0 | AE14: =IF(AA14=1,O14/H14,0) -> 0 | AF14: =IF(AA14=1,K14/H14,0) -> 0 | AG14: =IF(AA14=1,D14&"|"&TEXT(B14,"0"),"") | AH14: =IF(AA14=1,H14,0) -> 0
A15: =IF(B15="","","B-"&TEXT(ROW()-4,"0000")) | H15: =IF(AND(ISNUMBER(B15),ISNUMBER(C15)),MAX(0,C15-B15),"") | J15: =IF(OR(D15="",N(H15)=0),"",IFERROR(IF(I15<>"",H15*I15,ROUND(((H15-(INT((WEEKDAY(B15-6)+H15-1)/7)+INT((WEEKDAY(B15-7)+H15-1)/7)))*INDEX(Properties!$E$5:$E$24,MATCH(D15,Properties!$A$5:$A$24,0))+(INT((WEEKDAY(B15-6)+H15-1)/7)+INT((WEEKDAY(B15-7)+H15-1)/7))*INDEX(Properties!$F$5:$F$24,MATCH(D15,Properties!$A$5:$A$24,0)))*(1-IF(H15>=28,Settings!$B$10,IF(H15>=7,Settings!$B$9,0))),2)),0)) | K15: =IF(J15="","",IFERROR(N(INDEX(Properties!$G$5:$G$24,MATCH(D15,Properties!$A$5:$A$24,0))),0)) | L15: =IF(J15="","",IFERROR(MAX(0,N(G15)-INDEX(Properties!$I$5:$I$24,MATCH(D15,Properties!$A$5:$A$24,0)))*N(INDEX(Properties!$J$5:$J$24,MATCH(D15,Properties!$A$5:$A$24,0)))*H15,0)) | N15: =IF(J15="","",J15+K15+L15+N(M15)) | O15: =IF(N15="","",IF(P15<>"",N15-P15,ROUND(N15*IFERROR(INDEX(Settings!$E$5:$E$12,MATCH(F15,Settings!$D$5:$D$12,0)),0),2))) | Q15: =IF(N15="","",IF(P15<>"",P15,N15-O15)) | R15: =IF(J15="","",IFERROR(N(INDEX(Properties!$H$5:$H$24,MATCH(D15,Properties!$A$5:$A$24,0))),0)) | S15: =IF(Q15="","",Q15-R15) | Y15: =IF(OR(D15="",B15="",C15=""),"",IF(N(C15)<=N(B15),"Check dates",IF(T15="Cancelled","",IF(COUNTIFS($D$5:$D$1004,D15,$B$5:$B$1004,"<"&C15,$C$5:$C$1004,">"&B15,$T$5:$T$1004,"<>Cancelled")>1,"Double-booked","")))) | Z15: =IF(AND(AA15=1,ISNUMBER(C15)),C15+ROW()/100000,"") | AA15: =IF(AND(D15<>"",ISNUMBER(B15),ISNUMBER(C15),N(H15)>0,T15<>"Cancelled",J15<>""),1,0) -> 0 | AB15: =IF(AA15=1,J15/H15,0) -> 0 | AC15: =IF(AA15=1,Q15/H15,0) -> 0 | AD15: =IF(AA15=1,R15/H15,0) -> 0 | AE15: =IF(AA15=1,O15/H15,0) -> 0 | AF15: =IF(AA15=1,K15/H15,0) -> 0 | AG15: =IF(AA15=1,D15&"|"&TEXT(B15,"0"),"") | AH15: =IF(AA15=1,H15,0) -> 0
A16: =IF(B16="","","B-"&TEXT(ROW()-4,"0000")) | H16: =IF(AND(ISNUMBER(B16),ISNUMBER(C16)),MAX(0,C16-B16),"") | J16: =IF(OR(D16="",N(H16)=0),"",IFERROR(IF(I16<>"",H16*I16,ROUND(((H16-(INT((WEEKDAY(B16-6)+H16-1)/7)+INT((WEEKDAY(B16-7)+H16-1)/7)))*INDEX(Properties!$E$5:$E$24,MATCH(D16,Properties!$A$5:$A$24,0))+(INT((WEEKDAY(B16-6)+H16-1)/7)+INT((WEEKDAY(B16-7)+H16-1)/7))*INDEX(Properties!$F$5:$F$24,MATCH(D16,Properties!$A$5:$A$24,0)))*(1-IF(H16>=28,Settings!$B$10,IF(H16>=7,Settings!$B$9,0))),2)),0)) | K16: =IF(J16="","",IFERROR(N(INDEX(Properties!$G$5:$G$24,MATCH(D16,Properties!$A$5:$A$24,0))),0)) | L16: =IF(J16="","",IFERROR(MAX(0,N(G16)-INDEX(Properties!$I$5:$I$24,MATCH(D16,Properties!$A$5:$A$24,0)))*N(INDEX(Properties!$J$5:$J$24,MATCH(D16,Properties!$A$5:$A$24,0)))*H16,0)) | N16: =IF(J16="","",J16+K16+L16+N(M16)) | O16: =IF(N16="","",IF(P16<>"",N16-P16,ROUND(N16*IFERROR(INDEX(Settings!$E$5:$E$12,MATCH(F16,Settings!$D$5:$D$12,0)),0),2))) | Q16: =IF(N16="","",IF(P16<>"",P16,N16-O16)) | R16: =IF(J16="","",IFERROR(N(INDEX(Properties!$H$5:$H$24,MATCH(D16,Properties!$A$5:$A$24,0))),0)) | S16: =IF(Q16="","",Q16-R16) | Y16: =IF(OR(D16="",B16="",C16=""),"",IF(N(C16)<=N(B16),"Check dates",IF(T16="Cancelled","",IF(COUNTIFS($D$5:$D$1004,D16,$B$5:$B$1004,"<"&C16,$C$5:$C$1004,">"&B16,$T$5:$T$1004,"<>Cancelled")>1,"Double-booked","")))) | Z16: =IF(AND(AA16=1,ISNUMBER(C16)),C16+ROW()/100000,"") | AA16: =IF(AND(D16<>"",ISNUMBER(B16),ISNUMBER(C16),N(H16)>0,T16<>"Cancelled",J16<>""),1,0) -> 0 | AB16: =IF(AA16=1,J16/H16,0) -> 0 | AC16: =IF(AA16=1,Q16/H16,0) -> 0 | AD16: =IF(AA16=1,R16/H16,0) -> 0 | AE16: =IF(AA16=1,O16/H16,0) -> 0 | AF16: =IF(AA16=1,K16/H16,0) -> 0 | AG16: =IF(AA16=1,D16&"|"&TEXT(B16,"0"),"") | AH16: =IF(AA16=1,H16,0) -> 0
A17: =IF(B17="","","B-"&TEXT(ROW()-4,"0000")) | H17: =IF(AND(ISNUMBER(B17),ISNUMBER(C17)),MAX(0,C17-B17),"") | J17: =IF(OR(D17="",N(H17)=0),"",IFERROR(IF(I17<>"",H17*I17,ROUND(((H17-(INT((WEEKDAY(B17-6)+H17-1)/7)+INT((WEEKDAY(B17-7)+H17-1)/7)))*INDEX(Properties!$E$5:$E$24,MATCH(D17,Properties!$A$5:$A$24,0))+(INT((WEEKDAY(B17-6)+H17-1)/7)+INT((WEEKDAY(B17-7)+H17-1)/7))*INDEX(Properties!$F$5:$F$24,MATCH(D17,Properties!$A$5:$A$24,0)))*(1-IF(H17>=28,Settings!$B$10,IF(H17>=7,Settings!$B$9,0))),2)),0)) | K17: =IF(J17="","",IFERROR(N(INDEX(Properties!$G$5:$G$24,MATCH(D17,Properties!$A$5:$A$24,0))),0)) | L17: =IF(J17="","",IFERROR(MAX(0,N(G17)-INDEX(Properties!$I$5:$I$24,MATCH(D17,Properties!$A$5:$A$24,0)))*N(INDEX(Properties!$J$5:$J$24,MATCH(D17,Properties!$A$5:$A$24,0)))*H17,0)) | N17: =IF(J17="","",J17+K17+L17+N(M17)) | O17: =IF(N17="","",IF(P17<>"",N17-P17,ROUND(N17*IFERROR(INDEX(Settings!$E$5:$E$12,MATCH(F17,Settings!$D$5:$D$12,0)),0),2))) | Q17: =IF(N17="","",IF(P17<>"",P17,N17-O17)) | R17: =IF(J17="","",IFERROR(N(INDEX(Properties!$H$5:$H$24,MATCH(D17,Properties!$A$5:$A$24,0))),0)) | S17: =IF(Q17="","",Q17-R17) | Y17: =IF(OR(D17="",B17="",C17=""),"",IF(N(C17)<=N(B17),"Check dates",IF(T17="Cancelled","",IF(COUNTIFS($D$5:$D$1004,D17,$B$5:$B$1004,"<"&C17,$C$5:$C$1004,">"&B17,$T$5:$T$1004,"<>Cancelled")>1,"Double-booked","")))) | Z17: =IF(AND(AA17=1,ISNUMBER(C17)),C17+ROW()/100000,"") | AA17: =IF(AND(D17<>"",ISNUMBER(B17),ISNUMBER(C17),N(H17)>0,T17<>"Cancelled",J17<>""),1,0) -> 0 | AB17: =IF(AA17=1,J17/H17,0) -> 0 | AC17: =IF(AA17=1,Q17/H17,0) -> 0 | AD17: =IF(AA17=1,R17/H17,0) -> 0 | AE17: =IF(AA17=1,O17/H17,0) -> 0 | AF17: =IF(AA17=1,K17/H17,0) -> 0 | AG17: =IF(AA17=1,D17&"|"&TEXT(B17,"0"),"") | AH17: =IF(AA17=1,H17,0) -> 0
A18: =IF(B18="","","B-"&TEXT(ROW()-4,"0000")) | H18: =IF(AND(ISNUMBER(B18),ISNUMBER(C18)),MAX(0,C18-B18),"") | J18: =IF(OR(D18="",N(H18)=0),"",IFERROR(IF(I18<>"",H18*I18,ROUND(((H18-(INT((WEEKDAY(B18-6)+H18-1)/7)+INT((WEEKDAY(B18-7)+H18-1)/7)))*INDEX(Properties!$E$5:$E$24,MATCH(D18,Properties!$A$5:$A$24,0))+(INT((WEEKDAY(B18-6)+H18-1)/7)+INT((WEEKDAY(B18-7)+H18-1)/7))*INDEX(Properties!$F$5:$F$24,MATCH(D18,Properties!$A$5:$A$24,0)))*(1-IF(H18>=28,Settings!$B$10,IF(H18>=7,Settings!$B$9,0))),2)),0)) | K18: =IF(J18="","",IFERROR(N(INDEX(Properties!$G$5:$G$24,MATCH(D18,Properties!$A$5:$A$24,0))),0)) | L18: =IF(J18="","",IFERROR(MAX(0,N(G18)-INDEX(Properties!$I$5:$I$24,MATCH(D18,Properties!$A$5:$A$24,0)))*N(INDEX(Properties!$J$5:$J$24,MATCH(D18,Properties!$A$5:$A$24,0)))*H18,0)) | N18: =IF(J18="","",J18+K18+L18+N(M18)) | O18: =IF(N18="","",IF(P18<>"",N18-P18,ROUND(N18*IFERROR(INDEX(Settings!$E$5:$E$12,MATCH(F18,Settings!$D$5:$D$12,0)),0),2))) | Q18: =IF(N18="","",IF(P18<>"",P18,N18-O18)) | R18: =IF(J18="","",IFERROR(N(INDEX(Properties!$H$5:$H$24,MATCH(D18,Properties!$A$5:$A$24,0))),0)) | S18: =IF(Q18="","",Q18-R18) | Y18: =IF(OR(D18="",B18="",C18=""),"",IF(N(C18)<=N(B18),"Check dates",IF(T18="Cancelled","",IF(COUNTIFS($D$5:$D$1004,D18,$B$5:$B$1004,"<"&C18,$C$5:$C$1004,">"&B18,$T$5:$T$1004,"<>Cancelled")>1,"Double-booked","")))) | Z18: =IF(AND(AA18=1,ISNUMBER(C18)),C18+ROW()/100000,"") | AA18: =IF(AND(D18<>"",ISNUMBER(B18),ISNUMBER(C18),N(H18)>0,T18<>"Cancelled",J18<>""),1,0) -> 0 | AB18: =IF(AA18=1,J18/H18,0) -> 0 | AC18: =IF(AA18=1,Q18/H18,0) -> 0 | AD18: =IF(AA18=1,R18/H18,0) -> 0 | AE18: =IF(AA18=1,O18/H18,0) -> 0 | AF18: =IF(AA18=1,K18/H18,0) -> 0 | AG18: =IF(AA18=1,D18&"|"&TEXT(B18,"0"),"") | AH18: =IF(AA18=1,H18,0) -> 0
... A1004: =IF(B1004="","","B-"&TEXT(ROW()-4,"0000")) | H1004: =IF(AND(ISNUMBER(B1004),ISNUMBER(C1004)),MAX(0,C1004-B1004),"") | J1004: =IF(OR(D1004="",N(H1004)=0),"",IFERROR(IF(I1004<>"",H1004*I1004,ROUND(((H1004-(INT((WEEKDAY(B1004-6)+H1004-1)/7)+INT((WEEKDAY(B1004-7)+H1004-1)/7)))*INDEX(Properties!$E$5:$E$24,MATCH(D1004,Properties!$A$5:$A$24,0))+(INT((WEEKDAY(B1004-6)+H1004-1)/7)+INT((WEEKDAY(B1004-7)+H1004-1)/7))*INDEX(Properties!$F$5:$F$24,MATCH(D1004,Properties!$A$5:$A$24,0)))*(1-IF(H1004>=28,Settings!$B$10,IF(H1004>=7,Settings!$B$9,0))),2)),0)) | K1004: =IF(J1004="","",IFERROR(N(INDEX(Properties!$G$5:$G$24,MATCH(D1004,Properties!$A$5:$A$24,0))),0)) | L1004: =IF(J1004="","",IFERROR(MAX(0,N(G1004)-INDEX(Properties!$I$5:$I$24,MATCH(D1004,Properties!$A$5:$A$24,0)))*N(INDEX(Properties!$J$5:$J$24,MATCH(D1004,Properties!$A$5:$A$24,0)))*H1004,0)) | N1004: =IF(J1004="","",J1004+K1004+L1004+N(M1004)) | O1004: =IF(N1004="","",IF(P1004<>"",N1004-P1004,ROUND(N1004*IFERROR(INDEX(Settings!$E$5:$E$12,MATCH(F1004,Settings!$D$5:$D$12,0)),0),2))) | Q1004: =IF(N1004="","",IF(P1004<>"",P1004,N1004-O1004)) | R1004: =IF(J1004="","",IFERROR(N(INDEX(Properties!$H$5:$H$24,MATCH(D1004,Properties!$A$5:$A$24,0))),0)) | S1004: =IF(Q1004="","",Q1004-R1004) | Y1004: =IF(OR(D1004="",B1004="",C1004=""),"",IF(N(C1004)<=N(B1004),"Check dates",IF(T1004="Cancelled","",IF(COUNTIFS($D$5:$D$1004,D1004,$B$5:$B$1004,"<"&C1004,$C$5:$C$1004,">"&B1004,$T$5:$T$1004,"<>Cancelled")>1,"Double-booked","")))) | Z1004: =IF(AND(AA1004=1,ISNUMBER(C1004)),C1004+ROW()/100000,"") | AA1004: =IF(AND(D1004<>"",ISNUMBER(B1004),ISNUMBER(C1004),N(H1004)>0,T1004<>"Cancelled",J1004<>""),1,0) -> 0 | AB1004: =IF(AA1004=1,J1004/H1004,0) -> 0 | AC1004: =IF(AA1004=1,Q1004/H1004,0) -> 0 | AD1004: =IF(AA1004=1,R1004/H1004,0) -> 0 | AE1004: =IF(AA1004=1,O1004/H1004,0) -> 0 | AF1004: =IF(AA1004=1,K1004/H1004,0) -> 0 | AG1004: =IF(AA1004=1,D1004&"|"&TEXT(B1004,"0"),"") | AH1004: =IF(AA1004=1,H1004,0) -> 0

Sheet Turnovers
A1: Turnovers
A2: Your cleaning schedule: the next 40 check-outs, sorted by date. Assign cleaners and tick Done in Bookings.
A4: Show from | B4: =TODAY() -> 46315 | D4: ="Check-out "&Settings!$B$11&" · Check-in "&Settings!$B$12 -> Check-out 11:00 AM · Check-in 4:00 PM
A5: Leave 'Show from' as =TODAY(), or type a date to look ahead or back.
A6: Turnover date | B6: Day | C6: Property | D6: Checking out | E6: Next check-in | F6: Next guest | G6: Guests | H6: Gap (days) | I6: Alert | J6: Cleaner | K6: Done? | L6: Booking notes | M6: idx
A7: =IF($M7="","",INDEX(Bookings!$C$5:$C$1004,$M7)) | B7: =IF(A7="","",TEXT(A7,"ddd")) | C7: =IF($M7="","",INDEX(Bookings!$D$5:$D$1004,$M7)) | D7: =IF($M7="","",INDEX(Bookings!$E$5:$E$1004,$M7)&"") | E7: =IF($M7="","",IF(_xlfn.MINIFS(Bookings!$B$5:$B$1004,Bookings!$D$5:$D$1004,C7,Bookings!$B$5:$B$1004,">="&A7,Bookings!$AA$5:$AA$1004,1)=0,"",_xlfn.MINIFS(Bookings!$B$5:$B$1004,Bookings!$D$5:$D$1004,C7,Bookings!$B$5:$B$1004,">="&A7,Bookings!$AA$5:$AA$1004,1))) | F7: =IF(E7="","",IFERROR(INDEX(Bookings!$E$5:$E$1004,MATCH(C7&"|"&TEXT(E7,"0"),Bookings!$AG$5:$AG$1004,0))&"","")) | G7: =IF(E7="","",IFERROR(INDEX(Bookings!$G$5:$G$1004,MATCH(C7&"|"&TEXT(E7,"0"),Bookings!$AG$5:$AG$1004,0)),"")) | H7: =IF(OR(A7="",E7=""),"",E7-A7) | I7: =IF(A7="","",IF(E7="","No next booking",IF(H7=0,"SAME-DAY turnover",IF(H7=1,"Next-day check-in","")))) | J7: =IF($M7="","",IF(INDEX(Bookings!$V$5:$V$1004,$M7)="","Unassigned",INDEX(Bookings!$V$5:$V$1004,$M7))) | K7: =IF($M7="","",IF(INDEX(Bookings!$W$5:$W$1004,$M7)="Yes","Yes","")) | L7: =IF($M7="","",INDEX(Bookings!$X$5:$X$1004,$M7)&"") | M7: =IFERROR(MATCH(SMALL(Bookings!$Z$5:$Z$1004,COUNTIF(Bookings!$Z$5:$Z$1004,"<"&$B$4)+1),Bookings!$Z$5:$Z$1004,0),"")
A8: =IF($M8="","",INDEX(Bookings!$C$5:$C$1004,$M8)) | B8: =IF(A8="","",TEXT(A8,"ddd")) | C8: =IF($M8="","",INDEX(Bookings!$D$5:$D$1004,$M8)) | D8: =IF($M8="","",INDEX(Bookings!$E$5:$E$1004,$M8)&"") | E8: =IF($M8="","",IF(_xlfn.MINIFS(Bookings!$B$5:$B$1004,Bookings!$D$5:$D$1004,C8,Bookings!$B$5:$B$1004,">="&A8,Bookings!$AA$5:$AA$1004,1)=0,"",_xlfn.MINIFS(Bookings!$B$5:$B$1004,Bookings!$D$5:$D$1004,C8,Bookings!$B$5:$B$1004,">="&A8,Bookings!$AA$5:$AA$1004,1))) | F8: =IF(E8="","",IFERROR(INDEX(Bookings!$E$5:$E$1004,MATCH(C8&"|"&TEXT(E8,"0"),Bookings!$AG$5:$AG$1004,0))&"","")) | G8: =IF(E8="","",IFERROR(INDEX(Bookings!$G$5:$G$1004,MATCH(C8&"|"&TEXT(E8,"0"),Bookings!$AG$5:$AG$1004,0)),"")) | H8: =IF(OR(A8="",E8=""),"",E8-A8) | I8: =IF(A8="","",IF(E8="","No next booking",IF(H8=0,"SAME-DAY turnover",IF(H8=1,"Next-day check-in","")))) | J8: =IF($M8="","",IF(INDEX(Bookings!$V$5:$V$1004,$M8)="","Unassigned",INDEX(Bookings!$V$5:$V$1004,$M8))) | K8: =IF($M8="","",IF(INDEX(Bookings!$W$5:$W$1004,$M8)="Yes","Yes","")) | L8: =IF($M8="","",INDEX(Bookings!$X$5:$X$1004,$M8)&"") | M8: =IFERROR(MATCH(SMALL(Bookings!$Z$5:$Z$1004,COUNTIF(Bookings!$Z$5:$Z$1004,"<"&$B$4)+2),Bookings!$Z$5:$Z$1004,0),"")
A9: =IF($M9="","",INDEX(Bookings!$C$5:$C$1004,$M9)) | B9: =IF(A9="","",TEXT(A9,"ddd")) | C9: =IF($M9="","",INDEX(Bookings!$D$5:$D$1004,$M9)) | D9: =IF($M9="","",INDEX(Bookings!$E$5:$E$1004,$M9)&"") | E9: =IF($M9="","",IF(_xlfn.MINIFS(Bookings!$B$5:$B$1004,Bookings!$D$5:$D$1004,C9,Bookings!$B$5:$B$1004,">="&A9,Bookings!$AA$5:$AA$1004,1)=0,"",_xlfn.MINIFS(Bookings!$B$5:$B$1004,Bookings!$D$5:$D$1004,C9,Bookings!$B$5:$B$1004,">="&A9,Bookings!$AA$5:$AA$1004,1))) | F9: =IF(E9="","",IFERROR(INDEX(Bookings!$E$5:$E$1004,MATCH(C9&"|"&TEXT(E9,"0"),Bookings!$AG$5:$AG$1004,0))&"","")) | G9: =IF(E9="","",IFERROR(INDEX(Bookings!$G$5:$G$1004,MATCH(C9&"|"&TEXT(E9,"0"),Bookings!$AG$5:$AG$1004,0)),"")) | H9: =IF(OR(A9="",E9=""),"",E9-A9) | I9: =IF(A9="","",IF(E9="","No next booking",IF(H9=0,"SAME-DAY turnover",IF(H9=1,"Next-day check-in","")))) | J9: =IF($M9="","",IF(INDEX(Bookings!$V$5:$V$1004,$M9)="","Unassigned",INDEX(Bookings!$V$5:$V$1004,$M9))) | K9: =IF($M9="","",IF(INDEX(Bookings!$W$5:$W$1004,$M9)="Yes","Yes","")) | L9: =IF($M9="","",INDEX(Bookings!$X$5:$X$1004,$M9)&"") | M9: =IFERROR(MATCH(SMALL(Bookings!$Z$5:$Z$1004,COUNTIF(Bookings!$Z$5:$Z$1004,"<"&$B$4)+3),Bookings!$Z$5:$Z$1004,0),"")
A10: =IF($M10="","",INDEX(Bookings!$C$5:$C$1004,$M10)) | B10: =IF(A10="","",TEXT(A10,"ddd")) | C10: =IF($M10="","",INDEX(Bookings!$D$5:$D$1004,$M10)) | D10: =IF($M10="","",INDEX(Bookings!$E$5:$E$1004,$M10)&"") | E10: =IF($M10="","",IF(_xlfn.MINIFS(Bookings!$B$5:$B$1004,Bookings!$D$5:$D$1004,C10,Bookings!$B$5:$B$1004,">="&A10,Bookings!$AA$5:$AA$1004,1)=0,"",_xlfn.MINIFS(Bookings!$B$5:$B$1004,Bookings!$D$5:$D$1004,C10,Bookings!$B$5:$B$1004,">="&A10,Bookings!$AA$5:$AA$1004,1))) | F10: =IF(E10="","",IFERROR(INDEX(Bookings!$E$5:$E$1004,MATCH(C10&"|"&TEXT(E10,"0"),Bookings!$AG$5:$AG$1004,0))&"","")) | G10: =IF(E10="","",IFERROR(INDEX(Bookings!$G$5:$G$1004,MATCH(C10&"|"&TEXT(E10,"0"),Bookings!$AG$5:$AG$1004,0)),"")) | H10: =IF(OR(A10="",E10=""),"",E10-A10) | I10: =IF(A10="","",IF(E10="","No next booking",IF(H10=0,"SAME-DAY turnover",IF(H10=1,"Next-day check-in","")))) | J10: =IF($M10="","",IF(INDEX(Bookings!$V$5:$V$1004,$M10)="","Unassigned",INDEX(Bookings!$V$5:$V$1004,$M10))) | K10: =IF($M10="","",IF(INDEX(Bookings!$W$5:$W$1004,$M10)="Yes","Yes","")) | L10: =IF($M10="","",INDEX(Bookings!$X$5:$X$1004,$M10)&"") | M10: =IFERROR(MATCH(SMALL(Bookings!$Z$5:$Z$1004,COUNTIF(Bookings!$Z$5:$Z$1004,"<"&$B$4)+4),Bookings!$Z$5:$Z$1004,0),"")
A11: =IF($M11="","",INDEX(Bookings!$C$5:$C$1004,$M11)) | B11: =IF(A11="","",TEXT(A11,"ddd")) | C11: =IF($M11="","",INDEX(Bookings!$D$5:$D$1004,$M11)) | D11: =IF($M11="","",INDEX(Bookings!$E$5:$E$1004,$M11)&"") | E11: =IF($M11="","",IF(_xlfn.MINIFS(Bookings!$B$5:$B$1004,Bookings!$D$5:$D$1004,C11,Bookings!$B$5:$B$1004,">="&A11,Bookings!$AA$5:$AA$1004,1)=0,"",_xlfn.MINIFS(Bookings!$B$5:$B$1004,Bookings!$D$5:$D$1004,C11,Bookings!$B$5:$B$1004,">="&A11,Bookings!$AA$5:$AA$1004,1))) | F11: =IF(E11="","",IFERROR(INDEX(Bookings!$E$5:$E$1004,MATCH(C11&"|"&TEXT(E11,"0"),Bookings!$AG$5:$AG$1004,0))&"","")) | G11: =IF(E11="","",IFERROR(INDEX(Bookings!$G$5:$G$1004,MATCH(C11&"|"&TEXT(E11,"0"),Bookings!$AG$5:$AG$1004,0)),"")) | H11: =IF(OR(A11="",E11=""),"",E11-A11) | I11: =IF(A11="","",IF(E11="","No next booking",IF(H11=0,"SAME-DAY turnover",IF(H11=1,"Next-day check-in","")))) | J11: =IF($M11="","",IF(INDEX(Bookings!$V$5:$V$1004,$M11)="","Unassigned",INDEX(Bookings!$V$5:$V$1004,$M11))) | K11: =IF($M11="","",IF(INDEX(Bookings!$W$5:$W$1004,$M11)="Yes","Yes","")) | L11: =IF($M11="","",INDEX(Bookings!$X$5:$X$1004,$M11)&"") | M11: =IFERROR(MATCH(SMALL(Bookings!$Z$5:$Z$1004,COUNTIF(Bookings!$Z$5:$Z$1004,"<"&$B$4)+5),Bookings!$Z$5:$Z$1004,0),"")
A12: =IF($M12="","",INDEX(Bookings!$C$5:$C$1004,$M12)) | B12: =IF(A12="","",TEXT(A12,"ddd")) | C12: =IF($M12="","",INDEX(Bookings!$D$5:$D$1004,$M12)) | D12: =IF($M12="","",INDEX(Bookings!$E$5:$E$1004,$M12)&"") | E12: =IF($M12="","",IF(_xlfn.MINIFS(Bookings!$B$5:$B$1004,Bookings!$D$5:$D$1004,C12,Bookings!$B$5:$B$1004,">="&A12,Bookings!$AA$5:$AA$1004,1)=0,"",_xlfn.MINIFS(Bookings!$B$5:$B$1004,Bookings!$D$5:$D$1004,C12,Bookings!$B$5:$B$1004,">="&A12,Bookings!$AA$5:$AA$1004,1))) | F12: =IF(E12="","",IFERROR(INDEX(Bookings!$E$5:$E$1004,MATCH(C12&"|"&TEXT(E12,"0"),Bookings!$AG$5:$AG$1004,0))&"","")) | G12: =IF(E12="","",IFERROR(INDEX(Bookings!$G$5:$G$1004,MATCH(C12&"|"&TEXT(E12,"0"),Bookings!$AG$5:$AG$1004,0)),"")) | H12: =IF(OR(A12="",E12=""),"",E12-A12) | I12: =IF(A12="","",IF(E12="","No next booking",IF(H12=0,"SAME-DAY turnover",IF(H12=1,"Next-day check-in","")))) | J12: =IF($M12="","",IF(INDEX(Bookings!$V$5:$V$1004,$M12)="","Unassigned",INDEX(Bookings!$V$5:$V$1004,$M12))) | K12: =IF($M12="","",IF(INDEX(Bookings!$W$5:$W$1004,$M12)="Yes","Yes","")) | L12: =IF($M12="","",INDEX(Bookings!$X$5:$X$1004,$M12)&"") | M12: =IFERROR(MATCH(SMALL(Bookings!$Z$5:$Z$1004,COUNTIF(Bookings!$Z$5:$Z$1004,"<"&$B$4)+6),Bookings!$Z$5:$Z$1004,0),"")
A13: =IF($M13="","",INDEX(Bookings!$C$5:$C$1004,$M13)) | B13: =IF(A13="","",TEXT(A13,"ddd")) | C13: =IF($M13="","",INDEX(Bookings!$D$5:$D$1004,$M13)) | D13: =IF($M13="","",INDEX(Bookings!$E$5:$E$1004,$M13)&"") | E13: =IF($M13="","",IF(_xlfn.MINIFS(Bookings!$B$5:$B$1004,Bookings!$D$5:$D$1004,C13,Bookings!$B$5:$B$1004,">="&A13,Bookings!$AA$5:$AA$1004,1)=0,"",_xlfn.MINIFS(Bookings!$B$5:$B$1004,Bookings!$D$5:$D$1004,C13,Bookings!$B$5:$B$1004,">="&A13,Bookings!$AA$5:$AA$1004,1))) | F13: =IF(E13="","",IFERROR(INDEX(Bookings!$E$5:$E$1004,MATCH(C13&"|"&TEXT(E13,"0"),Bookings!$AG$5:$AG$1004,0))&"","")) | G13: =IF(E13="","",IFERROR(INDEX(Bookings!$G$5:$G$1004,MATCH(C13&"|"&TEXT(E13,"0"),Bookings!$AG$5:$AG$1004,0)),"")) | H13: =IF(OR(A13="",E13=""),"",E13-A13) | I13: =IF(A13="","",IF(E13="","No next booking",IF(H13=0,"SAME-DAY turnover",IF(H13=1,"Next-day check-in","")))) | J13: =IF($M13="","",IF(INDEX(Bookings!$V$5:$V$1004,$M13)="","Unassigned",INDEX(Bookings!$V$5:$V$1004,$M13))) | K13: =IF($M13="","",IF(INDEX(Bookings!$W$5:$W$1004,$M13)="Yes","Yes","")) | L13: =IF($M13="","",INDEX(Bookings!$X$5:$X$1004,$M13)&"") | M13: =IFERROR(MATCH(SMALL(Bookings!$Z$5:$Z$1004,COUNTIF(Bookings!$Z$5:$Z$1004,"<"&$B$4)+7),Bookings!$Z$5:$Z$1004,0),"")
A14: =IF($M14="","",INDEX(Bookings!$C$5:$C$1004,$M14)) | B14: =IF(A14="","",TEXT(A14,"ddd")) | C14: =IF($M14="","",INDEX(Bookings!$D$5:$D$1004,$M14)) | D14: =IF($M14="","",INDEX(Bookings!$E$5:$E$1004,$M14)&"") | E14: =IF($M14="","",IF(_xlfn.MINIFS(Bookings!$B$5:$B$1004,Bookings!$D$5:$D$1004,C14,Bookings!$B$5:$B$1004,">="&A14,Bookings!$AA$5:$AA$1004,1)=0,"",_xlfn.MINIFS(Bookings!$B$5:$B$1004,Bookings!$D$5:$D$1004,C14,Bookings!$B$5:$B$1004,">="&A14,Bookings!$AA$5:$AA$1004,1))) | F14: =IF(E14="","",IFERROR(INDEX(Bookings!$E$5:$E$1004,MATCH(C14&"|"&TEXT(E14,"0"),Bookings!$AG$5:$AG$1004,0))&"","")) | G14: =IF(E14="","",IFERROR(INDEX(Bookings!$G$5:$G$1004,MATCH(C14&"|"&TEXT(E14,"0"),Bookings!$AG$5:$AG$1004,0)),"")) | H14: =IF(OR(A14="",E14=""),"",E14-A14) | I14: =IF(A14="","",IF(E14="","No next booking",IF(H14=0,"SAME-DAY turnover",IF(H14=1,"Next-day check-in","")))) | J14: =IF($M14="","",IF(INDEX(Bookings!$V$5:$V$1004,$M14)="","Unassigned",INDEX(Bookings!$V$5:$V$1004,$M14))) | K14: =IF($M14="","",IF(INDEX(Bookings!$W$5:$W$1004,$M14)="Yes","Yes","")) | L14: =IF($M14="","",INDEX(Bookings!$X$5:$X$1004,$M14)&"") | M14: =IFERROR(MATCH(SMALL(Bookings!$Z$5:$Z$1004,COUNTIF(Bookings!$Z$5:$Z$1004,"<"&$B$4)+8),Bookings!$Z$5:$Z$1004,0),"")
A15: =IF($M15="","",INDEX(Bookings!$C$5:$C$1004,$M15)) | B15: =IF(A15="","",TEXT(A15,"ddd")) | C15: =IF($M15="","",INDEX(Bookings!$D$5:$D$1004,$M15)) | D15: =IF($M15="","",INDEX(Bookings!$E$5:$E$1004,$M15)&"") | E15: =IF($M15="","",IF(_xlfn.MINIFS(Bookings!$B$5:$B$1004,Bookings!$D$5:$D$1004,C15,Bookings!$B$5:$B$1004,">="&A15,Bookings!$AA$5:$AA$1004,1)=0,"",_xlfn.MINIFS(Bookings!$B$5:$B$1004,Bookings!$D$5:$D$1004,C15,Bookings!$B$5:$B$1004,">="&A15,Bookings!$AA$5:$AA$1004,1))) | F15: =IF(E15="","",IFERROR(INDEX(Bookings!$E$5:$E$1004,MATCH(C15&"|"&TEXT(E15,"0"),Bookings!$AG$5:$AG$1004,0))&"","")) | G15: =IF(E15="","",IFERROR(INDEX(Bookings!$G$5:$G$1004,MATCH(C15&"|"&TEXT(E15,"0"),Bookings!$AG$5:$AG$1004,0)),"")) | H15: =IF(OR(A15="",E15=""),"",E15-A15) | I15: =IF(A15="","",IF(E15="","No next booking",IF(H15=0,"SAME-DAY turnover",IF(H15=1,"Next-day check-in","")))) | J15: =IF($M15="","",IF(INDEX(Bookings!$V$5:$V$1004,$M15)="","Unassigned",INDEX(Bookings!$V$5:$V$1004,$M15))) | K15: =IF($M15="","",IF(INDEX(Bookings!$W$5:$W$1004,$M15)="Yes","Yes","")) | L15: =IF($M15="","",INDEX(Bookings!$X$5:$X$1004,$M15)&"") | M15: =IFERROR(MATCH(SMALL(Bookings!$Z$5:$Z$1004,COUNTIF(Bookings!$Z$5:$Z$1004,"<"&$B$4)+9),Bookings!$Z$5:$Z$1004,0),"")
A16: =IF($M16="","",INDEX(Bookings!$C$5:$C$1004,$M16)) | B16: =IF(A16="","",TEXT(A16,"ddd")) | C16: =IF($M16="","",INDEX(Bookings!$D$5:$D$1004,$M16)) | D16: =IF($M16="","",INDEX(Bookings!$E$5:$E$1004,$M16)&"") | E16: =IF($M16="","",IF(_xlfn.MINIFS(Bookings!$B$5:$B$1004,Bookings!$D$5:$D$1004,C16,Bookings!$B$5:$B$1004,">="&A16,Bookings!$AA$5:$AA$1004,1)=0,"",_xlfn.MINIFS(Bookings!$B$5:$B$1004,Bookings!$D$5:$D$1004,C16,Bookings!$B$5:$B$1004,">="&A16,Bookings!$AA$5:$AA$1004,1))) | F16: =IF(E16="","",IFERROR(INDEX(Bookings!$E$5:$E$1004,MATCH(C16&"|"&TEXT(E16,"0"),Bookings!$AG$5:$AG$1004,0))&"","")) | G16: =IF(E16="","",IFERROR(INDEX(Bookings!$G$5:$G$1004,MATCH(C16&"|"&TEXT(E16,"0"),Bookings!$AG$5:$AG$1004,0)),"")) | H16: =IF(OR(A16="",E16=""),"",E16-A16) | I16: =IF(A16="","",IF(E16="","No next booking",IF(H16=0,"SAME-DAY turnover",IF(H16=1,"Next-day check-in","")))) | J16: =IF($M16="","",IF(INDEX(Bookings!$V$5:$V$1004,$M16)="","Unassigned",INDEX(Bookings!$V$5:$V$1004,$M16))) | K16: =IF($M16="","",IF(INDEX(Bookings!$W$5:$W$1004,$M16)="Yes","Yes","")) | L16: =IF($M16="","",INDEX(Bookings!$X$5:$X$1004,$M16)&"") | M16: =IFERROR(MATCH(SMALL(Bookings!$Z$5:$Z$1004,COUNTIF(Bookings!$Z$5:$Z$1004,"<"&$B$4)+10),Bookings!$Z$5:$Z$1004,0),"")
A17: =IF($M17="","",INDEX(Bookings!$C$5:$C$1004,$M17)) | B17: =IF(A17="","",TEXT(A17,"ddd")) | C17: =IF($M17="","",INDEX(Bookings!$D$5:$D$1004,$M17)) | D17: =IF($M17="","",INDEX(Bookings!$E$5:$E$1004,$M17)&"") | E17: =IF($M17="","",IF(_xlfn.MINIFS(Bookings!$B$5:$B$1004,Bookings!$D$5:$D$1004,C17,Bookings!$B$5:$B$1004,">="&A17,Bookings!$AA$5:$AA$1004,1)=0,"",_xlfn.MINIFS(Bookings!$B$5:$B$1004,Bookings!$D$5:$D$1004,C17,Bookings!$B$5:$B$1004,">="&A17,Bookings!$AA$5:$AA$1004,1))) | F17: =IF(E17="","",IFERROR(INDEX(Bookings!$E$5:$E$1004,MATCH(C17&"|"&TEXT(E17,"0"),Bookings!$AG$5:$AG$1004,0))&"","")) | G17: =IF(E17="","",IFERROR(INDEX(Bookings!$G$5:$G$1004,MATCH(C17&"|"&TEXT(E17,"0"),Bookings!$AG$5:$AG$1004,0)),"")) | H17: =IF(OR(A17="",E17=""),"",E17-A17) | I17: =IF(A17="","",IF(E17="","No next booking",IF(H17=0,"SAME-DAY turnover",IF(H17=1,"Next-day check-in","")))) | J17: =IF($M17="","",IF(INDEX(Bookings!$V$5:$V$1004,$M17)="","Unassigned",INDEX(Bookings!$V$5:$V$1004,$M17))) | K17: =IF($M17="","",IF(INDEX(Bookings!$W$5:$W$1004,$M17)="Yes","Yes","")) | L17: =IF($M17="","",INDEX(Bookings!$X$5:$X$1004,$M17)&"") | M17: =IFERROR(MATCH(SMALL(Bookings!$Z$5:$Z$1004,COUNTIF(Bookings!$Z$5:$Z$1004,"<"&$B$4)+11),Bookings!$Z$5:$Z$1004,0),"")
A18: =IF($M18="","",INDEX(Bookings!$C$5:$C$1004,$M18)) | B18: =IF(A18="","",TEXT(A18,"ddd")) | C18: =IF($M18="","",INDEX(Bookings!$D$5:$D$1004,$M18)) | D18: =IF($M18="","",INDEX(Bookings!$E$5:$E$1004,$M18)&"") | E18: =IF($M18="","",IF(_xlfn.MINIFS(Bookings!$B$5:$B$1004,Bookings!$D$5:$D$1004,C18,Bookings!$B$5:$B$1004,">="&A18,Bookings!$AA$5:$AA$1004,1)=0,"",_xlfn.MINIFS(Bookings!$B$5:$B$1004,Bookings!$D$5:$D$1004,C18,Bookings!$B$5:$B$1004,">="&A18,Bookings!$AA$5:$AA$1004,1))) | F18: =IF(E18="","",IFERROR(INDEX(Bookings!$E$5:$E$1004,MATCH(C18&"|"&TEXT(E18,"0"),Bookings!$AG$5:$AG$1004,0))&"","")) | G18: =IF(E18="","",IFERROR(INDEX(Bookings!$G$5:$G$1004,MATCH(C18&"|"&TEXT(E18,"0"),Bookings!$AG$5:$AG$1004,0)),"")) | H18: =IF(OR(A18="",E18=""),"",E18-A18) | I18: =IF(A18="","",IF(E18="","No next booking",IF(H18=0,"SAME-DAY turnover",IF(H18=1,"Next-day check-in","")))) | J18: =IF($M18="","",IF(INDEX(Bookings!$V$5:$V$1004,$M18)="","Unassigned",INDEX(Bookings!$V$5:$V$1004,$M18))) | K18: =IF($M18="","",IF(INDEX(Bookings!$W$5:$W$1004,$M18)="Yes","Yes","")) | L18: =IF($M18="","",INDEX(Bookings!$X$5:$X$1004,$M18)&"") | M18: =IFERROR(MATCH(SMALL(Bookings!$Z$5:$Z$1004,COUNTIF(Bookings!$Z$5:$Z$1004,"<"&$B$4)+12),Bookings!$Z$5:$Z$1004,0),"")
A19: =IF($M19="","",INDEX(Bookings!$C$5:$C$1004,$M19)) | B19: =IF(A19="","",TEXT(A19,"ddd")) | C19: =IF($M19="","",INDEX(Bookings!$D$5:$D$1004,$M19)) | D19: =IF($M19="","",INDEX(Bookings!$E$5:$E$1004,$M19)&"") | E19: =IF($M19="","",IF(_xlfn.MINIFS(Bookings!$B$5:$B$1004,Bookings!$D$5:$D$1004,C19,Bookings!$B$5:$B$1004,">="&A19,Bookings!$AA$5:$AA$1004,1)=0,"",_xlfn.MINIFS(Bookings!$B$5:$B$1004,Bookings!$D$5:$D$1004,C19,Bookings!$B$5:$B$1004,">="&A19,Bookings!$AA$5:$AA$1004,1))) | F19: =IF(E19="","",IFERROR(INDEX(Bookings!$E$5:$E$1004,MATCH(C19&"|"&TEXT(E19,"0"),Bookings!$AG$5:$AG$1004,0))&"","")) | G19: =IF(E19="","",IFERROR(INDEX(Bookings!$G$5:$G$1004,MATCH(C19&"|"&TEXT(E19,"0"),Bookings!$AG$5:$AG$1004,0)),"")) | H19: =IF(OR(A19="",E19=""),"",E19-A19) | I19: =IF(A19="","",IF(E19="","No next booking",IF(H19=0,"SAME-DAY turnover",IF(H19=1,"Next-day check-in","")))) | J19: =IF($M19="","",IF(INDEX(Bookings!$V$5:$V$1004,$M19)="","Unassigned",INDEX(Bookings!$V$5:$V$1004,$M19))) | K19: =IF($M19="","",IF(INDEX(Bookings!$W$5:$W$1004,$M19)="Yes","Yes","")) | L19: =IF($M19="","",INDEX(Bookings!$X$5:$X$1004,$M19)&"") | M19: =IFERROR(MATCH(SMALL(Bookings!$Z$5:$Z$1004,COUNTIF(Bookings!$Z$5:$Z$1004,"<"&$B$4)+13),Bookings!$Z$5:$Z$1004,0),"")
A20: =IF($M20="","",INDEX(Bookings!$C$5:$C$1004,$M20)) | B20: =IF(A20="","",TEXT(A20,"ddd")) | C20: =IF($M20="","",INDEX(Bookings!$D$5:$D$1004,$M20)) | D20: =IF($M20="","",INDEX(Bookings!$E$5:$E$1004,$M20)&"") | E20: =IF($M20="","",IF(_xlfn.MINIFS(Bookings!$B$5:$B$1004,Bookings!$D$5:$D$1004,C20,Bookings!$B$5:$B$1004,">="&A20,Bookings!$AA$5:$AA$1004,1)=0,"",_xlfn.MINIFS(Bookings!$B$5:$B$1004,Bookings!$D$5:$D$1004,C20,Bookings!$B$5:$B$1004,">="&A20,Bookings!$AA$5:$AA$1004,1))) | F20: =IF(E20="","",IFERROR(INDEX(Bookings!$E$5:$E$1004,MATCH(C20&"|"&TEXT(E20,"0"),Bookings!$AG$5:$AG$1004,0))&"","")) | G20: =IF(E20="","",IFERROR(INDEX(Bookings!$G$5:$G$1004,MATCH(C20&"|"&TEXT(E20,"0"),Bookings!$AG$5:$AG$1004,0)),"")) | H20: =IF(OR(A20="",E20=""),"",E20-A20) | I20: =IF(A20="","",IF(E20="","No next booking",IF(H20=0,"SAME-DAY turnover",IF(H20=1,"Next-day check-in","")))) | J20: =IF($M20="","",IF(INDEX(Bookings!$V$5:$V$1004,$M20)="","Unassigned",INDEX(Bookings!$V$5:$V$1004,$M20))) | K20: =IF($M20="","",IF(INDEX(Bookings!$W$5:$W$1004,$M20)="Yes","Yes","")) | L20: =IF($M20="","",INDEX(Bookings!$X$5:$X$1004,$M20)&"") | M20: =IFERROR(MATCH(SMALL(Bookings!$Z$5:$Z$1004,COUNTIF(Bookings!$Z$5:$Z$1004,"<"&$B$4)+14),Bookings!$Z$5:$Z$1004,0),"")
A21: =IF($M21="","",INDEX(Bookings!$C$5:$C$1004,$M21)) | B21: =IF(A21="","",TEXT(A21,"ddd")) | C21: =IF($M21="","",INDEX(Bookings!$D$5:$D$1004,$M21)) | D21: =IF($M21="","",INDEX(Bookings!$E$5:$E$1004,$M21)&"") | E21: =IF($M21="","",IF(_xlfn.MINIFS(Bookings!$B$5:$B$1004,Bookings!$D$5:$D$1004,C21,Bookings!$B$5:$B$1004,">="&A21,Bookings!$AA$5:$AA$1004,1)=0,"",_xlfn.MINIFS(Bookings!$B$5:$B$1004,Bookings!$D$5:$D$1004,C21,Bookings!$B$5:$B$1004,">="&A21,Bookings!$AA$5:$AA$1004,1))) | F21: =IF(E21="","",IFERROR(INDEX(Bookings!$E$5:$E$1004,MATCH(C21&"|"&TEXT(E21,"0"),Bookings!$AG$5:$AG$1004,0))&"","")) | G21: =IF(E21="","",IFERROR(INDEX(Bookings!$G$5:$G$1004,MATCH(C21&"|"&TEXT(E21,"0"),Bookings!$AG$5:$AG$1004,0)),"")) | H21: =IF(OR(A21="",E21=""),"",E21-A21) | I21: =IF(A21="","",IF(E21="","No next booking",IF(H21=0,"SAME-DAY turnover",IF(H21=1,"Next-day check-in","")))) | J21: =IF($M21="","",IF(INDEX(Bookings!$V$5:$V$1004,$M21)="","Unassigned",INDEX(Bookings!$V$5:$V$1004,$M21))) | K21: =IF($M21="","",IF(INDEX(Bookings!$W$5:$W$1004,$M21)="Yes","Yes","")) | L21: =IF($M21="","",INDEX(Bookings!$X$5:$X$1004,$M21)&"") | M21: =IFERROR(MATCH(SMALL(Bookings!$Z$5:$Z$1004,COUNTIF(Bookings!$Z$5:$Z$1004,"<"&$B$4)+15),Bookings!$Z$5:$Z$1004,0),"")
A22: =IF($M22="","",INDEX(Bookings!$C$5:$C$1004,$M22)) | B22: =IF(A22="","",TEXT(A22,"ddd")) | C22: =IF($M22="","",INDEX(Bookings!$D$5:$D$1004,$M22)) | D22: =IF($M22="","",INDEX(Bookings!$E$5:$E$1004,$M22)&"") | E22: =IF($M22="","",IF(_xlfn.MINIFS(Bookings!$B$5:$B$1004,Bookings!$D$5:$D$1004,C22,Bookings!$B$5:$B$1004,">="&A22,Bookings!$AA$5:$AA$1004,1)=0,"",_xlfn.MINIFS(Bookings!$B$5:$B$1004,Bookings!$D$5:$D$1004,C22,Bookings!$B$5:$B$1004,">="&A22,Bookings!$AA$5:$AA$1004,1))) | F22: =IF(E22="","",IFERROR(INDEX(Bookings!$E$5:$E$1004,MATCH(C22&"|"&TEXT(E22,"0"),Bookings!$AG$5:$AG$1004,0))&"","")) | G22: =IF(E22="","",IFERROR(INDEX(Bookings!$G$5:$G$1004,MATCH(C22&"|"&TEXT(E22,"0"),Bookings!$AG$5:$AG$1004,0)),"")) | H22: =IF(OR(A22="",E22=""),"",E22-A22) | I22: =IF(A22="","",IF(E22="","No next booking",IF(H22=0,"SAME-DAY turnover",IF(H22=1,"Next-day check-in","")))) | J22: =IF($M22="","",IF(INDEX(Bookings!$V$5:$V$1004,$M22)="","Unassigned",INDEX(Bookings!$V$5:$V$1004,$M22))) | K22: =IF($M22="","",IF(INDEX(Bookings!$W$5:$W$1004,$M22)="Yes","Yes","")) | L22: =IF($M22="","",INDEX(Bookings!$X$5:$X$1004,$M22)&"") | M22: =IFERROR(MATCH(SMALL(Bookings!$Z$5:$Z$1004,COUNTIF(Bookings!$Z$5:$Z$1004,"<"&$B$4)+16),Bookings!$Z$5:$Z$1004,0),"")
A23: =IF($M23="","",INDEX(Bookings!$C$5:$C$1004,$M23)) | B23: =IF(A23="","",TEXT(A23,"ddd")) | C23: =IF($M23="","",INDEX(Bookings!$D$5:$D$1004,$M23)) | D23: =IF($M23="","",INDEX(Bookings!$E$5:$E$1004,$M23)&"") | E23: =IF($M23="","",IF(_xlfn.MINIFS(Bookings!$B$5:$B$1004,Bookings!$D$5:$D$1004,C23,Bookings!$B$5:$B$1004,">="&A23,Bookings!$AA$5:$AA$1004,1)=0,"",_xlfn.MINIFS(Bookings!$B$5:$B$1004,Bookings!$D$5:$D$1004,C23,Bookings!$B$5:$B$1004,">="&A23,Bookings!$AA$5:$AA$1004,1))) | F23: =IF(E23="","",IFERROR(INDEX(Bookings!$E$5:$E$1004,MATCH(C23&"|"&TEXT(E23,"0"),Bookings!$AG$5:$AG$1004,0))&"","")) | G23: =IF(E23="","",IFERROR(INDEX(Bookings!$G$5:$G$1004,MATCH(C23&"|"&TEXT(E23,"0"),Bookings!$AG$5:$AG$1004,0)),"")) | H23: =IF(OR(A23="",E23=""),"",E23-A23) | I23: =IF(A23="","",IF(E23="","No next booking",IF(H23=0,"SAME-DAY turnover",IF(H23=1,"Next-day check-in","")))) | J23: =IF($M23="","",IF(INDEX(Bookings!$V$5:$V$1004,$M23)="","Unassigned",INDEX(Bookings!$V$5:$V$1004,$M23))) | K23: =IF($M23="","",IF(INDEX(Bookings!$W$5:$W$1004,$M23)="Yes","Yes","")) | L23: =IF($M23="","",INDEX(Bookings!$X$5:$X$1004,$M23)&"") | M23: =IFERROR(MATCH(SMALL(Bookings!$Z$5:$Z$1004,COUNTIF(Bookings!$Z$5:$Z$1004,"<"&$B$4)+17),Bookings!$Z$5:$Z$1004,0),"")
A24: =IF($M24="","",INDEX(Bookings!$C$5:$C$1004,$M24)) | B24: =IF(A24="","",TEXT(A24,"ddd")) | C24: =IF($M24="","",INDEX(Bookings!$D$5:$D$1004,$M24)) | D24: =IF($M24="","",INDEX(Bookings!$E$5:$E$1004,$M24)&"") | E24: =IF($M24="","",IF(_xlfn.MINIFS(Bookings!$B$5:$B$1004,Bookings!$D$5:$D$1004,C24,Bookings!$B$5:$B$1004,">="&A24,Bookings!$AA$5:$AA$1004,1)=0,"",_xlfn.MINIFS(Bookings!$B$5:$B$1004,Bookings!$D$5:$D$1004,C24,Bookings!$B$5:$B$1004,">="&A24,Bookings!$AA$5:$AA$1004,1))) | F24: =IF(E24="","",IFERROR(INDEX(Bookings!$E$5:$E$1004,MATCH(C24&"|"&TEXT(E24,"0"),Bookings!$AG$5:$AG$1004,0))&"","")) | G24: =IF(E24="","",IFERROR(INDEX(Bookings!$G$5:$G$1004,MATCH(C24&"|"&TEXT(E24,"0"),Bookings!$AG$5:$AG$1004,0)),"")) | H24: =IF(OR(A24="",E24=""),"",E24-A24) | I24: =IF(A24="","",IF(E24="","No next booking",IF(H24=0,"SAME-DAY turnover",IF(H24=1,"Next-day check-in","")))) | J24: =IF($M24="","",IF(INDEX(Bookings!$V$5:$V$1004,$M24)="","Unassigned",INDEX(Bookings!$V$5:$V$1004,$M24))) | K24: =IF($M24="","",IF(INDEX(Bookings!$W$5:$W$1004,$M24)="Yes","Yes","")) | L24: =IF($M24="","",INDEX(Bookings!$X$5:$X$1004,$M24)&"") | M24: =IFERROR(MATCH(SMALL(Bookings!$Z$5:$Z$1004,COUNTIF(Bookings!$Z$5:$Z$1004,"<"&$B$4)+18),Bookings!$Z$5:$Z$1004,0),"")
A25: =IF($M25="","",INDEX(Bookings!$C$5:$C$1004,$M25)) | B25: =IF(A25="","",TEXT(A25,"ddd")) | C25: =IF($M25="","",INDEX(Bookings!$D$5:$D$1004,$M25)) | D25: =IF($M25="","",INDEX(Bookings!$E$5:$E$1004,$M25)&"") | E25: =IF($M25="","",IF(_xlfn.MINIFS(Bookings!$B$5:$B$1004,Bookings!$D$5:$D$1004,C25,Bookings!$B$5:$B$1004,">="&A25,Bookings!$AA$5:$AA$1004,1)=0,"",_xlfn.MINIFS(Bookings!$B$5:$B$1004,Bookings!$D$5:$D$1004,C25,Bookings!$B$5:$B$1004,">="&A25,Bookings!$AA$5:$AA$1004,1))) | F25: =IF(E25="","",IFERROR(INDEX(Bookings!$E$5:$E$1004,MATCH(C25&"|"&TEXT(E25,"0"),Bookings!$AG$5:$AG$1004,0))&"","")) | G25: =IF(E25="","",IFERROR(INDEX(Bookings!$G$5:$G$1004,MATCH(C25&"|"&TEXT(E25,"0"),Bookings!$AG$5:$AG$1004,0)),"")) | H25: =IF(OR(A25="",E25=""),"",E25-A25) | I25: =IF(A25="","",IF(E25="","No next booking",IF(H25=0,"SAME-DAY turnover",IF(H25=1,"Next-day check-in","")))) | J25: =IF($M25="","",IF(INDEX(Bookings!$V$5:$V$1004,$M25)="","Unassigned",INDEX(Bookings!$V$5:$V$1004,$M25))) | K25: =IF($M25="","",IF(INDEX(Bookings!$W$5:$W$1004,$M25)="Yes","Yes","")) | L25: =IF($M25="","",INDEX(Bookings!$X$5:$X$1004,$M25)&"") | M25: =IFERROR(MATCH(SMALL(Bookings!$Z$5:$Z$1004,COUNTIF(Bookings!$Z$5:$Z$1004,"<"&$B$4)+19),Bookings!$Z$5:$Z$1004,0),"")
A26: =IF($M26="","",INDEX(Bookings!$C$5:$C$1004,$M26)) | B26: =IF(A26="","",TEXT(A26,"ddd")) | C26: =IF($M26="","",INDEX(Bookings!$D$5:$D$1004,$M26)) | D26: =IF($M26="","",INDEX(Bookings!$E$5:$E$1004,$M26)&"") | E26: =IF($M26="","",IF(_xlfn.MINIFS(Bookings!$B$5:$B$1004,Bookings!$D$5:$D$1004,C26,Bookings!$B$5:$B$1004,">="&A26,Bookings!$AA$5:$AA$1004,1)=0,"",_xlfn.MINIFS(Bookings!$B$5:$B$1004,Bookings!$D$5:$D$1004,C26,Bookings!$B$5:$B$1004,">="&A26,Bookings!$AA$5:$AA$1004,1))) | F26: =IF(E26="","",IFERROR(INDEX(Bookings!$E$5:$E$1004,MATCH(C26&"|"&TEXT(E26,"0"),Bookings!$AG$5:$AG$1004,0))&"","")) | G26: =IF(E26="","",IFERROR(INDEX(Bookings!$G$5:$G$1004,MATCH(C26&"|"&TEXT(E26,"0"),Bookings!$AG$5:$AG$1004,0)),"")) | H26: =IF(OR(A26="",E26=""),"",E26-A26) | I26: =IF(A26="","",IF(E26="","No next booking",IF(H26=0,"SAME-DAY turnover",IF(H26=1,"Next-day check-in","")))) | J26: =IF($M26="","",IF(INDEX(Bookings!$V$5:$V$1004,$M26)="","Unassigned",INDEX(Bookings!$V$5:$V$1004,$M26))) | K26: =IF($M26="","",IF(INDEX(Bookings!$W$5:$W$1004,$M26)="Yes","Yes","")) | L26: =IF($M26="","",INDEX(Bookings!$X$5:$X$1004,$M26)&"") | M26: =IFERROR(MATCH(SMALL(Bookings!$Z$5:$Z$1004,COUNTIF(Bookings!$Z$5:$Z$1004,"<"&$B$4)+20),Bookings!$Z$5:$Z$1004,0),"")
A27: =IF($M27="","",INDEX(Bookings!$C$5:$C$1004,$M27)) | B27: =IF(A27="","",TEXT(A27,"ddd")) | C27: =IF($M27="","",INDEX(Bookings!$D$5:$D$1004,$M27)) | D27: =IF($M27="","",INDEX(Bookings!$E$5:$E$1004,$M27)&"") | E27: =IF($M27="","",IF(_xlfn.MINIFS(Bookings!$B$5:$B$1004,Bookings!$D$5:$D$1004,C27,Bookings!$B$5:$B$1004,">="&A27,Bookings!$AA$5:$AA$1004,1)=0,"",_xlfn.MINIFS(Bookings!$B$5:$B$1004,Bookings!$D$5:$D$1004,C27,Bookings!$B$5:$B$1004,">="&A27,Bookings!$AA$5:$AA$1004,1))) | F27: =IF(E27="","",IFERROR(INDEX(Bookings!$E$5:$E$1004,MATCH(C27&"|"&TEXT(E27,"0"),Bookings!$AG$5:$AG$1004,0))&"","")) | G27: =IF(E27="","",IFERROR(INDEX(Bookings!$G$5:$G$1004,MATCH(C27&"|"&TEXT(E27,"0"),Bookings!$AG$5:$AG$1004,0)),"")) | H27: =IF(OR(A27="",E27=""),"",E27-A27) | I27: =IF(A27="","",IF(E27="","No next booking",IF(H27=0,"SAME-DAY turnover",IF(H27=1,"Next-day check-in","")))) | J27: =IF($M27="","",IF(INDEX(Bookings!$V$5:$V$1004,$M27)="","Unassigned",INDEX(Bookings!$V$5:$V$1004,$M27))) | K27: =IF($M27="","",IF(INDEX(Bookings!$W$5:$W$1004,$M27)="Yes","Yes","")) | L27: =IF($M27="","",INDEX(Bookings!$X$5:$X$1004,$M27)&"") | M27: =IFERROR(MATCH(SMALL(Bookings!$Z$5:$Z$1004,COUNTIF(Bookings!$Z$5:$Z$1004,"<"&$B$4)+21),Bookings!$Z$5:$Z$1004,0),"")
A28: =IF($M28="","",INDEX(Bookings!$C$5:$C$1004,$M28)) | B28: =IF(A28="","",TEXT(A28,"ddd")) | C28: =IF($M28="","",INDEX(Bookings!$D$5:$D$1004,$M28)) | D28: =IF($M28="","",INDEX(Bookings!$E$5:$E$1004,$M28)&"") | E28: =IF($M28="","",IF(_xlfn.MINIFS(Bookings!$B$5:$B$1004,Bookings!$D$5:$D$1004,C28,Bookings!$B$5:$B$1004,">="&A28,Bookings!$AA$5:$AA$1004,1)=0,"",_xlfn.MINIFS(Bookings!$B$5:$B$1004,Bookings!$D$5:$D$1004,C28,Bookings!$B$5:$B$1004,">="&A28,Bookings!$AA$5:$AA$1004,1))) | F28: =IF(E28="","",IFERROR(INDEX(Bookings!$E$5:$E$1004,MATCH(C28&"|"&TEXT(E28,"0"),Bookings!$AG$5:$AG$1004,0))&"","")) | G28: =IF(E28="","",IFERROR(INDEX(Bookings!$G$5:$G$1004,MATCH(C28&"|"&TEXT(E28,"0"),Bookings!$AG$5:$AG$1004,0)),"")) | H28: =IF(OR(A28="",E28=""),"",E28-A28) | I28: =IF(A28="","",IF(E28="","No next booking",IF(H28=0,"SAME-DAY turnover",IF(H28=1,"Next-day check-in","")))) | J28: =IF($M28="","",IF(INDEX(Bookings!$V$5:$V$1004,$M28)="","Unassigned",INDEX(Bookings!$V$5:$V$1004,$M28))) | K28: =IF($M28="","",IF(INDEX(Bookings!$W$5:$W$1004,$M28)="Yes","Yes","")) | L28: =IF($M28="","",INDEX(Bookings!$X$5:$X$1004,$M28)&"") | M28: =IFERROR(MATCH(SMALL(Bookings!$Z$5:$Z$1004,COUNTIF(Bookings!$Z$5:$Z$1004,"<"&$B$4)+22),Bookings!$Z$5:$Z$1004,0),"")
A29: =IF($M29="","",INDEX(Bookings!$C$5:$C$1004,$M29)) | B29: =IF(A29="","",TEXT(A29,"ddd")) | C29: =IF($M29="","",INDEX(Bookings!$D$5:$D$1004,$M29)) | D29: =IF($M29="","",INDEX(Bookings!$E$5:$E$1004,$M29)&"") | E29: =IF($M29="","",IF(_xlfn.MINIFS(Bookings!$B$5:$B$1004,Bookings!$D$5:$D$1004,C29,Bookings!$B$5:$B$1004,">="&A29,Bookings!$AA$5:$AA$1004,1)=0,"",_xlfn.MINIFS(Bookings!$B$5:$B$1004,Bookings!$D$5:$D$1004,C29,Bookings!$B$5:$B$1004,">="&A29,Bookings!$AA$5:$AA$1004,1))) | F29: =IF(E29="","",IFERROR(INDEX(Bookings!$E$5:$E$1004,MATCH(C29&"|"&TEXT(E29,"0"),Bookings!$AG$5:$AG$1004,0))&"","")) | G29: =IF(E29="","",IFERROR(INDEX(Bookings!$G$5:$G$1004,MATCH(C29&"|"&TEXT(E29,"0"),Bookings!$AG$5:$AG$1004,0)),"")) | H29: =IF(OR(A29="",E29=""),"",E29-A29) | I29: =IF(A29="","",IF(E29="","No next booking",IF(H29=0,"SAME-DAY turnover",IF(H29=1,"Next-day check-in","")))) | J29: =IF($M29="","",IF(INDEX(Bookings!$V$5:$V$1004,$M29)="","Unassigned",INDEX(Bookings!$V$5:$V$1004,$M29))) | K29: =IF($M29="","",IF(INDEX(Bookings!$W$5:$W$1004,$M29)="Yes","Yes","")) | L29: =IF($M29="","",INDEX(Bookings!$X$5:$X$1004,$M29)&"") | M29: =IFERROR(MATCH(SMALL(Bookings!$Z$5:$Z$1004,COUNTIF(Bookings!$Z$5:$Z$1004,"<"&$B$4)+23),Bookings!$Z$5:$Z$1004,0),"")
A30: =IF($M30="","",INDEX(Bookings!$C$5:$C$1004,$M30)) | B30: =IF(A30="","",TEXT(A30,"ddd")) | C30: =IF($M30="","",INDEX(Bookings!$D$5:$D$1004,$M30)) | D30: =IF($M30="","",INDEX(Bookings!$E$5:$E$1004,$M30)&"") | E30: =IF($M30="","",IF(_xlfn.MINIFS(Bookings!$B$5:$B$1004,Bookings!$D$5:$D$1004,C30,Bookings!$B$5:$B$1004,">="&A30,Bookings!$AA$5:$AA$1004,1)=0,"",_xlfn.MINIFS(Bookings!$B$5:$B$1004,Bookings!$D$5:$D$1004,C30,Bookings!$B$5:$B$1004,">="&A30,Bookings!$AA$5:$AA$1004,1))) | F30: =IF(E30="","",IFERROR(INDEX(Bookings!$E$5:$E$1004,MATCH(C30&"|"&TEXT(E30,"0"),Bookings!$AG$5:$AG$1004,0))&"","")) | G30: =IF(E30="","",IFERROR(INDEX(Bookings!$G$5:$G$1004,MATCH(C30&"|"&TEXT(E30,"0"),Bookings!$AG$5:$AG$1004,0)),"")) | H30: =IF(OR(A30="",E30=""),"",E30-A30) | I30: =IF(A30="","",IF(E30="","No next booking",IF(H30=0,"SAME-DAY turnover",IF(H30=1,"Next-day check-in","")))) | J30: =IF($M30="","",IF(INDEX(Bookings!$V$5:$V$1004,$M30)="","Unassigned",INDEX(Bookings!$V$5:$V$1004,$M30))) | K30: =IF($M30="","",IF(INDEX(Bookings!$W$5:$W$1004,$M30)="Yes","Yes","")) | L30: =IF($M30="","",INDEX(Bookings!$X$5:$X$1004,$M30)&"") | M30: =IFERROR(MATCH(SMALL(Bookings!$Z$5:$Z$1004,COUNTIF(Bookings!$Z$5:$Z$1004,"<"&$B$4)+24),Bookings!$Z$5:$Z$1004,0),"")
A31: =IF($M31="","",INDEX(Bookings!$C$5:$C$1004,$M31)) | B31: =IF(A31="","",TEXT(A31,"ddd")) | C31: =IF($M31="","",INDEX(Bookings!$D$5:$D$1004,$M31)) | D31: =IF($M31="","",INDEX(Bookings!$E$5:$E$1004,$M31)&"") | E31: =IF($M31="","",IF(_xlfn.MINIFS(Bookings!$B$5:$B$1004,Bookings!$D$5:$D$1004,C31,Bookings!$B$5:$B$1004,">="&A31,Bookings!$AA$5:$AA$1004,1)=0,"",_xlfn.MINIFS(Bookings!$B$5:$B$1004,Bookings!$D$5:$D$1004,C31,Bookings!$B$5:$B$1004,">="&A31,Bookings!$AA$5:$AA$1004,1))) | F31: =IF(E31="","",IFERROR(INDEX(Bookings!$E$5:$E$1004,MATCH(C31&"|"&TEXT(E31,"0"),Bookings!$AG$5:$AG$1004,0))&"","")) | G31: =IF(E31="","",IFERROR(INDEX(Bookings!$G$5:$G$1004,MATCH(C31&"|"&TEXT(E31,"0"),Bookings!$AG$5:$AG$1004,0)),"")) | H31: =IF(OR(A31="",E31=""),"",E31-A31) | I31: =IF(A31="","",IF(E31="","No next booking",IF(H31=0,"SAME-DAY turnover",IF(H31=1,"Next-day check-in","")))) | J31: =IF($M31="","",IF(INDEX(Bookings!$V$5:$V$1004,$M31)="","Unassigned",INDEX(Bookings!$V$5:$V$1004,$M31))) | K31: =IF($M31="","",IF(INDEX(Bookings!$W$5:$W$1004,$M31)="Yes","Yes","")) | L31: =IF($M31="","",INDEX(Bookings!$X$5:$X$1004,$M31)&"") | M31: =IFERROR(MATCH(SMALL(Bookings!$Z$5:$Z$1004,COUNTIF(Bookings!$Z$5:$Z$1004,"<"&$B$4)+25),Bookings!$Z$5:$Z$1004,0),"")
A32: =IF($M32="","",INDEX(Bookings!$C$5:$C$1004,$M32)) | B32: =IF(A32="","",TEXT(A32,"ddd")) | C32: =IF($M32="","",INDEX(Bookings!$D$5:$D$1004,$M32)) | D32: =IF($M32="","",INDEX(Bookings!$E$5:$E$1004,$M32)&"") | E32: =IF($M32="","",IF(_xlfn.MINIFS(Bookings!$B$5:$B$1004,Bookings!$D$5:$D$1004,C32,Bookings!$B$5:$B$1004,">="&A32,Bookings!$AA$5:$AA$1004,1)=0,"",_xlfn.MINIFS(Bookings!$B$5:$B$1004,Bookings!$D$5:$D$1004,C32,Bookings!$B$5:$B$1004,">="&A32,Bookings!$AA$5:$AA$1004,1))) | F32: =IF(E32="","",IFERROR(INDEX(Bookings!$E$5:$E$1004,MATCH(C32&"|"&TEXT(E32,"0"),Bookings!$AG$5:$AG$1004,0))&"","")) | G32: =IF(E32="","",IFERROR(INDEX(Bookings!$G$5:$G$1004,MATCH(C32&"|"&TEXT(E32,"0"),Bookings!$AG$5:$AG$1004,0)),"")) | H32: =IF(OR(A32="",E32=""),"",E32-A32) | I32: =IF(A32="","",IF(E32="","No next booking",IF(H32=0,"SAME-DAY turnover",IF(H32=1,"Next-day check-in","")))) | J32: =IF($M32="","",IF(INDEX(Bookings!$V$5:$V$1004,$M32)="","Unassigned",INDEX(Bookings!$V$5:$V$1004,$M32))) | K32: =IF($M32="","",IF(INDEX(Bookings!$W$5:$W$1004,$M32)="Yes","Yes","")) | L32: =IF($M32="","",INDEX(Bookings!$X$5:$X$1004,$M32)&"") | M32: =IFERROR(MATCH(SMALL(Bookings!$Z$5:$Z$1004,COUNTIF(Bookings!$Z$5:$Z$1004,"<"&$B$4)+26),Bookings!$Z$5:$Z$1004,0),"")
A33: =IF($M33="","",INDEX(Bookings!$C$5:$C$1004,$M33)) | B33: =IF(A33="","",TEXT(A33,"ddd")) | C33: =IF($M33="","",INDEX(Bookings!$D$5:$D$1004,$M33)) | D33: =IF($M33="","",INDEX(Bookings!$E$5:$E$1004,$M33)&"") | E33: =IF($M33="","",IF(_xlfn.MINIFS(Bookings!$B$5:$B$1004,Bookings!$D$5:$D$1004,C33,Bookings!$B$5:$B$1004,">="&A33,Bookings!$AA$5:$AA$1004,1)=0,"",_xlfn.MINIFS(Bookings!$B$5:$B$1004,Bookings!$D$5:$D$1004,C33,Bookings!$B$5:$B$1004,">="&A33,Bookings!$AA$5:$AA$1004,1))) | F33: =IF(E33="","",IFERROR(INDEX(Bookings!$E$5:$E$1004,MATCH(C33&"|"&TEXT(E33,"0"),Bookings!$AG$5:$AG$1004,0))&"","")) | G33: =IF(E33="","",IFERROR(INDEX(Bookings!$G$5:$G$1004,MATCH(C33&"|"&TEXT(E33,"0"),Bookings!$AG$5:$AG$1004,0)),"")) | H33: =IF(OR(A33="",E33=""),"",E33-A33) | I33: =IF(A33="","",IF(E33="","No next booking",IF(H33=0,"SAME-DAY turnover",IF(H33=1,"Next-day check-in","")))) | J33: =IF($M33="","",IF(INDEX(Bookings!$V$5:$V$1004,$M33)="","Unassigned",INDEX(Bookings!$V$5:$V$1004,$M33))) | K33: =IF($M33="","",IF(INDEX(Bookings!$W$5:$W$1004,$M33)="Yes","Yes","")) | L33: =IF($M33="","",INDEX(Bookings!$X$5:$X$1004,$M33)&"") | M33: =IFERROR(MATCH(SMALL(Bookings!$Z$5:$Z$1004,COUNTIF(Bookings!$Z$5:$Z$1004,"<"&$B$4)+27),Bookings!$Z$5:$Z$1004,0),"")
A34: =IF($M34="","",INDEX(Bookings!$C$5:$C$1004,$M34)) | B34: =IF(A34="","",TEXT(A34,"ddd")) | C34: =IF($M34="","",INDEX(Bookings!$D$5:$D$1004,$M34)) | D34: =IF($M34="","",INDEX(Bookings!$E$5:$E$1004,$M34)&"") | E34: =IF($M34="","",IF(_xlfn.MINIFS(Bookings!$B$5:$B$1004,Bookings!$D$5:$D$1004,C34,Bookings!$B$5:$B$1004,">="&A34,Bookings!$AA$5:$AA$1004,1)=0,"",_xlfn.MINIFS(Bookings!$B$5:$B$1004,Bookings!$D$5:$D$1004,C34,Bookings!$B$5:$B$1004,">="&A34,Bookings!$AA$5:$AA$1004,1))) | F34: =IF(E34="","",IFERROR(INDEX(Bookings!$E$5:$E$1004,MATCH(C34&"|"&TEXT(E34,"0"),Bookings!$AG$5:$AG$1004,0))&"","")) | G34: =IF(E34="","",IFERROR(INDEX(Bookings!$G$5:$G$1004,MATCH(C34&"|"&TEXT(E34,"0"),Bookings!$AG$5:$AG$1004,0)),"")) | H34: =IF(OR(A34="",E34=""),"",E34-A34) | I34: =IF(A34="","",IF(E34="","No next booking",IF(H34=0,"SAME-DAY turnover",IF(H34=1,"Next-day check-in","")))) | J34: =IF($M34="","",IF(INDEX(Bookings!$V$5:$V$1004,$M34)="","Unassigned",INDEX(Bookings!$V$5:$V$1004,$M34))) | K34: =IF($M34="","",IF(INDEX(Bookings!$W$5:$W$1004,$M34)="Yes","Yes","")) | L34: =IF($M34="","",INDEX(Bookings!$X$5:$X$1004,$M34)&"") | M34: =IFERROR(MATCH(SMALL(Bookings!$Z$5:$Z$1004,COUNTIF(Bookings!$Z$5:$Z$1004,"<"&$B$4)+28),Bookings!$Z$5:$Z$1004,0),"")
A35: =IF($M35="","",INDEX(Bookings!$C$5:$C$1004,$M35)) | B35: =IF(A35="","",TEXT(A35,"ddd")) | C35: =IF($M35="","",INDEX(Bookings!$D$5:$D$1004,$M35)) | D35: =IF($M35="","",INDEX(Bookings!$E$5:$E$1004,$M35)&"") | E35: =IF($M35="","",IF(_xlfn.MINIFS(Bookings!$B$5:$B$1004,Bookings!$D$5:$D$1004,C35,Bookings!$B$5:$B$1004,">="&A35,Bookings!$AA$5:$AA$1004,1)=0,"",_xlfn.MINIFS(Bookings!$B$5:$B$1004,Bookings!$D$5:$D$1004,C35,Bookings!$B$5:$B$1004,">="&A35,Bookings!$AA$5:$AA$1004,1))) | F35: =IF(E35="","",IFERROR(INDEX(Bookings!$E$5:$E$1004,MATCH(C35&"|"&TEXT(E35,"0"),Bookings!$AG$5:$AG$1004,0))&"","")) | G35: =IF(E35="","",IFERROR(INDEX(Bookings!$G$5:$G$1004,MATCH(C35&"|"&TEXT(E35,"0"),Bookings!$AG$5:$AG$1004,0)),"")) | H35: =IF(OR(A35="",E35=""),"",E35-A35) | I35: =IF(A35="","",IF(E35="","No next booking",IF(H35=0,"SAME-DAY turnover",IF(H35=1,"Next-day check-in","")))) | J35: =IF($M35="","",IF(INDEX(Bookings!$V$5:$V$1004,$M35)="","Unassigned",INDEX(Bookings!$V$5:$V$1004,$M35))) | K35: =IF($M35="","",IF(INDEX(Bookings!$W$5:$W$1004,$M35)="Yes","Yes","")) | L35: =IF($M35="","",INDEX(Bookings!$X$5:$X$1004,$M35)&"") | M35: =IFERROR(MATCH(SMALL(Bookings!$Z$5:$Z$1004,COUNTIF(Bookings!$Z$5:$Z$1004,"<"&$B$4)+29),Bookings!$Z$5:$Z$1004,0),"")
A36: =IF($M36="","",INDEX(Bookings!$C$5:$C$1004,$M36)) | B36: =IF(A36="","",TEXT(A36,"ddd")) | C36: =IF($M36="","",INDEX(Bookings!$D$5:$D$1004,$M36)) | D36: =IF($M36="","",INDEX(Bookings!$E$5:$E$1004,$M36)&"") | E36: =IF($M36="","",IF(_xlfn.MINIFS(Bookings!$B$5:$B$1004,Bookings!$D$5:$D$1004,C36,Bookings!$B$5:$B$1004,">="&A36,Bookings!$AA$5:$AA$1004,1)=0,"",_xlfn.MINIFS(Bookings!$B$5:$B$1004,Bookings!$D$5:$D$1004,C36,Bookings!$B$5:$B$1004,">="&A36,Bookings!$AA$5:$AA$1004,1))) | F36: =IF(E36="","",IFERROR(INDEX(Bookings!$E$5:$E$1004,MATCH(C36&"|"&TEXT(E36,"0"),Bookings!$AG$5:$AG$1004,0))&"","")) | G36: =IF(E36="","",IFERROR(INDEX(Bookings!$G$5:$G$1004,MATCH(C36&"|"&TEXT(E36,"0"),Bookings!$AG$5:$AG$1004,0)),"")) | H36: =IF(OR(A36="",E36=""),"",E36-A36) | I36: =IF(A36="","",IF(E36="","No next booking",IF(H36=0,"SAME-DAY turnover",IF(H36=1,"Next-day check-in","")))) | J36: =IF($M36="","",IF(INDEX(Bookings!$V$5:$V$1004,$M36)="","Unassigned",INDEX(Bookings!$V$5:$V$1004,$M36))) | K36: =IF($M36="","",IF(INDEX(Bookings!$W$5:$W$1004,$M36)="Yes","Yes","")) | L36: =IF($M36="","",INDEX(Bookings!$X$5:$X$1004,$M36)&"") | M36: =IFERROR(MATCH(SMALL(Bookings!$Z$5:$Z$1004,COUNTIF(Bookings!$Z$5:$Z$1004,"<"&$B$4)+30),Bookings!$Z$5:$Z$1004,0),"")
A37: =IF($M37="","",INDEX(Bookings!$C$5:$C$1004,$M37)) | B37: =IF(A37="","",TEXT(A37,"ddd")) | C37: =IF($M37="","",INDEX(Bookings!$D$5:$D$1004,$M37)) | D37: =IF($M37="","",INDEX(Bookings!$E$5:$E$1004,$M37)&"") | E37: =IF($M37="","",IF(_xlfn.MINIFS(Bookings!$B$5:$B$1004,Bookings!$D$5:$D$1004,C37,Bookings!$B$5:$B$1004,">="&A37,Bookings!$AA$5:$AA$1004,1)=0,"",_xlfn.MINIFS(Bookings!$B$5:$B$1004,Bookings!$D$5:$D$1004,C37,Bookings!$B$5:$B$1004,">="&A37,Bookings!$AA$5:$AA$1004,1))) | F37: =IF(E37="","",IFERROR(INDEX(Bookings!$E$5:$E$1004,MATCH(C37&"|"&TEXT(E37,"0"),Bookings!$AG$5:$AG$1004,0))&"","")) | G37: =IF(E37="","",IFERROR(INDEX(Bookings!$G$5:$G$1004,MATCH(C37&"|"&TEXT(E37,"0"),Bookings!$AG$5:$AG$1004,0)),"")) | H37: =IF(OR(A37="",E37=""),"",E37-A37) | I37: =IF(A37="","",IF(E37="","No next booking",IF(H37=0,"SAME-DAY turnover",IF(H37=1,"Next-day check-in","")))) | J37: =IF($M37="","",IF(INDEX(Bookings!$V$5:$V$1004,$M37)="","Unassigned",INDEX(Bookings!$V$5:$V$1004,$M37))) | K37: =IF($M37="","",IF(INDEX(Bookings!$W$5:$W$1004,$M37)="Yes","Yes","")) | L37: =IF($M37="","",INDEX(Bookings!$X$5:$X$1004,$M37)&"") | M37: =IFERROR(MATCH(SMALL(Bookings!$Z$5:$Z$1004,COUNTIF(Bookings!$Z$5:$Z$1004,"<"&$B$4)+31),Bookings!$Z$5:$Z$1004,0),"")
